Workbook

Sheet Léeme
B2: LafroX — Carta Gantt del Subdocumento 7 (Formulario T-14)
B3: Licitación TFEP-01/2026, Caso 02 — Logística, Distribuidora Puelche S.A. Versión del 9 de octubre de 2026, generada desde el Formulario T-14 (EDT y carta Gantt, sección 3.1) y el Formulario T-15 (programación por paquete, secciones 4.2, 5 y 6).
B4: 1. Qué es una carta Gantt
B5: Una carta Gantt es un cronograma dibujado como barras sobre una línea de tiempo: cada fila es un trabajo y cada barra muestra cuándo empieza y cuándo termina. Sirve para ver de un vistazo qué se hace en paralelo, qué viene después de qué y cuánto falta para cada fecha comprometida. No muestra por sí sola las dependencias entre trabajos ni las horas: esos datos están en las hojas «Gantt paquetes» y «Actividades hasta H2».
B6: 2. Cómo está organizada esta planilla
B7: • Parámetros: la fecha de inicio del contrato (supuesto: febrero de 2027). Es la única celda que se edita; todas las fechas de la planilla se recalculan a partir de ella.
B8: • Períodos Art. 17: los períodos contractuales fijos de las Bases Administrativas (desarrollo, marcha blanca, producción y operación de cada etapa).
B9: • Hitos: los doce hitos del Formulario E-25, con su mes contractual, su fecha calendario, la fecha en que LafroX entrega, la fecha límite para que el CLIENTE alcance a revisar y la reserva entre ambas.
B10: • Gantt cuentas: la carta Gantt resumida, una fila por cuenta de control (49 filas), sobre los 56 meses del contrato.
B11: • Gantt paquetes: la carta Gantt detallada, una fila por paquete de trabajo de la EDT (222 filas), con su clase, su responsable y sus horas hombre.
B12: • Actividades hasta H2: las 108 actividades de los paquetes que terminan hasta el H2 (mes 4), con personas, horas, fechas y predecesoras. Los demás paquetes tienen fecha en la hoja «Gantt paquetes» y se detallan en actividades por planificación gradual antes de cada fase (H2, H4, H8 y H9).
B13: • Glosario: la definición de cada término usado (hito, cuenta de control, paquete, actividad, marcha blanca, reserva, P80, etc.).
... B27: • Texto azul sobre fondo amarillo: dato que se puede editar (sólo la fecha de inicio). Texto negro: fórmula o dato tomado de los formularios. Fondo naranja claro en la fila de meses: mes de congelamiento.

Sheet Parámetros
A1: Parámetros de la planilla
A3: Fecha de inicio del contrato (mes 1) | B3: 46419 | C3: Supuesto de calendario del SD7, Anexo 7.A: inicio en febrero de 2027. Editar sólo esta celda; debe ser un día 1 de mes.
A4: Días hábiles de revisión del CLIENTE | B4: 10 | C4: Bases Administrativas, Art. 18.3: el CLIENTE dispone de diez días hábiles para revisar cada entregable.
A5: Duración del contrato (meses) | B5: 56 | C5: Bases Administrativas, Art. 17°.

Sheet Hitos
A1: Hito | B1: Descripción y entregable que lo gatilla (Formulario E-25) | C1: Etapa | D1: Mes contractual | E1: Mes calendario | F1: % de pago (sobre la implementación) | G1: Paquetes que lo gatillan | H1: Entrega programada de LafroX | I1: Fecha límite de entrega (último día hábil del mes − revisión) | J1: Reserva (días hábiles) | K1: Probabilidad de entrega a tiempo (simulación SD8) | L1: Fecha P80 simulada | M1: Día hábil n.º de la entrega (dato del T-15)
A2: H1 | B2: Cierre del levantamiento y aprobación de la línea base de alcance y de la matriz de trazabilidad de requerimientos. | C2: Etapa 1 | D2: 2 | E2: =EDATE('Parámetros'!$B$3,D2-1) | F2: 0.08 | G2: 1.2.1, 1.2.4 | H2: =WORKDAY('Parámetros'!$B$3-1,M2+1) | I2: =WORKDAY(EOMONTH(E2,0)+1,-1-'Parámetros'!$B$4) | J2: =NETWORKDAYS(H2,I2)-1 | K2: 1 | L2: =WORKDAY('Parámetros'!$B$3-1,29) | M2: 26
A3: H2 | B3: Aprobación del documento de arquitectura, del plan de seguridad y del modelo de datos. | C3: Etapa 1 | D3: 4 | E3: =EDATE('Parámetros'!$B$3,D3-1) | F3: 0.07 | G3: 2.1.1–2.1.3, 2.2.1, 2.2.3, 2.2.4 (acta 2.4.1) | H3: =WORKDAY('Parámetros'!$B$3-1,M3+1) | I3: =WORKDAY(EOMONTH(E3,0)+1,-1-'Parámetros'!$B$4) | J3: =NETWORKDAYS(H3,I3)-1 | K3: 0.9736 | L3: =WORKDAY('Parámetros'!$B$3-1,71) | M3: 63
A4: H3 | B4: Entrega de la infraestructura híbrida y habilitación de los ambientes de Desarrollo, QA, Preproducción y Producción, con observabilidad operativa. | C4: Etapa 1 | D4: 6 | E4: =EDATE('Parámetros'!$B$3,D4-1) | F4: 0.1 | G4: 3.1.1–3.1.3, 3.1.5, 6.6.3 | H4: =WORKDAY('Parámetros'!$B$3-1,M4+1) | I4: =WORKDAY(EOMONTH(E4,0)+1,-1-'Parámetros'!$B$4) | J4: =NETWORKDAYS(H4,I4)-1 | K4: 0.8832 | L4: =WORKDAY('Parámetros'!$B$3-1,117) | M4: 100
A5: H4 | B5: Entrega del software de la Etapa 1 para pruebas, con QA superado y evidencia de cobertura. | C5: Etapa 1 | D5: 10 | E5: =EDATE('Parámetros'!$B$3,D5-1) | F5: 0.1 | G5: 3.4, 3.6.1–3.6.4 → 3.8.1 | H5: =WORKDAY('Parámetros'!$B$3-1,M5+1) | I5: =WORKDAY(EOMONTH(E5,0)+1,-1-'Parámetros'!$B$4) | J5: =NETWORKDAYS(H5,I5)-1 | K5: 0.8654 | L5: =WORKDAY('Parámetros'!$B$3-1,206) | M5: 187
A6: H5 | B6: Certificación de la solución de la Etapa 1: pruebas de aceptación de usuario, de carga, de resiliencia y de seguridad ofensiva aprobadas. | C6: Etapa 1 | D6: 12 | E6: =EDATE('Parámetros'!$B$3,D6-1) | F6: 0.1 | G6: 3.8.2–3.8.8 | H6: =WORKDAY('Parámetros'!$B$3-1,M6+1) | I6: =WORKDAY(EOMONTH(E6,0)+1,-1-'Parámetros'!$B$4) | J6: =NETWORKDAYS(H6,I6)-1 | K6: 0.8884 | L6: =WORKDAY('Parámetros'!$B$3-1,249) | M6: 215
A7: H6 | B7: Inicio de la marcha blanca de la Etapa 1, con plan de reversión activo y usuarios capacitados. | C7: Etapa 1 | D7: 13 | E7: =EDATE('Parámetros'!$B$3,D7-1) | F7: 0.05 | G7: 4.2.1 | H7: Fecha fija del Art. 17° | I7: — | J7: — | K7: — | L7: —
A8: H7 | B8: Paso a producción de la Etapa 1 y cierre conforme de la marcha blanca. | C8: Etapa 1 | D8: 16 | E8: =EDATE('Parámetros'!$B$3,D8-1) | F8: 0.1 | G8: 4.2.3 | H8: Fecha fija del Art. 17° | I8: — | J8: — | K8: — | L8: —
A9: H8 | B9: Aprobación de la línea base de alcance de la Etapa 2 y de su diseño detallado. | C9: Etapa 2 | D9: 14 | E9: =EDATE('Parámetros'!$B$3,D9-1) | F9: 0.05 | G9: 1.2.5, 2.1.4 (acta 2.4.2) | H9: =WORKDAY('Parámetros'!$B$3-1,M9+1) | I9: =WORKDAY(EOMONTH(E9,0)+1,-1-'Parámetros'!$B$4) | J9: =NETWORKDAYS(H9,I9)-1 | K9: 0.9108 | L9: =WORKDAY('Parámetros'!$B$3-1,294) | M9: 290
A10: H9 | B10: Entrega del software de la Etapa 2 para pruebas, con QA superado. | C10: Etapa 2 | D10: 17 | E10: =EDATE('Parámetros'!$B$3,D10-1) | F10: 0.1 | G10: 3.9.1 | H10: =WORKDAY('Parámetros'!$B$3-1,M10+1) | I10: =WORKDAY(EOMONTH(E10,0)+1,-1-'Parámetros'!$B$4) | J10: =NETWORKDAYS(H10,I10)-1 | K10: 1 | L10: =WORKDAY('Parámetros'!$B$3-1,346) | M10: 338
A11: H10 | B11: Certificación de la solución de la Etapa 2 y cierre del desarrollo. | C11: Etapa 2 | D11: 18 | E11: =EDATE('Parámetros'!$B$3,D11-1) | F11: 0.1 | G11: 3.9.2–3.9.7 (acta 3.9.6) | H11: =WORKDAY('Parámetros'!$B$3-1,M11+1) | I11: =WORKDAY(EOMONTH(E11,0)+1,-1-'Parámetros'!$B$4) | J11: =NETWORKDAYS(H11,I11)-1 | K11: 1 | L11: =WORKDAY('Parámetros'!$B$3-1,369) | M11: 355
A12: H11 | B12: Inicio de la marcha blanca de la Etapa 2 en convivencia con la Etapa 1 en producción. | C12: Etapa 2 | D12: 19 | E12: =EDATE('Parámetros'!$B$3,D12-1) | F12: 0.05 | G12: 4.3.1 | H12: Fecha fija del Art. 17° | I12: — | J12: — | K12: — | L12: —
A13: H12 | B13: Paso a producción de la Etapa 2 y aceptación final del proyecto de implementación. | C13: Etapa 2 | D13: 21 | E13: =EDATE('Parámetros'!$B$3,D13-1) | F13: 0.1 | G13: 4.3.3, 4.3.4 | H13: Fecha fija del Art. 17° | I13: — | J13: — | K13: — | L13: —
B14: Total implementación | F14: =SUM(F2:F13)
B16: Cómo leer esta hoja:
B17: • Mes contractual: mes del contrato en que se firma el acta del hito (Formulario E-25). Mes calendario: ese mes según la fecha de inicio de la hoja «Parámetros».
B18: • Entrega programada: día en que LafroX termina y presenta el último entregable que gatilla el hito (Formulario T-15, Tabla 5.2).
B19: • Fecha límite de entrega: último día hábil del mes del hito menos los diez días hábiles que el CLIENTE tiene para revisar (Art. 18.3). Si LafroX entrega después de esa fecha, el acta no alcanza a firmarse dentro del mes.
B20: • Reserva: días hábiles entre la entrega programada y la fecha límite. Absorbe atrasos sin mover el hito.
B21: • Probabilidad y P80: resultado de la simulación de Monte Carlo del SD8 (Anexo 8.C). P80 es la fecha de entrega que se alcanza en el 80 % de los escenarios; queda antes de la fecha límite en todos los hitos. El H4 exige además todas las integraciones externas de la Etapa 1.
B22: • H6, H7, H11 y H12 no tienen entrega previa calculada: son el inicio o el cierre de una marcha blanca, en fechas fijas del Art. 17°. H7 y H12 se firman en un día permitido del mes, después de los tres primeros días hábiles.
B23: • Además de estos doce hitos, la Operación tiene un hito mensual en producción (36 pagos, meses 21 a 56), con descuentos por incumplimiento de niveles de servicio.

Sheet Períodos Art. 17
A1: Período contractual | B1: Mes inicio | C1: Mes fin | D1: Duración (meses) | E1: Inicio calendario | F1: Fin calendario | G1: Qué ocurre
A2: Etapa 1 · Desarrollo | B2: 1 | C2: 12 | D2: =C2-B2+1 | E2: =EDATE('Parámetros'!$B$3,B2-1) | F2: =EOMONTH(EDATE('Parámetros'!$B$3,C2-1),0) | G2: Se diseña, construye y certifica la Etapa 1 (recepción, inventario, preparación, preventa, rutas, reparto, cobranza, devoluciones, calidad, telemetría e indicadores).
A3: Etapa 1 · Marcha blanca | B3: 13 | C3: 15 | D3: =C3-B3+1 | E3: =EDATE('Parámetros'!$B$3,B3-1) | F3: =EOMONTH(EDATE('Parámetros'!$B$3,C3-1),0) | G3: La Etapa 1 opera con usuarios reales en convivencia con la forma actual de trabajo; se mide diariamente hasta cumplir las seis condiciones del Art. 17.3.
A4: Etapa 1 · Producción | B4: 16 | C4: 56 | D4: =C4-B4+1 | E4: =EDATE('Parámetros'!$B$3,B4-1) | F4: =EOMONTH(EDATE('Parámetros'!$B$3,C4-1),0) | G4: La Etapa 1 queda en producción desde el H7; hasta el mes 20 recibe soporte puente y estabilización.
A5: Etapa 2 · Desarrollo | B5: 13 | C5: 18 | D5: =C5-B5+1 | E5: =EDATE('Parámetros'!$B$3,B5-1) | F5: =EOMONTH(EDATE('Parámetros'!$B$3,C5-1),0) | G5: Se diseña, construye y certifica la Etapa 2 (canal moderno, portales y costo de servir), en paralelo con la marcha blanca de la Etapa 1 (solapamiento de los meses 13 a 15, Art. 17.2).
A6: Etapa 2 · Marcha blanca | B6: 19 | C6: 20 | D6: =C6-B6+1 | E6: =EDATE('Parámetros'!$B$3,B6-1) | F6: =EOMONTH(EDATE('Parámetros'!$B$3,C6-1),0) | G6: La Etapa 2 opera con usuarios reales en convivencia con la Etapa 1 en producción.
A7: Etapa 2 · Producción y aceptación final | B7: 21 | C7: 21 | D7: =C7-B7+1 | E7: =EDATE('Parámetros'!$B$3,B7-1) | F7: =EOMONTH(EDATE('Parámetros'!$B$3,C7-1),0) | G7: Paso a producción de la Etapa 2 y aceptación final de la implementación (H12).
A8: Operación (36 meses) | B8: 21 | C8: 56 | D8: =C8-B8+1 | E8: =EDATE('Parámetros'!$B$3,B8-1) | F8: =EOMONTH(EDATE('Parámetros'!$B$3,C8-1),0) | G8: Servicio de operación, soporte y mantenimiento con niveles de servicio, pagado con el hito mensual.
A10: Fuente: Bases Administrativas, Art. 17° (cronograma contractual obligatorio). Estos períodos no se mueven: el plan de trabajo se ajusta a ellos.

Sheet Gantt cuentas
A1: Carta Gantt por cuenta de control (49 cuentas) y períodos del Art. 17°
A2: Leyenda de colores (fase de la EDT): | I2: 1 Inicio | Q2: 2 Elaboración | Y2: 3 Construcción | AG2: 4 Transición | AO2: 5 Adquisiciones y contrataciones
I3: 6 Infraestructura física y sitios | Q3: 7 Capacitación y gestión del cambio | Y3: 8 Operación y soporte | AG3: 9 Cierre
H4: «C» y fondo naranja = mes de congelamiento (septiembre y diciembre): sin pasos a producción. Fila «Hitos E-25» = mes del acta de cada hito.
A5: Fase | B5: Cuenta | C5: Nombre | D5: Inicio (mes) | E5: Fin (mes) | F5: Duración (meses) | G5: HH (E) | H5: 1 | I5: 2 | J5: 3 | K5: 4 | L5: 5 | M5: 6 | N5: 7 | O5: 8 | P5: 9 | Q5: 10 | R5: 11 | S5: 12 | T5: 13 | U5: 14 | V5: 15 | W5: 16 | X5: 17 | Y5: 18 | Z5: 19 | AA5: 20 | AB5: 21 | AC5: 22 | AD5: 23 | AE5: 24 | AF5: 25 | AG5: 26 | AH5: 27 | AI5: 28 | AJ5: 29 | AK5: 30 | AL5: 31 | AM5: 32 | AN5: 33 | AO5: 34 | AP5: 35 | AQ5: 36 | AR5: 37 | AS5: 38 | AT5: 39 | AU5: 40 | AV5: 41 | AW5: 42 | AX5: 43 | AY5: 44 | AZ5: 45 | BA5: 46 | BB5: 47 | BC5: 48 | BD5: 49 | BE5: 50 | BF5: 51 | BG5: 52 | BH5: 53 | BI5: 54 | BJ5: 55 | BK5: 56
G6: Mes calendario | H6: =EDATE('Parámetros'!$B$3,H5-1) | I6: =EDATE('Parámetros'!$B$3,I5-1) | J6: =EDATE('Parámetros'!$B$3,J5-1) | K6: =EDATE('Parámetros'!$B$3,K5-1) | L6: =EDATE('Parámetros'!$B$3,L5-1) | M6: =EDATE('Parámetros'!$B$3,M5-1) | N6: =EDATE('Parámetros'!$B$3,N5-1) | O6: =EDATE('Parámetros'!$B$3,O5-1) | ... BK6: =EDATE('Parámetros'!$B$3,BK5-1)
G7: Congelamiento | H7: =IF(OR(MONTH(H6)=9,MONTH(H6)=12),"C","") | I7: =IF(OR(MONTH(I6)=9,MONTH(I6)=12),"C","") | J7: =IF(OR(MONTH(J6)=9,MONTH(J6)=12),"C","") | K7: =IF(OR(MONTH(K6)=9,MONTH(K6)=12),"C","") | L7: =IF(OR(MONTH(L6)=9,MONTH(L6)=12),"C","") | M7: =IF(OR(MONTH(M6)=9,MONTH(M6)=12),"C","") | N7: =IF(OR(MONTH(N6)=9,MONTH(N6)=12),"C","") | O7: =IF(OR(MONTH(O6)=9,MONTH(O6)=12),"C","") | ... BK7: =IF(OR(MONTH(BK6)=9,MONTH(BK6)=12),"C","")
G8: Hitos E-25 | H8: {=IFERROR(INDEX(Hitos!$A$2:$A$13,MATCH(H5,Hitos!$D$2:$D$13,0)),"")} | I8: {=IFERROR(INDEX(Hitos!$A$2:$A$13,MATCH(I5,Hitos!$D$2:$D$13,0)),"")} | J8: {=IFERROR(INDEX(Hitos!$A$2:$A$13,MATCH(J5,Hitos!$D$2:$D$13,0)),"")} | K8: {=IFERROR(INDEX(Hitos!$A$2:$A$13,MATCH(K5,Hitos!$D$2:$D$13,0)),"")} | L8: {=IFERROR(INDEX(Hitos!$A$2:$A$13,MATCH(L5,Hitos!$D$2:$D$13,0)),"")} | M8: {=IFERROR(INDEX(Hitos!$A$2:$A$13,MATCH(M5,Hitos!$D$2:$D$13,0)),"")} | N8: {=IFERROR(INDEX(Hitos!$A$2:$A$13,MATCH(N5,Hitos!$D$2:$D$13,0)),"")} | O8: {=IFERROR(INDEX(Hitos!$A$2:$A$13,MATCH(O5,Hitos!$D$2:$D$13,0)),"")} | ... BK8: {=IFERROR(INDEX(Hitos!$A$2:$A$13,MATCH(BK5,Hitos!$D$2:$D$13,0)),"")}
A9: Período | B9: Art. 17 | C9: Etapa 1 · Desarrollo | D9: 1 | E9: 12 | F9: =E9-D9+1 | H9: =IF(AND(H$5>=$D9,H$5<=$E9),0,"") | I9: =IF(AND(I$5>=$D9,I$5<=$E9),0,"") | J9: =IF(AND(J$5>=$D9,J$5<=$E9),0,"") | K9: =IF(AND(K$5>=$D9,K$5<=$E9),0,"") | L9: =IF(AND(L$5>=$D9,L$5<=$E9),0,"") | M9: =IF(AND(M$5>=$D9,M$5<=$E9),0,"") | N9: =IF(AND(N$5>=$D9,N$5<=$E9),0,"") | O9: =IF(AND(O$5>=$D9,O$5<=$E9),0,"") | ... BK9: =IF(AND(BK$5>=$D9,BK$5<=$E9),0,"")
A10: Período | B10: Art. 17 | C10: Etapa 1 · Marcha blanca | D10: 13 | E10: 15 | F10: =E10-D10+1 | H10: =IF(AND(H$5>=$D10,H$5<=$E10),0,"") | I10: =IF(AND(I$5>=$D10,I$5<=$E10),0,"") | J10: =IF(AND(J$5>=$D10,J$5<=$E10),0,"") | K10: =IF(AND(K$5>=$D10,K$5<=$E10),0,"") | L10: =IF(AND(L$5>=$D10,L$5<=$E10),0,"") | M10: =IF(AND(M$5>=$D10,M$5<=$E10),0,"") | N10: =IF(AND(N$5>=$D10,N$5<=$E10),0,"") | O10: =IF(AND(O$5>=$D10,O$5<=$E10),0,"") | ... BK10: =IF(AND(BK$5>=$D10,BK$5<=$E10),0,"")
A11: Período | B11: Art. 17 | C11: Etapa 1 · Producción | D11: 16 | E11: 56 | F11: =E11-D11+1 | H11: =IF(AND(H$5>=$D11,H$5<=$E11),0,"") | I11: =IF(AND(I$5>=$D11,I$5<=$E11),0,"") | J11: =IF(AND(J$5>=$D11,J$5<=$E11),0,"") | K11: =IF(AND(K$5>=$D11,K$5<=$E11),0,"") | L11: =IF(AND(L$5>=$D11,L$5<=$E11),0,"") | M11: =IF(AND(M$5>=$D11,M$5<=$E11),0,"") | N11: =IF(AND(N$5>=$D11,N$5<=$E11),0,"") | O11: =IF(AND(O$5>=$D11,O$5<=$E11),0,"") | ... BK11: =IF(AND(BK$5>=$D11,BK$5<=$E11),0,"")
A12: Período | B12: Art. 17 | C12: Etapa 2 · Desarrollo | D12: 13 | E12: 18 | F12: =E12-D12+1 | H12: =IF(AND(H$5>=$D12,H$5<=$E12),0,"") | I12: =IF(AND(I$5>=$D12,I$5<=$E12),0,"") | J12: =IF(AND(J$5>=$D12,J$5<=$E12),0,"") | K12: =IF(AND(K$5>=$D12,K$5<=$E12),0,"") | L12: =IF(AND(L$5>=$D12,L$5<=$E12),0,"") | M12: =IF(AND(M$5>=$D12,M$5<=$E12),0,"") | N12: =IF(AND(N$5>=$D12,N$5<=$E12),0,"") | O12: =IF(AND(O$5>=$D12,O$5<=$E12),0,"") | ... BK12: =IF(AND(BK$5>=$D12,BK$5<=$E12),0,"")
A13: Período | B13: Art. 17 | C13: Etapa 2 · Marcha blanca | D13: 19 | E13: 20 | F13: =E13-D13+1 | H13: =IF(AND(H$5>=$D13,H$5<=$E13),0,"") | I13: =IF(AND(I$5>=$D13,I$5<=$E13),0,"") | J13: =IF(AND(J$5>=$D13,J$5<=$E13),0,"") | K13: =IF(AND(K$5>=$D13,K$5<=$E13),0,"") | L13: =IF(AND(L$5>=$D13,L$5<=$E13),0,"") | M13: =IF(AND(M$5>=$D13,M$5<=$E13),0,"") | N13: =IF(AND(N$5>=$D13,N$5<=$E13),0,"") | O13: =IF(AND(O$5>=$D13,O$5<=$E13),0,"") | ... BK13: =IF(AND(BK$5>=$D13,BK$5<=$E13),0,"")
A14: Período | B14: Art. 17 | C14: Etapa 2 · Producción y aceptación final | D14: 21 | E14: 21 | F14: =E14-D14+1 | H14: =IF(AND(H$5>=$D14,H$5<=$E14),0,"") | I14: =IF(AND(I$5>=$D14,I$5<=$E14),0,"") | J14: =IF(AND(J$5>=$D14,J$5<=$E14),0,"") | K14: =IF(AND(K$5>=$D14,K$5<=$E14),0,"") | L14: =IF(AND(L$5>=$D14,L$5<=$E14),0,"") | M14: =IF(AND(M$5>=$D14,M$5<=$E14),0,"") | N14: =IF(AND(N$5>=$D14,N$5<=$E14),0,"") | O14: =IF(AND(O$5>=$D14,O$5<=$E14),0,"") | ... BK14: =IF(AND(BK$5>=$D14,BK$5<=$E14),0,"")
A15: Período | B15: Art. 17 | C15: Operación (36 meses) | D15: 21 | E15: 56 | F15: =E15-D15+1 | H15: =IF(AND(H$5>=$D15,H$5<=$E15),0,"") | I15: =IF(AND(I$5>=$D15,I$5<=$E15),0,"") | J15: =IF(AND(J$5>=$D15,J$5<=$E15),0,"") | K15: =IF(AND(K$5>=$D15,K$5<=$E15),0,"") | L15: =IF(AND(L$5>=$D15,L$5<=$E15),0,"") | M15: =IF(AND(M$5>=$D15,M$5<=$E15),0,"") | N15: =IF(AND(N$5>=$D15,N$5<=$E15),0,"") | O15: =IF(AND(O$5>=$D15,O$5<=$E15),0,"") | ... BK15: =IF(AND(BK$5>=$D15,BK$5<=$E15),0,"")
A16: 1 Inicio | B16: 1.1 | C16: Definición inicial del proyecto | D16: 1 | E16: 1 | F16: =E16-D16+1 | G16: 240 | H16: =IF(AND(H$5>=$D16,H$5<=$E16),1,"") | I16: =IF(AND(I$5>=$D16,I$5<=$E16),1,"") | J16: =IF(AND(J$5>=$D16,J$5<=$E16),1,"") | K16: =IF(AND(K$5>=$D16,K$5<=$E16),1,"") | L16: =IF(AND(L$5>=$D16,L$5<=$E16),1,"") | M16: =IF(AND(M$5>=$D16,M$5<=$E16),1,"") | N16: =IF(AND(N$5>=$D16,N$5<=$E16),1,"") | O16: =IF(AND(O$5>=$D16,O$5<=$E16),1,"") | ... BK16: =IF(AND(BK$5>=$D16,BK$5<=$E16),1,"")
A17: 1 Inicio | B17: 1.2 | C17: Alcance del proyecto | D17: 1 | E17: 13 | F17: =E17-D17+1 | G17: 400 | H17: =IF(AND(H$5>=$D17,H$5<=$E17),1,"") | I17: =IF(AND(I$5>=$D17,I$5<=$E17),1,"") | J17: =IF(AND(J$5>=$D17,J$5<=$E17),1,"") | K17: =IF(AND(K$5>=$D17,K$5<=$E17),1,"") | L17: =IF(AND(L$5>=$D17,L$5<=$E17),1,"") | M17: =IF(AND(M$5>=$D17,M$5<=$E17),1,"") | N17: =IF(AND(N$5>=$D17,N$5<=$E17),1,"") | O17: =IF(AND(O$5>=$D17,O$5<=$E17),1,"") | ... BK17: =IF(AND(BK$5>=$D17,BK$5<=$E17),1,"")
A18: 1 Inicio | B18: 1.3 | C18: Planificación del proyecto | D18: 1 | E18: 20 | F18: =E18-D18+1 | G18: 800 | H18: =IF(AND(H$5>=$D18,H$5<=$E18),1,"") | I18: =IF(AND(I$5>=$D18,I$5<=$E18),1,"") | J18: =IF(AND(J$5>=$D18,J$5<=$E18),1,"") | K18: =IF(AND(K$5>=$D18,K$5<=$E18),1,"") | L18: =IF(AND(L$5>=$D18,L$5<=$E18),1,"") | M18: =IF(AND(M$5>=$D18,M$5<=$E18),1,"") | N18: =IF(AND(N$5>=$D18,N$5<=$E18),1,"") | O18: =IF(AND(O$5>=$D18,O$5<=$E18),1,"") | ... BK18: =IF(AND(BK$5>=$D18,BK$5<=$E18),1,"")
A19: 1 Inicio | B19: 1.4 | C19: Gestión de interesados y comunicaciones | D19: 1 | E19: 56 | F19: =E19-D19+1 | G19: 1056 | H19: =IF(AND(H$5>=$D19,H$5<=$E19),1,"") | I19: =IF(AND(I$5>=$D19,I$5<=$E19),1,"") | J19: =IF(AND(J$5>=$D19,J$5<=$E19),1,"") | K19: =IF(AND(K$5>=$D19,K$5<=$E19),1,"") | L19: =IF(AND(L$5>=$D19,L$5<=$E19),1,"") | M19: =IF(AND(M$5>=$D19,M$5<=$E19),1,"") | N19: =IF(AND(N$5>=$D19,N$5<=$E19),1,"") | O19: =IF(AND(O$5>=$D19,O$5<=$E19),1,"") | ... BK19: =IF(AND(BK$5>=$D19,BK$5<=$E19),1,"")
A20: 1 Inicio | B20: 1.5 | C20: Gestión de calidad | D20: 2 | E20: 20 | F20: =E20-D20+1 | G20: 160 | H20: =IF(AND(H$5>=$D20,H$5<=$E20),1,"") | I20: =IF(AND(I$5>=$D20,I$5<=$E20),1,"") | J20: =IF(AND(J$5>=$D20,J$5<=$E20),1,"") | K20: =IF(AND(K$5>=$D20,K$5<=$E20),1,"") | L20: =IF(AND(L$5>=$D20,L$5<=$E20),1,"") | M20: =IF(AND(M$5>=$D20,M$5<=$E20),1,"") | N20: =IF(AND(N$5>=$D20,N$5<=$E20),1,"") | O20: =IF(AND(O$5>=$D20,O$5<=$E20),1,"") | ... BK20: =IF(AND(BK$5>=$D20,BK$5<=$E20),1,"")
A21: 1 Inicio | B21: 1.6 | C21: Gestión de riesgos | D21: 1 | E21: 20 | F21: =E21-D21+1 | G21: 240 | H21: =IF(AND(H$5>=$D21,H$5<=$E21),1,"") | I21: =IF(AND(I$5>=$D21,I$5<=$E21),1,"") | J21: =IF(AND(J$5>=$D21,J$5<=$E21),1,"") | K21: =IF(AND(K$5>=$D21,K$5<=$E21),1,"") | L21: =IF(AND(L$5>=$D21,L$5<=$E21),1,"") | M21: =IF(AND(M$5>=$D21,M$5<=$E21),1,"") | N21: =IF(AND(N$5>=$D21,N$5<=$E21),1,"") | O21: =IF(AND(O$5>=$D21,O$5<=$E21),1,"") | ... BK21: =IF(AND(BK$5>=$D21,BK$5<=$E21),1,"")
A22: 1 Inicio | B22: 1.7 | C22: Plan de Reversibilidad | D22: 3 | E22: 15 | F22: =E22-D22+1 | G22: 160 | H22: =IF(AND(H$5>=$D22,H$5<=$E22),1,"") | I22: =IF(AND(I$5>=$D22,I$5<=$E22),1,"") | J22: =IF(AND(J$5>=$D22,J$5<=$E22),1,"") | K22: =IF(AND(K$5>=$D22,K$5<=$E22),1,"") | L22: =IF(AND(L$5>=$D22,L$5<=$E22),1,"") | M22: =IF(AND(M$5>=$D22,M$5<=$E22),1,"") | N22: =IF(AND(N$5>=$D22,N$5<=$E22),1,"") | O22: =IF(AND(O$5>=$D22,O$5<=$E22),1,"") | ... BK22: =IF(AND(BK$5>=$D22,BK$5<=$E22),1,"")
A23: 1 Inicio | B23: 1.8 | C23: Gobierno y control del proyecto | D23: 1 | E23: 56 | F23: =E23-D23+1 | G23: 3176 | H23: =IF(AND(H$5>=$D23,H$5<=$E23),1,"") | I23: =IF(AND(I$5>=$D23,I$5<=$E23),1,"") | J23: =IF(AND(J$5>=$D23,J$5<=$E23),1,"") | K23: =IF(AND(K$5>=$D23,K$5<=$E23),1,"") | L23: =IF(AND(L$5>=$D23,L$5<=$E23),1,"") | M23: =IF(AND(M$5>=$D23,M$5<=$E23),1,"") | N23: =IF(AND(N$5>=$D23,N$5<=$E23),1,"") | O23: =IF(AND(O$5>=$D23,O$5<=$E23),1,"") | ... BK23: =IF(AND(BK$5>=$D23,BK$5<=$E23),1,"")
A24: 1 Inicio | B24: 1.9 | C24: Cumplimiento normativo y contractual | D24: 1 | E24: 56 | F24: =E24-D24+1 | G24: 688 | H24: =IF(AND(H$5>=$D24,H$5<=$E24),1,"") | I24: =IF(AND(I$5>=$D24,I$5<=$E24),1,"") | J24: =IF(AND(J$5>=$D24,J$5<=$E24),1,"") | K24: =IF(AND(K$5>=$D24,K$5<=$E24),1,"") | L24: =IF(AND(L$5>=$D24,L$5<=$E24),1,"") | M24: =IF(AND(M$5>=$D24,M$5<=$E24),1,"") | N24: =IF(AND(N$5>=$D24,N$5<=$E24),1,"") | O24: =IF(AND(O$5>=$D24,O$5<=$E24),1,"") | ... BK24: =IF(AND(BK$5>=$D24,BK$5<=$E24),1,"")
A25: 2 Elaboración | B25: 2.1 | C25: Arquitectura de la solución | D25: 2 | E25: 13 | F25: =E25-D25+1 | G25: 960 | H25: =IF(AND(H$5>=$D25,H$5<=$E25),2,"") | I25: =IF(AND(I$5>=$D25,I$5<=$E25),2,"") | J25: =IF(AND(J$5>=$D25,J$5<=$E25),2,"") | K25: =IF(AND(K$5>=$D25,K$5<=$E25),2,"") | L25: =IF(AND(L$5>=$D25,L$5<=$E25),2,"") | M25: =IF(AND(M$5>=$D25,M$5<=$E25),2,"") | N25: =IF(AND(N$5>=$D25,N$5<=$E25),2,"") | O25: =IF(AND(O$5>=$D25,O$5<=$E25),2,"") | ... BK25: =IF(AND(BK$5>=$D25,BK$5<=$E25),2,"")
A26: 2 Elaboración | B26: 2.2 | C26: Diseño de la seguridad | D26: 2 | E26: 10 | F26: =E26-D26+1 | G26: 960 | H26: =IF(AND(H$5>=$D26,H$5<=$E26),2,"") | I26: =IF(AND(I$5>=$D26,I$5<=$E26),2,"") | J26: =IF(AND(J$5>=$D26,J$5<=$E26),2,"") | K26: =IF(AND(K$5>=$D26,K$5<=$E26),2,"") | L26: =IF(AND(L$5>=$D26,L$5<=$E26),2,"") | M26: =IF(AND(M$5>=$D26,M$5<=$E26),2,"") | N26: =IF(AND(N$5>=$D26,N$5<=$E26),2,"") | O26: =IF(AND(O$5>=$D26,O$5<=$E26),2,"") | ... BK26: =IF(AND(BK$5>=$D26,BK$5<=$E26),2,"")
A27: 2 Elaboración | B27: 2.3 | C27: Diseño de la sala técnica y de los racks | D27: 1 | E27: 2 | F27: =E27-D27+1 | G27: 720 | H27: =IF(AND(H$5>=$D27,H$5<=$E27),2,"") | I27: =IF(AND(I$5>=$D27,I$5<=$E27),2,"") | J27: =IF(AND(J$5>=$D27,J$5<=$E27),2,"") | K27: =IF(AND(K$5>=$D27,K$5<=$E27),2,"") | L27: =IF(AND(L$5>=$D27,L$5<=$E27),2,"") | M27: =IF(AND(M$5>=$D27,M$5<=$E27),2,"") | N27: =IF(AND(N$5>=$D27,N$5<=$E27),2,"") | O27: =IF(AND(O$5>=$D27,O$5<=$E27),2,"") | ... BK27: =IF(AND(BK$5>=$D27,BK$5<=$E27),2,"")
A28: 2 Elaboración | B28: 2.4 | C28: Validación de diseños | D28: 3 | E28: 14 | F28: =E28-D28+1 | G28: 480 | H28: =IF(AND(H$5>=$D28,H$5<=$E28),2,"") | I28: =IF(AND(I$5>=$D28,I$5<=$E28),2,"") | J28: =IF(AND(J$5>=$D28,J$5<=$E28),2,"") | K28: =IF(AND(K$5>=$D28,K$5<=$E28),2,"") | L28: =IF(AND(L$5>=$D28,L$5<=$E28),2,"") | M28: =IF(AND(M$5>=$D28,M$5<=$E28),2,"") | N28: =IF(AND(N$5>=$D28,N$5<=$E28),2,"") | O28: =IF(AND(O$5>=$D28,O$5<=$E28),2,"") | ... BK28: =IF(AND(BK$5>=$D28,BK$5<=$E28),2,"")
A29: 2 Elaboración | B29: 2.5 | C29: Continuidad del negocio | D29: 3 | E29: 3 | F29: =E29-D29+1 | G29: 480 | H29: =IF(AND(H$5>=$D29,H$5<=$E29),2,"") | I29: =IF(AND(I$5>=$D29,I$5<=$E29),2,"") | J29: =IF(AND(J$5>=$D29,J$5<=$E29),2,"") | K29: =IF(AND(K$5>=$D29,K$5<=$E29),2,"") | L29: =IF(AND(L$5>=$D29,L$5<=$E29),2,"") | M29: =IF(AND(M$5>=$D29,M$5<=$E29),2,"") | N29: =IF(AND(N$5>=$D29,N$5<=$E29),2,"") | O29: =IF(AND(O$5>=$D29,O$5<=$E29),2,"") | ... BK29: =IF(AND(BK$5>=$D29,BK$5<=$E29),2,"")
A30: 2 Elaboración | B30: 2.6 | C30: Experiencia de usuario | D30: 2 | E30: 4 | F30: =E30-D30+1 | G30: 720 | H30: =IF(AND(H$5>=$D30,H$5<=$E30),2,"") | I30: =IF(AND(I$5>=$D30,I$5<=$E30),2,"") | J30: =IF(AND(J$5>=$D30,J$5<=$E30),2,"") | K30: =IF(AND(K$5>=$D30,K$5<=$E30),2,"") | L30: =IF(AND(L$5>=$D30,L$5<=$E30),2,"") | M30: =IF(AND(M$5>=$D30,M$5<=$E30),2,"") | N30: =IF(AND(N$5>=$D30,N$5<=$E30),2,"") | O30: =IF(AND(O$5>=$D30,O$5<=$E30),2,"") | ... BK30: =IF(AND(BK$5>=$D30,BK$5<=$E30),2,"")
A31: 3 Construcción | B31: 3.1 | C31: Ambientes y cadena de desarrollo | D31: 4 | E31: 5 | F31: =E31-D31+1 | G31: 1200 | H31: =IF(AND(H$5>=$D31,H$5<=$E31),3,"") | I31: =IF(AND(I$5>=$D31,I$5<=$E31),3,"") | J31: =IF(AND(J$5>=$D31,J$5<=$E31),3,"") | K31: =IF(AND(K$5>=$D31,K$5<=$E31),3,"") | L31: =IF(AND(L$5>=$D31,L$5<=$E31),3,"") | M31: =IF(AND(M$5>=$D31,M$5<=$E31),3,"") | N31: =IF(AND(N$5>=$D31,N$5<=$E31),3,"") | O31: =IF(AND(O$5>=$D31,O$5<=$E31),3,"") | ... BK31: =IF(AND(BK$5>=$D31,BK$5<=$E31),3,"")
A32: 3 Construcción | B32: 3.2 | C32: Servicios de nube de la plataforma | D32: 4 | E32: 5 | F32: =E32-D32+1 | G32: 1440 | H32: =IF(AND(H$5>=$D32,H$5<=$E32),3,"") | I32: =IF(AND(I$5>=$D32,I$5<=$E32),3,"") | J32: =IF(AND(J$5>=$D32,J$5<=$E32),3,"") | K32: =IF(AND(K$5>=$D32,K$5<=$E32),3,"") | L32: =IF(AND(L$5>=$D32,L$5<=$E32),3,"") | M32: =IF(AND(M$5>=$D32,M$5<=$E32),3,"") | N32: =IF(AND(N$5>=$D32,N$5<=$E32),3,"") | O32: =IF(AND(O$5>=$D32,O$5<=$E32),3,"") | ... BK32: =IF(AND(BK$5>=$D32,BK$5<=$E32),3,"")
A33: 3 Construcción | B33: 3.3 | C33: Base compartida | D33: 5 | E33: 7 | F33: =E33-D33+1 | G33: 2880 | H33: =IF(AND(H$5>=$D33,H$5<=$E33),3,"") | I33: =IF(AND(I$5>=$D33,I$5<=$E33),3,"") | J33: =IF(AND(J$5>=$D33,J$5<=$E33),3,"") | K33: =IF(AND(K$5>=$D33,K$5<=$E33),3,"") | L33: =IF(AND(L$5>=$D33,L$5<=$E33),3,"") | M33: =IF(AND(M$5>=$D33,M$5<=$E33),3,"") | N33: =IF(AND(N$5>=$D33,N$5<=$E33),3,"") | O33: =IF(AND(O$5>=$D33,O$5<=$E33),3,"") | ... BK33: =IF(AND(BK$5>=$D33,BK$5<=$E33),3,"")
A34: 3 Construcción | B34: 3.4 | C34: Módulos de la Etapa 1 | D34: 5 | E34: 8 | F34: =E34-D34+1 | G34: 10560 | H34: =IF(AND(H$5>=$D34,H$5<=$E34),3,"") | I34: =IF(AND(I$5>=$D34,I$5<=$E34),3,"") | J34: =IF(AND(J$5>=$D34,J$5<=$E34),3,"") | K34: =IF(AND(K$5>=$D34,K$5<=$E34),3,"") | L34: =IF(AND(L$5>=$D34,L$5<=$E34),3,"") | M34: =IF(AND(M$5>=$D34,M$5<=$E34),3,"") | N34: =IF(AND(N$5>=$D34,N$5<=$E34),3,"") | O34: =IF(AND(O$5>=$D34,O$5<=$E34),3,"") | ... BK34: =IF(AND(BK$5>=$D34,BK$5<=$E34),3,"")
A35: 3 Construcción | B35: 3.5 | C35: Módulos de la Etapa 2 | D35: 15 | E35: 15 | F35: =E35-D35+1 | G35: 3840 | H35: =IF(AND(H$5>=$D35,H$5<=$E35),3,"") | I35: =IF(AND(I$5>=$D35,I$5<=$E35),3,"") | J35: =IF(AND(J$5>=$D35,J$5<=$E35),3,"") | K35: =IF(AND(K$5>=$D35,K$5<=$E35),3,"") | L35: =IF(AND(L$5>=$D35,L$5<=$E35),3,"") | M35: =IF(AND(M$5>=$D35,M$5<=$E35),3,"") | N35: =IF(AND(N$5>=$D35,N$5<=$E35),3,"") | O35: =IF(AND(O$5>=$D35,O$5<=$E35),3,"") | ... BK35: =IF(AND(BK$5>=$D35,BK$5<=$E35),3,"")
A36: 3 Construcción | B36: 3.6 | C36: Integraciones externas | D36: 6 | E36: 19 | F36: =E36-D36+1 | G36: 2880 | H36: =IF(AND(H$5>=$D36,H$5<=$E36),3,"") | I36: =IF(AND(I$5>=$D36,I$5<=$E36),3,"") | J36: =IF(AND(J$5>=$D36,J$5<=$E36),3,"") | K36: =IF(AND(K$5>=$D36,K$5<=$E36),3,"") | L36: =IF(AND(L$5>=$D36,L$5<=$E36),3,"") | M36: =IF(AND(M$5>=$D36,M$5<=$E36),3,"") | N36: =IF(AND(N$5>=$D36,N$5<=$E36),3,"") | O36: =IF(AND(O$5>=$D36,O$5<=$E36),3,"") | ... BK36: =IF(AND(BK$5>=$D36,BK$5<=$E36),3,"")
A37: 3 Construcción | B37: 3.7 | C37: Migración de datos | D37: 7 | E37: 12 | F37: =E37-D37+1 | G37: 2400 | H37: =IF(AND(H$5>=$D37,H$5<=$E37),3,"") | I37: =IF(AND(I$5>=$D37,I$5<=$E37),3,"") | J37: =IF(AND(J$5>=$D37,J$5<=$E37),3,"") | K37: =IF(AND(K$5>=$D37,K$5<=$E37),3,"") | L37: =IF(AND(L$5>=$D37,L$5<=$E37),3,"") | M37: =IF(AND(M$5>=$D37,M$5<=$E37),3,"") | N37: =IF(AND(N$5>=$D37,N$5<=$E37),3,"") | O37: =IF(AND(O$5>=$D37,O$5<=$E37),3,"") | ... BK37: =IF(AND(BK$5>=$D37,BK$5<=$E37),3,"")
A38: 3 Construcción | B38: 3.8 | C38: Pruebas de la Etapa 1 | D38: 9 | E38: 10 | F38: =E38-D38+1 | G38: 2080 | H38: =IF(AND(H$5>=$D38,H$5<=$E38),3,"") | I38: =IF(AND(I$5>=$D38,I$5<=$E38),3,"") | J38: =IF(AND(J$5>=$D38,J$5<=$E38),3,"") | K38: =IF(AND(K$5>=$D38,K$5<=$E38),3,"") | L38: =IF(AND(L$5>=$D38,L$5<=$E38),3,"") | M38: =IF(AND(M$5>=$D38,M$5<=$E38),3,"") | N38: =IF(AND(N$5>=$D38,N$5<=$E38),3,"") | O38: =IF(AND(O$5>=$D38,O$5<=$E38),3,"") | ... BK38: =IF(AND(BK$5>=$D38,BK$5<=$E38),3,"")
A39: 3 Construcción | B39: 3.9 | C39: Pruebas de la Etapa 2 | D39: 16 | E39: 17 | F39: =E39-D39+1 | G39: 1760 | H39: =IF(AND(H$5>=$D39,H$5<=$E39),3,"") | I39: =IF(AND(I$5>=$D39,I$5<=$E39),3,"") | J39: =IF(AND(J$5>=$D39,J$5<=$E39),3,"") | K39: =IF(AND(K$5>=$D39,K$5<=$E39),3,"") | L39: =IF(AND(L$5>=$D39,L$5<=$E39),3,"") | M39: =IF(AND(M$5>=$D39,M$5<=$E39),3,"") | N39: =IF(AND(N$5>=$D39,N$5<=$E39),3,"") | O39: =IF(AND(O$5>=$D39,O$5<=$E39),3,"") | ... BK39: =IF(AND(BK$5>=$D39,BK$5<=$E39),3,"")
A40: 3 Construcción | B40: 3.10 | C40: Innovaciones | D40: 2 | E40: 21 | F40: =E40-D40+1 | G40: 3840 | H40: =IF(AND(H$5>=$D40,H$5<=$E40),3,"") | I40: =IF(AND(I$5>=$D40,I$5<=$E40),3,"") | J40: =IF(AND(J$5>=$D40,J$5<=$E40),3,"") | K40: =IF(AND(K$5>=$D40,K$5<=$E40),3,"") | L40: =IF(AND(L$5>=$D40,L$5<=$E40),3,"") | M40: =IF(AND(M$5>=$D40,M$5<=$E40),3,"") | N40: =IF(AND(N$5>=$D40,N$5<=$E40),3,"") | O40: =IF(AND(O$5>=$D40,O$5<=$E40),3,"") | ... BK40: =IF(AND(BK$5>=$D40,BK$5<=$E40),3,"")
A41: 3 Construcción | B41: 3.11 | C41: Documentación técnica | D41: 4 | E41: 21 | F41: =E41-D41+1 | G41: 400 | H41: =IF(AND(H$5>=$D41,H$5<=$E41),3,"") | I41: =IF(AND(I$5>=$D41,I$5<=$E41),3,"") | J41: =IF(AND(J$5>=$D41,J$5<=$E41),3,"") | K41: =IF(AND(K$5>=$D41,K$5<=$E41),3,"") | L41: =IF(AND(L$5>=$D41,L$5<=$E41),3,"") | M41: =IF(AND(M$5>=$D41,M$5<=$E41),3,"") | N41: =IF(AND(N$5>=$D41,N$5<=$E41),3,"") | O41: =IF(AND(O$5>=$D41,O$5<=$E41),3,"") | ... BK41: =IF(AND(BK$5>=$D41,BK$5<=$E41),3,"")
A42: 4 Transición | B42: 4.1 | C42: Plan de implantación | D42: 10 | E42: 17 | F42: =E42-D42+1 | G42: 240 | H42: =IF(AND(H$5>=$D42,H$5<=$E42),4,"") | I42: =IF(AND(I$5>=$D42,I$5<=$E42),4,"") | J42: =IF(AND(J$5>=$D42,J$5<=$E42),4,"") | K42: =IF(AND(K$5>=$D42,K$5<=$E42),4,"") | L42: =IF(AND(L$5>=$D42,L$5<=$E42),4,"") | M42: =IF(AND(M$5>=$D42,M$5<=$E42),4,"") | N42: =IF(AND(N$5>=$D42,N$5<=$E42),4,"") | O42: =IF(AND(O$5>=$D42,O$5<=$E42),4,"") | ... BK42: =IF(AND(BK$5>=$D42,BK$5<=$E42),4,"")
A43: 4 Transición | B43: 4.2 | C43: Marcha blanca y producción de la Etapa 1 | D43: 13 | E43: 20 | F43: =E43-D43+1 | G43: 12880 | H43: =IF(AND(H$5>=$D43,H$5<=$E43),4,"") | I43: =IF(AND(I$5>=$D43,I$5<=$E43),4,"") | J43: =IF(AND(J$5>=$D43,J$5<=$E43),4,"") | K43: =IF(AND(K$5>=$D43,K$5<=$E43),4,"") | L43: =IF(AND(L$5>=$D43,L$5<=$E43),4,"") | M43: =IF(AND(M$5>=$D43,M$5<=$E43),4,"") | N43: =IF(AND(N$5>=$D43,N$5<=$E43),4,"") | O43: =IF(AND(O$5>=$D43,O$5<=$E43),4,"") | ... BK43: =IF(AND(BK$5>=$D43,BK$5<=$E43),4,"")
A44: 4 Transición | B44: 4.3 | C44: Marcha blanca y producción de la Etapa 2 | D44: 19 | E44: 22 | F44: =E44-D44+1 | G44: 7552 | H44: =IF(AND(H$5>=$D44,H$5<=$E44),4,"") | I44: =IF(AND(I$5>=$D44,I$5<=$E44),4,"") | J44: =IF(AND(J$5>=$D44,J$5<=$E44),4,"") | K44: =IF(AND(K$5>=$D44,K$5<=$E44),4,"") | L44: =IF(AND(L$5>=$D44,L$5<=$E44),4,"") | M44: =IF(AND(M$5>=$D44,M$5<=$E44),4,"") | N44: =IF(AND(N$5>=$D44,N$5<=$E44),4,"") | O44: =IF(AND(O$5>=$D44,O$5<=$E44),4,"") | ... BK44: =IF(AND(BK$5>=$D44,BK$5<=$E44),4,"")
A45: 5 Adquisiciones y contrataciones | B45: 5.1 | C45: Hardware e infraestructura | D45: 2 | E45: 5 | F45: =E45-D45+1 | G45: 240 | H45: =IF(AND(H$5>=$D45,H$5<=$E45),5,"") | I45: =IF(AND(I$5>=$D45,I$5<=$E45),5,"") | J45: =IF(AND(J$5>=$D45,J$5<=$E45),5,"") | K45: =IF(AND(K$5>=$D45,K$5<=$E45),5,"") | L45: =IF(AND(L$5>=$D45,L$5<=$E45),5,"") | M45: =IF(AND(M$5>=$D45,M$5<=$E45),5,"") | N45: =IF(AND(N$5>=$D45,N$5<=$E45),5,"") | O45: =IF(AND(O$5>=$D45,O$5<=$E45),5,"") | ... BK45: =IF(AND(BK$5>=$D45,BK$5<=$E45),5,"")
A46: 5 Adquisiciones y contrataciones | B46: 5.2 | C46: Servicios de nube y licencias | D46: 2 | E46: 4 | F46: =E46-D46+1 | G46: 240 | H46: =IF(AND(H$5>=$D46,H$5<=$E46),5,"") | I46: =IF(AND(I$5>=$D46,I$5<=$E46),5,"") | J46: =IF(AND(J$5>=$D46,J$5<=$E46),5,"") | K46: =IF(AND(K$5>=$D46,K$5<=$E46),5,"") | L46: =IF(AND(L$5>=$D46,L$5<=$E46),5,"") | M46: =IF(AND(M$5>=$D46,M$5<=$E46),5,"") | N46: =IF(AND(N$5>=$D46,N$5<=$E46),5,"") | O46: =IF(AND(O$5>=$D46,O$5<=$E46),5,"") | ... BK46: =IF(AND(BK$5>=$D46,BK$5<=$E46),5,"")
A47: 5 Adquisiciones y contrataciones | B47: 5.3 | C47: Enlaces de comunicaciones | D47: 4 | E47: 4 | F47: =E47-D47+1 | G47: 240 | H47: =IF(AND(H$5>=$D47,H$5<=$E47),5,"") | I47: =IF(AND(I$5>=$D47,I$5<=$E47),5,"") | J47: =IF(AND(J$5>=$D47,J$5<=$E47),5,"") | K47: =IF(AND(K$5>=$D47,K$5<=$E47),5,"") | L47: =IF(AND(L$5>=$D47,L$5<=$E47),5,"") | M47: =IF(AND(M$5>=$D47,M$5<=$E47),5,"") | N47: =IF(AND(N$5>=$D47,N$5<=$E47),5,"") | O47: =IF(AND(O$5>=$D47,O$5<=$E47),5,"") | ... BK47: =IF(AND(BK$5>=$D47,BK$5<=$E47),5,"")
A48: 5 Adquisiciones y contrataciones | B48: 5.4 | C48: Acuerdos con terceros | D48: 7 | E48: 20 | F48: =E48-D48+1 | G48: 320 | H48: =IF(AND(H$5>=$D48,H$5<=$E48),5,"") | I48: =IF(AND(I$5>=$D48,I$5<=$E48),5,"") | J48: =IF(AND(J$5>=$D48,J$5<=$E48),5,"") | K48: =IF(AND(K$5>=$D48,K$5<=$E48),5,"") | L48: =IF(AND(L$5>=$D48,L$5<=$E48),5,"") | M48: =IF(AND(M$5>=$D48,M$5<=$E48),5,"") | N48: =IF(AND(N$5>=$D48,N$5<=$E48),5,"") | O48: =IF(AND(O$5>=$D48,O$5<=$E48),5,"") | ... BK48: =IF(AND(BK$5>=$D48,BK$5<=$E48),5,"")
A49: 6 Infraestructura física y sitios | B49: 6.1 | C49: Adecuación de la sala técnica de Talca | D49: 3 | E49: 4 | F49: =E49-D49+1 | G49: 800 | H49: =IF(AND(H$5>=$D49,H$5<=$E49),6,"") | I49: =IF(AND(I$5>=$D49,I$5<=$E49),6,"") | J49: =IF(AND(J$5>=$D49,J$5<=$E49),6,"") | K49: =IF(AND(K$5>=$D49,K$5<=$E49),6,"") | L49: =IF(AND(L$5>=$D49,L$5<=$E49),6,"") | M49: =IF(AND(M$5>=$D49,M$5<=$E49),6,"") | N49: =IF(AND(N$5>=$D49,N$5<=$E49),6,"") | O49: =IF(AND(O$5>=$D49,O$5<=$E49),6,"") | ... BK49: =IF(AND(BK$5>=$D49,BK$5<=$E49),6,"")
A50: 6 Infraestructura física y sitios | B50: 6.2 | C50: Cableado estructurado | D50: 4 | E50: 7 | F50: =E50-D50+1 | G50: 480 | H50: =IF(AND(H$5>=$D50,H$5<=$E50),6,"") | I50: =IF(AND(I$5>=$D50,I$5<=$E50),6,"") | J50: =IF(AND(J$5>=$D50,J$5<=$E50),6,"") | K50: =IF(AND(K$5>=$D50,K$5<=$E50),6,"") | L50: =IF(AND(L$5>=$D50,L$5<=$E50),6,"") | M50: =IF(AND(M$5>=$D50,M$5<=$E50),6,"") | N50: =IF(AND(N$5>=$D50,N$5<=$E50),6,"") | O50: =IF(AND(O$5>=$D50,O$5<=$E50),6,"") | ... BK50: =IF(AND(BK$5>=$D50,BK$5<=$E50),6,"")
A51: 6 Infraestructura física y sitios | B51: 6.3 | C51: Montaje de racks y gabinetes | D51: 4 | E51: 9 | F51: =E51-D51+1 | G51: 640 | H51: =IF(AND(H$5>=$D51,H$5<=$E51),6,"") | I51: =IF(AND(I$5>=$D51,I$5<=$E51),6,"") | J51: =IF(AND(J$5>=$D51,J$5<=$E51),6,"") | K51: =IF(AND(K$5>=$D51,K$5<=$E51),6,"") | L51: =IF(AND(L$5>=$D51,L$5<=$E51),6,"") | M51: =IF(AND(M$5>=$D51,M$5<=$E51),6,"") | N51: =IF(AND(N$5>=$D51,N$5<=$E51),6,"") | O51: =IF(AND(O$5>=$D51,O$5<=$E51),6,"") | ... BK51: =IF(AND(BK$5>=$D51,BK$5<=$E51),6,"")
A52: 6 Infraestructura física y sitios | B52: 6.4 | C52: Sistemas de seguridad física | D52: 5 | E52: 6 | F52: =E52-D52+1 | G52: 480 | H52: =IF(AND(H$5>=$D52,H$5<=$E52),6,"") | I52: =IF(AND(I$5>=$D52,I$5<=$E52),6,"") | J52: =IF(AND(J$5>=$D52,J$5<=$E52),6,"") | K52: =IF(AND(K$5>=$D52,K$5<=$E52),6,"") | L52: =IF(AND(L$5>=$D52,L$5<=$E52),6,"") | M52: =IF(AND(M$5>=$D52,M$5<=$E52),6,"") | N52: =IF(AND(N$5>=$D52,N$5<=$E52),6,"") | O52: =IF(AND(O$5>=$D52,O$5<=$E52),6,"") | ... BK52: =IF(AND(BK$5>=$D52,BK$5<=$E52),6,"")
A53: 6 Infraestructura física y sitios | B53: 6.5 | C53: Equipamiento de campo | D53: 9 | E53: 12 | F53: =E53-D53+1 | G53: 960 | H53: =IF(AND(H$5>=$D53,H$5<=$E53),6,"") | I53: =IF(AND(I$5>=$D53,I$5<=$E53),6,"") | J53: =IF(AND(J$5>=$D53,J$5<=$E53),6,"") | K53: =IF(AND(K$5>=$D53,K$5<=$E53),6,"") | L53: =IF(AND(L$5>=$D53,L$5<=$E53),6,"") | M53: =IF(AND(M$5>=$D53,M$5<=$E53),6,"") | N53: =IF(AND(N$5>=$D53,N$5<=$E53),6,"") | O53: =IF(AND(O$5>=$D53,O$5<=$E53),6,"") | ... BK53: =IF(AND(BK$5>=$D53,BK$5<=$E53),6,"")
A54: 6 Infraestructura física y sitios | B54: 6.6 | C54: Configuración de la infraestructura de los sitios | D54: 5 | E54: 5 | F54: =E54-D54+1 | G54: 480 | H54: =IF(AND(H$5>=$D54,H$5<=$E54),6,"") | I54: =IF(AND(I$5>=$D54,I$5<=$E54),6,"") | J54: =IF(AND(J$5>=$D54,J$5<=$E54),6,"") | K54: =IF(AND(K$5>=$D54,K$5<=$E54),6,"") | L54: =IF(AND(L$5>=$D54,L$5<=$E54),6,"") | M54: =IF(AND(M$5>=$D54,M$5<=$E54),6,"") | N54: =IF(AND(N$5>=$D54,N$5<=$E54),6,"") | O54: =IF(AND(O$5>=$D54,O$5<=$E54),6,"") | ... BK54: =IF(AND(BK$5>=$D54,BK$5<=$E54),6,"")
A55: 7 Capacitación y gestión del cambio | B55: 7.1 | C55: Capacitación por roles | D55: 10 | E55: 56 | F55: =E55-D55+1 | G55: 3616 | H55: =IF(AND(H$5>=$D55,H$5<=$E55),7,"") | I55: =IF(AND(I$5>=$D55,I$5<=$E55),7,"") | J55: =IF(AND(J$5>=$D55,J$5<=$E55),7,"") | K55: =IF(AND(K$5>=$D55,K$5<=$E55),7,"") | L55: =IF(AND(L$5>=$D55,L$5<=$E55),7,"") | M55: =IF(AND(M$5>=$D55,M$5<=$E55),7,"") | N55: =IF(AND(N$5>=$D55,N$5<=$E55),7,"") | O55: =IF(AND(O$5>=$D55,O$5<=$E55),7,"") | ... BK55: =IF(AND(BK$5>=$D55,BK$5<=$E55),7,"")
A56: 7 Capacitación y gestión del cambio | B56: 7.2 | C56: Gestión del cambio | D56: 2 | E56: 21 | F56: =E56-D56+1 | G56: 800 | H56: =IF(AND(H$5>=$D56,H$5<=$E56),7,"") | I56: =IF(AND(I$5>=$D56,I$5<=$E56),7,"") | J56: =IF(AND(J$5>=$D56,J$5<=$E56),7,"") | K56: =IF(AND(K$5>=$D56,K$5<=$E56),7,"") | L56: =IF(AND(L$5>=$D56,L$5<=$E56),7,"") | M56: =IF(AND(M$5>=$D56,M$5<=$E56),7,"") | N56: =IF(AND(N$5>=$D56,N$5<=$E56),7,"") | O56: =IF(AND(O$5>=$D56,O$5<=$E56),7,"") | ... BK56: =IF(AND(BK$5>=$D56,BK$5<=$E56),7,"")
A57: 7 Capacitación y gestión del cambio | B57: 7.3 | C57: Evaluaciones y certificaciones | D57: 13 | E57: 18 | F57: =E57-D57+1 | G57: 320 | H57: =IF(AND(H$5>=$D57,H$5<=$E57),7,"") | I57: =IF(AND(I$5>=$D57,I$5<=$E57),7,"") | J57: =IF(AND(J$5>=$D57,J$5<=$E57),7,"") | K57: =IF(AND(K$5>=$D57,K$5<=$E57),7,"") | L57: =IF(AND(L$5>=$D57,L$5<=$E57),7,"") | M57: =IF(AND(M$5>=$D57,M$5<=$E57),7,"") | N57: =IF(AND(N$5>=$D57,N$5<=$E57),7,"") | O57: =IF(AND(O$5>=$D57,O$5<=$E57),7,"") | ... BK57: =IF(AND(BK$5>=$D57,BK$5<=$E57),7,"")
A58: 8 Operación y soporte | B58: 8.1 | C58: Servicios de operación | D58: 13 | E58: 56 | F58: =E58-D58+1 | G58: 113575 | H58: =IF(AND(H$5>=$D58,H$5<=$E58),8,"") | I58: =IF(AND(I$5>=$D58,I$5<=$E58),8,"") | J58: =IF(AND(J$5>=$D58,J$5<=$E58),8,"") | K58: =IF(AND(K$5>=$D58,K$5<=$E58),8,"") | L58: =IF(AND(L$5>=$D58,L$5<=$E58),8,"") | M58: =IF(AND(M$5>=$D58,M$5<=$E58),8,"") | N58: =IF(AND(N$5>=$D58,N$5<=$E58),8,"") | O58: =IF(AND(O$5>=$D58,O$5<=$E58),8,"") | ... BK58: =IF(AND(BK$5>=$D58,BK$5<=$E58),8,"")
A59: 8 Operación y soporte | B59: 8.2 | C59: Mantenimiento | D59: 21 | E59: 56 | F59: =E59-D59+1 | G59: 10656 | H59: =IF(AND(H$5>=$D59,H$5<=$E59),8,"") | I59: =IF(AND(I$5>=$D59,I$5<=$E59),8,"") | J59: =IF(AND(J$5>=$D59,J$5<=$E59),8,"") | K59: =IF(AND(K$5>=$D59,K$5<=$E59),8,"") | L59: =IF(AND(L$5>=$D59,L$5<=$E59),8,"") | M59: =IF(AND(M$5>=$D59,M$5<=$E59),8,"") | N59: =IF(AND(N$5>=$D59,N$5<=$E59),8,"") | O59: =IF(AND(O$5>=$D59,O$5<=$E59),8,"") | ... BK59: =IF(AND(BK$5>=$D59,BK$5<=$E59),8,"")
A60: 8 Operación y soporte | B60: 8.3 | C60: Innovaciones en operación | D60: 21 | E60: 56 | F60: =E60-D60+1 | G60: 1632 | H60: =IF(AND(H$5>=$D60,H$5<=$E60),8,"") | I60: =IF(AND(I$5>=$D60,I$5<=$E60),8,"") | J60: =IF(AND(J$5>=$D60,J$5<=$E60),8,"") | K60: =IF(AND(K$5>=$D60,K$5<=$E60),8,"") | L60: =IF(AND(L$5>=$D60,L$5<=$E60),8,"") | M60: =IF(AND(M$5>=$D60,M$5<=$E60),8,"") | N60: =IF(AND(N$5>=$D60,N$5<=$E60),8,"") | O60: =IF(AND(O$5>=$D60,O$5<=$E60),8,"") | ... BK60: =IF(AND(BK$5>=$D60,BK$5<=$E60),8,"")
A61: 8 Operación y soporte | B61: 8.4 | C61: Informes y obligaciones periódicas | D61: 21 | E61: 56 | F61: =E61-D61+1 | G61: 1728 | H61: =IF(AND(H$5>=$D61,H$5<=$E61),8,"") | I61: =IF(AND(I$5>=$D61,I$5<=$E61),8,"") | J61: =IF(AND(J$5>=$D61,J$5<=$E61),8,"") | K61: =IF(AND(K$5>=$D61,K$5<=$E61),8,"") | L61: =IF(AND(L$5>=$D61,L$5<=$E61),8,"") | M61: =IF(AND(M$5>=$D61,M$5<=$E61),8,"") | N61: =IF(AND(N$5>=$D61,N$5<=$E61),8,"") | O61: =IF(AND(O$5>=$D61,O$5<=$E61),8,"") | ... BK61: =IF(AND(BK$5>=$D61,BK$5<=$E61),8,"")
A62: 8 Operación y soporte | B62: 8.5 | C62: Capacitación y transferencia en operación | D62: 21 | E62: 56 | F62: =E62-D62+1 | G62: 1808 | H62: =IF(AND(H$5>=$D62,H$5<=$E62),8,"") | I62: =IF(AND(I$5>=$D62,I$5<=$E62),8,"") | J62: =IF(AND(J$5>=$D62,J$5<=$E62),8,"") | K62: =IF(AND(K$5>=$D62,K$5<=$E62),8,"") | L62: =IF(AND(L$5>=$D62,L$5<=$E62),8,"") | M62: =IF(AND(M$5>=$D62,M$5<=$E62),8,"") | N62: =IF(AND(N$5>=$D62,N$5<=$E62),8,"") | O62: =IF(AND(O$5>=$D62,O$5<=$E62),8,"") | ... BK62: =IF(AND(BK$5>=$D62,BK$5<=$E62),8,"")
A63: 9 Cierre | B63: 9.1 | C63: Cierre de la implementación | D63: 21 | E63: 21 | F63: =E63-D63+1 | G63: 160 | H63: =IF(AND(H$5>=$D63,H$5<=$E63),9,"") | I63: =IF(AND(I$5>=$D63,I$5<=$E63),9,"") | J63: =IF(AND(J$5>=$D63,J$5<=$E63),9,"") | K63: =IF(AND(K$5>=$D63,K$5<=$E63),9,"") | L63: =IF(AND(L$5>=$D63,L$5<=$E63),9,"") | M63: =IF(AND(M$5>=$D63,M$5<=$E63),9,"") | N63: =IF(AND(N$5>=$D63,N$5<=$E63),9,"") | O63: =IF(AND(O$5>=$D63,O$5<=$E63),9,"") | ... BK63: =IF(AND(BK$5>=$D63,BK$5<=$E63),9,"")
A64: 9 Cierre | B64: 9.2 | C64: Salida al término del contrato | D64: 54 | E64: 56 | F64: =E64-D64+1 | G64: 160 | H64: =IF(AND(H$5>=$D64,H$5<=$E64),9,"") | I64: =IF(AND(I$5>=$D64,I$5<=$E64),9,"") | J64: =IF(AND(J$5>=$D64,J$5<=$E64),9,"") | K64: =IF(AND(K$5>=$D64,K$5<=$E64),9,"") | L64: =IF(AND(L$5>=$D64,L$5<=$E64),9,"") | M64: =IF(AND(M$5>=$D64,M$5<=$E64),9,"") | N64: =IF(AND(N$5>=$D64,N$5<=$E64),9,"") | O64: =IF(AND(O$5>=$D64,O$5<=$E64),9,"") | ... BK64: =IF(AND(BK$5>=$D64,BK$5<=$E64),9,"")
C65: Total HH de los paquetes (sin soporte puente ni reserva protegida) | G65: =SUM(G16:G64)
C66: Fuente: Formulario T-15, sección 4.2 (meses y E de cada paquete) y Formulario T-14 (nombres de cuentas). La barra de una cuenta va del primer mes de su primer paquete al último mes de su último paquete; dentro de ese rango puede haber meses sin trabajo.

Sheet Gantt paquetes
A1: Carta Gantt por paquete de trabajo (222 paquetes de la EDT)
A2: Leyenda de colores (fase de la EDT): | L2: 1 Inicio | T2: 2 Elaboración | AB2: 3 Construcción | AJ2: 4 Transición | AR2: 5 Adquisiciones y contrataciones
L3: 6 Infraestructura física y sitios | T3: 7 Capacitación y gestión del cambio | AB3: 8 Operación y soporte | AJ3: 9 Cierre
K4: «C» y fondo naranja = mes de congelamiento (septiembre y diciembre): sin pasos a producción. Fila «Hitos E-25» = mes del acta de cada hito.
A5: Fase | B5: Paquete | C5: Nombre del paquete | D5: Clase | E5: Responsable (familia de rol) | F5: Inicio (mes) | G5: Fin (mes) | H5: Duración (meses) | I5: HH esperadas (E) | J5: Tipo de programación | K5: 1 | L5: 2 | M5: 3 | N5: 4 | O5: 5 | P5: 6 | Q5: 7 | R5: 8 | S5: 9 | T5: 10 | U5: 11 | V5: 12 | W5: 13 | X5: 14 | Y5: 15 | Z5: 16 | AA5: 17 | AB5: 18 | AC5: 19 | AD5: 20 | AE5: 21 | AF5: 22 | AG5: 23 | AH5: 24 | AI5: 25 | AJ5: 26 | AK5: 27 | AL5: 28 | AM5: 29 | AN5: 30 | AO5: 31 | AP5: 32 | AQ5: 33 | AR5: 34 | AS5: 35 | AT5: 36 | AU5: 37 | AV5: 38 | AW5: 39 | AX5: 40 | AY5: 41 | AZ5: 42 | BA5: 43 | BB5: 44 | BC5: 45 | BD5: 46 | BE5: 47 | BF5: 48 | BG5: 49 | BH5: 50 | BI5: 51 | BJ5: 52 | BK5: 53 | BL5: 54 | BM5: 55 | BN5: 56
J6: Mes calendario | K6: =EDATE('Parámetros'!$B$3,K5-1) | L6: =EDATE('Parámetros'!$B$3,L5-1) | M6: =EDATE('Parámetros'!$B$3,M5-1) | N6: =EDATE('Parámetros'!$B$3,N5-1) | O6: =EDATE('Parámetros'!$B$3,O5-1) | P6: =EDATE('Parámetros'!$B$3,P5-1) | Q6: =EDATE('Parámetros'!$B$3,Q5-1) | R6: =EDATE('Parámetros'!$B$3,R5-1) | ... BN6: =EDATE('Parámetros'!$B$3,BN5-1)
J7: Congelamiento | K7: =IF(OR(MONTH(K6)=9,MONTH(K6)=12),"C","") | L7: =IF(OR(MONTH(L6)=9,MONTH(L6)=12),"C","") | M7: =IF(OR(MONTH(M6)=9,MONTH(M6)=12),"C","") | N7: =IF(OR(MONTH(N6)=9,MONTH(N6)=12),"C","") | O7: =IF(OR(MONTH(O6)=9,MONTH(O6)=12),"C","") | P7: =IF(OR(MONTH(P6)=9,MONTH(P6)=12),"C","") | Q7: =IF(OR(MONTH(Q6)=9,MONTH(Q6)=12),"C","") | R7: =IF(OR(MONTH(R6)=9,MONTH(R6)=12),"C","") | ... BN7: =IF(OR(MONTH(BN6)=9,MONTH(BN6)=12),"C","")
J8: Hitos E-25 | K8: {=IFERROR(INDEX(Hitos!$A$2:$A$13,MATCH(K5,Hitos!$D$2:$D$13,0)),"")} | L8: {=IFERROR(INDEX(Hitos!$A$2:$A$13,MATCH(L5,Hitos!$D$2:$D$13,0)),"")} | M8: {=IFERROR(INDEX(Hitos!$A$2:$A$13,MATCH(M5,Hitos!$D$2:$D$13,0)),"")} | N8: {=IFERROR(INDEX(Hitos!$A$2:$A$13,MATCH(N5,Hitos!$D$2:$D$13,0)),"")} | O8: {=IFERROR(INDEX(Hitos!$A$2:$A$13,MATCH(O5,Hitos!$D$2:$D$13,0)),"")} | P8: {=IFERROR(INDEX(Hitos!$A$2:$A$13,MATCH(P5,Hitos!$D$2:$D$13,0)),"")} | Q8: {=IFERROR(INDEX(Hitos!$A$2:$A$13,MATCH(Q5,Hitos!$D$2:$D$13,0)),"")} | R8: {=IFERROR(INDEX(Hitos!$A$2:$A$13,MATCH(R5,Hitos!$D$2:$D$13,0)),"")} | ... BN8: {=IFERROR(INDEX(Hitos!$A$2:$A$13,MATCH(BN5,Hitos!$D$2:$D$13,0)),"")}
A9: 1 Inicio | B9: 1.1.1 | C9: Acta de constitución del proyecto, firmada con la Contraparte Técnica | D9: G | E9: Jefe de Proyecto | F9: 1 | G9: 1 | H9: =G9-F9+1 | I9: 80 | J9: Con entregable (actividades en hoja «Actividades hasta H2») | K9: =IF(AND(K$5>=$F9,K$5<=$G9),1,"") | L9: =IF(AND(L$5>=$F9,L$5<=$G9),1,"") | M9: =IF(AND(M$5>=$F9,M$5<=$G9),1,"") | N9: =IF(AND(N$5>=$F9,N$5<=$G9),1,"") | O9: =IF(AND(O$5>=$F9,O$5<=$G9),1,"") | P9: =IF(AND(P$5>=$F9,P$5<=$G9),1,"") | Q9: =IF(AND(Q$5>=$F9,Q$5<=$G9),1,"") | R9: =IF(AND(R$5>=$F9,R$5<=$G9),1,"") | ... BN9: =IF(AND(BN$5>=$F9,BN$5<=$G9),1,"")
A10: 1 Inicio | B10: 1.1.2 | C10: Documento de validación con el CLIENTE de los problemas y metas del proyecto | D10: G | E10: Jefe de Proyecto | F10: 1 | G10: 1 | H10: =G10-F10+1 | I10: 80 | J10: Con entregable (actividades en hoja «Actividades hasta H2») | K10: =IF(AND(K$5>=$F10,K$5<=$G10),1,"") | L10: =IF(AND(L$5>=$F10,L$5<=$G10),1,"") | M10: =IF(AND(M$5>=$F10,M$5<=$G10),1,"") | N10: =IF(AND(N$5>=$F10,N$5<=$G10),1,"") | O10: =IF(AND(O$5>=$F10,O$5<=$G10),1,"") | P10: =IF(AND(P$5>=$F10,P$5<=$G10),1,"") | Q10: =IF(AND(Q$5>=$F10,Q$5<=$G10),1,"") | R10: =IF(AND(R$5>=$F10,R$5<=$G10),1,"") | ... BN10: =IF(AND(BN$5>=$F10,BN$5<=$G10),1,"")
A11: 1 Inicio | B11: 1.1.3 | C11: Acta de confirmación con el CLIENTE de la fecha de inicio, la evidencia para el proveedor de lácteos, las ventanas de paso a producción y el acuse tributario | D11: G | E11: Jefe de Proyecto | F11: 1 | G11: 1 | H11: =G11-F11+1 | I11: 80 | J11: Con entregable (actividades en hoja «Actividades hasta H2») | K11: =IF(AND(K$5>=$F11,K$5<=$G11),1,"") | L11: =IF(AND(L$5>=$F11,L$5<=$G11),1,"") | M11: =IF(AND(M$5>=$F11,M$5<=$G11),1,"") | N11: =IF(AND(N$5>=$F11,N$5<=$G11),1,"") | O11: =IF(AND(O$5>=$F11,O$5<=$G11),1,"") | P11: =IF(AND(P$5>=$F11,P$5<=$G11),1,"") | Q11: =IF(AND(Q$5>=$F11,Q$5<=$G11),1,"") | R11: =IF(AND(R$5>=$F11,R$5<=$G11),1,"") | ... BN11: =IF(AND(BN$5>=$F11,BN$5<=$G11),1,"")
A12: 1 Inicio | B12: 1.2.1 | C12: Documento de especificación de requerimientos y línea base de alcance de la Etapa 1 (H1) | D12: G | E12: Arquitectura | F12: 1 | G12: 1 | H12: =G12-F12+1 | I12: 80 | J12: Con entregable (actividades en hoja «Actividades hasta H2») | K12: =IF(AND(K$5>=$F12,K$5<=$G12),1,"") | L12: =IF(AND(L$5>=$F12,L$5<=$G12),1,"") | M12: =IF(AND(M$5>=$F12,M$5<=$G12),1,"") | N12: =IF(AND(N$5>=$F12,N$5<=$G12),1,"") | O12: =IF(AND(O$5>=$F12,O$5<=$G12),1,"") | P12: =IF(AND(P$5>=$F12,P$5<=$G12),1,"") | Q12: =IF(AND(Q$5>=$F12,Q$5<=$G12),1,"") | R12: =IF(AND(R$5>=$F12,R$5<=$G12),1,"") | ... BN12: =IF(AND(BN$5>=$F12,BN$5<=$G12),1,"")
A13: 1 Inicio | B13: 1.2.2 | C13: Documento de reglas de ruteo capturadas al planificador de rutas | D13: G | E13: Implantación y gestión del cambio | F13: 1 | G13: 3 | H13: =G13-F13+1 | I13: 80 | J13: Esfuerzo continuo (por quincena u ocurrencia) | K13: =IF(AND(K$5>=$F13,K$5<=$G13),1,"") | L13: =IF(AND(L$5>=$F13,L$5<=$G13),1,"") | M13: =IF(AND(M$5>=$F13,M$5<=$G13),1,"") | N13: =IF(AND(N$5>=$F13,N$5<=$G13),1,"") | O13: =IF(AND(O$5>=$F13,O$5<=$G13),1,"") | P13: =IF(AND(P$5>=$F13,P$5<=$G13),1,"") | Q13: =IF(AND(Q$5>=$F13,Q$5<=$G13),1,"") | R13: =IF(AND(R$5>=$F13,R$5<=$G13),1,"") | ... BN13: =IF(AND(BN$5>=$F13,BN$5<=$G13),1,"")
A14: 1 Inicio | B14: 1.2.3 | C14: Documento de especificación de las interfaces sin documentación del ERP, del WMS de 2013 y de la telemetría del tercero | D14: G | E14: Arquitectura | F14: 1 | G14: 4 | H14: =G14-F14+1 | I14: 80 | J14: Con entregable (actividades en hoja «Actividades hasta H2») | K14: =IF(AND(K$5>=$F14,K$5<=$G14),1,"") | L14: =IF(AND(L$5>=$F14,L$5<=$G14),1,"") | M14: =IF(AND(M$5>=$F14,M$5<=$G14),1,"") | N14: =IF(AND(N$5>=$F14,N$5<=$G14),1,"") | O14: =IF(AND(O$5>=$F14,O$5<=$G14),1,"") | P14: =IF(AND(P$5>=$F14,P$5<=$G14),1,"") | Q14: =IF(AND(Q$5>=$F14,Q$5<=$G14),1,"") | R14: =IF(AND(R$5>=$F14,R$5<=$G14),1,"") | ... BN14: =IF(AND(BN$5>=$F14,BN$5<=$G14),1,"")
A15: 1 Inicio | B15: 1.2.4 | C15: Matriz de trazabilidad: requerimiento, módulo, paquete y prueba (H1) | D15: G | E15: Calidad y pruebas | F15: 2 | G15: 2 | H15: =G15-F15+1 | I15: 80 | J15: Con entregable (actividades en hoja «Actividades hasta H2») | K15: =IF(AND(K$5>=$F15,K$5<=$G15),1,"") | L15: =IF(AND(L$5>=$F15,L$5<=$G15),1,"") | M15: =IF(AND(M$5>=$F15,M$5<=$G15),1,"") | N15: =IF(AND(N$5>=$F15,N$5<=$G15),1,"") | O15: =IF(AND(O$5>=$F15,O$5<=$G15),1,"") | P15: =IF(AND(P$5>=$F15,P$5<=$G15),1,"") | Q15: =IF(AND(Q$5>=$F15,Q$5<=$G15),1,"") | R15: =IF(AND(R$5>=$F15,R$5<=$G15),1,"") | ... BN15: =IF(AND(BN$5>=$F15,BN$5<=$G15),1,"")
A16: 1 Inicio | B16: 1.2.5 | C16: Documento de línea base de alcance de la Etapa 2: canal moderno y costo de servir (H8) | D16: G | E16: Arquitectura | F16: 13 | G16: 13 | H16: =G16-F16+1 | I16: 80 | J16: Con entregable (detalle por planificación gradual) | K16: =IF(AND(K$5>=$F16,K$5<=$G16),1,"") | L16: =IF(AND(L$5>=$F16,L$5<=$G16),1,"") | M16: =IF(AND(M$5>=$F16,M$5<=$G16),1,"") | N16: =IF(AND(N$5>=$F16,N$5<=$G16),1,"") | O16: =IF(AND(O$5>=$F16,O$5<=$G16),1,"") | P16: =IF(AND(P$5>=$F16,P$5<=$G16),1,"") | Q16: =IF(AND(Q$5>=$F16,Q$5<=$G16),1,"") | R16: =IF(AND(R$5>=$F16,R$5<=$G16),1,"") | ... BN16: =IF(AND(BN$5>=$F16,BN$5<=$G16),1,"")
A17: 1 Inicio | B17: 1.3.1 | C17: Plan para la dirección del proyecto, con el calendario de congelamientos de septiembre, diciembre y el cierre mensual | D17: G | E17: Jefe de Proyecto | F17: 1 | G17: 1 | H17: =G17-F17+1 | I17: 80 | J17: Con entregable (actividades en hoja «Actividades hasta H2») | K17: =IF(AND(K$5>=$F17,K$5<=$G17),1,"") | L17: =IF(AND(L$5>=$F17,L$5<=$G17),1,"") | M17: =IF(AND(M$5>=$F17,M$5<=$G17),1,"") | N17: =IF(AND(N$5>=$F17,N$5<=$G17),1,"") | O17: =IF(AND(O$5>=$F17,O$5<=$G17),1,"") | P17: =IF(AND(P$5>=$F17,P$5<=$G17),1,"") | Q17: =IF(AND(Q$5>=$F17,Q$5<=$G17),1,"") | R17: =IF(AND(R$5>=$F17,R$5<=$G17),1,"") | ... BN17: =IF(AND(BN$5>=$F17,BN$5<=$G17),1,"")
A18: 1 Inicio | B18: 1.3.2 | C18: EDT y diccionario de la EDT (línea base del alcance) | D18: G | E18: Jefe de Proyecto | F18: 2 | G18: 2 | H18: =G18-F18+1 | I18: 80 | J18: Con entregable (actividades en hoja «Actividades hasta H2») | K18: =IF(AND(K$5>=$F18,K$5<=$G18),1,"") | L18: =IF(AND(L$5>=$F18,L$5<=$G18),1,"") | M18: =IF(AND(M$5>=$F18,M$5<=$G18),1,"") | N18: =IF(AND(N$5>=$F18,N$5<=$G18),1,"") | O18: =IF(AND(O$5>=$F18,O$5<=$G18),1,"") | P18: =IF(AND(P$5>=$F18,P$5<=$G18),1,"") | Q18: =IF(AND(Q$5>=$F18,Q$5<=$G18),1,"") | R18: =IF(AND(R$5>=$F18,R$5<=$G18),1,"") | ... BN18: =IF(AND(BN$5>=$F18,BN$5<=$G18),1,"")
A19: 1 Inicio | B19: 1.3.3 | C19: Carta Gantt de 56 meses con los hitos H1 a H12 y la ruta crítica | D19: G | E19: Jefe de Proyecto | F19: 2 | G19: 2 | H19: =G19-F19+1 | I19: 80 | J19: Con entregable (actividades en hoja «Actividades hasta H2») | K19: =IF(AND(K$5>=$F19,K$5<=$G19),1,"") | L19: =IF(AND(L$5>=$F19,L$5<=$G19),1,"") | M19: =IF(AND(M$5>=$F19,M$5<=$G19),1,"") | N19: =IF(AND(N$5>=$F19,N$5<=$G19),1,"") | O19: =IF(AND(O$5>=$F19,O$5<=$G19),1,"") | P19: =IF(AND(P$5>=$F19,P$5<=$G19),1,"") | Q19: =IF(AND(Q$5>=$F19,Q$5<=$G19),1,"") | R19: =IF(AND(R$5>=$F19,R$5<=$G19),1,"") | ... BN19: =IF(AND(BN$5>=$F19,BN$5<=$G19),1,"")
A20: 1 Inicio | B20: 1.3.4 | C20: Documento de nivelación de recursos y frentes del solapamiento de los meses 13 a 15 y 19 a 20 | D20: G | E20: Jefe de Proyecto | F20: 2 | G20: 2 | H20: =G20-F20+1 | I20: 80 | J20: Con entregable (actividades en hoja «Actividades hasta H2») | K20: =IF(AND(K$5>=$F20,K$5<=$G20),1,"") | L20: =IF(AND(L$5>=$F20,L$5<=$G20),1,"") | M20: =IF(AND(M$5>=$F20,M$5<=$G20),1,"") | N20: =IF(AND(N$5>=$F20,N$5<=$G20),1,"") | O20: =IF(AND(O$5>=$F20,O$5<=$G20),1,"") | P20: =IF(AND(P$5>=$F20,P$5<=$G20),1,"") | Q20: =IF(AND(Q$5>=$F20,Q$5<=$G20),1,"") | R20: =IF(AND(R$5>=$F20,R$5<=$G20),1,"") | ... BN20: =IF(AND(BN$5>=$F20,BN$5<=$G20),1,"")
... A43: 1 Inicio | B43: 1.9.5 | C43: Garantía de fiel cumplimiento, seguros y certificados laborales vigentes durante el contrato | D43: R | E43: Jefe de Proyecto | F43: 1 | G43: 56 | H43: =G43-F43+1 | I43: 224 | J43: Esfuerzo continuo (por quincena u ocurrencia) | K43: =IF(AND(K$5>=$F43,K$5<=$G43),1,"") | L43: =IF(AND(L$5>=$F43,L$5<=$G43),1,"") | M43: =IF(AND(M$5>=$F43,M$5<=$G43),1,"") | N43: =IF(AND(N$5>=$F43,N$5<=$G43),1,"") | O43: =IF(AND(O$5>=$F43,O$5<=$G43),1,"") | P43: =IF(AND(P$5>=$F43,P$5<=$G43),1,"") | Q43: =IF(AND(Q$5>=$F43,Q$5<=$G43),1,"") | R43: =IF(AND(R$5>=$F43,R$5<=$G43),1,"") | ... BN43: =IF(AND(BN$5>=$F43,BN$5<=$G43),1,"")
A44: 2 Elaboración | B44: 2.1.1 | C44: Documento de arquitectura lógica: capas, módulos M1 a M12 e interfaces | D44: E | E44: Arquitectura | F44: 2 | G44: 2 | H44: =G44-F44+1 | I44: 240 | J44: Con entregable (actividades en hoja «Actividades hasta H2») | K44: =IF(AND(K$5>=$F44,K$5<=$G44),2,"") | L44: =IF(AND(L$5>=$F44,L$5<=$G44),2,"") | M44: =IF(AND(M$5>=$F44,M$5<=$G44),2,"") | N44: =IF(AND(N$5>=$F44,N$5<=$G44),2,"") | O44: =IF(AND(O$5>=$F44,O$5<=$G44),2,"") | P44: =IF(AND(P$5>=$F44,P$5<=$G44),2,"") | Q44: =IF(AND(Q$5>=$F44,Q$5<=$G44),2,"") | R44: =IF(AND(R$5>=$F44,R$5<=$G44),2,"") | ... BN44: =IF(AND(BN$5>=$F44,BN$5<=$G44),2,"")
A45: 2 Elaboración | B45: 2.1.2 | C45: Documento de arquitectura física híbrida: nube, centros de distribución y plataformas de cross-docking | D45: E | E45: Arquitectura | F45: 2 | G45: 2 | H45: =G45-F45+1 | I45: 240 | J45: Con entregable (actividades en hoja «Actividades hasta H2») | K45: =IF(AND(K$5>=$F45,K$5<=$G45),2,"") | L45: =IF(AND(L$5>=$F45,L$5<=$G45),2,"") | M45: =IF(AND(M$5>=$F45,M$5<=$G45),2,"") | N45: =IF(AND(N$5>=$F45,N$5<=$G45),2,"") | O45: =IF(AND(O$5>=$F45,O$5<=$G45),2,"") | P45: =IF(AND(P$5>=$F45,P$5<=$G45),2,"") | Q45: =IF(AND(Q$5>=$F45,Q$5<=$G45),2,"") | R45: =IF(AND(R$5>=$F45,R$5<=$G45),2,"") | ... BN45: =IF(AND(BN$5>=$F45,BN$5<=$G45),2,"")
A46: 2 Elaboración | B46: 2.1.3 | C46: Modelo de datos y diccionario de datos, con la trazabilidad por lote | D46: E | E46: Datos | F46: 2 | G46: 2 | H46: =G46-F46+1 | I46: 240 | J46: Con entregable (actividades en hoja «Actividades hasta H2») | K46: =IF(AND(K$5>=$F46,K$5<=$G46),2,"") | L46: =IF(AND(L$5>=$F46,L$5<=$G46),2,"") | M46: =IF(AND(M$5>=$F46,M$5<=$G46),2,"") | N46: =IF(AND(N$5>=$F46,N$5<=$G46),2,"") | O46: =IF(AND(O$5>=$F46,O$5<=$G46),2,"") | P46: =IF(AND(P$5>=$F46,P$5<=$G46),2,"") | Q46: =IF(AND(Q$5>=$F46,Q$5<=$G46),2,"") | R46: =IF(AND(R$5>=$F46,R$5<=$G46),2,"") | ... BN46: =IF(AND(BN$5>=$F46,BN$5<=$G46),2,"")
A47: 2 Elaboración | B47: 2.1.4 | C47: Documento de diseño detallado de M11 y del intercambio con las cadenas | D47: E | E47: Arquitectura | F47: 13 | G47: 13 | H47: =G47-F47+1 | I47: 240 | J47: Con entregable (detalle por planificación gradual) | K47: =IF(AND(K$5>=$F47,K$5<=$G47),2,"") | L47: =IF(AND(L$5>=$F47,L$5<=$G47),2,"") | M47: =IF(AND(M$5>=$F47,M$5<=$G47),2,"") | N47: =IF(AND(N$5>=$F47,N$5<=$G47),2,"") | O47: =IF(AND(O$5>=$F47,O$5<=$G47),2,"") | P47: =IF(AND(P$5>=$F47,P$5<=$G47),2,"") | Q47: =IF(AND(Q$5>=$F47,Q$5<=$G47),2,"") | R47: =IF(AND(R$5>=$F47,R$5<=$G47),2,"") | ... BN47: =IF(AND(BN$5>=$F47,BN$5<=$G47),2,"")
A48: 2 Elaboración | B48: 2.2.1 | C48: Plan de seguridad de la información | D48: E | E48: Seguridad | F48: 2 | G48: 2 | H48: =G48-F48+1 | I48: 240 | J48: Con entregable (actividades en hoja «Actividades hasta H2») | K48: =IF(AND(K$5>=$F48,K$5<=$G48),2,"") | L48: =IF(AND(L$5>=$F48,L$5<=$G48),2,"") | M48: =IF(AND(M$5>=$F48,M$5<=$G48),2,"") | N48: =IF(AND(N$5>=$F48,N$5<=$G48),2,"") | O48: =IF(AND(O$5>=$F48,O$5<=$G48),2,"") | P48: =IF(AND(P$5>=$F48,P$5<=$G48),2,"") | Q48: =IF(AND(Q$5>=$F48,Q$5<=$G48),2,"") | R48: =IF(AND(R$5>=$F48,R$5<=$G48),2,"") | ... BN48: =IF(AND(BN$5>=$F48,BN$5<=$G48),2,"")
A49: 2 Elaboración | B49: 2.2.2 | C49: Modelado de amenazas por componente y por integración externa, actualizado ante cada cambio | D49: E | E49: Seguridad | F49: 3 | G49: 10 | H49: =G49-F49+1 | I49: 240 | J49: Esfuerzo continuo (por quincena u ocurrencia) | K49: =IF(AND(K$5>=$F49,K$5<=$G49),2,"") | L49: =IF(AND(L$5>=$F49,L$5<=$G49),2,"") | M49: =IF(AND(M$5>=$F49,M$5<=$G49),2,"") | N49: =IF(AND(N$5>=$F49,N$5<=$G49),2,"") | O49: =IF(AND(O$5>=$F49,O$5<=$G49),2,"") | P49: =IF(AND(P$5>=$F49,P$5<=$G49),2,"") | Q49: =IF(AND(Q$5>=$F49,Q$5<=$G49),2,"") | R49: =IF(AND(R$5>=$F49,R$5<=$G49),2,"") | ... BN49: =IF(AND(BN$5>=$F49,BN$5<=$G49),2,"")
A50: 2 Elaboración | B50: 2.2.3 | C50: Plan de respuesta a incidentes de seguridad, con aviso al CLIENTE en dos horas | D50: E | E50: Seguridad | F50: 3 | G50: 3 | H50: =G50-F50+1 | I50: 240 | J50: Con entregable (actividades en hoja «Actividades hasta H2») | K50: =IF(AND(K$5>=$F50,K$5<=$G50),2,"") | L50: =IF(AND(L$5>=$F50,L$5<=$G50),2,"") | M50: =IF(AND(M$5>=$F50,M$5<=$G50),2,"") | N50: =IF(AND(N$5>=$F50,N$5<=$G50),2,"") | O50: =IF(AND(O$5>=$F50,O$5<=$G50),2,"") | P50: =IF(AND(P$5>=$F50,P$5<=$G50),2,"") | Q50: =IF(AND(Q$5>=$F50,Q$5<=$G50),2,"") | R50: =IF(AND(R$5>=$F50,R$5<=$G50),2,"") | ... BN50: =IF(AND(BN$5>=$F50,BN$5<=$G50),2,"")
A51: 2 Elaboración | B51: 2.2.4 | C51: Matriz de clasificación de la información y matriz de controles | D51: E | E51: Seguridad | F51: 2 | G51: 2 | H51: =G51-F51+1 | I51: 240 | J51: Con entregable (actividades en hoja «Actividades hasta H2») | K51: =IF(AND(K$5>=$F51,K$5<=$G51),2,"") | L51: =IF(AND(L$5>=$F51,L$5<=$G51),2,"") | M51: =IF(AND(M$5>=$F51,M$5<=$G51),2,"") | N51: =IF(AND(N$5>=$F51,N$5<=$G51),2,"") | O51: =IF(AND(O$5>=$F51,O$5<=$G51),2,"") | P51: =IF(AND(P$5>=$F51,P$5<=$G51),2,"") | Q51: =IF(AND(Q$5>=$F51,Q$5<=$G51),2,"") | R51: =IF(AND(R$5>=$F51,R$5<=$G51),2,"") | ... BN51: =IF(AND(BN$5>=$F51,BN$5<=$G51),2,"")
A52: 2 Elaboración | B52: 2.3.1 | C52: Plano de la sala técnica de Talca, con su cálculo eléctrico y térmico | D52: E | E52: Operación / SRE | F52: 1 | G52: 2 | H52: =G52-F52+1 | I52: 240 | J52: Con entregable (actividades en hoja «Actividades hasta H2») | K52: =IF(AND(K$5>=$F52,K$5<=$G52),2,"") | L52: =IF(AND(L$5>=$F52,L$5<=$G52),2,"") | M52: =IF(AND(M$5>=$F52,M$5<=$G52),2,"") | N52: =IF(AND(N$5>=$F52,N$5<=$G52),2,"") | O52: =IF(AND(O$5>=$F52,O$5<=$G52),2,"") | P52: =IF(AND(P$5>=$F52,P$5<=$G52),2,"") | Q52: =IF(AND(Q$5>=$F52,Q$5<=$G52),2,"") | R52: =IF(AND(R$5>=$F52,R$5<=$G52),2,"") | ... BN52: =IF(AND(BN$5>=$F52,BN$5<=$G52),2,"")
A53: 2 Elaboración | B53: 2.3.2 | C53: Plano de distribución de los racks R01 de servidores y R02 de comunicaciones | D53: E | E53: Operación / SRE | F53: 1 | G53: 2 | H53: =G53-F53+1 | I53: 240 | J53: Con entregable (actividades en hoja «Actividades hasta H2») | K53: =IF(AND(K$5>=$F53,K$5<=$G53),2,"") | L53: =IF(AND(L$5>=$F53,L$5<=$G53),2,"") | M53: =IF(AND(M$5>=$F53,M$5<=$G53),2,"") | N53: =IF(AND(N$5>=$F53,N$5<=$G53),2,"") | O53: =IF(AND(O$5>=$F53,O$5<=$G53),2,"") | P53: =IF(AND(P$5>=$F53,P$5<=$G53),2,"") | Q53: =IF(AND(Q$5>=$F53,Q$5<=$G53),2,"") | R53: =IF(AND(R$5>=$F53,R$5<=$G53),2,"") | ... BN53: =IF(AND(BN$5>=$F53,BN$5<=$G53),2,"")
A54: 2 Elaboración | B54: 2.3.3 | C54: Plano de los gabinetes de borde de Concepción y de las plataformas de cross-docking | D54: E | E54: Operación / SRE | F54: 2 | G54: 2 | H54: =G54-F54+1 | I54: 240 | J54: Con entregable (actividades en hoja «Actividades hasta H2») | K54: =IF(AND(K$5>=$F54,K$5<=$G54),2,"") | L54: =IF(AND(L$5>=$F54,L$5<=$G54),2,"") | M54: =IF(AND(M$5>=$F54,M$5<=$G54),2,"") | N54: =IF(AND(N$5>=$F54,N$5<=$G54),2,"") | O54: =IF(AND(O$5>=$F54,O$5<=$G54),2,"") | P54: =IF(AND(P$5>=$F54,P$5<=$G54),2,"") | Q54: =IF(AND(Q$5>=$F54,Q$5<=$G54),2,"") | R54: =IF(AND(R$5>=$F54,R$5<=$G54),2,"") | ... BN54: =IF(AND(BN$5>=$F54,BN$5<=$G54),2,"")
A55: 2 Elaboración | B55: 2.4.1 | C55: Acta de aprobación de la arquitectura, el plan de seguridad y el modelo de datos (H2) | D55: E | E55: Arquitectura | F55: 3 | G55: 3 | H55: =G55-F55+1 | I55: 240 | J55: Con entregable (actividades en hoja «Actividades hasta H2») | K55: =IF(AND(K$5>=$F55,K$5<=$G55),2,"") | L55: =IF(AND(L$5>=$F55,L$5<=$G55),2,"") | M55: =IF(AND(M$5>=$F55,M$5<=$G55),2,"") | N55: =IF(AND(N$5>=$F55,N$5<=$G55),2,"") | O55: =IF(AND(O$5>=$F55,O$5<=$G55),2,"") | P55: =IF(AND(P$5>=$F55,P$5<=$G55),2,"") | Q55: =IF(AND(Q$5>=$F55,Q$5<=$G55),2,"") | R55: =IF(AND(R$5>=$F55,R$5<=$G55),2,"") | ... BN55: =IF(AND(BN$5>=$F55,BN$5<=$G55),2,"")
... A61: 2 Elaboración | B61: 2.6.3 | C61: Indicadores de usabilidad comprometidos por transacción crítica | D61: E | E61: Implantación y gestión del cambio | F61: 4 | G61: 4 | H61: =G61-F61+1 | I61: 240 | J61: Con entregable (actividades en hoja «Actividades hasta H2») | K61: =IF(AND(K$5>=$F61,K$5<=$G61),2,"") | L61: =IF(AND(L$5>=$F61,L$5<=$G61),2,"") | M61: =IF(AND(M$5>=$F61,M$5<=$G61),2,"") | N61: =IF(AND(N$5>=$F61,N$5<=$G61),2,"") | O61: =IF(AND(O$5>=$F61,O$5<=$G61),2,"") | P61: =IF(AND(P$5>=$F61,P$5<=$G61),2,"") | Q61: =IF(AND(Q$5>=$F61,Q$5<=$G61),2,"") | R61: =IF(AND(R$5>=$F61,R$5<=$G61),2,"") | ... BN61: =IF(AND(BN$5>=$F61,BN$5<=$G61),2,"")
A62: 3 Construcción | B62: 3.1.1 | C62: Ambientes de Desarrollo y QA en la nube (H3) | D62: E | E62: Operación / SRE | F62: 5 | G62: 5 | H62: =G62-F62+1 | I62: 240 | J62: Con entregable (detalle por planificación gradual) | K62: =IF(AND(K$5>=$F62,K$5<=$G62),3,"") | L62: =IF(AND(L$5>=$F62,L$5<=$G62),3,"") | M62: =IF(AND(M$5>=$F62,M$5<=$G62),3,"") | N62: =IF(AND(N$5>=$F62,N$5<=$G62),3,"") | O62: =IF(AND(O$5>=$F62,O$5<=$G62),3,"") | P62: =IF(AND(P$5>=$F62,P$5<=$G62),3,"") | Q62: =IF(AND(Q$5>=$F62,Q$5<=$G62),3,"") | R62: =IF(AND(R$5>=$F62,R$5<=$G62),3,"") | ... BN62: =IF(AND(BN$5>=$F62,BN$5<=$G62),3,"")
A63: 3 Construcción | B63: 3.1.2 | C63: Ambientes de Preproducción y Producción en la nube (H3) | D63: E | E63: Operación / SRE | F63: 5 | G63: 5 | H63: =G63-F63+1 | I63: 240 | J63: Con entregable (detalle por planificación gradual) | K63: =IF(AND(K$5>=$F63,K$5<=$G63),3,"") | L63: =IF(AND(L$5>=$F63,L$5<=$G63),3,"") | M63: =IF(AND(M$5>=$F63,M$5<=$G63),3,"") | N63: =IF(AND(N$5>=$F63,N$5<=$G63),3,"") | O63: =IF(AND(O$5>=$F63,O$5<=$G63),3,"") | P63: =IF(AND(P$5>=$F63,P$5<=$G63),3,"") | Q63: =IF(AND(Q$5>=$F63,Q$5<=$G63),3,"") | R63: =IF(AND(R$5>=$F63,R$5<=$G63),3,"") | ... BN63: =IF(AND(BN$5>=$F63,BN$5<=$G63),3,"")
A64: 3 Construcción | B64: 3.1.3 | C64: Ambiente de recuperación ante desastres en la región secundaria (H3) | D64: E | E64: Operación / SRE | F64: 5 | G64: 5 | H64: =G64-F64+1 | I64: 240 | J64: Con entregable (detalle por planificación gradual) | K64: =IF(AND(K$5>=$F64,K$5<=$G64),3,"") | L64: =IF(AND(L$5>=$F64,L$5<=$G64),3,"") | M64: =IF(AND(M$5>=$F64,M$5<=$G64),3,"") | N64: =IF(AND(N$5>=$F64,N$5<=$G64),3,"") | O64: =IF(AND(O$5>=$F64,O$5<=$G64),3,"") | P64: =IF(AND(P$5>=$F64,P$5<=$G64),3,"") | Q64: =IF(AND(Q$5>=$F64,Q$5<=$G64),3,"") | R64: =IF(AND(R$5>=$F64,R$5<=$G64),3,"") | ... BN64: =IF(AND(BN$5>=$F64,BN$5<=$G64),3,"")
A65: 3 Construcción | B65: 3.1.4 | C65: Cadena de integración y entrega continua, e infraestructura como código | D65: E | E65: Operación / SRE | F65: 4 | G65: 4 | H65: =G65-F65+1 | I65: 240 | J65: Con entregable (actividades en hoja «Actividades hasta H2») | K65: =IF(AND(K$5>=$F65,K$5<=$G65),3,"") | L65: =IF(AND(L$5>=$F65,L$5<=$G65),3,"") | M65: =IF(AND(M$5>=$F65,M$5<=$G65),3,"") | N65: =IF(AND(N$5>=$F65,N$5<=$G65),3,"") | O65: =IF(AND(O$5>=$F65,O$5<=$G65),3,"") | P65: =IF(AND(P$5>=$F65,P$5<=$G65),3,"") | Q65: =IF(AND(Q$5>=$F65,Q$5<=$G65),3,"") | R65: =IF(AND(R$5>=$F65,R$5<=$G65),3,"") | ... BN65: =IF(AND(BN$5>=$F65,BN$5<=$G65),3,"")
A66: 3 Construcción | B66: 3.1.5 | C66: Observabilidad de los doce módulos y de los sitios, con tableros para el CLIENTE (H3) | D66: E | E66: Operación / SRE | F66: 5 | G66: 5 | H66: =G66-F66+1 | I66: 240 | J66: Con entregable (detalle por planificación gradual) | K66: =IF(AND(K$5>=$F66,K$5<=$G66),3,"") | L66: =IF(AND(L$5>=$F66,L$5<=$G66),3,"") | M66: =IF(AND(M$5>=$F66,M$5<=$G66),3,"") | N66: =IF(AND(N$5>=$F66,N$5<=$G66),3,"") | O66: =IF(AND(O$5>=$F66,O$5<=$G66),3,"") | P66: =IF(AND(P$5>=$F66,P$5<=$G66),3,"") | Q66: =IF(AND(Q$5>=$F66,Q$5<=$G66),3,"") | R66: =IF(AND(R$5>=$F66,R$5<=$G66),3,"") | ... BN66: =IF(AND(BN$5>=$F66,BN$5<=$G66),3,"")
A67: 3 Construcción | B67: 3.2.1 | C67: Servicio de nube para la aplicación y los portales | D67: E | E67: Operación / SRE | F67: 4 | G67: 4 | H67: =G67-F67+1 | I67: 240 | J67: Con entregable (actividades en hoja «Actividades hasta H2») | K67: =IF(AND(K$5>=$F67,K$5<=$G67),3,"") | L67: =IF(AND(L$5>=$F67,L$5<=$G67),3,"") | M67: =IF(AND(M$5>=$F67,M$5<=$G67),3,"") | N67: =IF(AND(N$5>=$F67,N$5<=$G67),3,"") | O67: =IF(AND(O$5>=$F67,O$5<=$G67),3,"") | P67: =IF(AND(P$5>=$F67,P$5<=$G67),3,"") | Q67: =IF(AND(Q$5>=$F67,Q$5<=$G67),3,"") | R67: =IF(AND(R$5>=$F67,R$5<=$G67),3,"") | ... BN67: =IF(AND(BN$5>=$F67,BN$5<=$G67),3,"")
A68: 3 Construcción | B68: 3.2.2 | C68: Servicio de nube de base de datos, caché y mensajería | D68: E | E68: Operación / SRE | F68: 4 | G68: 4 | H68: =G68-F68+1 | I68: 240 | J68: Con entregable (actividades en hoja «Actividades hasta H2») | K68: =IF(AND(K$5>=$F68,K$5<=$G68),3,"") | L68: =IF(AND(L$5>=$F68,L$5<=$G68),3,"") | M68: =IF(AND(M$5>=$F68,M$5<=$G68),3,"") | N68: =IF(AND(N$5>=$F68,N$5<=$G68),3,"") | O68: =IF(AND(O$5>=$F68,O$5<=$G68),3,"") | P68: =IF(AND(P$5>=$F68,P$5<=$G68),3,"") | Q68: =IF(AND(Q$5>=$F68,Q$5<=$G68),3,"") | R68: =IF(AND(R$5>=$F68,R$5<=$G68),3,"") | ... BN68: =IF(AND(BN$5>=$F68,BN$5<=$G68),3,"")
A69: 3 Construcción | B69: 3.2.3 | C69: Servicio de nube de ingesta de IoT, telemetría cruda y plataforma analítica | D69: E | E69: Operación / SRE | F69: 4 | G69: 4 | H69: =G69-F69+1 | I69: 240 | J69: Con entregable (actividades en hoja «Actividades hasta H2») | K69: =IF(AND(K$5>=$F69,K$5<=$G69),3,"") | L69: =IF(AND(L$5>=$F69,L$5<=$G69),3,"") | M69: =IF(AND(M$5>=$F69,M$5<=$G69),3,"") | N69: =IF(AND(N$5>=$F69,N$5<=$G69),3,"") | O69: =IF(AND(O$5>=$F69,O$5<=$G69),3,"") | P69: =IF(AND(P$5>=$F69,P$5<=$G69),3,"") | Q69: =IF(AND(Q$5>=$F69,Q$5<=$G69),3,"") | R69: =IF(AND(R$5>=$F69,R$5<=$G69),3,"") | ... BN69: =IF(AND(BN$5>=$F69,BN$5<=$G69),3,"")
A70: 3 Construcción | B70: 3.2.4 | C70: Servicio de nube de respaldo inmutable y réplica entre regiones | D70: E | E70: Operación / SRE | F70: 4 | G70: 4 | H70: =G70-F70+1 | I70: 240 | J70: Con entregable (actividades en hoja «Actividades hasta H2») | K70: =IF(AND(K$5>=$F70,K$5<=$G70),3,"") | L70: =IF(AND(L$5>=$F70,L$5<=$G70),3,"") | M70: =IF(AND(M$5>=$F70,M$5<=$G70),3,"") | N70: =IF(AND(N$5>=$F70,N$5<=$G70),3,"") | O70: =IF(AND(O$5>=$F70,O$5<=$G70),3,"") | P70: =IF(AND(P$5>=$F70,P$5<=$G70),3,"") | Q70: =IF(AND(Q$5>=$F70,Q$5<=$G70),3,"") | R70: =IF(AND(R$5>=$F70,R$5<=$G70),3,"") | ... BN70: =IF(AND(BN$5>=$F70,BN$5<=$G70),3,"")
A71: 3 Construcción | B71: 3.2.5 | C71: Servicio de nube de seguridad y gobierno, y detección en endpoints | D71: E | E71: Seguridad | F71: 4 | G71: 4 | H71: =G71-F71+1 | I71: 240 | J71: Con entregable (actividades en hoja «Actividades hasta H2») | K71: =IF(AND(K$5>=$F71,K$5<=$G71),3,"") | L71: =IF(AND(L$5>=$F71,L$5<=$G71),3,"") | M71: =IF(AND(M$5>=$F71,M$5<=$G71),3,"") | N71: =IF(AND(N$5>=$F71,N$5<=$G71),3,"") | O71: =IF(AND(O$5>=$F71,O$5<=$G71),3,"") | P71: =IF(AND(P$5>=$F71,P$5<=$G71),3,"") | Q71: =IF(AND(Q$5>=$F71,Q$5<=$G71),3,"") | R71: =IF(AND(R$5>=$F71,R$5<=$G71),3,"") | ... BN71: =IF(AND(BN$5>=$F71,BN$5<=$G71),3,"")
A72: 3 Construcción | B72: 3.2.6 | C72: Servicio de gestión de dispositivos móviles | D72: E | E72: Operación / SRE | F72: 5 | G72: 5 | H72: =G72-F72+1 | I72: 240 | J72: Con entregable (detalle por planificación gradual) | K72: =IF(AND(K$5>=$F72,K$5<=$G72),3,"") | L72: =IF(AND(L$5>=$F72,L$5<=$G72),3,"") | M72: =IF(AND(M$5>=$F72,M$5<=$G72),3,"") | N72: =IF(AND(N$5>=$F72,N$5<=$G72),3,"") | O72: =IF(AND(O$5>=$F72,O$5<=$G72),3,"") | P72: =IF(AND(P$5>=$F72,P$5<=$G72),3,"") | Q72: =IF(AND(Q$5>=$F72,Q$5<=$G72),3,"") | R72: =IF(AND(R$5>=$F72,R$5<=$G72),3,"") | ... BN72: =IF(AND(BN$5>=$F72,BN$5<=$G72),3,"")
A73: 3 Construcción | B73: 3.3.1 | C73: Identidad y control de acceso, incluidos los conductores externos que rotan sin aviso | D73: I | E73: Seguridad | F73: 5 | G73: 7 | H73: =G73-F73+1 | I73: 480 | J73: Con entregable (detalle por planificación gradual) | K73: =IF(AND(K$5>=$F73,K$5<=$G73),3,"") | L73: =IF(AND(L$5>=$F73,L$5<=$G73),3,"") | M73: =IF(AND(M$5>=$F73,M$5<=$G73),3,"") | N73: =IF(AND(N$5>=$F73,N$5<=$G73),3,"") | O73: =IF(AND(O$5>=$F73,O$5<=$G73),3,"") | P73: =IF(AND(P$5>=$F73,P$5<=$G73),3,"") | Q73: =IF(AND(Q$5>=$F73,Q$5<=$G73),3,"") | R73: =IF(AND(R$5>=$F73,R$5<=$G73),3,"") | ... BN73: =IF(AND(BN$5>=$F73,BN$5<=$G73),3,"")
... A140: 3 Construcción | B140: 3.11.5 | C140: Depósito del código fuente en el repositorio del CLIENTE en cada liberación | D140: G | E140: Desarrollo | F140: 6 | G140: 20 | H140: =G140-F140+1 | I140: 80 | J140: Esfuerzo continuo (por quincena u ocurrencia) | K140: =IF(AND(K$5>=$F140,K$5<=$G140),3,"") | L140: =IF(AND(L$5>=$F140,L$5<=$G140),3,"") | M140: =IF(AND(M$5>=$F140,M$5<=$G140),3,"") | N140: =IF(AND(N$5>=$F140,N$5<=$G140),3,"") | O140: =IF(AND(O$5>=$F140,O$5<=$G140),3,"") | P140: =IF(AND(P$5>=$F140,P$5<=$G140),3,"") | Q140: =IF(AND(Q$5>=$F140,Q$5<=$G140),3,"") | R140: =IF(AND(R$5>=$F140,R$5<=$G140),3,"") | ... BN140: =IF(AND(BN$5>=$F140,BN$5<=$G140),3,"")
A141: 4 Transición | B141: 4.1.1 | C141: Plan de olas de la Etapa 1 por sitio y zona: Talca, Concepción y plataformas de cross-docking | D141: G | E141: Implantación y gestión del cambio | F141: 10 | G141: 10 | H141: =G141-F141+1 | I141: 80 | J141: Con entregable (detalle por planificación gradual) | K141: =IF(AND(K$5>=$F141,K$5<=$G141),4,"") | L141: =IF(AND(L$5>=$F141,L$5<=$G141),4,"") | M141: =IF(AND(M$5>=$F141,M$5<=$G141),4,"") | N141: =IF(AND(N$5>=$F141,N$5<=$G141),4,"") | O141: =IF(AND(O$5>=$F141,O$5<=$G141),4,"") | P141: =IF(AND(P$5>=$F141,P$5<=$G141),4,"") | Q141: =IF(AND(Q$5>=$F141,Q$5<=$G141),4,"") | R141: =IF(AND(R$5>=$F141,R$5<=$G141),4,"") | ... BN141: =IF(AND(BN$5>=$F141,BN$5<=$G141),4,"")
A142: 4 Transición | B142: 4.1.2 | C142: Procedimiento de reversión de la Etapa 1 antes de las 05:30, con hoja de picking y guía en papel | D142: G | E142: Implantación y gestión del cambio | F142: 11 | G142: 11 | H142: =G142-F142+1 | I142: 80 | J142: Con entregable (detalle por planificación gradual) | K142: =IF(AND(K$5>=$F142,K$5<=$G142),4,"") | L142: =IF(AND(L$5>=$F142,L$5<=$G142),4,"") | M142: =IF(AND(M$5>=$F142,M$5<=$G142),4,"") | N142: =IF(AND(N$5>=$F142,N$5<=$G142),4,"") | O142: =IF(AND(O$5>=$F142,O$5<=$G142),4,"") | P142: =IF(AND(P$5>=$F142,P$5<=$G142),4,"") | Q142: =IF(AND(Q$5>=$F142,Q$5<=$G142),4,"") | R142: =IF(AND(R$5>=$F142,R$5<=$G142),4,"") | ... BN142: =IF(AND(BN$5>=$F142,BN$5<=$G142),4,"")
A143: 4 Transición | B143: 4.1.3 | C143: Plan de implantación y reversión de la Etapa 2 fuera de la ventana de 05:30 a 07:00 | D143: G | E143: Implantación y gestión del cambio | F143: 17 | G143: 17 | H143: =G143-F143+1 | I143: 80 | J143: Con entregable (detalle por planificación gradual) | K143: =IF(AND(K$5>=$F143,K$5<=$G143),4,"") | L143: =IF(AND(L$5>=$F143,L$5<=$G143),4,"") | M143: =IF(AND(M$5>=$F143,M$5<=$G143),4,"") | N143: =IF(AND(N$5>=$F143,N$5<=$G143),4,"") | O143: =IF(AND(O$5>=$F143,O$5<=$G143),4,"") | P143: =IF(AND(P$5>=$F143,P$5<=$G143),4,"") | Q143: =IF(AND(Q$5>=$F143,Q$5<=$G143),4,"") | R143: =IF(AND(R$5>=$F143,R$5<=$G143),4,"") | ... BN143: =IF(AND(BN$5>=$F143,BN$5<=$G143),4,"")
A144: 4 Transición | B144: 4.2.1 | C144: Marcha blanca de la Etapa 1 con conciliación diaria (H6) | D144: A | E144: Implantación y gestión del cambio | F144: 13 | G144: 15 | H144: =G144-F144+1 | I144: 7392 | J144: Esfuerzo continuo (por quincena u ocurrencia) | K144: =IF(AND(K$5>=$F144,K$5<=$G144),4,"") | L144: =IF(AND(L$5>=$F144,L$5<=$G144),4,"") | M144: =IF(AND(M$5>=$F144,M$5<=$G144),4,"") | N144: =IF(AND(N$5>=$F144,N$5<=$G144),4,"") | O144: =IF(AND(O$5>=$F144,O$5<=$G144),4,"") | P144: =IF(AND(P$5>=$F144,P$5<=$G144),4,"") | Q144: =IF(AND(Q$5>=$F144,Q$5<=$G144),4,"") | R144: =IF(AND(R$5>=$F144,R$5<=$G144),4,"") | ... BN144: =IF(AND(BN$5>=$F144,BN$5<=$G144),4,"")
A145: 4 Transición | B145: 4.2.2 | C145: Estabilización de la Etapa 1 en el turno de noche y acompañamiento en ruta | D145: A | E145: Implantación y gestión del cambio | F145: 16 | G145: 20 | H145: =G145-F145+1 | I145: 5408 | J145: Esfuerzo continuo (por quincena u ocurrencia) | K145: =IF(AND(K$5>=$F145,K$5<=$G145),4,"") | L145: =IF(AND(L$5>=$F145,L$5<=$G145),4,"") | M145: =IF(AND(M$5>=$F145,M$5<=$G145),4,"") | N145: =IF(AND(N$5>=$F145,N$5<=$G145),4,"") | O145: =IF(AND(O$5>=$F145,O$5<=$G145),4,"") | P145: =IF(AND(P$5>=$F145,P$5<=$G145),4,"") | Q145: =IF(AND(Q$5>=$F145,Q$5<=$G145),4,"") | R145: =IF(AND(R$5>=$F145,R$5<=$G145),4,"") | ... BN145: =IF(AND(BN$5>=$F145,BN$5<=$G145),4,"")
A146: 4 Transición | B146: 4.2.3 | C146: Acta de paso a producción y cierre de la Etapa 1 (H7) | D146: G | E146: Jefe de Proyecto | F146: 16 | G146: 16 | H146: =G146-F146+1 | I146: 80 | J146: Con entregable (detalle por planificación gradual) | K146: =IF(AND(K$5>=$F146,K$5<=$G146),4,"") | L146: =IF(AND(L$5>=$F146,L$5<=$G146),4,"") | M146: =IF(AND(M$5>=$F146,M$5<=$G146),4,"") | N146: =IF(AND(N$5>=$F146,N$5<=$G146),4,"") | O146: =IF(AND(O$5>=$F146,O$5<=$G146),4,"") | P146: =IF(AND(P$5>=$F146,P$5<=$G146),4,"") | Q146: =IF(AND(Q$5>=$F146,Q$5<=$G146),4,"") | R146: =IF(AND(R$5>=$F146,R$5<=$G146),4,"") | ... BN146: =IF(AND(BN$5>=$F146,BN$5<=$G146),4,"")
A147: 4 Transición | B147: 4.3.1 | C147: Marcha blanca de la Etapa 2 en convivencia con la Etapa 1 y fuente única de datos (H11) | D147: A | E147: Implantación y gestión del cambio | F147: 19 | G147: 20 | H147: =G147-F147+1 | I147: 4928 | J147: Esfuerzo continuo (por quincena u ocurrencia) | K147: =IF(AND(K$5>=$F147,K$5<=$G147),4,"") | L147: =IF(AND(L$5>=$F147,L$5<=$G147),4,"") | M147: =IF(AND(M$5>=$F147,M$5<=$G147),4,"") | N147: =IF(AND(N$5>=$F147,N$5<=$G147),4,"") | O147: =IF(AND(O$5>=$F147,O$5<=$G147),4,"") | P147: =IF(AND(P$5>=$F147,P$5<=$G147),4,"") | Q147: =IF(AND(Q$5>=$F147,Q$5<=$G147),4,"") | R147: =IF(AND(R$5>=$F147,R$5<=$G147),4,"") | ... BN147: =IF(AND(BN$5>=$F147,BN$5<=$G147),4,"")
A148: 4 Transición | B148: 4.3.2 | C148: Estabilización de la Etapa 2 con Comercial, Finanzas, cadenas y transportistas | D148: A | E148: Implantación y gestión del cambio | F148: 21 | G148: 22 | H148: =G148-F148+1 | I148: 2464 | J148: Esfuerzo continuo (por quincena u ocurrencia) | K148: =IF(AND(K$5>=$F148,K$5<=$G148),4,"") | L148: =IF(AND(L$5>=$F148,L$5<=$G148),4,"") | M148: =IF(AND(M$5>=$F148,M$5<=$G148),4,"") | N148: =IF(AND(N$5>=$F148,N$5<=$G148),4,"") | O148: =IF(AND(O$5>=$F148,O$5<=$G148),4,"") | P148: =IF(AND(P$5>=$F148,P$5<=$G148),4,"") | Q148: =IF(AND(Q$5>=$F148,Q$5<=$G148),4,"") | R148: =IF(AND(R$5>=$F148,R$5<=$G148),4,"") | ... BN148: =IF(AND(BN$5>=$F148,BN$5<=$G148),4,"")
A149: 4 Transición | B149: 4.3.3 | C149: Acta de paso a producción y aceptación final de la implementación (H12) | D149: G | E149: Jefe de Proyecto | F149: 21 | G149: 21 | H149: =G149-F149+1 | I149: 80 | J149: Con entregable (detalle por planificación gradual) | K149: =IF(AND(K$5>=$F149,K$5<=$G149),4,"") | L149: =IF(AND(L$5>=$F149,L$5<=$G149),4,"") | M149: =IF(AND(M$5>=$F149,M$5<=$G149),4,"") | N149: =IF(AND(N$5>=$F149,N$5<=$G149),4,"") | O149: =IF(AND(O$5>=$F149,O$5<=$G149),4,"") | P149: =IF(AND(P$5>=$F149,P$5<=$G149),4,"") | Q149: =IF(AND(Q$5>=$F149,Q$5<=$G149),4,"") | R149: =IF(AND(R$5>=$F149,R$5<=$G149),4,"") | ... BN149: =IF(AND(BN$5>=$F149,BN$5<=$G149),4,"")
A150: 4 Transición | B150: 4.3.4 | C150: Garantía de correcto funcionamiento constituida, condición de la aceptación final (H12) | D150: G | E150: Jefe de Proyecto | F150: 21 | G150: 21 | H150: =G150-F150+1 | I150: 80 | J150: Con entregable (detalle por planificación gradual) | K150: =IF(AND(K$5>=$F150,K$5<=$G150),4,"") | L150: =IF(AND(L$5>=$F150,L$5<=$G150),4,"") | M150: =IF(AND(M$5>=$F150,M$5<=$G150),4,"") | N150: =IF(AND(N$5>=$F150,N$5<=$G150),4,"") | O150: =IF(AND(O$5>=$F150,O$5<=$G150),4,"") | P150: =IF(AND(P$5>=$F150,P$5<=$G150),4,"") | Q150: =IF(AND(Q$5>=$F150,Q$5<=$G150),4,"") | R150: =IF(AND(R$5>=$F150,R$5<=$G150),4,"") | ... BN150: =IF(AND(BN$5>=$F150,BN$5<=$G150),4,"")
A151: 5 Adquisiciones y contrataciones | B151: 5.1.1 | C151: Especificación de compra del equipamiento de terreno para el CLIENTE | D151: G | E151: Arquitectura | F151: 2 | G151: 2 | H151: =G151-F151+1 | I151: 80 | J151: Con entregable (actividades en hoja «Actividades hasta H2») | K151: =IF(AND(K$5>=$F151,K$5<=$G151),5,"") | L151: =IF(AND(L$5>=$F151,L$5<=$G151),5,"") | M151: =IF(AND(M$5>=$F151,M$5<=$G151),5,"") | N151: =IF(AND(N$5>=$F151,N$5<=$G151),5,"") | O151: =IF(AND(O$5>=$F151,O$5<=$G151),5,"") | P151: =IF(AND(P$5>=$F151,P$5<=$G151),5,"") | Q151: =IF(AND(Q$5>=$F151,Q$5<=$G151),5,"") | R151: =IF(AND(R$5>=$F151,R$5<=$G151),5,"") | ... BN151: =IF(AND(BN$5>=$F151,BN$5<=$G151),5,"")
A152: 5 Adquisiciones y contrataciones | B152: 5.1.2 | C152: Especificación de compra de la sala técnica, los racks y los gabinetes de borde para el CLIENTE | D152: G | E152: Arquitectura | F152: 2 | G152: 2 | H152: =G152-F152+1 | I152: 80 | J152: Con entregable (actividades en hoja «Actividades hasta H2») | K152: =IF(AND(K$5>=$F152,K$5<=$G152),5,"") | L152: =IF(AND(L$5>=$F152,L$5<=$G152),5,"") | M152: =IF(AND(M$5>=$F152,M$5<=$G152),5,"") | N152: =IF(AND(N$5>=$F152,N$5<=$G152),5,"") | O152: =IF(AND(O$5>=$F152,O$5<=$G152),5,"") | P152: =IF(AND(P$5>=$F152,P$5<=$G152),5,"") | Q152: =IF(AND(Q$5>=$F152,Q$5<=$G152),5,"") | R152: =IF(AND(R$5>=$F152,R$5<=$G152),5,"") | ... BN152: =IF(AND(BN$5>=$F152,BN$5<=$G152),5,"")
A153: 5 Adquisiciones y contrataciones | B153: 5.1.3 | C153: Actas de recepción técnica de los equipos comprados por el CLIENTE | D153: G | E153: Operación / SRE | F153: 5 | G153: 5 | H153: =G153-F153+1 | I153: 80 | J153: Con entregable (detalle por planificación gradual) | K153: =IF(AND(K$5>=$F153,K$5<=$G153),5,"") | L153: =IF(AND(L$5>=$F153,L$5<=$G153),5,"") | M153: =IF(AND(M$5>=$F153,M$5<=$G153),5,"") | N153: =IF(AND(N$5>=$F153,N$5<=$G153),5,"") | O153: =IF(AND(O$5>=$F153,O$5<=$G153),5,"") | P153: =IF(AND(P$5>=$F153,P$5<=$G153),5,"") | Q153: =IF(AND(Q$5>=$F153,Q$5<=$G153),5,"") | R153: =IF(AND(R$5>=$F153,R$5<=$G153),5,"") | ... BN153: =IF(AND(BN$5>=$F153,BN$5<=$G153),5,"")
A154: 5 Adquisiciones y contrataciones | B154: 5.2.1 | C154: Contrato de los servicios de AWS | D154: G | E154: Operación / SRE | F154: 2 | G154: 2 | H154: =G154-F154+1 | I154: 80 | J154: Con entregable (actividades en hoja «Actividades hasta H2») | K154: =IF(AND(K$5>=$F154,K$5<=$G154),5,"") | L154: =IF(AND(L$5>=$F154,L$5<=$G154),5,"") | M154: =IF(AND(M$5>=$F154,M$5<=$G154),5,"") | N154: =IF(AND(N$5>=$F154,N$5<=$G154),5,"") | O154: =IF(AND(O$5>=$F154,O$5<=$G154),5,"") | P154: =IF(AND(P$5>=$F154,P$5<=$G154),5,"") | Q154: =IF(AND(Q$5>=$F154,Q$5<=$G154),5,"") | R154: =IF(AND(R$5>=$F154,R$5<=$G154),5,"") | ... BN154: =IF(AND(BN$5>=$F154,BN$5<=$G154),5,"")
A155: 5 Adquisiciones y contrataciones | B155: 5.2.2 | C155: Suscripción del servicio de gestión de dispositivos y de detección en endpoints | D155: G | E155: Operación / SRE | F155: 4 | G155: 4 | H155: =G155-F155+1 | I155: 80 | J155: Con entregable (actividades en hoja «Actividades hasta H2») | K155: =IF(AND(K$5>=$F155,K$5<=$G155),5,"") | L155: =IF(AND(L$5>=$F155,L$5<=$G155),5,"") | M155: =IF(AND(M$5>=$F155,M$5<=$G155),5,"") | N155: =IF(AND(N$5>=$F155,N$5<=$G155),5,"") | O155: =IF(AND(O$5>=$F155,O$5<=$G155),5,"") | P155: =IF(AND(P$5>=$F155,P$5<=$G155),5,"") | Q155: =IF(AND(Q$5>=$F155,Q$5<=$G155),5,"") | R155: =IF(AND(R$5>=$F155,R$5<=$G155),5,"") | ... BN155: =IF(AND(BN$5>=$F155,BN$5<=$G155),5,"")
A156: 5 Adquisiciones y contrataciones | B156: 5.2.3 | C156: Licencias de software de terceros constituidas a nombre del CLIENTE | D156: G | E156: Arquitectura | F156: 4 | G156: 4 | H156: =G156-F156+1 | I156: 80 | J156: Con entregable (actividades en hoja «Actividades hasta H2») | K156: =IF(AND(K$5>=$F156,K$5<=$G156),5,"") | L156: =IF(AND(L$5>=$F156,L$5<=$G156),5,"") | M156: =IF(AND(M$5>=$F156,M$5<=$G156),5,"") | N156: =IF(AND(N$5>=$F156,N$5<=$G156),5,"") | O156: =IF(AND(O$5>=$F156,O$5<=$G156),5,"") | P156: =IF(AND(P$5>=$F156,P$5<=$G156),5,"") | Q156: =IF(AND(Q$5>=$F156,Q$5<=$G156),5,"") | R156: =IF(AND(R$5>=$F156,R$5<=$G156),5,"") | ... BN156: =IF(AND(BN$5>=$F156,BN$5<=$G156),5,"")
A157: 5 Adquisiciones y contrataciones | B157: 5.3.1 | C157: Contrato de fibra óptica de los CD de Talca y Concepción | D157: G | E157: Operación / SRE | F157: 4 | G157: 4 | H157: =G157-F157+1 | I157: 80 | J157: Con entregable (actividades en hoja «Actividades hasta H2») | K157: =IF(AND(K$5>=$F157,K$5<=$G157),5,"") | L157: =IF(AND(L$5>=$F157,L$5<=$G157),5,"") | M157: =IF(AND(M$5>=$F157,M$5<=$G157),5,"") | N157: =IF(AND(N$5>=$F157,N$5<=$G157),5,"") | O157: =IF(AND(O$5>=$F157,O$5<=$G157),5,"") | P157: =IF(AND(P$5>=$F157,P$5<=$G157),5,"") | Q157: =IF(AND(Q$5>=$F157,Q$5<=$G157),5,"") | R157: =IF(AND(R$5>=$F157,R$5<=$G157),5,"") | ... BN157: =IF(AND(BN$5>=$F157,BN$5<=$G157),5,"")
A158: 5 Adquisiciones y contrataciones | B158: 5.3.2 | C158: Contrato de planes LTE con dos proveedores | D158: G | E158: Operación / SRE | F158: 4 | G158: 4 | H158: =G158-F158+1 | I158: 80 | J158: Con entregable (actividades en hoja «Actividades hasta H2») | K158: =IF(AND(K$5>=$F158,K$5<=$G158),5,"") | L158: =IF(AND(L$5>=$F158,L$5<=$G158),5,"") | M158: =IF(AND(M$5>=$F158,M$5<=$G158),5,"") | N158: =IF(AND(N$5>=$F158,N$5<=$G158),5,"") | O158: =IF(AND(O$5>=$F158,O$5<=$G158),5,"") | P158: =IF(AND(P$5>=$F158,P$5<=$G158),5,"") | Q158: =IF(AND(Q$5>=$F158,Q$5<=$G158),5,"") | R158: =IF(AND(R$5>=$F158,R$5<=$G158),5,"") | ... BN158: =IF(AND(BN$5>=$F158,BN$5<=$G158),5,"")
A159: 5 Adquisiciones y contrataciones | B159: 5.3.3 | C159: Contrato de Starlink para las tres plataformas de cross-docking | D159: G | E159: Operación / SRE | F159: 4 | G159: 4 | H159: =G159-F159+1 | I159: 80 | J159: Con entregable (actividades en hoja «Actividades hasta H2») | K159: =IF(AND(K$5>=$F159,K$5<=$G159),5,"") | L159: =IF(AND(L$5>=$F159,L$5<=$G159),5,"") | M159: =IF(AND(M$5>=$F159,M$5<=$G159),5,"") | N159: =IF(AND(N$5>=$F159,N$5<=$G159),5,"") | O159: =IF(AND(O$5>=$F159,O$5<=$G159),5,"") | P159: =IF(AND(P$5>=$F159,P$5<=$G159),5,"") | Q159: =IF(AND(Q$5>=$F159,Q$5<=$G159),5,"") | R159: =IF(AND(R$5>=$F159,R$5<=$G159),5,"") | ... BN159: =IF(AND(BN$5>=$F159,BN$5<=$G159),5,"")
A160: 5 Adquisiciones y contrataciones | B160: 5.4.1 | C160: Acuerdos operacionales firmados con los diez transportistas | D160: G | E160: Implantación y gestión del cambio | F160: 9 | G160: 12 | H160: =G160-F160+1 | I160: 80 | J160: Con entregable (detalle por planificación gradual) | K160: =IF(AND(K$5>=$F160,K$5<=$G160),5,"") | L160: =IF(AND(L$5>=$F160,L$5<=$G160),5,"") | M160: =IF(AND(M$5>=$F160,M$5<=$G160),5,"") | N160: =IF(AND(N$5>=$F160,N$5<=$G160),5,"") | O160: =IF(AND(O$5>=$F160,O$5<=$G160),5,"") | P160: =IF(AND(P$5>=$F160,P$5<=$G160),5,"") | Q160: =IF(AND(Q$5>=$F160,Q$5<=$G160),5,"") | R160: =IF(AND(R$5>=$F160,R$5<=$G160),5,"") | ... BN160: =IF(AND(BN$5>=$F160,BN$5<=$G160),5,"")
A161: 5 Adquisiciones y contrataciones | B161: 5.4.2 | C161: Acta de acuerdo con el sindicato sobre terminales, GPS y cámaras | D161: G | E161: Implantación y gestión del cambio | F161: 9 | G161: 12 | H161: =G161-F161+1 | I161: 80 | J161: Con entregable (detalle por planificación gradual) | K161: =IF(AND(K$5>=$F161,K$5<=$G161),5,"") | L161: =IF(AND(L$5>=$F161,L$5<=$G161),5,"") | M161: =IF(AND(M$5>=$F161,M$5<=$G161),5,"") | N161: =IF(AND(N$5>=$F161,N$5<=$G161),5,"") | O161: =IF(AND(O$5>=$F161,O$5<=$G161),5,"") | P161: =IF(AND(P$5>=$F161,P$5<=$G161),5,"") | Q161: =IF(AND(Q$5>=$F161,Q$5<=$G161),5,"") | R161: =IF(AND(R$5>=$F161,R$5<=$G161),5,"") | ... BN161: =IF(AND(BN$5>=$F161,BN$5<=$G161),5,"")
A162: 5 Adquisiciones y contrataciones | B162: 5.4.3 | C162: Fórmula aprobada del tramo variable: reglas de atribución, canasta e índices (INN-04.P1) | D162: G | E162: Jefe de Proyecto | F162: 17 | G162: 20 | H162: =G162-F162+1 | I162: 80 | J162: Con entregable (detalle por planificación gradual) | K162: =IF(AND(K$5>=$F162,K$5<=$G162),5,"") | L162: =IF(AND(L$5>=$F162,L$5<=$G162),5,"") | M162: =IF(AND(M$5>=$F162,M$5<=$G162),5,"") | N162: =IF(AND(N$5>=$F162,N$5<=$G162),5,"") | O162: =IF(AND(O$5>=$F162,O$5<=$G162),5,"") | P162: =IF(AND(P$5>=$F162,P$5<=$G162),5,"") | Q162: =IF(AND(Q$5>=$F162,Q$5<=$G162),5,"") | R162: =IF(AND(R$5>=$F162,R$5<=$G162),5,"") | ... BN162: =IF(AND(BN$5>=$F162,BN$5<=$G162),5,"")
A163: 5 Adquisiciones y contrataciones | B163: 5.4.4 | C163: Contrato de custodia de fuentes con un tercero independiente | D163: G | E163: Jefe de Proyecto | F163: 7 | G163: 7 | H163: =G163-F163+1 | I163: 80 | J163: Con entregable (detalle por planificación gradual) | K163: =IF(AND(K$5>=$F163,K$5<=$G163),5,"") | L163: =IF(AND(L$5>=$F163,L$5<=$G163),5,"") | M163: =IF(AND(M$5>=$F163,M$5<=$G163),5,"") | N163: =IF(AND(N$5>=$F163,N$5<=$G163),5,"") | O163: =IF(AND(O$5>=$F163,O$5<=$G163),5,"") | P163: =IF(AND(P$5>=$F163,P$5<=$G163),5,"") | Q163: =IF(AND(Q$5>=$F163,Q$5<=$G163),5,"") | R163: =IF(AND(R$5>=$F163,R$5<=$G163),5,"") | ... BN163: =IF(AND(BN$5>=$F163,BN$5<=$G163),5,"")
A164: 6 Infraestructura física y sitios | B164: 6.1.1 | C164: Obra civil y piso técnico de la sala | D164: T | E164: Operación / SRE | F164: 3 | G164: 3 | H164: =G164-F164+1 | I164: 160 | J164: Con entregable (actividades en hoja «Actividades hasta H2») | K164: =IF(AND(K$5>=$F164,K$5<=$G164),6,"") | L164: =IF(AND(L$5>=$F164,L$5<=$G164),6,"") | M164: =IF(AND(M$5>=$F164,M$5<=$G164),6,"") | N164: =IF(AND(N$5>=$F164,N$5<=$G164),6,"") | O164: =IF(AND(O$5>=$F164,O$5<=$G164),6,"") | P164: =IF(AND(P$5>=$F164,P$5<=$G164),6,"") | Q164: =IF(AND(Q$5>=$F164,Q$5<=$G164),6,"") | R164: =IF(AND(R$5>=$F164,R$5<=$G164),6,"") | ... BN164: =IF(AND(BN$5>=$F164,BN$5<=$G164),6,"")
A165: 6 Infraestructura física y sitios | B165: 6.1.2 | C165: Hardware de energía instalado: UPS modular N+1, generador con 24 horas de autonomía, transferencia automática y PDU A/B | D165: T | E165: Operación / SRE | F165: 3 | G165: 3 | H165: =G165-F165+1 | I165: 160 | J165: Con entregable (actividades en hoja «Actividades hasta H2») | K165: =IF(AND(K$5>=$F165,K$5<=$G165),6,"") | L165: =IF(AND(L$5>=$F165,L$5<=$G165),6,"") | M165: =IF(AND(M$5>=$F165,M$5<=$G165),6,"") | N165: =IF(AND(N$5>=$F165,N$5<=$G165),6,"") | O165: =IF(AND(O$5>=$F165,O$5<=$G165),6,"") | P165: =IF(AND(P$5>=$F165,P$5<=$G165),6,"") | Q165: =IF(AND(Q$5>=$F165,Q$5<=$G165),6,"") | R165: =IF(AND(R$5>=$F165,R$5<=$G165),6,"") | ... BN165: =IF(AND(BN$5>=$F165,BN$5<=$G165),6,"")
A166: 6 Infraestructura física y sitios | B166: 6.1.3 | C166: Hardware de climatización de precisión N+1 instalado | D166: T | E166: Operación / SRE | F166: 3 | G166: 3 | H166: =G166-F166+1 | I166: 160 | J166: Con entregable (actividades en hoja «Actividades hasta H2») | K166: =IF(AND(K$5>=$F166,K$5<=$G166),6,"") | L166: =IF(AND(L$5>=$F166,L$5<=$G166),6,"") | M166: =IF(AND(M$5>=$F166,M$5<=$G166),6,"") | N166: =IF(AND(N$5>=$F166,N$5<=$G166),6,"") | O166: =IF(AND(O$5>=$F166,O$5<=$G166),6,"") | P166: =IF(AND(P$5>=$F166,P$5<=$G166),6,"") | Q166: =IF(AND(Q$5>=$F166,Q$5<=$G166),6,"") | R166: =IF(AND(R$5>=$F166,R$5<=$G166),6,"") | ... BN166: =IF(AND(BN$5>=$F166,BN$5<=$G166),6,"")
A167: 6 Infraestructura física y sitios | B167: 6.1.4 | C167: Hardware de detección temprana de incendio y extinción por agente limpio instalado | D167: T | E167: Operación / SRE | F167: 3 | G167: 3 | H167: =G167-F167+1 | I167: 160 | J167: Con entregable (actividades en hoja «Actividades hasta H2») | K167: =IF(AND(K$5>=$F167,K$5<=$G167),6,"") | L167: =IF(AND(L$5>=$F167,L$5<=$G167),6,"") | M167: =IF(AND(M$5>=$F167,M$5<=$G167),6,"") | N167: =IF(AND(N$5>=$F167,N$5<=$G167),6,"") | O167: =IF(AND(O$5>=$F167,O$5<=$G167),6,"") | P167: =IF(AND(P$5>=$F167,P$5<=$G167),6,"") | Q167: =IF(AND(Q$5>=$F167,Q$5<=$G167),6,"") | R167: =IF(AND(R$5>=$F167,R$5<=$G167),6,"") | ... BN167: =IF(AND(BN$5>=$F167,BN$5<=$G167),6,"")
A168: 6 Infraestructura física y sitios | B168: 6.1.5 | C168: Acta de recepción técnica de la sala | D168: T | E168: Operación / SRE | F168: 4 | G168: 4 | H168: =G168-F168+1 | I168: 160 | J168: Con entregable (actividades en hoja «Actividades hasta H2») | K168: =IF(AND(K$5>=$F168,K$5<=$G168),6,"") | L168: =IF(AND(L$5>=$F168,L$5<=$G168),6,"") | M168: =IF(AND(M$5>=$F168,M$5<=$G168),6,"") | N168: =IF(AND(N$5>=$F168,N$5<=$G168),6,"") | O168: =IF(AND(O$5>=$F168,O$5<=$G168),6,"") | P168: =IF(AND(P$5>=$F168,P$5<=$G168),6,"") | Q168: =IF(AND(Q$5>=$F168,Q$5<=$G168),6,"") | R168: =IF(AND(R$5>=$F168,R$5<=$G168),6,"") | ... BN168: =IF(AND(BN$5>=$F168,BN$5<=$G168),6,"")
A169: 6 Infraestructura física y sitios | B169: 6.2.1 | C169: Cableado de cobre Cat6A y fibra OM4 tendido, con dos ductos de ingreso independientes | D169: T | E169: Operación / SRE | F169: 4 | G169: 4 | H169: =G169-F169+1 | I169: 160 | J169: Con entregable (actividades en hoja «Actividades hasta H2») | K169: =IF(AND(K$5>=$F169,K$5<=$G169),6,"") | L169: =IF(AND(L$5>=$F169,L$5<=$G169),6,"") | M169: =IF(AND(M$5>=$F169,M$5<=$G169),6,"") | N169: =IF(AND(N$5>=$F169,N$5<=$G169),6,"") | O169: =IF(AND(O$5>=$F169,O$5<=$G169),6,"") | P169: =IF(AND(P$5>=$F169,P$5<=$G169),6,"") | Q169: =IF(AND(Q$5>=$F169,Q$5<=$G169),6,"") | R169: =IF(AND(R$5>=$F169,R$5<=$G169),6,"") | ... BN169: =IF(AND(BN$5>=$F169,BN$5<=$G169),6,"")
A170: 6 Infraestructura física y sitios | B170: 6.2.2 | C170: Certificación de enlaces, etiquetado y planos as-built | D170: T | E170: Operación / SRE | F170: 6 | G170: 6 | H170: =G170-F170+1 | I170: 160 | J170: Con entregable (detalle por planificación gradual) | K170: =IF(AND(K$5>=$F170,K$5<=$G170),6,"") | L170: =IF(AND(L$5>=$F170,L$5<=$G170),6,"") | M170: =IF(AND(M$5>=$F170,M$5<=$G170),6,"") | N170: =IF(AND(N$5>=$F170,N$5<=$G170),6,"") | O170: =IF(AND(O$5>=$F170,O$5<=$G170),6,"") | P170: =IF(AND(P$5>=$F170,P$5<=$G170),6,"") | Q170: =IF(AND(Q$5>=$F170,Q$5<=$G170),6,"") | R170: =IF(AND(R$5>=$F170,R$5<=$G170),6,"") | ... BN170: =IF(AND(BN$5>=$F170,BN$5<=$G170),6,"")
A171: 6 Infraestructura física y sitios | B171: 6.2.3 | C171: Gabinetes de piso y switches de acceso instalados en las bodegas de Talca y Concepción | D171: T | E171: Operación / SRE | F171: 7 | G171: 7 | H171: =G171-F171+1 | I171: 160 | J171: Con entregable (detalle por planificación gradual) | K171: =IF(AND(K$5>=$F171,K$5<=$G171),6,"") | L171: =IF(AND(L$5>=$F171,L$5<=$G171),6,"") | M171: =IF(AND(M$5>=$F171,M$5<=$G171),6,"") | N171: =IF(AND(N$5>=$F171,N$5<=$G171),6,"") | O171: =IF(AND(O$5>=$F171,O$5<=$G171),6,"") | P171: =IF(AND(P$5>=$F171,P$5<=$G171),6,"") | Q171: =IF(AND(Q$5>=$F171,Q$5<=$G171),6,"") | R171: =IF(AND(R$5>=$F171,R$5<=$G171),6,"") | ... BN171: =IF(AND(BN$5>=$F171,BN$5<=$G171),6,"")
A172: 6 Infraestructura física y sitios | B172: 6.3.1 | C172: Rack R01 de servidores montado: clúster de tres nodos, respaldo local y consola KVM | D172: T | E172: Operación / SRE | F172: 4 | G172: 5 | H172: =G172-F172+1 | I172: 160 | J172: Con entregable (detalle por planificación gradual) | K172: =IF(AND(K$5>=$F172,K$5<=$G172),6,"") | L172: =IF(AND(L$5>=$F172,L$5<=$G172),6,"") | M172: =IF(AND(M$5>=$F172,M$5<=$G172),6,"") | N172: =IF(AND(N$5>=$F172,N$5<=$G172),6,"") | O172: =IF(AND(O$5>=$F172,O$5<=$G172),6,"") | P172: =IF(AND(P$5>=$F172,P$5<=$G172),6,"") | Q172: =IF(AND(Q$5>=$F172,Q$5<=$G172),6,"") | R172: =IF(AND(R$5>=$F172,R$5<=$G172),6,"") | ... BN172: =IF(AND(BN$5>=$F172,BN$5<=$G172),6,"")
A173: 6 Infraestructura física y sitios | B173: 6.3.2 | C173: Rack R02 de comunicaciones montado: firewalls, switches de núcleo y de gestión, y distribución de fibra | D173: T | E173: Operación / SRE | F173: 4 | G173: 5 | H173: =G173-F173+1 | I173: 160 | J173: Con entregable (detalle por planificación gradual) | K173: =IF(AND(K$5>=$F173,K$5<=$G173),6,"") | L173: =IF(AND(L$5>=$F173,L$5<=$G173),6,"") | M173: =IF(AND(M$5>=$F173,M$5<=$G173),6,"") | N173: =IF(AND(N$5>=$F173,N$5<=$G173),6,"") | O173: =IF(AND(O$5>=$F173,O$5<=$G173),6,"") | P173: =IF(AND(P$5>=$F173,P$5<=$G173),6,"") | Q173: =IF(AND(Q$5>=$F173,Q$5<=$G173),6,"") | R173: =IF(AND(R$5>=$F173,R$5<=$G173),6,"") | ... BN173: =IF(AND(BN$5>=$F173,BN$5<=$G173),6,"")
A174: 6 Infraestructura física y sitios | B174: 6.3.3 | C174: Gabinete de borde de Concepción montado: servidor, firewalls, switches, UPS, climatización y monitoreo | D174: T | E174: Operación / SRE | F174: 4 | G174: 4 | H174: =G174-F174+1 | I174: 160 | J174: Con entregable (actividades en hoja «Actividades hasta H2») | K174: =IF(AND(K$5>=$F174,K$5<=$G174),6,"") | L174: =IF(AND(L$5>=$F174,L$5<=$G174),6,"") | M174: =IF(AND(M$5>=$F174,M$5<=$G174),6,"") | N174: =IF(AND(N$5>=$F174,N$5<=$G174),6,"") | O174: =IF(AND(O$5>=$F174,O$5<=$G174),6,"") | P174: =IF(AND(P$5>=$F174,P$5<=$G174),6,"") | Q174: =IF(AND(Q$5>=$F174,Q$5<=$G174),6,"") | R174: =IF(AND(R$5>=$F174,R$5<=$G174),6,"") | ... BN174: =IF(AND(BN$5>=$F174,BN$5<=$G174),6,"")
A175: 6 Infraestructura física y sitios | B175: 6.3.4 | C175: Gabinetes de borde montados en Curicó, Chillán y Los Ángeles | D175: T | E175: Operación / SRE | F175: 9 | G175: 9 | H175: =G175-F175+1 | I175: 160 | J175: Con entregable (detalle por planificación gradual) | K175: =IF(AND(K$5>=$F175,K$5<=$G175),6,"") | L175: =IF(AND(L$5>=$F175,L$5<=$G175),6,"") | M175: =IF(AND(M$5>=$F175,M$5<=$G175),6,"") | N175: =IF(AND(N$5>=$F175,N$5<=$G175),6,"") | O175: =IF(AND(O$5>=$F175,O$5<=$G175),6,"") | P175: =IF(AND(P$5>=$F175,P$5<=$G175),6,"") | Q175: =IF(AND(Q$5>=$F175,Q$5<=$G175),6,"") | R175: =IF(AND(R$5>=$F175,R$5<=$G175),6,"") | ... BN175: =IF(AND(BN$5>=$F175,BN$5<=$G175),6,"")
... A187: 6 Infraestructura física y sitios | B187: 6.6.3 | C187: Borde de los CD en servicio, con la prueba de autonomía de 24 horas aprobada | D187: T | E187: Operación / SRE | F187: 5 | G187: 5 | H187: =G187-F187+1 | I187: 160 | J187: Con entregable (detalle por planificación gradual) | K187: =IF(AND(K$5>=$F187,K$5<=$G187),6,"") | L187: =IF(AND(L$5>=$F187,L$5<=$G187),6,"") | M187: =IF(AND(M$5>=$F187,M$5<=$G187),6,"") | N187: =IF(AND(N$5>=$F187,N$5<=$G187),6,"") | O187: =IF(AND(O$5>=$F187,O$5<=$G187),6,"") | P187: =IF(AND(P$5>=$F187,P$5<=$G187),6,"") | Q187: =IF(AND(Q$5>=$F187,Q$5<=$G187),6,"") | R187: =IF(AND(R$5>=$F187,R$5<=$G187),6,"") | ... BN187: =IF(AND(BN$5>=$F187,BN$5<=$G187),6,"")
A188: 7 Capacitación y gestión del cambio | B188: 7.1.1 | C188: Plan de capacitación por perfil: usuarios finales, avanzados, administradores, equipo técnico y soporte | D188: T | E188: Implantación y gestión del cambio | F188: 10 | G188: 12 | H188: =G188-F188+1 | I188: 160 | J188: Con entregable (detalle por planificación gradual) | K188: =IF(AND(K$5>=$F188,K$5<=$G188),7,"") | L188: =IF(AND(L$5>=$F188,L$5<=$G188),7,"") | M188: =IF(AND(M$5>=$F188,M$5<=$G188),7,"") | N188: =IF(AND(N$5>=$F188,N$5<=$G188),7,"") | O188: =IF(AND(O$5>=$F188,O$5<=$G188),7,"") | P188: =IF(AND(P$5>=$F188,P$5<=$G188),7,"") | Q188: =IF(AND(Q$5>=$F188,Q$5<=$G188),7,"") | R188: =IF(AND(R$5>=$F188,R$5<=$G188),7,"") | ... BN188: =IF(AND(BN$5>=$F188,BN$5<=$G188),7,"")
A189: 7 Capacitación y gestión del cambio | B189: 7.1.2 | C189: Programa de capacitación continua del turno de noche por la rotación del 38 % | D189: R | E189: Implantación y gestión del cambio | F189: 13 | G189: 56 | H189: =G189-F189+1 | I189: 2816 | J189: Esfuerzo continuo (por quincena u ocurrencia) | K189: =IF(AND(K$5>=$F189,K$5<=$G189),7,"") | L189: =IF(AND(L$5>=$F189,L$5<=$G189),7,"") | M189: =IF(AND(M$5>=$F189,M$5<=$G189),7,"") | N189: =IF(AND(N$5>=$F189,N$5<=$G189),7,"") | O189: =IF(AND(O$5>=$F189,O$5<=$G189),7,"") | P189: =IF(AND(P$5>=$F189,P$5<=$G189),7,"") | Q189: =IF(AND(Q$5>=$F189,Q$5<=$G189),7,"") | R189: =IF(AND(R$5>=$F189,R$5<=$G189),7,"") | ... BN189: =IF(AND(BN$5>=$F189,BN$5<=$G189),7,"")
A190: 7 Capacitación y gestión del cambio | B190: 7.1.3 | C190: Procedimiento de incorporación de los conductores de los transportistas en el andén | D190: T | E190: Implantación y gestión del cambio | F190: 13 | G190: 20 | H190: =G190-F190+1 | I190: 160 | J190: Esfuerzo continuo (por quincena u ocurrencia) | K190: =IF(AND(K$5>=$F190,K$5<=$G190),7,"") | L190: =IF(AND(L$5>=$F190,L$5<=$G190),7,"") | M190: =IF(AND(M$5>=$F190,M$5<=$G190),7,"") | N190: =IF(AND(N$5>=$F190,N$5<=$G190),7,"") | O190: =IF(AND(O$5>=$F190,O$5<=$G190),7,"") | P190: =IF(AND(P$5>=$F190,P$5<=$G190),7,"") | Q190: =IF(AND(Q$5>=$F190,Q$5<=$G190),7,"") | R190: =IF(AND(R$5>=$F190,R$5<=$G190),7,"") | ... BN190: =IF(AND(BN$5>=$F190,BN$5<=$G190),7,"")
A191: 7 Capacitación y gestión del cambio | B191: 7.1.4 | C191: Traspaso al equipo de TI de cuatro personas del CLIENTE | D191: T | E191: Implantación y gestión del cambio | F191: 15 | G191: 20 | H191: =G191-F191+1 | I191: 160 | J191: Esfuerzo continuo (por quincena u ocurrencia) | K191: =IF(AND(K$5>=$F191,K$5<=$G191),7,"") | L191: =IF(AND(L$5>=$F191,L$5<=$G191),7,"") | M191: =IF(AND(M$5>=$F191,M$5<=$G191),7,"") | N191: =IF(AND(N$5>=$F191,N$5<=$G191),7,"") | O191: =IF(AND(O$5>=$F191,O$5<=$G191),7,"") | P191: =IF(AND(P$5>=$F191,P$5<=$G191),7,"") | Q191: =IF(AND(Q$5>=$F191,Q$5<=$G191),7,"") | R191: =IF(AND(R$5>=$F191,R$5<=$G191),7,"") | ... BN191: =IF(AND(BN$5>=$F191,BN$5<=$G191),7,"")
A192: 7 Capacitación y gestión del cambio | B192: 7.1.5 | C192: Materiales de capacitación: manuales por perfil, guías rápidas, preguntas frecuentes y videos tutoriales | D192: T | E192: Implantación y gestión del cambio | F192: 10 | G192: 18 | H192: =G192-F192+1 | I192: 160 | J192: Esfuerzo continuo (por quincena u ocurrencia) | K192: =IF(AND(K$5>=$F192,K$5<=$G192),7,"") | L192: =IF(AND(L$5>=$F192,L$5<=$G192),7,"") | M192: =IF(AND(M$5>=$F192,M$5<=$G192),7,"") | N192: =IF(AND(N$5>=$F192,N$5<=$G192),7,"") | O192: =IF(AND(O$5>=$F192,O$5<=$G192),7,"") | P192: =IF(AND(P$5>=$F192,P$5<=$G192),7,"") | Q192: =IF(AND(Q$5>=$F192,Q$5<=$G192),7,"") | R192: =IF(AND(R$5>=$F192,R$5<=$G192),7,"") | ... BN192: =IF(AND(BN$5>=$F192,BN$5<=$G192),7,"")
A193: 7 Capacitación y gestión del cambio | B193: 7.1.6 | C193: Plataforma de autoformación en línea con registro de avance | D193: T | E193: Implantación y gestión del cambio | F193: 10 | G193: 12 | H193: =G193-F193+1 | I193: 160 | J193: Con entregable (detalle por planificación gradual) | K193: =IF(AND(K$5>=$F193,K$5<=$G193),7,"") | L193: =IF(AND(L$5>=$F193,L$5<=$G193),7,"") | M193: =IF(AND(M$5>=$F193,M$5<=$G193),7,"") | N193: =IF(AND(N$5>=$F193,N$5<=$G193),7,"") | O193: =IF(AND(O$5>=$F193,O$5<=$G193),7,"") | P193: =IF(AND(P$5>=$F193,P$5<=$G193),7,"") | Q193: =IF(AND(Q$5>=$F193,Q$5<=$G193),7,"") | R193: =IF(AND(R$5>=$F193,R$5<=$G193),7,"") | ... BN193: =IF(AND(BN$5>=$F193,BN$5<=$G193),7,"")
A194: 7 Capacitación y gestión del cambio | B194: 7.2.1 | C194: Acompañamiento del personal con 20 o 30 años en la compañía | D194: T | E194: Implantación y gestión del cambio | F194: 10 | G194: 16 | H194: =G194-F194+1 | I194: 160 | J194: Esfuerzo continuo (por quincena u ocurrencia) | K194: =IF(AND(K$5>=$F194,K$5<=$G194),7,"") | L194: =IF(AND(L$5>=$F194,L$5<=$G194),7,"") | M194: =IF(AND(M$5>=$F194,M$5<=$G194),7,"") | N194: =IF(AND(N$5>=$F194,N$5<=$G194),7,"") | O194: =IF(AND(O$5>=$F194,O$5<=$G194),7,"") | P194: =IF(AND(P$5>=$F194,P$5<=$G194),7,"") | Q194: =IF(AND(Q$5>=$F194,Q$5<=$G194),7,"") | R194: =IF(AND(R$5>=$F194,R$5<=$G194),7,"") | ... BN194: =IF(AND(BN$5>=$F194,BN$5<=$G194),7,"")
A195: 7 Capacitación y gestión del cambio | B195: 7.2.2 | C195: Gestión del cambio con las cadenas y los transportistas | D195: T | E195: Implantación y gestión del cambio | F195: 16 | G195: 18 | H195: =G195-F195+1 | I195: 160 | J195: Con entregable (detalle por planificación gradual) | K195: =IF(AND(K$5>=$F195,K$5<=$G195),7,"") | L195: =IF(AND(L$5>=$F195,L$5<=$G195),7,"") | M195: =IF(AND(M$5>=$F195,M$5<=$G195),7,"") | N195: =IF(AND(N$5>=$F195,N$5<=$G195),7,"") | O195: =IF(AND(O$5>=$F195,O$5<=$G195),7,"") | P195: =IF(AND(P$5>=$F195,P$5<=$G195),7,"") | Q195: =IF(AND(Q$5>=$F195,Q$5<=$G195),7,"") | R195: =IF(AND(R$5>=$F195,R$5<=$G195),7,"") | ... BN195: =IF(AND(BN$5>=$F195,BN$5<=$G195),7,"")
A196: 7 Capacitación y gestión del cambio | B196: 7.2.3 | C196: Diagnóstico del impacto organizacional por área y perfil, con agentes de cambio | D196: T | E196: Implantación y gestión del cambio | F196: 2 | G196: 6 | H196: =G196-F196+1 | I196: 160 | J196: Con entregable (actividades en hoja «Actividades hasta H2») | K196: =IF(AND(K$5>=$F196,K$5<=$G196),7,"") | L196: =IF(AND(L$5>=$F196,L$5<=$G196),7,"") | M196: =IF(AND(M$5>=$F196,M$5<=$G196),7,"") | N196: =IF(AND(N$5>=$F196,N$5<=$G196),7,"") | O196: =IF(AND(O$5>=$F196,O$5<=$G196),7,"") | P196: =IF(AND(P$5>=$F196,P$5<=$G196),7,"") | Q196: =IF(AND(Q$5>=$F196,Q$5<=$G196),7,"") | R196: =IF(AND(R$5>=$F196,R$5<=$G196),7,"") | ... BN196: =IF(AND(BN$5>=$F196,BN$5<=$G196),7,"")
A197: 7 Capacitación y gestión del cambio | B197: 7.2.4 | C197: Procedimientos operativos afectados, rediseñados y documentados | D197: T | E197: Implantación y gestión del cambio | F197: 11 | G197: 20 | H197: =G197-F197+1 | I197: 160 | J197: Esfuerzo continuo (por quincena u ocurrencia) | K197: =IF(AND(K$5>=$F197,K$5<=$G197),7,"") | L197: =IF(AND(L$5>=$F197,L$5<=$G197),7,"") | M197: =IF(AND(M$5>=$F197,M$5<=$G197),7,"") | N197: =IF(AND(N$5>=$F197,N$5<=$G197),7,"") | O197: =IF(AND(O$5>=$F197,O$5<=$G197),7,"") | P197: =IF(AND(P$5>=$F197,P$5<=$G197),7,"") | Q197: =IF(AND(Q$5>=$F197,Q$5<=$G197),7,"") | R197: =IF(AND(R$5>=$F197,R$5<=$G197),7,"") | ... BN197: =IF(AND(BN$5>=$F197,BN$5<=$G197),7,"")
A198: 7 Capacitación y gestión del cambio | B198: 7.2.5 | C198: Medición de la adopción y plan de acción correctiva | D198: T | E198: Implantación y gestión del cambio | F198: 13 | G198: 21 | H198: =G198-F198+1 | I198: 160 | J198: Esfuerzo continuo (por quincena u ocurrencia) | K198: =IF(AND(K$5>=$F198,K$5<=$G198),7,"") | L198: =IF(AND(L$5>=$F198,L$5<=$G198),7,"") | M198: =IF(AND(M$5>=$F198,M$5<=$G198),7,"") | N198: =IF(AND(N$5>=$F198,N$5<=$G198),7,"") | O198: =IF(AND(O$5>=$F198,O$5<=$G198),7,"") | P198: =IF(AND(P$5>=$F198,P$5<=$G198),7,"") | Q198: =IF(AND(Q$5>=$F198,Q$5<=$G198),7,"") | R198: =IF(AND(R$5>=$F198,R$5<=$G198),7,"") | ... BN198: =IF(AND(BN$5>=$F198,BN$5<=$G198),7,"")
A199: 7 Capacitación y gestión del cambio | B199: 7.3.1 | C199: Certificación de preventistas, conductores y preparadores (Etapa 1) | D199: T | E199: Implantación y gestión del cambio | F199: 13 | G199: 15 | H199: =G199-F199+1 | I199: 160 | J199: Con entregable (detalle por planificación gradual) | K199: =IF(AND(K$5>=$F199,K$5<=$G199),7,"") | L199: =IF(AND(L$5>=$F199,L$5<=$G199),7,"") | M199: =IF(AND(M$5>=$F199,M$5<=$G199),7,"") | N199: =IF(AND(N$5>=$F199,N$5<=$G199),7,"") | O199: =IF(AND(O$5>=$F199,O$5<=$G199),7,"") | P199: =IF(AND(P$5>=$F199,P$5<=$G199),7,"") | Q199: =IF(AND(Q$5>=$F199,Q$5<=$G199),7,"") | R199: =IF(AND(R$5>=$F199,R$5<=$G199),7,"") | ... BN199: =IF(AND(BN$5>=$F199,BN$5<=$G199),7,"")
A200: 7 Capacitación y gestión del cambio | B200: 7.3.2 | C200: Certificación de Comercial y Finanzas en costo de servir (Etapa 2) | D200: T | E200: Implantación y gestión del cambio | F200: 18 | G200: 18 | H200: =G200-F200+1 | I200: 160 | J200: Con entregable (detalle por planificación gradual) | K200: =IF(AND(K$5>=$F200,K$5<=$G200),7,"") | L200: =IF(AND(L$5>=$F200,L$5<=$G200),7,"") | M200: =IF(AND(M$5>=$F200,M$5<=$G200),7,"") | N200: =IF(AND(N$5>=$F200,N$5<=$G200),7,"") | O200: =IF(AND(O$5>=$F200,O$5<=$G200),7,"") | P200: =IF(AND(P$5>=$F200,P$5<=$G200),7,"") | Q200: =IF(AND(Q$5>=$F200,Q$5<=$G200),7,"") | R200: =IF(AND(R$5>=$F200,R$5<=$G200),7,"") | ... BN200: =IF(AND(BN$5>=$F200,BN$5<=$G200),7,"")
A201: 8 Operación y soporte | B201: 8.1.1 | C201: Servicio de centro de operaciones 24×7 y mesa de servicio durante los 36 meses de operación (04:00 a 22:00; 24×7 en septiembre y diciembre) | D201: C | E201: Operación / SRE | F201: 21 | G201: 56 | H201: =G201-F201+1 | I201: 26280 | J201: Esfuerzo continuo (por quincena u ocurrencia) | K201: =IF(AND(K$5>=$F201,K$5<=$G201),8,"") | L201: =IF(AND(L$5>=$F201,L$5<=$G201),8,"") | M201: =IF(AND(M$5>=$F201,M$5<=$G201),8,"") | N201: =IF(AND(N$5>=$F201,N$5<=$G201),8,"") | O201: =IF(AND(O$5>=$F201,O$5<=$G201),8,"") | P201: =IF(AND(P$5>=$F201,P$5<=$G201),8,"") | Q201: =IF(AND(Q$5>=$F201,Q$5<=$G201),8,"") | R201: =IF(AND(R$5>=$F201,R$5<=$G201),8,"") | ... BN201: =IF(AND(BN$5>=$F201,BN$5<=$G201),8,"")
A202: 8 Operación y soporte | B202: 8.1.2 | C202: Servicio de gestión de incidentes, problemas y niveles de servicio del Art. 78° durante los 36 meses de operación | D202: C | E202: Operación / SRE | F202: 21 | G202: 56 | H202: =G202-F202+1 | I202: 54239 | J202: Esfuerzo continuo (por quincena u ocurrencia) | K202: =IF(AND(K$5>=$F202,K$5<=$G202),8,"") | L202: =IF(AND(L$5>=$F202,L$5<=$G202),8,"") | M202: =IF(AND(M$5>=$F202,M$5<=$G202),8,"") | N202: =IF(AND(N$5>=$F202,N$5<=$G202),8,"") | O202: =IF(AND(O$5>=$F202,O$5<=$G202),8,"") | P202: =IF(AND(P$5>=$F202,P$5<=$G202),8,"") | Q202: =IF(AND(Q$5>=$F202,Q$5<=$G202),8,"") | R202: =IF(AND(R$5>=$F202,R$5<=$G202),8,"") | ... BN202: =IF(AND(BN$5>=$F202,BN$5<=$G202),8,"")
A203: 8 Operación y soporte | B203: 8.1.3 | C203: Servicio de continuidad y pruebas semestrales de recuperación ante desastres durante los 36 meses de operación | D203: G | E203: Operación / SRE | F203: 21 | G203: 56 | H203: =G203-F203+1 | I203: 80 | J203: Esfuerzo continuo (por quincena u ocurrencia) | K203: =IF(AND(K$5>=$F203,K$5<=$G203),8,"") | L203: =IF(AND(L$5>=$F203,L$5<=$G203),8,"") | M203: =IF(AND(M$5>=$F203,M$5<=$G203),8,"") | N203: =IF(AND(N$5>=$F203,N$5<=$G203),8,"") | O203: =IF(AND(O$5>=$F203,O$5<=$G203),8,"") | P203: =IF(AND(P$5>=$F203,P$5<=$G203),8,"") | Q203: =IF(AND(Q$5>=$F203,Q$5<=$G203),8,"") | R203: =IF(AND(R$5>=$F203,R$5<=$G203),8,"") | ... BN203: =IF(AND(BN$5>=$F203,BN$5<=$G203),8,"")
A204: 8 Operación y soporte | B204: 8.1.4 | C204: Actualizaciones anuales del Plan de Reversibilidad durante los 36 meses de operación | D204: R | E204: Jefe de Proyecto | F204: 21 | G204: 56 | H204: =G204-F204+1 | I204: 288 | J204: Esfuerzo continuo (por quincena u ocurrencia) | K204: =IF(AND(K$5>=$F204,K$5<=$G204),8,"") | L204: =IF(AND(L$5>=$F204,L$5<=$G204),8,"") | M204: =IF(AND(M$5>=$F204,M$5<=$G204),8,"") | N204: =IF(AND(N$5>=$F204,N$5<=$G204),8,"") | O204: =IF(AND(O$5>=$F204,O$5<=$G204),8,"") | P204: =IF(AND(P$5>=$F204,P$5<=$G204),8,"") | Q204: =IF(AND(Q$5>=$F204,Q$5<=$G204),8,"") | R204: =IF(AND(R$5>=$F204,R$5<=$G204),8,"") | ... BN204: =IF(AND(BN$5>=$F204,BN$5<=$G204),8,"")
...

Sheet Actividades hasta H2
A1: Actividad | B1: Paquete | C1: Nombre de la actividad | D1: Responsable (familia de rol) | E1: Personas asignadas | F1: HH | G1: Inicio | H1: Fin | I1: Días hábiles | J1: Predecesoras | K1: Día hábil n.º de inicio (dato T-15) | L1: Día hábil n.º de fin (dato T-15)
A2: 1.1.1.A01 | B2: 1.1.1 | C2: Elaboración, revisión y aprobación del entregable | D2: Jefe de Proyecto | E2: 2 | F2: 80 | G2: =WORKDAY('Parámetros'!$B$3-1,K2+1) | H2: =WORKDAY('Parámetros'!$B$3-1,L2+1) | I2: =NETWORKDAYS(G2,H2) | J2: — | K2: 0 | L2: 6
A3: 1.1.2.A01 | B3: 1.1.2 | C3: Elaboración, revisión y aprobación del entregable | D3: Jefe de Proyecto | E3: 2 | F3: 80 | G3: =WORKDAY('Parámetros'!$B$3-1,K3+1) | H3: =WORKDAY('Parámetros'!$B$3-1,L3+1) | I3: =NETWORKDAYS(G3,H3) | J3: — | K3: 0 | L3: 6
A4: 1.1.3.A01 | B4: 1.1.3 | C4: Elaboración, revisión y aprobación del entregable | D4: Jefe de Proyecto | E4: 2 | F4: 80 | G4: =WORKDAY('Parámetros'!$B$3-1,K4+1) | H4: =WORKDAY('Parámetros'!$B$3-1,L4+1) | I4: =NETWORKDAYS(G4,H4) | J4: — | K4: 0 | L4: 6
A5: 1.2.1.A01 | B5: 1.2.1 | C5: Elaboración, revisión y aprobación del entregable | D5: Arquitectura | E5: 2 | F5: 80 | G5: =WORKDAY('Parámetros'!$B$3-1,K5+1) | H5: =WORKDAY('Parámetros'!$B$3-1,L5+1) | I5: =NETWORKDAYS(G5,H5) | J5: — | K5: 0 | L5: 6
A6: 1.2.3.A01 | B6: 1.2.3 | C6: Elaboración, revisión y aprobación del entregable | D6: Arquitectura | E6: 2 | F6: 80 | G6: =WORKDAY('Parámetros'!$B$3-1,K6+1) | H6: =WORKDAY('Parámetros'!$B$3-1,L6+1) | I6: =NETWORKDAYS(G6,H6) | J6: — | K6: 0 | L6: 6
A7: 1.2.4.A01 | B7: 1.2.4 | C7: Elaboración, revisión y aprobación del entregable | D7: Calidad y pruebas | E7: 2 | F7: 80 | G7: =WORKDAY('Parámetros'!$B$3-1,K7+1) | H7: =WORKDAY('Parámetros'!$B$3-1,L7+1) | I7: =NETWORKDAYS(G7,H7) | J7: — | K7: 20 | L7: 26
A8: 1.3.1.A01 | B8: 1.3.1 | C8: Elaboración, revisión y aprobación del entregable | D8: Jefe de Proyecto | E8: 2 | F8: 80 | G8: =WORKDAY('Parámetros'!$B$3-1,K8+1) | H8: =WORKDAY('Parámetros'!$B$3-1,L8+1) | I8: =NETWORKDAYS(G8,H8) | J8: — | K8: 7 | L8: 13
A9: 1.3.2.A01 | B9: 1.3.2 | C9: Elaboración, revisión y aprobación del entregable | D9: Jefe de Proyecto | E9: 2 | F9: 80 | G9: =WORKDAY('Parámetros'!$B$3-1,K9+1) | H9: =WORKDAY('Parámetros'!$B$3-1,L9+1) | I9: =NETWORKDAYS(G9,H9) | J9: — | K9: 20 | L9: 26
A10: 1.3.3.A01 | B10: 1.3.3 | C10: Elaboración, revisión y aprobación del entregable | D10: Jefe de Proyecto | E10: 2 | F10: 80 | G10: =WORKDAY('Parámetros'!$B$3-1,K10+1) | H10: =WORKDAY('Parámetros'!$B$3-1,L10+1) | I10: =NETWORKDAYS(G10,H10) | J10: — | K10: 20 | L10: 26
A11: 1.3.4.A01 | B11: 1.3.4 | C11: Elaboración, revisión y aprobación del entregable | D11: Jefe de Proyecto | E11: 2 | F11: 80 | G11: =WORKDAY('Parámetros'!$B$3-1,K11+1) | H11: =WORKDAY('Parámetros'!$B$3-1,L11+1) | I11: =NETWORKDAYS(G11,H11) | J11: — | K11: 20 | L11: 26
A12: 1.4.1.A01 | B12: 1.4.1 | C12: Elaboración, revisión y aprobación del entregable | D12: Jefe de Proyecto | E12: 2 | F12: 80 | G12: =WORKDAY('Parámetros'!$B$3-1,K12+1) | H12: =WORKDAY('Parámetros'!$B$3-1,L12+1) | I12: =NETWORKDAYS(G12,H12) | J12: — | K12: 0 | L12: 6
A13: 1.4.2.A01 | B13: 1.4.2 | C13: Elaboración, revisión y aprobación del entregable | D13: Jefe de Proyecto | E13: 2 | F13: 80 | G13: =WORKDAY('Parámetros'!$B$3-1,K13+1) | H13: =WORKDAY('Parámetros'!$B$3-1,L13+1) | I13: =NETWORKDAYS(G13,H13) | J13: — | K13: 0 | L13: 6
... A109: 7.2.3.A02 | B109: 7.2.3 | C109: Prueba o evaluación, corrección y acta | D109: Implantación | E109: 2 | F109: 80 | G109: =WORKDAY('Parámetros'!$B$3-1,K109+1) | H109: =WORKDAY('Parámetros'!$B$3-1,L109+1) | I109: =NETWORKDAYS(G109,H109) | J109: 7.2.3.A01 | K109: 75 | L109: 81
A111: Fuente: Formulario T-15, Tabla 6.1b. Se muestran las 108 actividades de los paquetes que terminan hasta el H2; los demás paquetes se detallan por planificación gradual antes de cada fase (T-15, sección 6.1 y Figura T15.3).

Sheet Esfuerzo continuo
A1: Paquete | B1: Nombre del paquete | C1: Clase | D1: Inicio (mes) | E1: Fin (mes) | F1: HH (E) | G1: Regla de programación | H1: Relevos u ocurrencias | I1: HH máximas por relevo u ocurrencia
A2: 1.2.2 | B2: Documento de reglas de ruteo capturadas al planificador de rutas | C2: G | D2: 1 | E2: 3 | F2: 80 | G2: Una actividad por quincena, por presencia continua o periódica | H2: 6 | I2: 13.3
A3: 1.3.5 | B3: Reunión semanal de seguimiento con su informe semanal | C3: R | D3: 1 | E3: 20 | F3: 480 | G3: Una actividad de nivel de esfuerzo por quincena | H3: 40 | I3: 12
A4: 1.4.3 | B4: Registro de solicitudes de cambio con análisis de impacto | C4: R | D4: 1 | E4: 56 | F4: 896 | G4: Una actividad de nivel de esfuerzo por quincena | H4: 112 | I4: 8
A5: 1.5.2 | B5: Puertas de calidad automáticas en la cadena de integración (cobertura mínima del 80 %) | C5: G | D5: 6 | E5: 20 | F5: 80 | G5: Una actividad cada 3 quincenas, por presencia continua o periódica | H5: 10 | I5: 8
A6: 1.6.2 | B6: Registro de riesgos revisado en cada Comité de Proyecto | C6: R | D6: 1 | E6: 20 | F6: 160 | G6: Una actividad por ocurrencia (quincenal, en cada Comité de Proyecto), ejecutada dentro de una quincena; 1 actividad(es) por ocurrencia | H6: 40 | I6: 4
A7: 1.8.1 | B7: Oficina de gestión del proyecto con metodología basada en el PMBOK | C7: R | D7: 1 | E7: 20 | F7: 320 | G7: Una actividad de nivel de esfuerzo por quincena | H7: 40 | I7: 8
A8: 1.8.2 | B8: Actas del Comité Ejecutivo mensual, con la aprobación de los cambios de alcance | C8: R | D8: 1 | E8: 56 | F8: 448 | G8: Una actividad por ocurrencia (mensual), ejecutada dentro de una quincena; 1 actividad(es) por ocurrencia | H8: 56 | I8: 8
A9: 1.8.3 | B9: Actas del Comité de Proyecto quincenal | C9: R | D9: 1 | E9: 20 | F9: 240 | G9: Una actividad por ocurrencia (quincenal), ejecutada dentro de una quincena; 1 actividad(es) por ocurrencia | H9: 40 | I9: 6
A10: 1.8.4 | B10: Actas del Comité de Arquitectura mensual | C10: R | D10: 1 | E10: 56 | F10: 448 | G10: Una actividad por ocurrencia (mensual), ejecutada dentro de una quincena; 1 actividad(es) por ocurrencia | H10: 56 | I10: 8
A11: 1.8.5 | B11: Actas del Comité de Operación mensual, desde el mes 13 | C11: R | D11: 13 | E11: 56 | F11: 352 | G11: Una actividad por ocurrencia (mensual), ejecutada dentro de una quincena; 1 actividad(es) por ocurrencia | H11: 44 | I11: 8
A12: 1.8.6 | B12: Informe mensual de avance con valor ganado | C12: R | D12: 1 | E12: 20 | F12: 480 | G12: Una actividad por ocurrencia (mensual), ejecutada dentro de una quincena; 1 actividad(es) por ocurrencia | H12: 20 | I12: 24
A13: 1.8.7 | B13: Tablero de estado del proyecto disponible para el CLIENTE | C13: R | D13: 2 | E13: 56 | F13: 440 | G13: Una actividad cada 2 quincenas, ejecutada en la última quincena del grupo | H13: 55 | I13: 8
... A60: 9.2.1 | B60: Ejecución del Plan de Reversibilidad y acompañamiento de 90 días | C60: G | D60: 54 | E60: 56 | F60: 80 | G60: Una actividad por quincena, por presencia continua o periódica | H60: 6 | I60: 13.3
B62: Fuente: Formulario T-15, Tabla 6.2. Estos paquetes no producen un entregable único sino un servicio o una reunión que se repite; por eso no se dividen en actividades distintas.

Sheet Glosario
A1: Término | B1: Qué es | C1: Ejemplo en este proyecto | D1: Fuente
A2: Carta Gantt | B2: Cronograma representado con barras sobre una línea de tiempo: cada fila es un trabajo y su barra va de su inicio a su fin. | C2: Hojas «Gantt cuentas» y «Gantt paquetes». | D2: Formulario T-14, sección 3.1
A3: Hito | B3: Punto verificable del cronograma contractual, sin duración, asociado a entregables, criterios de aceptación y, cuando corresponde, a un pago. Se cumple sólo con el acta firmada por la Contraparte Técnica. | C3: H4: entrega del software de la Etapa 1 para pruebas, mes 10, 10 % del pago de la implementación. | D3: Bases Administrativas, glosario, Art. 18.1 y Formulario E-25
A4: Acta de aceptación | B4: Documento con que la Contraparte Técnica del CLIENTE da por cumplido un hito. | C4: Acta del H5 (paquete 3.8.7). | D4: Bases Administrativas, Art. 18.1
A5: Revisión del CLIENTE | B5: Plazo de diez días hábiles que tiene el CLIENTE para revisar un entregable; si formula observaciones, LafroX tiene otros diez para subsanarlas. | C5: La entrega del H4 es el 20-10-2027 y su fecha límite el 16-11-2027. | D5: Bases Administrativas, Art. 18.3
A6: Mes contractual | B6: Mes contado desde el inicio del contrato (1 a 56). Las Bases fijan los meses, no las fechas. | C6: El H7 ocurre en el mes 16. | D6: Bases Administrativas, Art. 17°
A7: Mes calendario | B7: Mes real que corresponde a un mes contractual según la fecha de inicio. | C7: Con inicio en febrero de 2027, el mes 16 es mayo de 2028. | D7: SD7, Anexo 7.A
A8: Etapa | B8: Cada una de las dos entregas de la solución: la Etapa 1 (operación de bodega y reparto) y la Etapa 2 (canal moderno, portales y costo de servir). | C8: Etapa 1: desarrollo meses 1 a 12. | D8: Bases Administrativas, Art. 17°; SD3
A9: Marcha blanca | B9: Período en que la solución opera con usuarios y volumen reales, en convivencia con la forma actual de trabajar, hasta cumplir las condiciones de cierre. | C9: Etapa 1: meses 13 a 15; Etapa 2: meses 19 y 20. | D9: Bases Administrativas, Art. 17.3
A10: Paso a producción | B10: Momento en que la solución reemplaza formalmente la forma anterior de trabajar, con acta. | C10: H7 en el mes 16 y H12 en el mes 21. | D10: Formulario E-25
A11: Congelamiento | B11: Período en que el caso prohíbe pasos a producción o cambios con impacto: del 1 al 25 de septiembre, todo diciembre y los tres primeros días hábiles de cada mes. | C11: Mes 20 (septiembre de 2028). | D11: Caso 02, RT-10.05 y sección 13.3
A12: EDT | B12: Estructura de descomposición del trabajo: árbol que divide el 100 % del alcance en fases, cuentas de control y paquetes de trabajo. | C12: 9 fases, 49 cuentas de control y 222 paquetes. | D12: Formulario T-14; PMBOK 6.ª ed., cap. 5
... A33: Planificación gradual | B33: Técnica que detalla en actividades sólo el trabajo cercano y deja el trabajo futuro a nivel de paquete hasta que se conoce mejor. | C33: Actividades detalladas hasta el H2; las fases siguientes se detallan antes del H2, H4, H8 y H9. | D33: PMBOK 6.ª ed., p. 185; Formulario T-15, sección 6.1
