Workbook

Sheet PARAMETROS
B2: Conversiones
B3: Dólar | C3: 800 | D3: =+C3/C5 -> 0.025
B4: Euro | C4: 900 | D4: =+C4/C5 -> 0.028125
B5: UF | C5: 32000 | D5: =+C5/C3 -> 40
B6: HH Mes | C6: 160
B8: Datos
B9: Tasa Interes de Prestamo (Mensual) | C9: 0.015
B10: Linea de Credito | C10: 20000000
B11: Tasa Interes de LC (Mensual) | C11: 0.035
B12: Impuestos | C12: 0.27
B13: Tasa Inversionista (Anual) | C13: 0.18
B14: Tasa Inversionista (Mensual) | C14: =((1+C13)^(1/12))-1 -> 0.01388843

Sheet RESUMEN (Obligatorio)
B3: UTILICE LOS VALORES DE LA HOJA PARAMETROS
A5: RESUMENES
B7: Cobro / A Pagar
C8: UF | D8: CLP | E8: USD
B9: Total en Implementación / Implantación
B10: Total en Operación
B11: Total en Proyecto | C11: =SUM(C9:C10) -> 0 | D11: =SUM(D9:D10) -> 0 | E11: =SUM(E9:E10) -> 0
B12: VAN
B13: TIR
B16: Costos por Etapa
C17: UF | D17: CLP | E17: USD
B18: Total en Implementación / Implantación
B19: Total en Operación
B20: Total en Proyecto | C20: =SUM(C18:C19) -> 0 | D20: =SUM(D18:D19) -> 0 | E20: =SUM(E18:E19) -> 0
B23: Costos por Concepto
C24: UF | D24: CLP | E24: USD
B25: Total Componentes
B26: Total Arquitectura Fisica
B27: Total Equipo desarrollo
B28: Total Capacitaciones
B29: Total Arquitectura Logica
B30: Total Sueldos
B31: Total General
B33: Punto de Caso de Uso
C34: Valor
B35: Cantidad Punto Caso de Uso Ajustados
B36: Factor de Conversión a HH
B37: Cantidad HH Desarrollo
B38: Cantidad HH Proyecto
B39: Costo Total (Según Tablas) en UF del Proyecto
B40: Venta Total (Según Tablas) en UF del Proyecto

Sheet CURVA S (Obligatorio)
A21: FLUJO DE CAJA
C23: 43466 | D23: 43497 | E23: 43525 | F23: 43556 | G23: 43586 | H23: 43617 | I23: 43647 | J23: 43678 | K23: 43709 | L23: 43739 | M23: 43770 | N23: 43800 | O23: 43831 | P23: 43862 | Q23: 43891 | R23: 43922 | S23: 43952 | T23: 43983 | U23: 44013 | V23: 44044 | W23: 44075 | X23: 44105 | Y23: 44136 | Z23: 44166 | AA23: 44197 | AB23: 44228 | AC23: 44256 | AD23: 44287 | AE23: 44317 | AF23: 44348 | AG23: 44378 | AH23: 44409 | AI23: 44440 | AJ23: 44470 | AK23: 44501 | AL23: 44531
B24: A.2 - INGRESO ACUMULADO | C24: =+'FLUJO CAJA NETO (Obligatorio)'!C17 -> 0 | D24: =+'FLUJO CAJA NETO (Obligatorio)'!D17 -> 1000 | E24: =+'FLUJO CAJA NETO (Obligatorio)'!E17 -> 1200 | F24: =+'FLUJO CAJA NETO (Obligatorio)'!F17 -> 2200 | G24: =+'FLUJO CAJA NETO (Obligatorio)'!G17 -> 3200 | H24: =+'FLUJO CAJA NETO (Obligatorio)'!H17 -> 4200 | I24: =+'FLUJO CAJA NETO (Obligatorio)'!I17 -> 5200 | J24: =+'FLUJO CAJA NETO (Obligatorio)'!J17 -> 6200 | ... AL24: =+'FLUJO CAJA NETO (Obligatorio)'!AL17 -> 34200
B25: B.2.- EGRESO TOTAL | C25: =+'FLUJO CAJA NETO (Obligatorio)'!C39 -> 10000 | D25: =+'FLUJO CAJA NETO (Obligatorio)'!D39 -> 10500 | E25: =+'FLUJO CAJA NETO (Obligatorio)'!E39 -> 11000 | F25: =+'FLUJO CAJA NETO (Obligatorio)'!F39 -> 11500 | G25: =+'FLUJO CAJA NETO (Obligatorio)'!G39 -> 17000 | H25: =+'FLUJO CAJA NETO (Obligatorio)'!H39 -> 17500 | I25: =+'FLUJO CAJA NETO (Obligatorio)'!I39 -> 17500 | J25: =+'FLUJO CAJA NETO (Obligatorio)'!J39 -> 18000 | ... AL25: =+'FLUJO CAJA NETO (Obligatorio)'!AL39 -> 32000
B27: RESULTADO DEL MES | C27: =+'FLUJO CAJA NETO (Obligatorio)'!C8 -> -10000 | D27: =+'FLUJO CAJA NETO (Obligatorio)'!D8 -> 500 | E27: =+'FLUJO CAJA NETO (Obligatorio)'!E8 -> -300 | F27: =+'FLUJO CAJA NETO (Obligatorio)'!F8 -> 500 | G27: =+'FLUJO CAJA NETO (Obligatorio)'!G8 -> -4500 | H27: =+'FLUJO CAJA NETO (Obligatorio)'!H8 -> 500 | I27: =+'FLUJO CAJA NETO (Obligatorio)'!I8 -> 1000 | J27: =+'FLUJO CAJA NETO (Obligatorio)'!J8 -> 500 | ... AL27: =+'FLUJO CAJA NETO (Obligatorio)'!AL8 -> 500
B28: RESULTADO ACUMULADO | C28: =+C27 -> -10000 | D28: =+D27+C28 -> -9500 | E28: =+E27+D28 -> -9800 | F28: =+F27+E28 -> -9300 | G28: =+G27+F28 -> -13800 | H28: =+H27+G28 -> -13300 | I28: =+I27+H28 -> -12300 | J28: =+J27+I28 -> -11800 | K28: =+K27+J28 -> -11300 | ... AL28: =+AL27+AK28 -> 2200
B30: PUNTO EQUILIBRIO | C30: =INDEX($C$28:$AL$28,0,MATCH(TRUE,INDEX($C$28:$AL$28>0,1,0),0)) -> 200 | D30: =INDEX($C$23:$AL$23,0,MATCH(TRUE,INDEX($C$28:$AL$28>0,1,0),0)) -> 44409
B31: MES MAS BAJO | C31: =INDEX($C$28:$AL$28,0,MATCH(TRUE,INDEX($C$28:$AL$28=MIN($C$28:$AL$28),1,0),0)) -> -13800 | D31: =INDEX($C$23:$AL$23,0,MATCH(TRUE,INDEX($C$28:$AL$28=MIN($C$28:$AL$28),1,0),0)) -> 43586
B32: TIR | C32: =IRR(C27:AL27,1) -> 0.0082368812
B34: UTILICE LOS VALORES DE LA HOJA PARAMETROS

Sheet FLUJO CAJA NETO (Obligatorio)
B2: Valor de UF | C2: =+PARAMETROS!C5 -> 32000 | D2: =+PARAMETROS!D5 -> 40
B3: Valor del Dólar | C3: =+PARAMETROS!C3 -> 800 | D3: =+PARAMETROS!D3 -> 0.025
A6: FLUJO DE CAJA
B8: FLUJO MES | C8: =+C16-C38 -> -10000 | D8: =+D16-D38 -> 500 | E8: =+E16-E38 -> -300 | F8: =+F16-F38 -> 500 | G8: =+G16-G38 -> -4500 | H8: =+H16-H38 -> 500 | I8: =+I16-I38 -> 1000 | J8: =+J16-J38 -> 500 | ... AL8: =+AL16-AL38 -> 500
B9: FLUJO ACUMULADO | C9: =+C8 -> -10000 | D9: =+D8+C9 -> -9500 | E9: =+E8+D9 -> -9800 | F9: =+F8+E9 -> -9300 | G9: =+G8+F9 -> -13800 | H9: =+H8+G9 -> -13300 | I9: =+I8+H9 -> -12300 | J9: =+J8+I9 -> -11800 | K9: =+K8+J9 -> -11300 | ... AL9: =+AL8+AK9 -> 2200
A12: DETALLE FLUJO DE CAJA
A14: A.- INGRESOS
B16: A.1 - INGRESOS MES | C16: =+SUM(C21:C31) -> 0 | D16: =+SUM(D21:D31) -> 1000 | E16: =+SUM(E21:E31) -> 200 | F16: =+SUM(F21:F31) -> 1000 | G16: =+SUM(G21:G31) -> 1000 | H16: =+SUM(H21:H31) -> 1000 | I16: =+SUM(I21:I31) -> 1000 | J16: =+SUM(J21:J31) -> 1000 | ... AL16: =+SUM(AL21:AL31) -> 1000
B17: A.2 - INGRESO ACUMULADO | C17: =+C16 -> 0 | D17: =+D16+C17 -> 1000 | E17: =+E16+D17 -> 1200 | F17: =+F16+E17 -> 2200 | G17: =+G16+F17 -> 3200 | H17: =+H16+G17 -> 4200 | I17: =+I16+H17 -> 5200 | J17: =+J16+I17 -> 6200 | K17: =+K16+J17 -> 7200 | ... AL17: =+AL16+AK17 -> 34200
C20: 43466 | D20: 43497 | E20: 43525 | F20: 43556 | G20: 43586 | H20: 43617 | I20: 43647 | J20: 43678 | K20: 43709 | L20: 43739 | M20: 43770 | N20: 43800 | O20: 43831 | P20: 43862 | Q20: 43891 | R20: 43922 | S20: 43952 | T20: 43983 | U20: 44013 | V20: 44044 | W20: 44075 | X20: 44105 | Y20: 44136 | Z20: 44166 | AA20: 44197 | AB20: 44228 | AC20: 44256 | AD20: 44287 | AE20: 44317 | AF20: 44348 | AG20: 44378 | AH20: 44409 | AI20: 44440 | AJ20: 44470 | AK20: 44501 | AL20: 44531
B21: EJEMPLO | C21: 0 | D21: 1000 | E21: 200 | F21: 1000 | G21: 1000 | H21: 1000 | I21: 1000 | J21: 1000 | K21: 1000 | L21: 1000 | M21: 1000 | N21: 1000 | O21: 1000 | P21: 1000 | Q21: 1000 | R21: 1000 | S21: 1000 | T21: 1000 | U21: 1000 | V21: 1000 | W21: 1000 | X21: 1000 | Y21: 1000 | Z21: 1000 | AA21: 1000 | AB21: 1000 | AC21: 1000 | AD21: 1000 | AE21: 1000 | AF21: 1000 | AG21: 1000 | AH21: 1000 | AI21: 1000 | AJ21: 1000 | AK21: 1000 | AL21: 1000
C22: 0 | D22: 0 | E22: 0 | F22: 0 | G22: 0 | H22: 0 | I22: 0 | J22: 0 | K22: 0 | L22: 0 | M22: 0 | N22: 0 | O22: 0 | P22: 0 | Q22: 0 | R22: 0 | S22: 0 | T22: 0 | U22: 0 | V22: 0 | W22: 0 | X22: 0 | Y22: 0 | Z22: 0 | AA22: 0 | AB22: 0 | AC22: 0 | AD22: 0 | AE22: 0 | AF22: 0 | AG22: 0 | AH22: 0 | AI22: 0 | AJ22: 0 | AK22: 0 | AL22: 0
C23: 0 | D23: 0 | E23: 0 | F23: 0 | G23: 0 | H23: 0 | I23: 0 | J23: 0 | K23: 0 | L23: 0 | M23: 0 | N23: 0 | O23: 0 | P23: 0 | Q23: 0 | R23: 0 | S23: 0 | T23: 0 | U23: 0 | V23: 0 | W23: 0 | X23: 0 | Y23: 0 | Z23: 0 | AA23: 0 | AB23: 0 | AC23: 0 | AD23: 0 | AE23: 0 | AF23: 0 | AG23: 0 | AH23: 0 | AI23: 0 | AJ23: 0 | AK23: 0 | AL23: 0
C24: 0 | D24: 0 | E24: 0 | F24: 0 | G24: 0 | H24: 0 | I24: 0 | J24: 0 | K24: 0 | L24: 0 | M24: 0 | N24: 0 | O24: 0 | P24: 0 | Q24: 0 | R24: 0 | S24: 0 | T24: 0 | U24: 0 | V24: 0 | W24: 0 | X24: 0 | Y24: 0 | Z24: 0 | AA24: 0 | AB24: 0 | AC24: 0 | AD24: 0 | AE24: 0 | AF24: 0 | AG24: 0 | AH24: 0 | AI24: 0 | AJ24: 0 | AK24: 0 | AL24: 0
C25: 0 | D25: 0 | E25: 0 | F25: 0 | G25: 0 | H25: 0 | I25: 0 | J25: 0 | K25: 0 | L25: 0 | M25: 0 | N25: 0 | O25: 0 | P25: 0 | Q25: 0 | R25: 0 | S25: 0 | T25: 0 | U25: 0 | V25: 0 | W25: 0 | X25: 0 | Y25: 0 | Z25: 0 | AA25: 0 | AB25: 0 | AC25: 0 | AD25: 0 | AE25: 0 | AF25: 0 | AG25: 0 | AH25: 0 | AI25: 0 | AJ25: 0 | AK25: 0 | AL25: 0
C26: 0 | D26: 0 | E26: 0 | F26: 0 | G26: 0 | H26: 0 | I26: 0 | J26: 0 | K26: 0 | L26: 0 | M26: 0 | N26: 0 | O26: 0 | P26: 0 | Q26: 0 | R26: 0 | S26: 0 | T26: 0 | U26: 0 | V26: 0 | W26: 0 | X26: 0 | Y26: 0 | Z26: 0 | AA26: 0 | AB26: 0 | AC26: 0 | AD26: 0 | AE26: 0 | AF26: 0 | AG26: 0 | AH26: 0 | AI26: 0 | AJ26: 0 | AK26: 0 | AL26: 0
C27: 0 | D27: 0 | E27: 0 | F27: 0 | G27: 0 | H27: 0 | I27: 0 | J27: 0 | K27: 0 | L27: 0 | M27: 0 | N27: 0 | O27: 0 | P27: 0 | Q27: 0 | R27: 0 | S27: 0 | T27: 0 | U27: 0 | V27: 0 | W27: 0 | X27: 0 | Y27: 0 | Z27: 0 | AA27: 0 | AB27: 0 | AC27: 0 | AD27: 0 | AE27: 0 | AF27: 0 | AG27: 0 | AH27: 0 | AI27: 0 | AJ27: 0 | AK27: 0 | AL27: 0
C28: 0 | D28: 0 | E28: 0 | F28: 0 | G28: 0 | H28: 0 | I28: 0 | J28: 0 | K28: 0 | L28: 0 | M28: 0 | N28: 0 | O28: 0 | P28: 0 | Q28: 0 | R28: 0 | S28: 0 | T28: 0 | U28: 0 | V28: 0 | W28: 0 | X28: 0 | Y28: 0 | Z28: 0 | AA28: 0 | AB28: 0 | AC28: 0 | AD28: 0 | AE28: 0 | AF28: 0 | AG28: 0 | AH28: 0 | AI28: 0 | AJ28: 0 | AK28: 0 | AL28: 0
C29: 0 | D29: 0 | E29: 0 | F29: 0 | G29: 0 | H29: 0 | I29: 0 | J29: 0 | K29: 0 | L29: 0 | M29: 0 | N29: 0 | O29: 0 | P29: 0 | Q29: 0 | R29: 0 | S29: 0 | T29: 0 | U29: 0 | V29: 0 | W29: 0 | X29: 0 | Y29: 0 | Z29: 0 | AA29: 0 | AB29: 0 | AC29: 0 | AD29: 0 | AE29: 0 | AF29: 0 | AG29: 0 | AH29: 0 | AI29: 0 | AJ29: 0 | AK29: 0 | AL29: 0
C30: 0 | D30: 0 | E30: 0 | F30: 0 | G30: 0 | H30: 0 | I30: 0 | J30: 0 | K30: 0 | L30: 0 | M30: 0 | N30: 0 | O30: 0 | P30: 0 | Q30: 0 | R30: 0 | S30: 0 | T30: 0 | U30: 0 | V30: 0 | W30: 0 | X30: 0 | Y30: 0 | Z30: 0 | AA30: 0 | AB30: 0 | AC30: 0 | AD30: 0 | AE30: 0 | AF30: 0 | AG30: 0 | AH30: 0 | AI30: 0 | AJ30: 0 | AK30: 0 | AL30: 0
C31: 0 | D31: 0 | E31: 0 | F31: 0 | G31: 0 | H31: 0 | I31: 0 | J31: 0 | K31: 0 | L31: 0 | M31: 0 | N31: 0 | O31: 0 | P31: 0 | Q31: 0 | R31: 0 | S31: 0 | T31: 0 | U31: 0 | V31: 0 | W31: 0 | X31: 0 | Y31: 0 | Z31: 0 | AA31: 0 | AB31: 0 | AC31: 0 | AD31: 0 | AE31: 0 | AF31: 0 | AG31: 0 | AH31: 0 | AI31: 0 | AJ31: 0 | AK31: 0 | AL31: 0
A35: B.- EGRESOS
B38: B.1.- EGRESO TOTAL MES | C38: =+SUM(C42:C50) -> 10000 | D38: =+SUM(D42:D50) -> 500 | E38: =+SUM(E42:E50) -> 500 | F38: =+SUM(F42:F50) -> 500 | G38: =+SUM(G42:G50) -> 5500 | H38: =+SUM(H42:H50) -> 500 | I38: =+SUM(I42:I50) -> 0 | J38: =+SUM(J42:J50) -> 500 | ... AL38: =+SUM(AL42:AL50) -> 500
B39: B.2.- EGRESO TOTAL | C39: =+C38 -> 10000 | D39: =+D38+C39 -> 10500 | E39: =+E38+D39 -> 11000 | F39: =+F38+E39 -> 11500 | G39: =+G38+F39 -> 17000 | H39: =+H38+G39 -> 17500 | I39: =+I38+H39 -> 17500 | J39: =+J38+I39 -> 18000 | K39: =+K38+J39 -> 18500 | ... AL39: =+AL38+AK39 -> 32000
C41: 43466 | D41: 43497 | E41: 43525 | F41: 43556 | G41: 43586 | H41: 43617 | I41: 43647 | J41: 43678 | K41: 43709 | L41: 43739 | M41: 43770 | N41: 43800 | O41: 43831 | P41: 43862 | Q41: 43891 | R41: 43922 | S41: 43952 | T41: 43983 | U41: 44013 | V41: 44044 | W41: 44075 | X41: 44105 | Y41: 44136 | Z41: 44166 | AA41: 44197 | AB41: 44228 | AC41: 44256 | AD41: 44287 | AE41: 44317 | AF41: 44348 | AG41: 44378 | AH41: 44409 | AI41: 44440 | AJ41: 44470 | AK41: 44501 | AL41: 44531
B42: INVERSION | C42: 10000 | D42: 0 | E42: 0 | F42: 0 | G42: 5000 | H42: 0 | I42: 0 | J42: 0 | K42: 0 | L42: 0 | M42: 0 | N42: 0 | O42: 0 | P42: 0 | Q42: 0 | R42: 0 | S42: 0 | T42: 0 | U42: 0 | V42: 0 | W42: 0 | X42: 0 | Y42: 0 | Z42: 0 | AA42: 0 | AB42: 0 | AC42: 0 | AD42: 0 | AE42: 0 | AF42: 0 | AG42: 0 | AH42: 0 | AI42: 0 | AJ42: 0 | AK42: 0 | AL42: 0
B43: EJEMPLO1 | C43: 0 | D43: 500 | E43: 500 | F43: 500 | G43: 500 | H43: 500 | I43: 0 | J43: 500 | K43: 500 | L43: 500 | M43: 500 | N43: 500 | O43: 500 | P43: 500 | Q43: 500 | R43: 500 | S43: 500 | T43: 500 | U43: 500 | V43: 500 | W43: 500 | X43: 500 | Y43: 500 | Z43: 500 | AA43: 500 | AB43: 500 | AC43: 500 | AD43: 500 | AE43: 500 | AF43: 500 | AG43: 500 | AH43: 500 | AI43: 500 | AJ43: 500 | AK43: 500 | AL43: 500
C44: 0 | D44: 0 | E44: 0 | F44: 0 | G44: 0 | H44: 0 | I44: 0 | J44: 0 | K44: 0 | L44: 0 | M44: 0 | N44: 0 | O44: 0 | P44: 0 | Q44: 0 | R44: 0 | S44: 0 | T44: 0 | U44: 0 | V44: 0 | W44: 0 | X44: 0 | Y44: 0 | Z44: 0 | AA44: 0 | AB44: 0 | AC44: 0 | AD44: 0 | AE44: 0 | AF44: 0 | AG44: 0 | AH44: 0 | AI44: 0 | AJ44: 0 | AK44: 0 | AL44: 0
C45: 0 | D45: 0 | E45: 0 | F45: 0 | G45: 0 | H45: 0 | I45: 0 | J45: 0 | K45: 0 | L45: 0 | M45: 0 | N45: 0 | O45: 0 | P45: 0 | Q45: 0 | R45: 0 | S45: 0 | T45: 0 | U45: 0 | V45: 0 | W45: 0 | X45: 0 | Y45: 0 | Z45: 0 | AA45: 0 | AB45: 0 | AC45: 0 | AD45: 0 | AE45: 0 | AF45: 0 | AG45: 0 | AH45: 0 | AI45: 0 | AJ45: 0 | AK45: 0 | AL45: 0
C46: 0 | D46: 0 | E46: 0 | F46: 0 | G46: 0 | H46: 0 | I46: 0 | J46: 0 | K46: 0 | L46: 0 | M46: 0 | N46: 0 | O46: 0 | P46: 0 | Q46: 0 | R46: 0 | S46: 0 | T46: 0 | U46: 0 | V46: 0 | W46: 0 | X46: 0 | Y46: 0 | Z46: 0 | AA46: 0 | AB46: 0 | AC46: 0 | AD46: 0 | AE46: 0 | AF46: 0 | AG46: 0 | AH46: 0 | AI46: 0 | AJ46: 0 | AK46: 0 | AL46: 0
C47: 0 | D47: 0 | E47: 0 | F47: 0 | G47: 0 | H47: 0 | I47: 0 | J47: 0 | K47: 0 | L47: 0 | M47: 0 | N47: 0 | O47: 0 | P47: 0 | Q47: 0 | R47: 0 | S47: 0 | T47: 0 | U47: 0 | V47: 0 | W47: 0 | X47: 0 | Y47: 0 | Z47: 0 | AA47: 0 | AB47: 0 | AC47: 0 | AD47: 0 | AE47: 0 | AF47: 0 | AG47: 0 | AH47: 0 | AI47: 0 | AJ47: 0 | AK47: 0 | AL47: 0
C48: 0 | D48: 0 | E48: 0 | F48: 0 | G48: 0 | H48: 0 | I48: 0 | J48: 0 | K48: 0 | L48: 0 | M48: 0 | N48: 0 | O48: 0 | P48: 0 | Q48: 0 | R48: 0 | S48: 0 | T48: 0 | U48: 0 | V48: 0 | W48: 0 | X48: 0 | Y48: 0 | Z48: 0 | AA48: 0 | AB48: 0 | AC48: 0 | AD48: 0 | AE48: 0 | AF48: 0 | AG48: 0 | AH48: 0 | AI48: 0 | AJ48: 0 | AK48: 0 | AL48: 0
C49: 0 | D49: 0 | E49: 0 | F49: 0 | G49: 0 | H49: 0 | I49: 0 | J49: 0 | K49: 0 | L49: 0 | M49: 0 | N49: 0 | O49: 0 | P49: 0 | Q49: 0 | R49: 0 | S49: 0 | T49: 0 | U49: 0 | V49: 0 | W49: 0 | X49: 0 | Y49: 0 | Z49: 0 | AA49: 0 | AB49: 0 | AC49: 0 | AD49: 0 | AE49: 0 | AF49: 0 | AG49: 0 | AH49: 0 | AI49: 0 | AJ49: 0 | AK49: 0 | AL49: 0
C50: 0 | D50: 0 | E50: 0 | F50: 0 | G50: 0 | H50: 0 | I50: 0 | J50: 0 | K50: 0 | L50: 0 | M50: 0 | N50: 0 | O50: 0 | P50: 0 | Q50: 0 | R50: 0 | S50: 0 | T50: 0 | U50: 0 | V50: 0 | W50: 0 | X50: 0 | Y50: 0 | Z50: 0 | AA50: 0 | AB50: 0 | AC50: 0 | AD50: 0 | AE50: 0 | AF50: 0 | AG50: 0 | AH50: 0 | AI50: 0 | AJ50: 0 | AK50: 0 | AL50: 0

Sheet FLUJO DE CAJA COMPLETO
B2: UTILICE LOS VALORES DE LA HOJA PARAMETROS

Sheet FINANCIAMIENTO
C2: Valor de UF | D2: =+PARAMETROS!C5 -> 32000 | E2: =+PARAMETROS!D5 -> 40
C3: Valor del Dólar | D3: =+PARAMETROS!C3 -> 800 | E3: =+PARAMETROS!D3 -> 0.025
C4: HH Mensuales | D4: =+PARAMETROS!C6 -> 160
B9: Tabla Amortización del Crédito
B11: Mes | C11: Saldo | D11: Cuota | E11: Interés Mensual | F11: Amortización
B12: 1
B13: 2
B14: 3
B15: 4
B16: 5
B17: 6
B18: 7
B19: 8
B20: 9
B21: 10
B22: 11
B23: 12
... B33: 22

Sheet PCU-Esfuerzo

Sheet Adquisiciones
A2: Conversiones
A3: Dólar | B3: 600
A4: Euro | B4: 700
A5: UF | B5: 27000
A6: HH Mes | B6: 160
A9: Componente | B9: Descripcion | C9: Precio unitario Dolar | D9: Precio unitario CLP | E9: Precio Unitario UF | F9: Cantidad | G9: Total CLP | H9: Total UF | I9: Vida Util (Años) | J9: Depreciación Anual | K9: Depreciación Total
A10: Componente 1 | B10: Descripcion Componente 1 | C10: - | D10: 1000 | E10: 0.1 | F10: 1 | G10: =F10*D10 -> 1000 | H10: =E10*F10 -> 0.1 | I10: 1 | J10: =H10/I10 -> 0.1 | K10: =SUM(J10:J17)+SUM(J20:J29)+J31 -> 1.9
A11: Componente 1 | B11: Descripcion Componente 1 | C11: - | D11: 1000 | E11: 0.1 | F11: 1 | G11: =F11*D11 -> 1000 | H11: =E11*F11 -> 0.1 | I11: 1 | J11: =H11/I11 -> 0.1
A12: Componente 1 | B12: Descripcion Componente 1 | C12: - | D12: 1000 | E12: 0.1 | F12: 1 | G12: =F12*D12 -> 1000 | H12: =E12*F12 -> 0.1 | I12: 1 | J12: =H12/I12 -> 0.1
A13: Componente 1 | B13: Descripcion Componente 1 | C13: - | D13: 1000 | E13: 0.1 | F13: 1 | G13: =F13*D13 -> 1000 | H13: =E13*F13 -> 0.1 | I13: 1 | J13: =H13/I13 -> 0.1
A14: Componente 1 | B14: Descripcion Componente 1 | C14: - | D14: 1000 | E14: 0.1 | F14: 1 | G14: =F14*D14 -> 1000 | H14: =E14*F14 -> 0.1 | I14: 1 | J14: =H14/I14 -> 0.1
A15: Componente 1 | B15: Descripcion Componente 1 | C15: 10 | D15: 1000 | E15: 0.1 | F15: 1 | G15: =F15*D15 -> 1000 | H15: =E15*F15 -> 0.1 | I15: 1 | J15: =H15/I15 -> 0.1
A16: Componente 1 | B16: Descripcion Componente 1 | C16: 10 | D16: 1000 | E16: 0.1 | F16: 1 | G16: =F16*D16 -> 1000 | H16: =E16*F16 -> 0.1 | I16: 1 | J16: =H16/I16 -> 0.1
A17: Componente 1 | B17: Descripcion Componente 1 | C17: 10 | D17: 1000 | E17: 0.1 | F17: 1 | G17: =F17*D17 -> 1000 | H17: =E17*F17 -> 0.1 | I17: 1 | J17: =H17/I17 -> 0.1
A18: Componente 1 | B18: Descripcion Componente 1 | C18: - | D18: 1000 | E18: 0.1 | F18: 1 | G18: =F18*D18 -> 1000 | H18: =E18*F18 -> 0.1 | I18: 1 | J18: =H18/I18 -> 0.1
A19: Total Componentes | G19: =SUM(G10:G18) -> 9000 | H19: =SUM(H10:H18) -> 0.9
A20: Equipo 1 | B20: Descripción Equipo 1 | C20: - | D20: 1000 | E20: 0.1 | F20: 1 | G20: =D20*F20 -> 1000 | H20: =E20*F20 -> 0.1 | I20: 1 | J20: =H20/I20 -> 0.1
A21: Equipo 1 | B21: Descripción Equipo 1 | C21: 10 | D21: 1000 | E21: 0.1 | F21: 1 | G21: =D21*F21 -> 1000 | H21: =E21*F21 -> 0.1 | I21: 1 | J21: =H21/I21 -> 0.1
A22: Equipo 1 | B22: Descripción Equipo 1 | C22: 10 | D22: 1000 | E22: 0.1 | F22: 1 | G22: =D22*F22 -> 1000 | H22: =E22*F22 -> 0.1 | I22: 1 | J22: =H22/I22 -> 0.1
A23: Equipo 1 | B23: Descripción Equipo 1 | C23: 10 | D23: 1000 | E23: 0.1 | F23: 1 | G23: =D23*F23 -> 1000 | H23: =E23*F23 -> 0.1 | I23: 1 | J23: =H23/I23 -> 0.1
A24: Equipo 1 | B24: Descripción Equipo 1 | C24: 10 | D24: 1000 | E24: 0.1 | F24: 1 | G24: =D24*F24 -> 1000 | H24: =E24*F24 -> 0.1 | I24: 1 | J24: =H24/I24 -> 0.1
A25: Equipo 1 | B25: Descripción Equipo 1 | C25: 10 | D25: 1000 | E25: 0.1 | F25: 1 | G25: =D25*F25 -> 1000 | H25: =E25*F25 -> 0.1 | I25: 1 | J25: =H25/I25 -> 0.1
A26: Equipo 1 | B26: Descripción Equipo 1 | C26: 10 | D26: 1000 | E26: 0.1 | F26: 1 | G26: =D26*F26 -> 1000 | H26: =E26*F26 -> 0.1 | I26: 1 | J26: =H26/I26 -> 0.1
A27: Equipo 1 | B27: Descripción Equipo 1 | C27: 10 | D27: 1000 | E27: 0.1 | F27: 1 | G27: =D27*F27 -> 1000 | H27: =E27*F27 -> 0.1 | I27: 1 | J27: =H27/I27 -> 0.1
A28: Equipo 1 | B28: Descripción Equipo 1 | C28: 10 | D28: 1000 | E28: 0.1 | F28: 1 | G28: =D28*F28 -> 1000 | H28: =E28*F28 -> 0.1 | I28: 1 | J28: =H28/I28 -> 0.1
A29: Equipo 1 | B29: Descripción Equipo 1 | C29: 10 | D29: 1000 | E29: 0.1 | F29: 1 | G29: =D29*F29 -> 1000 | H29: =E29*F29 -> 0.1 | I29: 1 | J29: =H29/I29 -> 0.1
A30: Total Arquitectura Fisica | G30: =SUM(G20:G29) -> 10000 | H30: =SUM(H20:H29) -> 1
A31: Equipo 1 | B31: Descripción Equipo 1 | C31: 10 | D31: 1000 | E31: 0.1 | F31: 1 | G31: =D31*F31 -> 1000 | H31: =E31*F31 -> 0.1 | I31: 1 | J31: =H31/I31 -> 0.1
A32: Equipo 1 | B32: Descripción Equipo 1 | C32: 10 | D32: 1000 | E32: 0.1 | F32: 1 | G32: =D32*F32 -> 1000 | H32: =E32*F32 -> 0.1 | I32: 1 | J32: =H32/I32 -> 0.1
A33: Equipo 1 | B33: Descripción Equipo 1 | C33: 10 | D33: 1000 | E33: 0.1 | F33: 1 | G33: =D33*F33 -> 1000 | H33: =E33*F33 -> 0.1 | I33: 1 | J33: =H33/I33 -> 0.1
A34: Equipo 1 | B34: Descripción Equipo 1 | C34: 10 | D34: 1000 | E34: 0.1 | F34: 1 | G34: =D34*F34 -> 1000 | H34: =E34*F34 -> 0.1 | I34: 1 | J34: =H34/I34 -> 0.1
A35: Total equipo desarrollo | G35: =G31 -> 1000 | H35: =H31 -> 0.1
A36: Software 1 | B36: Descripción Software 1 | C36: 10 | D36: 1000 | E36: 0.1 | F36: 1 | G36: =D36*F36 -> 1000 | H36: =E36*F36 -> 0.1 | I36: 1 | J36: =H36/I36 -> 0.1
A37: Software 1 | B37: Descripción Software 1 | C37: 10 | D37: 1000 | E37: 0.1 | F37: 1 | G37: =D37*F37 -> 1000 | H37: =E37*F37 -> 0.1 | I37: 1 | J37: =H37/I37 -> 0.1
A38: Software 1 | B38: Descripción Software 1 | C38: 10 | D38: 1000 | E38: 0.1 | F38: 1 | G38: =D38*F38 -> 1000 | H38: =E38*F38 -> 0.1 | I38: 1 | J38: =H38/I38 -> 0.1
A39: Software 1 | B39: Descripción Software 1 | C39: 10 | D39: 1000 | E39: 0.1 | F39: 1 | G39: =D39*F39 -> 1000 | H39: =E39*F39 -> 0.1 | I39: 1 | J39: =H39/I39 -> 0.1
A40: Software 1 | B40: Descripción Software 1 | C40: 10 | D40: 1000 | E40: 0.1 | F40: 1 | G40: =D40*F40 -> 1000 | H40: =E40*F40 -> 0.1 | I40: 1 | J40: =H40/I40 -> 0.1
A41: Software 1 | B41: Descripción Software 1 | C41: 10 | D41: 1000 | E41: 0.1 | F41: 1 | G41: =D41 -> 1000 | H41: =E41*F41 -> 0.1 | I41: 1 | J41: =H41/I41 -> 0.1
A42: Total Arquitectura Logica | G42: =SUM(G36:G41) -> 6000 | H42: =SUM(H36:H41) -> 0.6

Sheet Costos HH - Sueldos
A2: Conversiones
A3: Dólar | B3: 600
A4: Euro | B4: 700
A5: UF | B5: 27000
A6: HH Mes | B6: 160
B8: Dias según Gantt | C8: Horas (8 hrs x dia) | D8: Costo $ UF/HH | E8: Tarifa$ UF/HH | F8: Total Costo | G8: Total Tarifa | H8: Cant de personas | I8: Horas x Persona | J8: Sueldo costo CLP | K8: Sueldo tarifa CLP | L8: Sueldo Costo UF | M8: Sueldo Tarifa UF
A9: Analista/Diseñador senior | B9: 100 | C9: 10 | D9: 0.6 | E9: 0.8 | F9: =C9*D9 -> 6 | G9: =C9*E9 -> 8 | H9: 1 | I9: =C9/H9 -> 10 | J9: =C9*D9*$B$6 -> 960 | K9: =C9*E9*$B$6 -> 1280 | L9: =J9/$B$5 -> 0.035555556 | M9: =K9/$B$5 -> 0.047407407
A10: Arquitecto senior | D10: 1.1 | E10: 1.5 | F10: =C10*D10 -> 0 | G10: =C10*E10 -> 0 | H10: 1 | I10: =C10/H10 -> 0 | J10: =C10*D10*$B$6 -> 0 | K10: =C10*E10*$B$6 -> 0 | L10: =J10/$B$5 -> 0 | M10: =K10/$B$5 -> 0
A11: Documentador | D11: 0.5 | E11: 0.9 | F11: =C11*D11 -> 0 | G11: =C11*E11 -> 0 | H11: 1 | I11: =C11/H11 -> 0 | J11: =C11*D11*$B$6 -> 0 | K11: =C11*E11*$B$6 -> 0 | L11: =J11/$B$5 -> 0 | M11: =K11/$B$5 -> 0
A12: Ingeniero senior | D12: 0.7 | E12: 0.9 | F12: =C12*D12 -> 0 | G12: =C12*E12 -> 0 | H12: 1 | I12: =C12/H12 -> 0 | J12: =C12*D12*$B$6 -> 0 | K12: =C12*E12*$B$6 -> 0 | L12: =J12/$B$5 -> 0 | M12: =K12/$B$5 -> 0
A13: Encargado de la Seguridad TI | D13: 1.2 | E13: 2.3 | F13: =C13*D13 -> 0 | G13: =C13*E13 -> 0 | H13: 1 | I13: =C13/H13 -> 0 | J13: =C13*D13*$B$6 -> 0 | K13: =C13*E13*$B$6 -> 0 | L13: =J13/$B$5 -> 0 | M13: =K13/$B$5 -> 0
A14: QA senior | D14: 0.5 | E14: 0.7 | F14: =C14*D14 -> 0 | G14: =C14*E14 -> 0 | H14: 1 | I14: =C14/H14 -> 0 | J14: =C14*D14*$B$6 -> 0 | K14: =C14*E14*$B$6 -> 0 | L14: =J14/$B$5 -> 0 | M14: =K14/$B$5 -> 0
A15: Jefe de analisis y diseño | D15: 1 | E15: 1.5 | F15: =C15*D15 -> 0 | G15: =C15*E15 -> 0 | H15: 1 | I15: =C15/H15 -> 0 | J15: =C15*D15*$B$6 -> 0 | K15: =C15*E15*$B$6 -> 0 | L15: =J15/$B$5 -> 0 | M15: =K15/$B$5 -> 0
A16: Jefe de desarrollo | D16: 1.3 | E16: 1.7 | F16: =C16*D16 -> 0 | G16: =C16*E16 -> 0 | H16: 1 | I16: =C16/H16 -> 0 | J16: =C16*D16*$B$6 -> 0 | K16: =C16*E16*$B$6 -> 0 | L16: =J16/$B$5 -> 0 | M16: =K16/$B$5 -> 0
A17: Jefe de proyecto | D17: 2 | E17: 2.5 | F17: =C17*D17 -> 0 | G17: =C17*E17 -> 0 | H17: 1 | I17: =C17/H17 -> 0 | J17: =C17*D17*$B$6 -> 0 | K17: =C17*E17*$B$6 -> 0 | L17: =J17/$B$5 -> 0 | M17: =K17/$B$5 -> 0
A18: Total | H18: =SUM(H9:H17) -> 9 | J18: =SUM(J9:J17) -> 960 | K18: =SUM(K9:K17) -> 1280 | L18: =SUM(L9:L17) -> 0.035555556 | M18: =SUM(M9:M17) -> 0.047407407
C22: Costo | E22: Tarifa
B23: Cantidad Personas | C23: UF Mensuales (160 Hrs) /Persona | D23: CLP Mensuales/persona | E23: UF Mensuales (160 Hrs) /Persona | F23: CLP Mensual/persona
A24: Analista/Diseñador senior | B24: 1 | C24: =(B$6*D9)/B24 -> 96 | D24: =C24*B$5 -> 2592000 | E24: =(B$6*E9)/B24 -> 128 | F24: =E24*B$5 -> 3456000
A25: Arquitecto senior | B25: 1 | C25: =(B$6*D10)/B25 -> 176 | D25: =C25*B$5 -> 4752000 | E25: =(B$6*E10)/B25 -> 240 | F25: =E25*B$5 -> 6480000
A26: Documentador | B26: 1 | C26: =(B$6*D11)/B26 -> 80 | D26: =C26*B$5 -> 2160000 | E26: =(B$6*E11)/B26 -> 144 | F26: =E26*B$5 -> 3888000
A27: Ingeniero senior | B27: 1 | C27: =(B$6*D12)/B27 -> 112 | D27: =C27*B$5 -> 3024000 | E27: =(B$6*E12)/B27 -> 144 | F27: =E27*B$5 -> 3888000
A28: Encargado de la Seguridad TI | B28: 1 | C28: =(B$6*D13)/B28 -> 192 | D28: =C28*B$5 -> 5184000 | E28: =(B$6*E13)/B28 -> 368 | F28: =E28*B$5 -> 9936000
A29: QA senior | B29: 1 | C29: =(B$6*D14)/B29 -> 80 | D29: =C29*B$5 -> 2160000 | E29: =(B$6*E14)/B29 -> 112 | F29: =E29*B$5 -> 3024000
A30: Jefe de analisis y diseño | B30: 1 | C30: =(B$6*D15)/B30 -> 160 | D30: =C30*B$5 -> 4320000 | E30: =(B$6*E15)/B30 -> 240 | F30: =E30*B$5 -> 6480000
A31: Jefe de desarrollo | B31: 1 | C31: =(B$6*D16)/B31 -> 208 | D31: =C31*B$5 -> 5616000 | E31: =(B$6*E16)/B31 -> 272 | F31: =E31*B$5 -> 7344000
A32: Jefe de proyecto | B32: 1 | C32: =(B$6*D17)/B32 -> 320 | D32: =C32*B$5 -> 8640000 | E32: =(B$6*E17)/B32 -> 400 | F32: =E32*B$5 -> 10800000
A33: Totales | B33: =SUM(B24:B32) -> 9 | C33: =SUM(C24:C32) -> 1424 | D33: =SUM(D24:D32) -> 38448000 | E33: =SUM(E24:E32) -> 2048 | F33: =SUM(F24:F32) -> 55296000

Sheet Costos HH por Mes
A2: Conversiones
A3: Dólar | B3: 600
A4: Euro | B4: 700
A5: UF | B5: 27000
A6: HH Mes | B6: 160
B8: Dias según Gantt
A9: Analista/Diseñador senior | B9: 100
A10: Arquitecto senior
A11: Documentador
A12: Ingeniero senior
A13: Encargado de la Seguridad TI
A14: QA senior
A15: Jefe de analisis y diseño
A16: Jefe de desarrollo
A17: Jefe de proyecto
A18: Total
C22: Costo | E22: Tarifa
B23: Cantidad Personas | C23: UF Mensuales (160 Hrs) /Persona | D23: CLP Mensuales/persona | E23: UF Mensuales (160 Hrs) /Persona | F23: CLP Mensual/persona
A24: Analista/Diseñador senior | B24: 1 | C24: =(B$6*D9)/B24 -> 0 | D24: =C24*B$5 -> 0 | E24: =(B$6*E9)/B24 -> 0 | F24: =E24*B$5 -> 0
A25: Arquitecto senior | B25: 1 | C25: =(B$6*D10)/B25 -> 0 | D25: =C25*B$5 -> 0 | E25: =(B$6*E10)/B25 -> 0 | F25: =E25*B$5 -> 0
A26: Documentador | B26: 1 | C26: =(B$6*D11)/B26 -> 0 | D26: =C26*B$5 -> 0 | E26: =(B$6*E11)/B26 -> 0 | F26: =E26*B$5 -> 0
A27: Ingeniero senior | B27: 1 | C27: =(B$6*D12)/B27 -> 0 | D27: =C27*B$5 -> 0 | E27: =(B$6*E12)/B27 -> 0 | F27: =E27*B$5 -> 0
A28: Encargado de la Seguridad TI | B28: 1 | C28: =(B$6*D13)/B28 -> 0 | D28: =C28*B$5 -> 0 | E28: =(B$6*E13)/B28 -> 0 | F28: =E28*B$5 -> 0
A29: QA senior | B29: 1 | C29: =(B$6*D14)/B29 -> 0 | D29: =C29*B$5 -> 0 | E29: =(B$6*E14)/B29 -> 0 | F29: =E29*B$5 -> 0
A30: Jefe de analisis y diseño | B30: 1 | C30: =(B$6*D15)/B30 -> 0 | D30: =C30*B$5 -> 0 | E30: =(B$6*E15)/B30 -> 0 | F30: =E30*B$5 -> 0
A31: Jefe de desarrollo | B31: 1 | C31: =(B$6*D16)/B31 -> 0 | D31: =C31*B$5 -> 0 | E31: =(B$6*E16)/B31 -> 0 | F31: =E31*B$5 -> 0
A32: Jefe de proyecto | B32: 1 | C32: =(B$6*D17)/B32 -> 0 | D32: =C32*B$5 -> 0 | E32: =(B$6*E17)/B32 -> 0 | F32: =E32*B$5 -> 0
A33: Totales | B33: =SUM(B24:B32) -> 9 | C33: =SUM(C24:C32) -> 0 | D33: =SUM(D24:D32) -> 0 | E33: =SUM(E24:E32) -> 0 | F33: =SUM(F24:F32) -> 0

Sheet Costo Operacion
C2: Mes 1 | D2: Mes 2 | E2: Mes 3 | F2: Mes 4 | G2: Mes 5 | H2: Mes 6 | I2: Mes 7 | J2: Mes 8 | K2: Mes 9 | L2: Mes 10 | M2: Mes 11 | N2: Mes 12 | O2: Mes 13 | P2: Mes 14 | Q2: Mes 15 | R2: Mes 16 | S2: Mes 17 | T2: Mes 18 | U2: Mes 19 | V2: Mes 20 | W2: Mes 21 | X2: Mes 22 | Y2: Mes 23 | Z2: Mes 24 | AA2: Mes 25
A3: Director de Proyecto
A4: Gerente de Proyecto
A5: Jefe de Proyecto
A6: Jefe de Análisis de Diseño
A7: Jefe de Desarrollo
A8: Jefe de TIC
A9: Analista/Diseñador Experto A
A10: Analista/Diseñador Senior A
A11: Analista/Diseñador Junior A
A12: Ingeniero Experto A
A13: Ingeniero Senior A
A14: Ingeniero Senior B
... A32: Analista QA Junior A
A33: Total | C33: ='[1]Costo en HH'!N214 -> 0 | D33: ='[1]Costo en HH'!O214 -> 0 | E33: ='[1]Costo en HH'!P214 -> 0 | F33: ='[1]Costo en HH'!Q214 -> 0 | G33: ='[1]Costo en HH'!R214 -> 0 | H33: ='[1]Costo en HH'!S214 -> 0 | I33: ='[1]Costo en HH'!T214 -> 0 | J33: ='[1]Costo en HH'!U214 -> 0 | ... AA33: ='[1]Costo en HH'!AL214 -> 0
A35: Adquisiciones
A36: Servicios Recurrentes | K36: |
