Workbook

Sheet RESUMEN
A1: Resumen
A4: Costo de proyecto total Cliente (Sin IVA) | F4: Tarifa de proyecto total Empresa | K4: Margen / Utilidad
B5: UF | C5: CLP | D5: USD | G5: UF | H5: CLP | I5: USD | L5: UF | M5: CLP | N5: USD
A6: Total en Implementación | B6: =B18 -> 0 | C6: =B6*PARÁMETROS!$B$6 -> 0 | D6: =C6/PARÁMETROS!$B$4 -> 0 | F6: Total en Implementación | G6: =G18 -> 0 | H6: =G6*PARÁMETROS!$B$6 -> 0 | I6: =H6/PARÁMETROS!$B$4 -> 0 | K6: Total en Implementación | L6: =+G6-B6 -> 0 | M6: =L6*PARÁMETROS!B6 -> 0 | N6: =M6/PARÁMETROS!B4 -> 0
A7: Total en Soporte | B7: =B19 -> 0 | C7: =B7*PARÁMETROS!$B$6 -> 0 | D7: =C7/PARÁMETROS!$B$4 -> 0 | F7: Total en Soporte | G7: =G19 -> 0 | H7: =G7*PARÁMETROS!$B$6 -> 0 | I7: =H7/PARÁMETROS!$B$4 -> 0 | K7: Total en Soporte | L7: =+G7-B7 -> 0 | M7: =L7*PARÁMETROS!B6 -> 0 | N7: =M7/PARÁMETROS!B4 -> 0
A8: Total en Proyecto | B8: =SUM(B6:B7) -> 0 | C8: =SUM(C6:C7) -> 0 | D8: =SUM(D6:D7) -> 0 | F8: Total en Proyecto | G8: =SUM(G6:G7) -> 0 | H8: =SUM(H6:H7) -> 0 | I8: =SUM(I6:I7) -> 0 | K8: Total en Proyecto | L8: =SUM(L6:L7) -> 0 | M8: =SUM(M6:M7) -> 0 | N8: =SUM(N6:N7) -> 0
K9: Rentabilidad Nominal | L9: =+L8/B8 -> #DIV/0! | M9: =+M8/C8 -> #DIV/0! | N9: =+N8/D8 -> #DIV/0!
A10: Costo por Ítem Cliente (Sin IVA) | F10: Tarifa por Ítem Empresa
B11: UF | C11: CLP | D11: USD | G11: UF | H11: CLP | I11: USD
A12: Implementación Recursos Humanos | B12: ='COSTOS DE OPERACION'!V35 -> 0 | C12: =B12*PARÁMETROS!$B$6 -> 0 | D12: =C12/PARÁMETROS!$B$4 -> 0 | F12: Implementación Recursos Humanos | G12: ='TARIFAS DE OPERACION'!V35 -> 0 | H12: =G12*PARÁMETROS!$B$6 -> 0 | I12: =H12/PARÁMETROS!$B$4 -> 0
A13: Implementacion Adquisiciones | B13: =-SUM('FLUJO DE CAJA NETO'!C33:BB33) -> 0 | C13: =B13*PARÁMETROS!$B$6 -> 0 | D13: =C13/PARÁMETROS!$B$4 -> 0 | F13: Implementacion Adquisiciones | G13: =B13*(1+'TARIFAS DE OPERACION'!B47) -> 0 | H13: =G13*PARÁMETROS!$B$6 -> 0 | I13: =H13/PARÁMETROS!$B$4 -> 0
A14: Implementación Capacitaciones | B14: ='COSTOS DE OPERACION'!V45 -> 0 | C14: =B14*PARÁMETROS!$B$6 -> 0 | D14: =C14/PARÁMETROS!$B$4 -> 0 | F14: Implementación Capacitaciones | G14: ='TARIFAS DE OPERACION'!V45 -> 0 | H14: =G14*PARÁMETROS!$B$6 -> 0 | I14: =H14/PARÁMETROS!$B$4 -> 0
A15: Implementacion Servicios | B15: =-SUM('FLUJO DE CAJA NETO'!B35:N35) -> 0 | C15: =B15*PARÁMETROS!$B$6 -> 0 | D15: =C15/PARÁMETROS!$B$4 -> 0 | F15: Implementacion Servicios | G15: =-SUM('FLUJO DE CAJA NETO'!B35:N35)*(1+'TARIFAS DE OPERACION'!B47) -> 0 | H15: =G15*PARÁMETROS!$B$6 -> 0 | I15: =H15/PARÁMETROS!$B$4 -> 0
A16: Soporte Recursos Humanos | B16: ='COSTOS DE OPERACION'!AL35 -> 0 | C16: =B16*PARÁMETROS!$B$6 -> 0 | D16: =C16/PARÁMETROS!$B$4 -> 0 | F16: Soporte Recursos Humanos | G16: ='TARIFAS DE OPERACION'!AL35 -> 0 | H16: =G16*PARÁMETROS!$B$6 -> 0 | I16: =H16/PARÁMETROS!$B$4 -> 0
A17: Soporte Servicios | B17: =-SUM('FLUJO DE CAJA NETO'!O35:AL35) -> 0 | C17: =B17*PARÁMETROS!$B$6 -> 0 | D17: =C17/PARÁMETROS!$B$4 -> 0 | F17: Soporte Servicios | G17: =-SUM('FLUJO DE CAJA NETO'!O35:AL35) -> 0 | H17: =G17*PARÁMETROS!$B$6 -> 0 | I17: =H17/PARÁMETROS!$B$4 -> 0
A18: Total Implementación | B18: =SUM(B12:B15) -> 0 | C18: =SUM(C12:C15) -> 0 | D18: =SUM(D12:D15) -> 0 | F18: Total Implementación | G18: =SUM(G12:G15) -> 0 | H18: =SUM(H12:H15) -> 0 | I18: =SUM(I12:I15) -> 0
A19: Total Soporte | B19: =SUM(B16:B17) -> 0 | C19: =SUM(C16:C17) -> 0 | D19: =SUM(D16:D17) -> 0 | F19: Total Soporte | G19: =SUM(G16:G17) -> 0 | H19: =SUM(H16:H17) -> 0 | I19: =SUM(I16:I17) -> 0
A20: Total Proyecto | B20: =SUM(B18:B19) -> 0 | C20: =SUM(C18:C19) -> 0 | D20: =SUM(D18:D19) -> 0 | F20: Total Proyecto | G20: =SUM(G18:G19) -> 0 | H20: =SUM(H18:H19) -> 0 | I20: =SUM(I18:I19) -> 0
F21: VAN | G21: ='FLUJO DE CAJA COMPLETO'!B23 -> 0
F22: TIR | G22: ='FLUJO DE CAJA COMPLETO'!B26 -> #NUM!
A23: Viabilidad y HH
B24: Valor
A25: Cantidad Punto Caso de Uso Ajustados | B25: =PCUESFUERZO!I164 -> 0 | C25: Puntos
A26: Factor de Conversión a HH | B26: =PCUESFUERZO!N39 -> 28
A27: Cantidad HH Programacion | B27: =PCUESFUERZO!N52 -> 0 | C27: Horas
A28: Cantidad HH Proyecto | B28: =PCUESFUERZO!N55 -> 0 | C28: Horas
A29: Costo Total (Según Tablas) del Proyecto | B29: =G8 -> 0 | C29: UF
A30: Venta Total (Según Tablas) del Proyecto | B30: =B8 -> 0 | C30: UF

Sheet PARÁMETROS
A1: Conversiones de Monedas
A2: Moneda | B2: CLP | C2: USD | D2: UF
A3: Peso Chileno (CLP) | B3: 1 | C3: =+B3/B4 -> 0.0011111111 | D3: =+B3/B6 -> 2.5e-05
A4: Dólar (USD) | B4: 900 | C4: 1 | D4: =+B4/B6 -> 0.0225
A5: Euro (EUR) | B5: 1000 | C5: =+B5/B4 -> 1.1111111 | D5: =+B5/B6 -> 0.025
A6: Unidad de Fomento (UF) | B6: 40000 | C6: =+B6/B4 -> 44.444444 | D6: 1
A8: HH Mes | B8: 160 | C8: horas
A12: Datos | B12: Valor
A13: Tasa Interes de Prestamo (Mensual) | B13: 0.009
A14: Linea de Credito (CLP) | B14: 50000000
A15: Tasa Interes de LC (Mensual) | B15: 0.03
A16: Impuestos | B16: 0.27
A17: Tasa Inversionista (Anual) | B17: 0.0192
A18: Tasa Inversionista (Mensual) | B18: =((1+B17)^(1/12))-1 -> 0.0015860903
A19: Porcentaje de financiamiento propio | B19: 0.2
A20: Porcentaje de financiamiento banco | B20: 0.8

Sheet CURVA S
A30: FLUJO DE CAJA
A32: Mes | B32: 0 | C32: 1 | D32: 2 | E32: 3 | F32: 4 | G32: 5 | H32: 6 | I32: 7 | J32: 8 | K32: 9 | L32: 10 | M32: 11 | N32: 12 | O32: 13 | P32: 14 | Q32: 15 | R32: 16 | S32: 17 | T32: 18 | U32: 19 | V32: 20 | W32: 21 | X32: 22 | Y32: 23 | Z32: 24 | AA32: 25 | AB32: 26 | AC32: 27 | AD32: 28 | AE32: 29 | AF32: 30 | AG32: 31 | AH32: 32 | AI32: 33 | AJ32: 34 | AK32: 35 | AL32: =AK32+1 -> 36
A33: Fecha | C33: 46023 | D33: 46054 | E33: 46082 | F33: 46113 | G33: 46143 | H33: 46174 | I33: 46204 | J33: 46235 | K33: 46266 | L33: 46296 | M33: 46327 | N33: 46357 | O33: 46388 | P33: 46419 | Q33: 46447 | R33: 46478 | S33: 46508 | T33: 46539 | U33: 46569 | V33: 46600 | W33: 46631 | X33: 46661 | Y33: 46692 | Z33: 46722 | AA33: 46753 | AB33: 46784 | AC33: 46813 | AD33: 46844 | AE33: 46874 | AF33: 46905 | AG33: 46935 | AH33: 46966 | AI33: 46997 | AJ33: 47027 | AK33: 47058 | AL33: 47088
A34: A.2 - INGRESO ACUMULADO | B34: ='FLUJO DE CAJA COMPLETO'!B5 -> 0 | C34: =B34+'FLUJO DE CAJA COMPLETO'!C5 -> 0 | D34: =C34+'FLUJO DE CAJA COMPLETO'!D5 -> 0 | E34: =D34+'FLUJO DE CAJA COMPLETO'!E5 -> 0 | F34: =E34+'FLUJO DE CAJA COMPLETO'!F5 -> 0 | G34: =F34+'FLUJO DE CAJA COMPLETO'!G5 -> 0 | H34: =G34+'FLUJO DE CAJA COMPLETO'!H5 -> 0 | I34: =H34+'FLUJO DE CAJA COMPLETO'!I5 -> 0 | J34: =I34+'FLUJO DE CAJA COMPLETO'!J5 -> 0 | ... AL34: =AK34+'FLUJO DE CAJA COMPLETO'!AL5 -> 0
A35: B.2.- EGRESO TOTAL | B35: ='FLUJO DE CAJA NETO'!B28 -> 0 | C35: ='FLUJO DE CAJA NETO'!C28 -> 0 | D35: ='FLUJO DE CAJA NETO'!D28 -> 0 | E35: ='FLUJO DE CAJA NETO'!E28 -> 0 | F35: ='FLUJO DE CAJA NETO'!F28 -> 0 | G35: ='FLUJO DE CAJA NETO'!G28 -> 0 | H35: ='FLUJO DE CAJA NETO'!H28 -> 0 | I35: ='FLUJO DE CAJA NETO'!I28 -> 0 | ... AL35: ='FLUJO DE CAJA NETO'!AL28 -> 0
A37: RESULTADO DEL MES | B37: ='FLUJO DE CAJA COMPLETO'!B16 -> 0 | C37: ='FLUJO DE CAJA COMPLETO'!C16 -> 0 | D37: ='FLUJO DE CAJA COMPLETO'!D16 -> 0 | E37: ='FLUJO DE CAJA COMPLETO'!E16 -> 0 | F37: ='FLUJO DE CAJA COMPLETO'!F16 -> 0 | G37: ='FLUJO DE CAJA COMPLETO'!G16 -> 0 | H37: ='FLUJO DE CAJA COMPLETO'!H16 -> 0 | I37: ='FLUJO DE CAJA COMPLETO'!I16 -> 0 | ... AL37: ='FLUJO DE CAJA COMPLETO'!AL16 -> 0
A38: RESULTADO ACUMULADO | B38: ='FLUJO DE CAJA COMPLETO'!B21 -> 0 | C38: ='FLUJO DE CAJA COMPLETO'!C21 -> 0 | D38: ='FLUJO DE CAJA COMPLETO'!D21 -> 0 | E38: ='FLUJO DE CAJA COMPLETO'!E21 -> 0 | F38: ='FLUJO DE CAJA COMPLETO'!F21 -> 0 | G38: ='FLUJO DE CAJA COMPLETO'!G21 -> 0 | H38: ='FLUJO DE CAJA COMPLETO'!H21 -> 0 | I38: ='FLUJO DE CAJA COMPLETO'!I21 -> 0 | ... AL38: ='FLUJO DE CAJA COMPLETO'!AL21 -> 0
A40: PUNTO EQUILIBRIO | B40: {=INDEX(C38:AL38,0,MATCH(TRUE,INDEX(C35:AL35>0,1,0),0))} -> #N/A | C40: {=INDEX(C33:AK33,0,MATCH(TRUE,INDEX(C35:AK35>0,1,0),0))} -> #N/A
A41: MES MAS BAJO | B41: {=INDEX(C38:AL38,0,MATCH(TRUE,INDEX(C38:AL38=MIN(C38:AL38),1,0),0))} -> 0 | C41: {=INDEX(C33:AK33,0,MATCH(TRUE,INDEX(C38:AK38=MIN(C38:AK38),1,0),0))} -> 46023
A42: TIR | B42: =IRR(C37:AL37) -> #NUM!

Sheet PCUESFUERZO
A1: CASOS DE USO | L1: FACTORES TÉCNICOS
A2: N° | B2: Módulo | C2: Caso de uso | D2: Peso
A3: 1 | B3: Mod1 | D3: 0 | K3: Factor | L3: Descripcion | M3: Valor(0-5) | N3: Peso | O3: Total | P3: Justificación
D4: 0 | K4: T1 | L4: Sistema distribuido | M4: 0 | N4: 2 | O4: =M4*N4 -> 0 | P4: El sistema se compone de múltiples nodos conectados, los que requieren sincronización y redundancia en datos a tiempo real.
D5: 0 | K5: T2 | L5: Objetivos de performance o tiempo de respuesta | M5: 0 | N5: 1 | O5: =M5*N5 -> 0 | P5: Se exige una disponibilidad de 99.95% para garantizar la continuidad operativa del servicio hacia los clientes.
D6: 0 | K6: T3 | L6: Eficiencia del usuario final | M6: 0 | N6: 1 | O6: =M6*N6 -> 0 | P6: No es contemplado como un requerimiento expresado por el cliente.
D7: 0 | K7: T4 | L7: Procesamiento interno complejo | M7: 0 | N7: 1 | O7: =M7*N7 -> 0 | P7: La solución implica el procesamiento de cálculos predictivos de demanda energética, rutas inteligentes, procesamiento de eventos, entre otros.
D8: 0 | K8: T5 | L8: El código debe ser reutilizable | M8: 0 | N8: 1 | O8: =M8*N8 -> 0 | P8: El sistema está diseñado para los requerimientos que pidió expresamente el cliente, sin un mayor enfoque en la reutilizabilidad del código.
D9: 0 | K9: T6 | L9: Facilidad de instalación | M9: 0 | N9: 0.5 | O9: =M9*N9 -> 0 | P9: La instalación requiere despliegues controlados, la configuración de redes seguras y validación de operaciones en entornos, reduciendo su facilidad
D10: 0 | K10: T7 | L10: Facilidad de uso | M10: 0 | N10: 0.5 | O10: =M10*N10 -> 0 | P10: El sistema debe ser intuitivo para los operadores, funcionarios y clientes de la empresa de Energía Eléctrica, faciliitando la toma de desiciones e interacción, con enfoque en la usabilidad.
D11: 0 | K11: T8 | L11: Portabilidad | M11: 0 | N11: 2 | O11: =M11*N11 -> 0 | P11: Se proyecta una solución con un diseño multiplataforma con soporte cloud híbrido y componentes que operen mediante APIs.
D12: 0 | K12: T9 | L12: Facilidad de cambio | M12: 0 | N12: 1 | O12: =M12*N12 -> 0 | P12: La arquitectura está pensada para ser escalable y modular, por lo que adaptaciones futuras al sistema no presentarán mayores dificultades.
D13: 0 | K13: T10 | L13: Concurrencia | M13: 0 | N13: 1 | O13: =M13*N13 -> 0 | P13: El sistema soporta transacciones y accesos simultáneos de usuarios y datos con un control de concurrencia estricto.
K14: T11 | L14: Incluye objetivos especiales de seguridad | M14: 0 | N14: 1 | O14: =M14*N14 -> 0 | P14: El sistema exige cumplimiento de normativas ISO27001 con herramienta de cifrado. Se integra metodología Devsecops para implementar directrices de seguridad en las operaciones de desarrollo del código.
A15: 2 | B15: Mod2 | D15: 0 | K15: T12 | L15: Provee acceso directo a terceras partes | M15: 0 | N15: 1 | O15: =M15*N15 -> 0 | P15: Incluye interoperabilidad con plataformas externas mediante servicios APIs y servicios de AWS.
D16: 0 | K16: T13 | L16: Se requieren facilidades especiales de entrenamiento a usuarios | M16: 0 | N16: 1 | O16: =M16*N16 -> 0 | P16: La operación requiere capacitación técnica inicial para la formación de los empleados de la empresa según lo establecido en el plan de capacitación.
D17: 0 | L17: TOTAL | O17: =SUM(O4:O16) -> 0
D18: 0 | L18: FCT | M18: =0.6+0.01*O17 -> 0.6
D19: 0
D20: 0
D21: 0
D22: 0
D23: 0
D24: 0 | L24: FACTORES AMBIENTALES
A26: 3 | B26: Mod3 | D26: 0 | K26: Factor | L26: Descripcion | M26: Valor(0-5) | N26: Peso | O26: Total | P26: Justificación
D27: 0 | K27: E1 | L27: Familiaridad con el modelo del proyecto | M27: 0 | N27: 1.5 | O27: =M27*N27 -> 0 | P27: El equipo conoce metodologías y tiene experiencia en proyectos de TI que involucren tecnologías siimilares.
D28: 0 | K28: E2 | L28: Experiencia en la aplicación | M28: 0 | N28: 0.5 | O28: =M28*N28 -> 0 | P28: Existe experiencia previa en aplicaciones, aunque no todos han trabajado bajo los mismos dominios
D29: 0 | K29: E3 | L29: Experiencia en orientación a objetos | M29: 0 | N29: 1 | O29: =M29*N29 -> 0 | P29: El equipo de desarrollo domina el diseño de orientación a objetos y principios SOLID, útiles para una arquitectura modular mantenible.
D30: 0 | K30: E4 | L30: Capacidad del analista líder | M30: 0 | N30: 0.5 | O30: =M30*N30 -> 0 | P30: Analista con experiencia pero con carga compartida, domina técnicas pero no es un referente exclusivo para el dominio de la solución.
D31: 0 | K31: E5 | L31: Motivación | M31: 0 | N31: 1 | O31: =M31*N31 -> 0 | P31: Motivación moderada del equipo, existe compromiso y buen ambiente en general.
D32: 0 | K32: E6 | L32: Estabilidad de los requerimientos | M32: 0 | N32: 2 | O32: =M32*N32 -> 0 | P32: Requerimientos estables, aunque pueden surgir ajustes por los stakeholder principales.
K33: E7 | L33: Personal part-time | M33: 0 | N33: -1 | O33: =M33*N33 -> 0 | P33: No hay una dependencia de recursos humanos part-time, el equipo principal es full-time
A34: 4 | B34: Mod4 | D34: 0 | K34: E8 | L34: Dificultad del lenguaje de programación | M34: 0 | N34: -1 | O34: =M34*N34 -> 0 | P34: Se emplean lenguajes y frameworks con una curva de aprendizaje baja, donde los desarrolladores cuentan con experiencia.
D35: 0 | L35: TOTAL | O35: =SUM(O27:O34) -> 0
D36: 0 | L36: FA | M36: =1.4+(-0.03*O35) -> 1.4
D37: 0
D38: 0 | M38: Conteo factores | N38: =COUNTIF($M$27:$M$32,"<3")+COUNTIF($M$33:$M$34,">3") -> 6
D39: 0 | M39: FC | N39: =IF(N38<=2,20,IF(5>N38>2, 28,0)) -> 28
D40: 0
D41: 0 | M41: UUCP | N41: =PCUESFUERZO!$I$157+PCUESFUERZO!$I$164 -> 0
D42: 0 | M42: UCP | N42: =N41*M36*M18 -> 0
D43: 0
A45: 5 | B45: Mod4 | D45: 0 | M45: E | N45: =N42*N39 -> 0
D46: 0 | M46: E TOTAL | N46: =N45/0.4 -> 0
D47: 0
D48: 0 | L48: Distribución del esfuerzo
D49: 0 | L49: Actividad | M49: Porcentaje | N49: HH
D50: 0 | L50: Análisis | M50: 0.1 | N50: =M50*$N$46 -> 0
D51: 0 | L51: Diseño | M51: 0.2 | N51: =M51*$N$46 -> 0
D52: 0 | L52: Programación | M52: 0.4 | N52: =M52*$N$46 -> 0
D53: 0 | L53: Pruebas | M53: 0.15 | N53: =M53*$N$46 -> 0
D54: 0 | L54: Sobrecarga | M54: 0.15 | N54: =M54*$N$46 -> 0
D55: 0 | M55: TOTAL HH: | N55: =SUM(N50:N54) -> 0
D56: 0
D57: 0
D58: 0
D59: 0
D60: 0
A62: 6 | B62: Mod4 | D62: 0
D63: 0
D64: 0
D65: 0
D66: 0
D67: 0
D68: 0
D69: 0
D70: 0
D71: 0
D72: 0
D73: 0
D74: 0
A76: 7 | B76: Mod4 | D76: 0
D77: 0
D78: 0
D79: 0
D80: 0
D81: 0
D82: 0
A84: 8 | B84: Mod4 | D84: 0
D85: 0
D86: 0
D87: 0
D88: 0
A90: 9 | B90: Mod4 | D90: 0 | S90: PCUSA | T90: =T87+T65 -> 0
D91: 0
D92: 0
B105: ACTORES
B106: N | C106: Actores | D106: Peso
B107: 1 | D107: 0
B108: =B107+1 -> 2 | D108: 0
B109: =B108+1 -> 3 | D109: 0
B110: =B109+1 -> 4 | D110: 0
B111: =B110+1 -> 5 | D111: 0
B112: =B111+1 -> 6 | D112: 0
B113: =B112+1 -> 7 | D113: 0
B114: =B113+1 -> 8 | D114: 0
B115: =B114+1 -> 9 | D115: 0
B116: =B115+1 -> 10 | D116: 0
B117: =B116+1 -> 11 | D117: 0
B118: =B117+1 -> 12 | D118: 0
...

Sheet Costos HH - Sueldos
A2: Conversiones
A3: Elemento | B3: Valor
A4: Dólar | B4: =PARÁMETROS!$B$4 -> 900
A5: Euro | B5: =PARÁMETROS!$B$5 -> 1000
A6: UF | B6: =PARÁMETROS!$B$6 -> 40000
A7: HH Mes | B7: =PARÁMETROS!$B$8 -> 160
A9: Costo implementación
A10: Rol | B10: Dias según Gantt | C10: Horas Totales / Día | D10: Costo $ UF/HH | E10: Tarifa $ UF/HH | F10: Total Costo | G10: Total Tarifa | H10: Cant de personas | I10: Horas x Persona | J10: Sueldo costo CLP | K10: Sueldo tarifa CLP | L10: Sueldo Costo UF | M10: Sueldo Tarifa UF
A11: Jefe de Proyecto | B11: =(SUM('COSTOS DE OPERACION'!C3:V3)/'Costos HH - Sueldos'!$D$11:$D$40)/C11 -> 0 | C11: =I11*H11 -> 8 | D11: 2.5 | E11: 2.95 | F11: =C11*D11 -> 20 | G11: =C11*E11 -> 23.6 | H11: 1 | I11: 8 | J11: =B11*C11*D11*$B$6 -> 0 | K11: =B11*C11*E11*$B$6 -> 0 | L11: =B11*C11*D11 -> 0 | M11: =B11*C11*E11 -> 0
A12: Líder de Integración | B12: 0 | C12: =I12*H12 -> 0 | D12: =D13 -> 1.2 | E12: =E13 -> 1.5 | F12: =C12*D12 -> 0 | G12: =C12*E12 -> 0 | H12: 0 | I12: 8 | J12: =B12*C12*D12*$B$6 -> 0 | K12: =B12*C12*E12*$B$6 -> 0 | L12: =B12*C12*D12 -> 0 | M12: =B12*C12*E12 -> 0
A13: Arquitecto de Solución | B13: =(SUM('COSTOS DE OPERACION'!C5:V5)/'Costos HH - Sueldos'!$D$11:$D$40)/C13 -> 0 | C13: =I13*H13 -> 8 | D13: 1.2 | E13: 1.5 | F13: =C13*D13 -> 9.6 | G13: =C13*E13 -> 12 | H13: 1 | I13: 8 | J13: =B13*C13*D13*$B$6 -> 0 | K13: =B13*C13*E13*$B$6 -> 0 | L13: =B13*C13*D13 -> 0 | M13: =B13*C13*E13 -> 0
A14: Líder de Desarrollo | B14: =(SUM('COSTOS DE OPERACION'!C6:V6)/'Costos HH - Sueldos'!$D$11:$D$40)/C14 -> 0 | C14: =I14*H14 -> 8 | D14: 0.9 | E14: 1 | F14: =C14*D14 -> 7.2 | G14: =C14*E14 -> 8 | H14: 1 | I14: 8 | J14: =B14*C14*D14*$B$6 -> 0 | K14: =B14*C14*E14*$B$6 -> 0 | L14: =B14*C14*D14 -> 0 | M14: =B14*C14*E14 -> 0
A15: Líder Funcional | B15: =((SUM('COSTOS DE OPERACION'!C7:V7)+SUM('COSTOS DE OPERACION'!C42:V42))/'Costos HH - Sueldos'!$D$11:$D$40)/C15 -> 0 | C15: =I15*H15 -> 8 | D15: 1.2 | E15: 1.3 | F15: =C15*D15 -> 9.6 | G15: =C15*E15 -> 10.4 | H15: 1 | I15: 8 | J15: =B15*C15*D15*$B$6 -> 0 | K15: =B15*C15*E15*$B$6 -> 0 | L15: =B15*C15*D15 -> 0 | M15: =B15*C15*E15 -> 0
A16: Analista de Requerimientos | B16: =(SUM('COSTOS DE OPERACION'!C8:V8)/'Costos HH - Sueldos'!$D$11:$D$40)/C16 -> 0 | C16: =I16*H16 -> 32 | D16: 0.7 | E16: 0.8 | F16: =C16*D16 -> 22.4 | G16: =C16*E16 -> 25.6 | H16: 4 | I16: 8 | J16: =B16*C16*D16*$B$6 -> 0 | K16: =B16*C16*E16*$B$6 -> 0 | L16: =B16*C16*D16 -> 0 | M16: =B16*C16*E16 -> 0
A17: Desarrollador Full Stack | B17: =(SUM('COSTOS DE OPERACION'!C9:V9)/'Costos HH - Sueldos'!$D$11:$D$40)/C17 -> 0 | C17: =I17*H17 -> 64 | D17: 0.8 | E17: 0.9 | F17: =C17*D17 -> 51.2 | G17: =C17*E17 -> 57.6 | H17: 8 | I17: 8 | J17: =B17*C17*D17*$B$6 -> 0 | K17: =B17*C17*E17*$B$6 -> 0 | L17: =B17*C17*D17 -> 0 | M17: =B17*C17*E17 -> 0
A18: Desarrollador Front-end | B18: =(SUM('COSTOS DE OPERACION'!C10:V10)/'Costos HH - Sueldos'!$D$11:$D$40)/C18 -> 0 | C18: =I18*H18 -> 8 | D18: 0.6 | E18: 0.7 | F18: =C18*D18 -> 4.8 | G18: =C18*E18 -> 5.6 | H18: 1 | I18: 8 | J18: =B18*C18*D18*$B$6 -> 0 | K18: =B18*C18*E18*$B$6 -> 0 | L18: =B18*C18*D18 -> 0 | M18: =B18*C18*E18 -> 0
A19: Desarrollador Back-end | B19: =(SUM('COSTOS DE OPERACION'!C11:V11)/'Costos HH - Sueldos'!$D$11:$D$40)/C19 -> 0 | C19: =I19*H19 -> 8 | D19: 0.6 | E19: 0.7 | F19: =C19*D19 -> 4.8 | G19: =C19*E19 -> 5.6 | H19: 1 | I19: 8 | J19: =B19*C19*D19*$B$6 -> 0 | K19: =B19*C19*E19*$B$6 -> 0 | L19: =B19*C19*D19 -> 0 | M19: =B19*C19*E19 -> 0
A20: Desarrollador de Base de Datos | B20: =(SUM('COSTOS DE OPERACION'!C12:V12)/'Costos HH - Sueldos'!$D$11:$D$40)/C20 -> 0 | C20: =I20*H20 -> 8 | D20: 0.8 | E20: 0.9 | F20: =C20*D20 -> 6.4 | G20: =C20*E20 -> 7.2 | H20: 1 | I20: 8 | J20: =B20*C20*D20*$B$6 -> 0 | K20: =B20*C20*E20*$B$6 -> 0 | L20: =B20*C20*D20 -> 0 | M20: =B20*C20*E20 -> 0
A21: Diseñador UX | B21: =(SUM('COSTOS DE OPERACION'!C13:V13)/'Costos HH - Sueldos'!$D$11:$D$40)/C21 -> 0 | C21: =I21*H21 -> 8 | D21: 0.6 | E21: 0.7 | F21: =C21*D21 -> 4.8 | G21: =C21*E21 -> 5.6 | H21: 1 | I21: 8 | J21: =B21*C21*D21*$B$6 -> 0 | K21: =B21*C21*E21*$B$6 -> 0 | L21: =B21*C21*D21 -> 0 | M21: =B21*C21*E21 -> 0
A22: Especialista en Integración | B22: =(SUM('COSTOS DE OPERACION'!C14:V14)/'Costos HH - Sueldos'!$D$11:$D$40)/C22 -> 0 | C22: =I22*H22 -> 24 | D22: 1 | E22: 1.2 | F22: =C22*D22 -> 24 | G22: =C22*E22 -> 28.8 | H22: 3 | I22: 8 | J22: =B22*C22*D22*$B$6 -> 0 | K22: =B22*C22*E22*$B$6 -> 0 | L22: =B22*C22*D22 -> 0 | M22: =B22*C22*E22 -> 0
A23: Encargado de Seguridad | B23: =(SUM('COSTOS DE OPERACION'!C15:V15)/'Costos HH - Sueldos'!$D$11:$D$40)/C23 -> 0 | C23: =I23*H23 -> 8 | D23: 1.2 | E23: 1.4 | F23: =C23*D23 -> 9.6 | G23: =C23*E23 -> 11.2 | H23: 1 | I23: 8 | J23: =B23*C23*D23*$B$6 -> 0 | K23: =B23*C23*E23*$B$6 -> 0 | L23: =B23*C23*D23 -> 0 | M23: =B23*C23*E23 -> 0
A24: Ingeniero DevOps | B24: =(SUM('COSTOS DE OPERACION'!C16:V16)/'Costos HH - Sueldos'!$D$11:$D$40)/C24 -> 0 | C24: =I24*H24 -> 16 | D24: 1 | E24: 1.1 | F24: =C24*D24 -> 16 | G24: =C24*E24 -> 17.6 | H24: 2 | I24: 8 | J24: =B24*C24*D24*$B$6 -> 0 | K24: =B24*C24*E24*$B$6 -> 0 | L24: =B24*C24*D24 -> 0 | M24: =B24*C24*E24 -> 0
A25: Administrador de Base de Datos | B25: =(SUM('COSTOS DE OPERACION'!C17:V17)/'Costos HH - Sueldos'!$D$11:$D$40)/C25 -> 0 | C25: =I25*H25 -> 8 | D25: 0.8 | E25: 1 | F25: =C25*D25 -> 6.4 | G25: =C25*E25 -> 8 | H25: 1 | I25: 8 | J25: =B25*C25*D25*$B$6 -> 0 | K25: =B25*C25*E25*$B$6 -> 0 | L25: =B25*C25*D25 -> 0 | M25: =B25*C25*E25 -> 0
A26: Líder de Calidad y Pruebas | B26: =(SUM('COSTOS DE OPERACION'!C18:V18)/'Costos HH - Sueldos'!$D$11:$D$40)/C26 -> 0 | C26: =I26*H26 -> 8 | D26: 0.6 | E26: 0.7 | F26: =C26*D26 -> 4.8 | G26: =C26*E26 -> 5.6 | H26: 1 | I26: 8 | J26: =B26*C26*D26*$B$6 -> 0 | K26: =B26*C26*E26*$B$6 -> 0 | L26: =B26*C26*D26 -> 0 | M26: =B26*C26*E26 -> 0
A27: Operador de Mesa de Servicio (N1) | B27: =(SUM('COSTOS DE OPERACION'!C19:V19)/'Costos HH - Sueldos'!$D$11:$D$40)/C27 -> 0 | C27: =I27*H27 -> 40 | D27: 0.4 | E27: 0.6 | F27: =C27*D27 -> 16 | G27: =C27*E27 -> 24 | H27: 5 | I27: 8 | J27: =B27*C27*D27*$B$6 -> 0 | K27: =B27*C27*E27*$B$6 -> 0 | L27: =B27*C27*D27 -> 0 | M27: =B27*C27*E27 -> 0
... A29: Tester | B29: =(SUM('COSTOS DE OPERACION'!C21:V21)/'Costos HH - Sueldos'!$D$11:$D$40)/C29 -> 0 | C29: =I29*H29 -> 32 | D29: 0.5 | E29: 0.6 | F29: =C29*D29 -> 16 | G29: =C29*E29 -> 19.2 | H29: 4 | I29: 8 | J29: =B29*C29*D29*$B$6 -> 0 | K29: =B29*C29*E29*$B$6 -> 0 | L29: =B29*C29*D29 -> 0 | M29: =B29*C29*E29 -> 0
A30: Documentador | B30: =((SUM('COSTOS DE OPERACION'!C22:V22)+SUM('COSTOS DE OPERACION'!C43:V43))/'Costos HH - Sueldos'!$D$11:$D$40)/C30 -> 0 | C30: =I30*H30 -> 16 | D30: 0.4 | E30: 0.5 | F30: =C30*D30 -> 6.4 | G30: =C30*E30 -> 8 | H30: 2 | I30: 8 | J30: =B30*C30*D30*$B$6 -> 0 | K30: =B30*C30*E30*$B$6 -> 0 | L30: =B30*C30*D30 -> 0 | M30: =B30*C30*E30 -> 0
A31: Líder de Implantación / Cambio | B31: 0 | C31: =I31*H31 -> 0 | D31: =D15 -> 1.2 | E31: =E15 -> 1.3 | F31: =C31*D31 -> 0 | G31: =C31*E31 -> 0 | H31: 0 | I31: 8 | J31: =B31*C31*D31*$B$6 -> 0 | K31: =B31*C31*E31*$B$6 -> 0 | L31: =B31*C31*D31 -> 0 | M31: =B31*C31*E31 -> 0
A32: Instructor de Capacitación | B32: =((SUM('COSTOS DE OPERACION'!C24:V24)+SUM('COSTOS DE OPERACION'!C41:V41))/'Costos HH - Sueldos'!$D$11:$D$40)/C32 -> 0 | C32: =I32*H32 -> 8 | D32: 0.5 | E32: 0.6 | F32: =C32*D32 -> 4 | G32: =C32*E32 -> 4.8 | H32: 1 | I32: 8 | J32: =B32*C32*D32*$B$6 -> 0 | K32: =B32*C32*E32*$B$6 -> 0 | L32: =B32*C32*D32 -> 0 | M32: =B32*C32*E32 -> 0
A33: Líder de Datos | B33: 0 | C33: =I33*H33 -> 8 | F33: =IF(D33="","",C33*D33) | G33: =IF(E33="","",C33*E33) | H33: 1 | I33: 8 | J33: =IF(D33="","",B33*C33*D33*$B$6) | K33: =IF(E33="","",B33*C33*E33*$B$6) | L33: =IF(D33="","",J33/$B$6) | M33: =IF(E33="","",K33/$B$6)
A34: Líder de Operación / SRE | B34: 0 | C34: =I34*H34 -> 8 | F34: =IF(D34="","",C34*D34) | G34: =IF(E34="","",C34*E34) | H34: 1 | I34: 8 | J34: =IF(D34="","",B34*C34*D34*$B$6) | K34: =IF(E34="","",B34*C34*E34*$B$6) | L34: =IF(D34="","",J34/$B$6) | M34: =IF(E34="","",K34/$B$6)
A35: Gestor de Adquisiciones | B35: =(SUM('COSTOS DE OPERACION'!C27:V27)/'Costos HH - Sueldos'!$D$11:$D$40)/C35 -> 0 | C35: =I35*H35 -> 8 | D35: 1 | E35: 1.3 | F35: =IF(D35="","",C35*D35) -> 8 | G35: =IF(E35="","",C35*E35) -> 10.4 | H35: 1 | I35: 8 | J35: =IF(D35="","",B35*C35*D35*$B$6) -> 0 | K35: =IF(E35="","",B35*C35*E35*$B$6) -> 0 | L35: =IF(D35="","",J35/$B$6) -> 0 | M35: =IF(E35="","",K35/$B$6) -> 0
A36: Asesor Legal | B36: =(SUM('COSTOS DE OPERACION'!C28:V28)/'Costos HH - Sueldos'!$D$11:$D$40)/C36 -> 0 | C36: =I36*H36 -> 8 | D36: 1.2 | E36: 1.3 | F36: =IF(D36="","",C36*D36) -> 9.6 | G36: =IF(E36="","",C36*E36) -> 10.4 | H36: 1 | I36: 8 | J36: =IF(D36="","",B36*C36*D36*$B$6) -> 0 | K36: =IF(E36="","",B36*C36*E36*$B$6) -> 0 | L36: =IF(D36="","",J36/$B$6) -> 0 | M36: =IF(E36="","",K36/$B$6) -> 0
A37: Apoyo en bodega nocturna | B37: 0 | C37: =I37*H37 -> 16 | F37: =IF(D37="","",C37*D37) | G37: =IF(E37="","",C37*E37) | H37: 2 | I37: 8 | J37: =IF(D37="","",B37*C37*D37*$B$6) | K37: =IF(E37="","",B37*C37*E37*$B$6) | L37: =IF(D37="","",J37/$B$6) | M37: =IF(E37="","",K37/$B$6)
A38: Apoyo en cross-docking | B38: 0 | C38: =I38*H38 -> 24 | F38: =IF(D38="","",C38*D38) | G38: =IF(E38="","",C38*E38) | H38: 3 | I38: 8 | J38: =IF(D38="","",B38*C38*D38*$B$6) | K38: =IF(E38="","",B38*C38*E38*$B$6) | L38: =IF(D38="","",J38/$B$6) | M38: =IF(E38="","",K38/$B$6)
A39: Acompañante en ruta | B39: =IF(D39="","",SUM('COSTOS DE OPERACION'!C31:V31)/D39/C39) | C39: =I39*H39 -> 56 | F39: =IF(D39="","",C39*D39) | G39: =IF(E39="","",C39*E39) | H39: 7 | I39: 8 | J39: =IF(D39="","",B39*C39*D39*$B$6) | K39: =IF(E39="","",B39*C39*E39*$B$6) | L39: =IF(D39="","",J39/$B$6) | M39: =IF(E39="","",K39/$B$6)
A40: Administrador de plataforma | B40: =(SUM('COSTOS DE OPERACION'!C32:V32)/'Costos HH - Sueldos'!$D$11:$D$40)/C40 -> 0 | C40: =I40*H40 -> 40 | D40: 0.8 | E40: 1 | F40: =IF(D40="","",C40*D40) -> 32 | G40: =IF(E40="","",C40*E40) -> 40 | H40: 5 | I40: 8 | J40: =IF(D40="","",B40*C40*D40*$B$6) -> 0 | K40: =IF(E40="","",B40*C40*E40*$B$6) -> 0 | L40: =IF(D40="","",J40/$B$6) -> 0 | M40: =IF(E40="","",K40/$B$6) -> 0
A41: Total | B41: =SUM('Costos HH - Sueldos'!$B$11:$B$40) -> 0 | H41: =SUM('Costos HH - Sueldos'!$H$11:$H$40) -> 62 | J41: =SUM(J10:J40) -> 0 | K41: =SUM(K10:K40) -> 0 | L41: =SUM(L10:L40) -> 0 | M41: =SUM(M10:M40) -> 0
B42: =(B41*8) -> 0
A44: Fuente: Subdocumento 3, secciones 3.4.4–3.4.6 y Anexo 3.I; estructura del Subdocumento 1, sección 1.5.
A45: Roles compartidos: Integración se incluye en Arquitectura. Implantación y Cambio se incluye en el Líder Funcional. No son contrataciones adicionales.
A46: Datos, Operación/SRE y los tres perfiles de apoyo: costo y tarifa pendientes. Los totales monetarios son parciales hasta valorizarlos.
A47: Apoyo por ola: 2 personas en bodega nocturna, 3 en cross-docking y 7 en ruta. Cuatro semanas de estabilización por ola. No es dotación permanente simultánea.
A48: Las demás cantidades y tarifas provienen de la planilla original. El SD3 no las acredita. Programar dedicaciones mensuales según el T-15.
A49: Jefe de TI y gerencias del cliente son contraparte o validadores. Los cargos corporativos reemplazados no forman parte de los roles de ejecución del SD3.
C50: Costo / Persona | E50: Tarifa / Persona
A51: Rol | B51: Cantidad Personas | C51: C UF Mensual | D51: C CLP Mensual | E51: T UF Mensual | F51: T CLP Mensual
A52: ='Costos HH - Sueldos'!$A11 -> Jefe de Proyecto | B52: {='Costos HH - Sueldos'!$H$11:$H$40} -> 1 | C52: =PARÁMETROS!$B$8*'Costos HH - Sueldos'!$D11 -> 400 | D52: =PARÁMETROS!$B$6*'Costos HH - Sueldos'!$C52 -> 16000000 | E52: =PARÁMETROS!$B$8*'Costos HH - Sueldos'!$E11 -> 472 | F52: =PARÁMETROS!$B$6*'Costos HH - Sueldos'!$E52 -> 18880000
A53: ='Costos HH - Sueldos'!$A12 -> LÃ­der de IntegraciÃ³n | B53: =H12 -> 0 | C53: =PARÁMETROS!$B$8*'Costos HH - Sueldos'!$D12 -> 192 | D53: =PARÁMETROS!$B$6*'Costos HH - Sueldos'!$C53 -> 7680000 | E53: =PARÁMETROS!$B$8*'Costos HH - Sueldos'!$E12 -> 240 | F53: =PARÁMETROS!$B$6*'Costos HH - Sueldos'!$E53 -> 9600000
A54: ='Costos HH - Sueldos'!$A13 -> Arquitecto de SoluciÃ³n | B54: 1 | C54: =PARÁMETROS!$B$8*'Costos HH - Sueldos'!$D13 -> 192 | D54: =PARÁMETROS!$B$6*'Costos HH - Sueldos'!$C54 -> 7680000 | E54: =PARÁMETROS!$B$8*'Costos HH - Sueldos'!$E13 -> 240 | F54: =PARÁMETROS!$B$6*'Costos HH - Sueldos'!$E54 -> 9600000
A55: ='Costos HH - Sueldos'!$A14 -> LÃ­der de Desarrollo | B55: 1 | C55: =PARÁMETROS!$B$8*'Costos HH - Sueldos'!$D14 -> 144 | D55: =PARÁMETROS!$B$6*'Costos HH - Sueldos'!$C55 -> 5760000 | E55: =PARÁMETROS!$B$8*'Costos HH - Sueldos'!$E14 -> 160 | F55: =PARÁMETROS!$B$6*'Costos HH - Sueldos'!$E55 -> 6400000
A56: ='Costos HH - Sueldos'!$A15 -> LÃ­der Funcional | B56: 1 | C56: =PARÁMETROS!$B$8*'Costos HH - Sueldos'!$D15 -> 192 | D56: =PARÁMETROS!$B$6*'Costos HH - Sueldos'!$C56 -> 7680000 | E56: =PARÁMETROS!$B$8*'Costos HH - Sueldos'!$E15 -> 208 | F56: =PARÁMETROS!$B$6*'Costos HH - Sueldos'!$E56 -> 8320000
A57: ='Costos HH - Sueldos'!$A16 -> Analista de Requerimientos | B57: 4 | C57: =PARÁMETROS!$B$8*'Costos HH - Sueldos'!$D16 -> 112 | D57: =PARÁMETROS!$B$6*'Costos HH - Sueldos'!$C57 -> 4480000 | E57: =PARÁMETROS!$B$8*'Costos HH - Sueldos'!$E16 -> 128 | F57: =PARÁMETROS!$B$6*'Costos HH - Sueldos'!$E57 -> 5120000
A58: ='Costos HH - Sueldos'!$A17 -> Desarrollador Full Stack | B58: 8 | C58: =PARÁMETROS!$B$8*'Costos HH - Sueldos'!$D17 -> 128 | D58: =PARÁMETROS!$B$6*'Costos HH - Sueldos'!$C58 -> 5120000 | E58: =PARÁMETROS!$B$8*'Costos HH - Sueldos'!$E17 -> 144 | F58: =PARÁMETROS!$B$6*'Costos HH - Sueldos'!$E58 -> 5760000
A59: ='Costos HH - Sueldos'!$A18 -> Desarrollador Front-end | B59: 1 | C59: =PARÁMETROS!$B$8*'Costos HH - Sueldos'!$D18 -> 96 | D59: =PARÁMETROS!$B$6*'Costos HH - Sueldos'!$C59 -> 3840000 | E59: =PARÁMETROS!$B$8*'Costos HH - Sueldos'!$E18 -> 112 | F59: =PARÁMETROS!$B$6*'Costos HH - Sueldos'!$E59 -> 4480000
A60: ='Costos HH - Sueldos'!$A19 -> Desarrollador Back-end | B60: 1 | C60: =PARÁMETROS!$B$8*'Costos HH - Sueldos'!$D19 -> 96 | D60: =PARÁMETROS!$B$6*'Costos HH - Sueldos'!$C60 -> 3840000 | E60: =PARÁMETROS!$B$8*'Costos HH - Sueldos'!$E19 -> 112 | F60: =PARÁMETROS!$B$6*'Costos HH - Sueldos'!$E60 -> 4480000
A61: ='Costos HH - Sueldos'!$A20 -> Desarrollador de Base de Datos | B61: 1 | C61: =PARÁMETROS!$B$8*'Costos HH - Sueldos'!$D20 -> 128 | D61: =PARÁMETROS!$B$6*'Costos HH - Sueldos'!$C61 -> 5120000 | E61: =PARÁMETROS!$B$8*'Costos HH - Sueldos'!$E20 -> 144 | F61: =PARÁMETROS!$B$6*'Costos HH - Sueldos'!$E61 -> 5760000
A62: ='Costos HH - Sueldos'!$A21 -> Diseñador UX | B62: 1 | C62: =PARÁMETROS!$B$8*'Costos HH - Sueldos'!$D21 -> 96 | D62: =PARÁMETROS!$B$6*'Costos HH - Sueldos'!$C62 -> 3840000 | E62: =PARÁMETROS!$B$8*'Costos HH - Sueldos'!$E21 -> 112 | F62: =PARÁMETROS!$B$6*'Costos HH - Sueldos'!$E62 -> 4480000
A63: ='Costos HH - Sueldos'!$A22 -> Especialista en Integración | B63: 3 | C63: =PARÁMETROS!$B$8*'Costos HH - Sueldos'!$D22 -> 160 | D63: =PARÁMETROS!$B$6*'Costos HH - Sueldos'!$C63 -> 6400000 | E63: =PARÁMETROS!$B$8*'Costos HH - Sueldos'!$E22 -> 192 | F63: =PARÁMETROS!$B$6*'Costos HH - Sueldos'!$E63 -> 7680000
A64: ='Costos HH - Sueldos'!$A23 -> Encargado de Seguridad | B64: 1 | C64: =PARÁMETROS!$B$8*'Costos HH - Sueldos'!$D23 -> 192 | D64: =PARÁMETROS!$B$6*'Costos HH - Sueldos'!$C64 -> 7680000 | E64: =PARÁMETROS!$B$8*'Costos HH - Sueldos'!$E23 -> 224 | F64: =PARÁMETROS!$B$6*'Costos HH - Sueldos'!$E64 -> 8960000
A65: ='Costos HH - Sueldos'!$A24 -> Ingeniero DevOps | B65: 2 | C65: =PARÁMETROS!$B$8*'Costos HH - Sueldos'!$D24 -> 160 | D65: =PARÁMETROS!$B$6*'Costos HH - Sueldos'!$C65 -> 6400000 | E65: =PARÁMETROS!$B$8*'Costos HH - Sueldos'!$E24 -> 176 | F65: =PARÁMETROS!$B$6*'Costos HH - Sueldos'!$E65 -> 7040000
... A73: ='Costos HH - Sueldos'!$A32 -> Instructor de Capacitación | B73: 1 | C73: =PARÁMETROS!$B$8*'Costos HH - Sueldos'!$D32 -> 80 | D73: =PARÁMETROS!$B$6*'Costos HH - Sueldos'!$C73 -> 3200000 | E73: =PARÁMETROS!$B$8*'Costos HH - Sueldos'!$E32 -> 96 | F73: =PARÁMETROS!$B$6*'Costos HH - Sueldos'!$E73 -> 3840000
A74: ='Costos HH - Sueldos'!$A33 -> LÃ­der de Datos | B74: 1 | C74: =IF(D33="","",D33*$B$7) | D74: =IF(C74="","",C74*$B$6) | E74: =IF(E33="","",E33*$B$7) | F74: =IF(E74="","",E74*$B$6)
A75: ='Costos HH - Sueldos'!$A34 -> LÃ­der de OperaciÃ³n / SRE | B75: 1 | C75: =IF(D34="","",D34*$B$7) | D75: =IF(C75="","",C75*$B$6) | E75: =IF(E34="","",E34*$B$7) | F75: =IF(E75="","",E75*$B$6)
A76: ='Costos HH - Sueldos'!$A35 -> Gestor de Adquisiciones | B76: 1 | C76: =PARÁMETROS!$B$8*'Costos HH - Sueldos'!$D35 -> 160 | D76: =PARÁMETROS!$B$6*'Costos HH - Sueldos'!$C76 -> 6400000 | E76: =PARÁMETROS!$B$8*'Costos HH - Sueldos'!$E35 -> 208 | F76: =PARÁMETROS!$B$6*'Costos HH - Sueldos'!$E76 -> 8320000
A77: ='Costos HH - Sueldos'!$A36 -> Asesor Legal | B77: 1 | C77: =PARÁMETROS!$B$8*'Costos HH - Sueldos'!$D36 -> 192 | D77: =PARÁMETROS!$B$6*'Costos HH - Sueldos'!$C77 -> 7680000 | E77: =PARÁMETROS!$B$8*'Costos HH - Sueldos'!$E36 -> 208 | F77: =PARÁMETROS!$B$6*'Costos HH - Sueldos'!$E77 -> 8320000
A78: ='Costos HH - Sueldos'!$A37 -> Apoyo en bodega nocturna | B78: 2 | C78: =IF(D37="","",D37*$B$7) | D78: =IF(C78="","",C78*$B$6) | E78: =IF(E37="","",E37*$B$7) | F78: =IF(E78="","",E78*$B$6)
A79: ='Costos HH - Sueldos'!$A38 -> Apoyo en cross-docking | B79: 3 | C79: =IF(D38="","",D38*$B$7) | D79: =IF(C79="","",C79*$B$6) | E79: =IF(E38="","",E38*$B$7) | F79: =IF(E79="","",E79*$B$6)
A80: ='Costos HH - Sueldos'!$A39 -> AcompaÃ±ante en ruta | B80: 7 | C80: =IF(D39="","",D39*$B$7) | D80: =IF(C80="","",C80*$B$6) | E80: =IF(E39="","",E39*$B$7) | F80: =IF(E80="","",E80*$B$6)
A81: ='Costos HH - Sueldos'!$A40 -> Administrador de plataforma | B81: 5 | C81: =PARÁMETROS!$B$8*'Costos HH - Sueldos'!$D40 -> 128 | D81: =PARÁMETROS!$B$6*'Costos HH - Sueldos'!$C81 -> 5120000 | E81: =PARÁMETROS!$B$8*'Costos HH - Sueldos'!$E40 -> 160 | F81: =PARÁMETROS!$B$6*'Costos HH - Sueldos'!$E81 -> 6400000
A82: Totales | B82: =SUM(B52:B81) -> 62 | C82: =SUM('Costos HH - Sueldos'!$C$52:$C$81) -> 4288 | D82: =SUM('Costos HH - Sueldos'!$D$52:$D$81) -> 171520000 | E82: =SUM('Costos HH - Sueldos'!$E$52:$E$81) -> 5096 | F82: =SUM('Costos HH - Sueldos'!$F$52:$F$81) -> 203840000

Sheet Costos HH por MES
F4: Costo / Persona | H4: Tarifa
A5: Rol | B5: Dias según Gantt | D5: Rol | E5: Cantidad Personas | F5: C UF Mensual | G5: C CLP Mensual | H5: T UF Mensual | I5: T CLP Mensual
A6: ='Costos HH - Sueldos'!$A11 -> Jefe de Proyecto | B6: ='Costos HH - Sueldos'!$B11 -> 0 | D6: ='Costos HH - Sueldos'!$A11 -> Jefe de Proyecto | E6: ='Costos HH - Sueldos'!$H11 -> 1 | F6: =PARÁMETROS!$B$8*'Costos HH - Sueldos'!$D11 -> 400 | G6: =PARÁMETROS!$B$6*'Costos HH - Sueldos'!$C52 -> 16000000 | H6: =PARÁMETROS!$B$8*'Costos HH - Sueldos'!$E11 -> 472 | I6: =PARÁMETROS!$B$6*'Costos HH - Sueldos'!$E52 -> 18880000
A7: ='Costos HH - Sueldos'!$A12 -> LÃ­der de IntegraciÃ³n | B7: ='Costos HH - Sueldos'!$B12 -> 0 | D7: ='Costos HH - Sueldos'!$A12 -> LÃ­der de IntegraciÃ³n | E7: ='Costos HH - Sueldos'!$H12 -> 0 | F7: =PARÁMETROS!$B$8*'Costos HH - Sueldos'!$D12 -> 192 | G7: =PARÁMETROS!$B$6*'Costos HH - Sueldos'!$C53 -> 7680000 | H7: =PARÁMETROS!$B$8*'Costos HH - Sueldos'!$E12 -> 240 | I7: =PARÁMETROS!$B$6*'Costos HH - Sueldos'!$E53 -> 9600000
A8: ='Costos HH - Sueldos'!$A13 -> Arquitecto de SoluciÃ³n | B8: ='Costos HH - Sueldos'!$B13 -> 0 | D8: ='Costos HH - Sueldos'!$A13 -> Arquitecto de SoluciÃ³n | E8: ='Costos HH - Sueldos'!$H13 -> 1 | F8: =PARÁMETROS!$B$8*'Costos HH - Sueldos'!$D13 -> 192 | G8: =PARÁMETROS!$B$6*'Costos HH - Sueldos'!$C54 -> 7680000 | H8: =PARÁMETROS!$B$8*'Costos HH - Sueldos'!$E13 -> 240 | I8: =PARÁMETROS!$B$6*'Costos HH - Sueldos'!$E54 -> 9600000
A9: ='Costos HH - Sueldos'!$A14 -> LÃ­der de Desarrollo | B9: ='Costos HH - Sueldos'!$B14 -> 0 | D9: ='Costos HH - Sueldos'!$A14 -> LÃ­der de Desarrollo | E9: ='Costos HH - Sueldos'!$H14 -> 1 | F9: =PARÁMETROS!$B$8*'Costos HH - Sueldos'!$D14 -> 144 | G9: =PARÁMETROS!$B$6*'Costos HH - Sueldos'!$C55 -> 5760000 | H9: =PARÁMETROS!$B$8*'Costos HH - Sueldos'!$E14 -> 160 | I9: =PARÁMETROS!$B$6*'Costos HH - Sueldos'!$E55 -> 6400000
A10: ='Costos HH - Sueldos'!$A15 -> LÃ­der Funcional | B10: ='Costos HH - Sueldos'!$B15 -> 0 | D10: ='Costos HH - Sueldos'!$A15 -> LÃ­der Funcional | E10: ='Costos HH - Sueldos'!$H15 -> 1 | F10: =PARÁMETROS!$B$8*'Costos HH - Sueldos'!$D15 -> 192 | G10: =PARÁMETROS!$B$6*'Costos HH - Sueldos'!$C56 -> 7680000 | H10: =PARÁMETROS!$B$8*'Costos HH - Sueldos'!$E15 -> 208 | I10: =PARÁMETROS!$B$6*'Costos HH - Sueldos'!$E56 -> 8320000
A11: ='Costos HH - Sueldos'!$A16 -> Analista de Requerimientos | B11: ='Costos HH - Sueldos'!$B16 -> 0 | D11: ='Costos HH - Sueldos'!$A16 -> Analista de Requerimientos | E11: ='Costos HH - Sueldos'!$H16 -> 4 | F11: =PARÁMETROS!$B$8*'Costos HH - Sueldos'!$D16 -> 112 | G11: =PARÁMETROS!$B$6*'Costos HH - Sueldos'!$C57 -> 4480000 | H11: =PARÁMETROS!$B$8*'Costos HH - Sueldos'!$E16 -> 128 | I11: =PARÁMETROS!$B$6*'Costos HH - Sueldos'!$E57 -> 5120000
A12: ='Costos HH - Sueldos'!$A17 -> Desarrollador Full Stack | B12: ='Costos HH - Sueldos'!$B17 -> 0 | D12: ='Costos HH - Sueldos'!$A17 -> Desarrollador Full Stack | E12: ='Costos HH - Sueldos'!$H17 -> 8 | F12: =PARÁMETROS!$B$8*'Costos HH - Sueldos'!$D17 -> 128 | G12: =PARÁMETROS!$B$6*'Costos HH - Sueldos'!$C58 -> 5120000 | H12: =PARÁMETROS!$B$8*'Costos HH - Sueldos'!$E17 -> 144 | I12: =PARÁMETROS!$B$6*'Costos HH - Sueldos'!$E58 -> 5760000
A13: ='Costos HH - Sueldos'!$A18 -> Desarrollador Front-end | B13: ='Costos HH - Sueldos'!$B18 -> 0 | D13: ='Costos HH - Sueldos'!$A18 -> Desarrollador Front-end | E13: ='Costos HH - Sueldos'!$H18 -> 1 | F13: =PARÁMETROS!$B$8*'Costos HH - Sueldos'!$D18 -> 96 | G13: =PARÁMETROS!$B$6*'Costos HH - Sueldos'!$C59 -> 3840000 | H13: =PARÁMETROS!$B$8*'Costos HH - Sueldos'!$E18 -> 112 | I13: =PARÁMETROS!$B$6*'Costos HH - Sueldos'!$E59 -> 4480000
A14: ='Costos HH - Sueldos'!$A19 -> Desarrollador Back-end | B14: ='Costos HH - Sueldos'!$B19 -> 0 | D14: ='Costos HH - Sueldos'!$A19 -> Desarrollador Back-end | E14: ='Costos HH - Sueldos'!$H19 -> 1 | F14: =PARÁMETROS!$B$8*'Costos HH - Sueldos'!$D19 -> 96 | G14: =PARÁMETROS!$B$6*'Costos HH - Sueldos'!$C60 -> 3840000 | H14: =PARÁMETROS!$B$8*'Costos HH - Sueldos'!$E19 -> 112 | I14: =PARÁMETROS!$B$6*'Costos HH - Sueldos'!$E60 -> 4480000
A15: ='Costos HH - Sueldos'!$A20 -> Desarrollador de Base de Datos | B15: ='Costos HH - Sueldos'!$B20 -> 0 | D15: ='Costos HH - Sueldos'!$A20 -> Desarrollador de Base de Datos | E15: ='Costos HH - Sueldos'!$H20 -> 1 | F15: =PARÁMETROS!$B$8*'Costos HH - Sueldos'!$D20 -> 128 | G15: =PARÁMETROS!$B$6*'Costos HH - Sueldos'!$C61 -> 5120000 | H15: =PARÁMETROS!$B$8*'Costos HH - Sueldos'!$E20 -> 144 | I15: =PARÁMETROS!$B$6*'Costos HH - Sueldos'!$E61 -> 5760000
A16: ='Costos HH - Sueldos'!$A21 -> Diseñador UX | B16: ='Costos HH - Sueldos'!$B21 -> 0 | D16: ='Costos HH - Sueldos'!$A21 -> Diseñador UX | E16: ='Costos HH - Sueldos'!$H21 -> 1 | F16: =PARÁMETROS!$B$8*'Costos HH - Sueldos'!$D21 -> 96 | G16: =PARÁMETROS!$B$6*'Costos HH - Sueldos'!$C62 -> 3840000 | H16: =PARÁMETROS!$B$8*'Costos HH - Sueldos'!$E21 -> 112 | I16: =PARÁMETROS!$B$6*'Costos HH - Sueldos'!$E62 -> 4480000
A17: ='Costos HH - Sueldos'!$A22 -> Especialista en Integración | B17: ='Costos HH - Sueldos'!$B22 -> 0 | D17: ='Costos HH - Sueldos'!$A22 -> Especialista en Integración | E17: ='Costos HH - Sueldos'!$H22 -> 3 | F17: =PARÁMETROS!$B$8*'Costos HH - Sueldos'!$D22 -> 160 | G17: =PARÁMETROS!$B$6*'Costos HH - Sueldos'!$C63 -> 6400000 | H17: =PARÁMETROS!$B$8*'Costos HH - Sueldos'!$E22 -> 192 | I17: =PARÁMETROS!$B$6*'Costos HH - Sueldos'!$E63 -> 7680000
... A27: ='Costos HH - Sueldos'!$A32 -> Instructor de Capacitación | B27: ='Costos HH - Sueldos'!$B32 -> 0 | D27: ='Costos HH - Sueldos'!$A32 -> Instructor de Capacitación | E27: ='Costos HH - Sueldos'!$H32 -> 1 | F27: =PARÁMETROS!$B$8*'Costos HH - Sueldos'!$D32 -> 80 | G27: =PARÁMETROS!$B$6*'Costos HH - Sueldos'!$C73 -> 3200000 | H27: =PARÁMETROS!$B$8*'Costos HH - Sueldos'!$E32 -> 96 | I27: =PARÁMETROS!$B$6*'Costos HH - Sueldos'!$E73 -> 3840000
A28: ='Costos HH - Sueldos'!$A33 -> LÃ­der de Datos | B28: ='Costos HH - Sueldos'!$B33 | D28: ='Costos HH - Sueldos'!$A33 -> LÃ­der de Datos | E28: ='Costos HH - Sueldos'!$H33 -> 1 | F28: =IF('Costos HH - Sueldos'!C74="","",'Costos HH - Sueldos'!C74) | G28: =IF('Costos HH - Sueldos'!D74="","",'Costos HH - Sueldos'!D74) | H28: =IF('Costos HH - Sueldos'!E74="","",'Costos HH - Sueldos'!E74) | I28: =IF('Costos HH - Sueldos'!F74="","",'Costos HH - Sueldos'!F74)
A29: ='Costos HH - Sueldos'!$A34 -> LÃ­der de OperaciÃ³n / SRE | B29: ='Costos HH - Sueldos'!$B34 | D29: ='Costos HH - Sueldos'!$A34 -> LÃ­der de OperaciÃ³n / SRE | E29: ='Costos HH - Sueldos'!$H34 -> 1 | F29: =IF('Costos HH - Sueldos'!C75="","",'Costos HH - Sueldos'!C75) | G29: =IF('Costos HH - Sueldos'!D75="","",'Costos HH - Sueldos'!D75) | H29: =IF('Costos HH - Sueldos'!E75="","",'Costos HH - Sueldos'!E75) | I29: =IF('Costos HH - Sueldos'!F75="","",'Costos HH - Sueldos'!F75)
A30: ='Costos HH - Sueldos'!$A35 -> Gestor de Adquisiciones | B30: ='Costos HH - Sueldos'!$B35 -> 0 | D30: ='Costos HH - Sueldos'!$A35 -> Gestor de Adquisiciones | E30: ='Costos HH - Sueldos'!$H35 -> 1 | F30: =PARÁMETROS!$B$8*'Costos HH - Sueldos'!$D35 -> 160 | G30: =PARÁMETROS!$B$6*'Costos HH - Sueldos'!$C76 -> 6400000 | H30: =PARÁMETROS!$B$8*'Costos HH - Sueldos'!$E35 -> 208 | I30: =PARÁMETROS!$B$6*'Costos HH - Sueldos'!$E76 -> 8320000
A31: ='Costos HH - Sueldos'!$A36 -> Asesor Legal | B31: ='Costos HH - Sueldos'!$B36 -> 0 | D31: ='Costos HH - Sueldos'!$A36 -> Asesor Legal | E31: ='Costos HH - Sueldos'!$H36 -> 1 | F31: =PARÁMETROS!$B$8*'Costos HH - Sueldos'!$D36 -> 192 | G31: =PARÁMETROS!$B$6*'Costos HH - Sueldos'!$C77 -> 7680000 | H31: =PARÁMETROS!$B$8*'Costos HH - Sueldos'!$E36 -> 208 | I31: =PARÁMETROS!$B$6*'Costos HH - Sueldos'!$E77 -> 8320000
A32: ='Costos HH - Sueldos'!$A37 -> Apoyo en bodega nocturna | B32: ='Costos HH - Sueldos'!$B37 | D32: ='Costos HH - Sueldos'!$A37 -> Apoyo en bodega nocturna | E32: ='Costos HH - Sueldos'!$H37 -> 2 | F32: =IF('Costos HH - Sueldos'!C78="","",'Costos HH - Sueldos'!C78) | G32: =IF('Costos HH - Sueldos'!D78="","",'Costos HH - Sueldos'!D78) | H32: =IF('Costos HH - Sueldos'!E78="","",'Costos HH - Sueldos'!E78) | I32: =IF('Costos HH - Sueldos'!F78="","",'Costos HH - Sueldos'!F78)
A33: ='Costos HH - Sueldos'!$A38 -> Apoyo en cross-docking | B33: ='Costos HH - Sueldos'!$B38 | D33: ='Costos HH - Sueldos'!$A38 -> Apoyo en cross-docking | E33: ='Costos HH - Sueldos'!$H38 -> 3 | F33: =IF('Costos HH - Sueldos'!C79="","",'Costos HH - Sueldos'!C79) | G33: =IF('Costos HH - Sueldos'!D79="","",'Costos HH - Sueldos'!D79) | H33: =IF('Costos HH - Sueldos'!E79="","",'Costos HH - Sueldos'!E79) | I33: =IF('Costos HH - Sueldos'!F79="","",'Costos HH - Sueldos'!F79)
A34: ='Costos HH - Sueldos'!$A39 -> AcompaÃ±ante en ruta | B34: ='Costos HH - Sueldos'!$B39 | D34: ='Costos HH - Sueldos'!$A39 -> AcompaÃ±ante en ruta | E34: ='Costos HH - Sueldos'!$H39 -> 7 | F34: =IF('Costos HH - Sueldos'!C80="","",'Costos HH - Sueldos'!C80) | G34: =IF('Costos HH - Sueldos'!D80="","",'Costos HH - Sueldos'!D80) | H34: =IF('Costos HH - Sueldos'!E80="","",'Costos HH - Sueldos'!E80) | I34: =IF('Costos HH - Sueldos'!F80="","",'Costos HH - Sueldos'!F80)
A35: ='Costos HH - Sueldos'!$A40 -> Administrador de plataforma | B35: ='Costos HH - Sueldos'!$B40 -> 0 | D35: ='Costos HH - Sueldos'!$A40 -> Administrador de plataforma | E35: ='Costos HH - Sueldos'!$H40 -> 5 | F35: =PARÁMETROS!$B$8*'Costos HH - Sueldos'!$D40 -> 128 | G35: =PARÁMETROS!$B$6*'Costos HH - Sueldos'!$C81 -> 5120000 | H35: =PARÁMETROS!$B$8*'Costos HH - Sueldos'!$E40 -> 160 | I35: =PARÁMETROS!$B$6*'Costos HH - Sueldos'!$E81 -> 6400000
A36: =+'Costos HH - Sueldos'!A41 -> Total | B36: =+'Costos HH - Sueldos'!B41 -> 0 | D36: Totales | E36: =SUM('Costos HH por MES'!$E$6:$E$35) -> 62 | F36: =SUM('Costos HH por MES'!$F$6:$F$35) -> 3568 | G36: =SUM('Costos HH por MES'!$G$6:$G$35) -> 142720000 | H36: =SUM('Costos HH por MES'!$H$6:$H$35) -> 4216 | I36: =SUM('Costos HH por MES'!$I$6:$I$35) -> 168640000

Sheet TARIFAS DE OPERACION
C1: Tarifa de implementación | W1: Tarifa de soporte
B2: Tarifas(UF) | C2: Mes 1 | D2: Mes 2 | E2: Mes 3 | F2: Mes 4 | G2: Mes 5 | H2: Mes 6 | I2: Mes 7 | J2: Mes 8 | K2: Mes 9 | L2: Mes 10 | M2: Mes 11 | N2: Mes 12 | O2: Mes 13 | P2: Mes 14 | Q2: Mes 15 | R2: Mes 16 | S2: Mes 17 | T2: Mes 18 | U2: Mes 19 | V2: Mes 20 | W2: Mes 21 | X2: Mes 22 | Y2: Mes 23 | Z2: Mes 24 | AA2: Mes 25 | AB2: Mes 26 | AC2: Mes 27 | AD2: Mes 28 | AE2: Mes 29 | AF2: Mes 30 | AG2: Mes 31 | AH2: Mes 32 | AI2: Mes 33 | AJ2: Mes 34 | AK2: Mes 35 | AL2: Mes 36
A3: =+'COSTOS DE OPERACION'!A3 -> Project Manager | B3: 0 | C3: =B$3 -> 0 | D3: =B$3*1 -> 0 | E3: =B$3*1 -> 0 | F3: =B$3*1 -> 0 | G3: =B$3*1 -> 0 | H3: =B$3*1 -> 0 | I3: =B$3*1 -> 0 | J3: =B$3*1 -> 0 | K3: =B$3*1 -> 0 | L3: =B$3*1 -> 0 | M3: =B$3*1 -> 0 | N3: =B$3*1 -> 0 | O3: =B$3*1 -> 0 | P3: =B$3*1 -> 0 | Q3: =B$3*1 -> 0 | R3: =B$3*1 -> 0 | S3: =B$3*1 -> 0 | T3: =B$3*1 -> 0 | U3: =B$3*1 -> 0 | V3: =B$3*1 -> 0 | W3: =B$3*1 -> 0 | X3: =C$3*1 -> 0 | Y3: =D$3*1 -> 0 | Z3: =E$3*1 -> 0 | AA3: =F$3*1 -> 0 | AB3: =G$3*1 -> 0 | AC3: =H$3*1 -> 0 | AD3: =I$3*1 -> 0 | ... AL3: =Q$3*1 -> 0
A4: =+'COSTOS DE OPERACION'!A4 -> Jefe de TIC | B4: 0 | E4: =B$4 -> 0 | F4: =B$4*1 -> 0 | G4: =B$4*1 -> 0 | H4: =B$4*1 -> 0 | I4: =B$4*1 -> 0 | P4: =B$4 -> 0 | V4: =B$4 -> 0
A5: =+'COSTOS DE OPERACION'!A5 -> Arquitecto de soluciones | B5: 0 | D5: =B$5*1 -> 0 | E5: =B$5 -> 0 | J5: =B$5 -> 0 | R5: =B$5 -> 0 | S5: =B$5*1 -> 0 | T5: =B$5 -> 0
A6: =+'COSTOS DE OPERACION'!A6 -> Líder Técnico | B6: 0 | D6: =B$6 -> 0 | E6: =B$6 -> 0 | F6: =B$6*1 -> 0 | G6: =B$6*1 -> 0 | H6: =B$6 -> 0 | I6: =B$6 -> 0 | K6: =B$6*1 -> 0 | L6: =B$6 -> 0 | N6: =B$6 -> 0 | R6: =B$6 -> 0 | S6: =B$6*1 -> 0 | T6: =B$6*1 -> 0 | U6: =B$6*1 -> 0
A7: =+'COSTOS DE OPERACION'!A7 -> Product Owner (Líder Funcional) | B7: 0 | C7: =B$7 -> 0 | E7: =B$7 -> 0 | F7: =B$7*1 -> 0 | G7: =B$7*1 -> 0 | H7: =B$7 -> 0 | I7: =B$7*1 -> 0 | J7: =B$7*1 -> 0 | N7: =B$7 -> 0 | O7: =B$7 -> 0 | P7: =B$7 -> 0 | R7: =B$7 -> 0 | V7: =B$7 -> 0
A8: =+'COSTOS DE OPERACION'!A8 -> Analista de Requerimientos | B8: 0 | C8: =B$8*4 -> 0 | D8: =B$8*4 -> 0 | E8: =B$8*4 -> 0 | J8: =(B$8*4/20)*3 -> 0
A9: =+'COSTOS DE OPERACION'!A9 -> Desarrollador Full Stack | B9: 0 | F9: =B$9*1*8 -> 0 | G9: =B$9*1*8 -> 0 | H9: =B$9*1*8 -> 0 | I9: =B$9*1*8 -> 0 | J9: =B$9*1*8 -> 0 | K9: =B$9*8 -> 0 | L9: =B$9*8*0.5 -> 0 | R9: =B$9*8 -> 0 | S9: =B$9*1*8 -> 0 | T9: =B$9*1*8 -> 0 | U9: =B$9*1*8 -> 0
A10: =+'COSTOS DE OPERACION'!A10 -> Desarrollador Front-end | B10: 0 | F10: =B$10*1 -> 0 | G10: =B$10*1 -> 0 | H10: =B$10*1 -> 0 | I10: =B$10*1 -> 0 | J10: =B$10*1 -> 0 | R10: =B$10 -> 0 | S10: =B$10*1 -> 0 | T10: =B$10*1 -> 0 | U10: =B$10*1 -> 0
A11: =+'COSTOS DE OPERACION'!A11 -> Desarrollador Back-end | B11: 0 | F11: =B$11*1 -> 0 | G11: =B$11*1 -> 0 | H11: =B$11*1 -> 0 | I11: =B$11*1 -> 0 | J11: =B$11*1 -> 0 | K11: =B$11*1 -> 0 | L11: =B$11*1 -> 0 | R11: =B$11 -> 0 | S11: =B$11*1 -> 0 | T11: =B$11*1 -> 0 | U11: =B$11*1 -> 0
A12: =+'COSTOS DE OPERACION'!A12 -> Desarrollador de Base de Datos | B12: 0 | I12: =B$12*1 -> 0 | J12: =B$12*1 -> 0 | K12: =B$12*1 -> 0
A13: =+'COSTOS DE OPERACION'!A13 -> Diseñador UX | B13: 0 | D13: =B$13 -> 0 | E13: =(B$13/20)*5 -> 0
A14: =+'COSTOS DE OPERACION'!A14 -> Especialista en Integración | B14: 0 | D14: =B$14*3 -> 0 | I14: =B$14*1*3 -> 0 | J14: =B$14*1*3 -> 0 | K14: =B$14*3 -> 0 | L14: =B$14*3 -> 0
A15: =+'COSTOS DE OPERACION'!A15 -> Encargado de Seguridad TI | B15: 0 | F15: =B$15*1 -> 0 | G15: =B$15*1 -> 0 | H15: =B$15 -> 0 | I15: =B$15 -> 0 | P15: =B$15 -> 0 | V15: =B$15 -> 0 | W15: =$B$15*1 -> 0 | X15: =$B$15*1 -> 0 | Y15: =$B$15*1 -> 0 | Z15: =$B$15*1 -> 0 | AA15: =$B$15*1 -> 0 | AB15: =$B$15*1 -> 0 | AC15: =$B$15*1 -> 0 | AD15: =$B$15*1 -> 0 | ... AL15: =$B$15*1 -> 0
A16: =+'COSTOS DE OPERACION'!A16 -> Ingeniero DevOps | B16: 0 | E16: =$B$16*2 -> 0 | F16: =$B$16*2 -> 0 | G16: =B$16*1*2 -> 0 | H16: =B$16*1*2 -> 0 | I16: =B$16*1*2 -> 0 | L16: =B$16*2 -> 0 | N16: =B$16*2 -> 0 | O16: =B$16*1*2 -> 0 | P16: =B$16*1*2 -> 0 | Q16: =B$16*1*2 -> 0 | R16: =B$16*2 -> 0
A17: =+'COSTOS DE OPERACION'!A17 -> Administrador de Base de Datos | B17: 0 | I17: =B$17*1 -> 0 | J17: =B$17*1 -> 0 | K17: =B$17*1 -> 0 | O17: =B$17*1 -> 0
A18: =+'COSTOS DE OPERACION'!A18 -> QA Lead | B18: 0 | C18: =B$18 -> 0 | H18: =B$18*1 -> 0 | I18: =B$18 -> 0 | K18: =$B$18*1 -> 0 | L18: =$B$18*1 -> 0 | M18: =$B$18*1 -> 0 | N18: =$B$18*1 -> 0 | P18: =$B$18*1 -> 0 | Q18: =$B$18*1 -> 0 | R18: =$B$18*1 -> 0
A19: =+'COSTOS DE OPERACION'!A19 -> Operador Service Desk | B19: 0 | L19: =B$19 -> 0 | M19: =B$19 -> 0 | W19: =B$19*1 -> 0 | X19: =B$19*1 -> 0 | Y19: =B$19*1 -> 0 | Z19: =B$19*1 -> 0 | AA19: =B$19*1 -> 0 | AB19: =B$19*1 -> 0 | AC19: =B$19*1 -> 0 | AD19: =B$19*1 -> 0 | AE19: =B$19*1 -> 0 | AF19: =B$19*1 -> 0 | AG19: =B$19*1 -> 0 | AH19: =B$19*1 -> 0 | AI19: =B$19*1 -> 0 | AJ19: =B$19*1 -> 0 | AK19: =B$19*1 -> 0 | AL19: =B$19*1 -> 0
A20: =+'COSTOS DE OPERACION'!A20 -> Especialista en Soporte Técnico Nivel 2 | B20: 0 | L20: =B$20 -> 0 | M20: =B$20*1 -> 0 | N20: =B$20 -> 0 | W20: =B$20*1 -> 0 | X20: =B$20*1 -> 0 | Y20: =B$20*1 -> 0 | Z20: =B$20*1 -> 0 | AA20: =B$20*1 -> 0 | AB20: =B$20*1 -> 0 | AC20: =B$20*1 -> 0 | AD20: =B$20*1 -> 0 | AE20: =B$20*1 -> 0 | AF20: =B$20*1 -> 0 | AG20: =B$20*1 -> 0 | AH20: =B$20*1 -> 0 | AI20: =B$20*1 -> 0 | AJ20: =B$20*1 -> 0 | AK20: =B$20*1 -> 0 | AL20: =B$20*1 -> 0
A21: =+'COSTOS DE OPERACION'!A21 -> Tester | B21: 0 | H21: =B$21*1*4 -> 0 | I21: =B$21*4 -> 0 | K21: =B$21*1*4 -> 0
A22: =+'COSTOS DE OPERACION'!A22 -> Documentador | B22: 0 | I22: =B$22*1*2 -> 0 | R22: =B$22*2 -> 0 | T22: =B$22*2 -> 0 | U22: =B$22*2 -> 0 | V22: =B$22*2 -> 0 | W22: =$B$22*1 -> 0 | X22: =$B$22*1 -> 0 | Y22: =$B$22*1 -> 0 | Z22: =$B$22*1 -> 0 | AA22: =$B$22*1 -> 0 | AB22: =$B$22*1 -> 0 | AC22: =$B$22*1 -> 0 | AD22: =$B$22*1 -> 0 | ... AL22: =$B$22*1 -> 0
A23: =+'COSTOS DE OPERACION'!A23 -> Change Manager | B23: 0 | C23: =B$23 -> 0 | W23: =B$23*1 -> 0 | X23: =B$23*1 -> 0 | Y23: =B$23*1 -> 0 | Z23: =B$23*1 -> 0 | AA23: =B$23*1 -> 0 | AB23: =B$23*1 -> 0 | AC23: =B$23*1 -> 0 | AD23: =B$23*1 -> 0 | AE23: =B$23*1 -> 0 | AF23: =B$23*1 -> 0 | AG23: =B$23*1 -> 0 | AH23: =B$23*1 -> 0 | AI23: =B$23*1 -> 0 | AJ23: =B$23*1 -> 0 | AK23: =B$23*1 -> 0 | AL23: =B$23*1 -> 0
A24: =+'COSTOS DE OPERACION'!A24 -> Instructor de Capacitación | B24: 0 | P24: =B$24 -> 0 | R24: =B$24 -> 0
A25: =+'COSTOS DE OPERACION'!A25 -> Gerente de Administración de Finanzas | B25: 0 | V25: =B$25 -> 0
A26: =+'COSTOS DE OPERACION'!A26 -> Especialista en Contabilidad | B26: 0 | V26: =B$26 -> 0
A27: =+'COSTOS DE OPERACION'!A27 -> Gestor de Adquisiciones | B27: 0 | C27: =B$27 -> 0 | E27: =B$27 -> 0 | F27: =B$27*1 -> 0 | G27: =B$27*1 -> 0 | H27: =B$27*1 -> 0 | I27: =B$27*1 -> 0 | V27: =B$27 -> 0 | W27: =$B$27*1 -> 0 | X27: =$B$27*1 -> 0 | Y27: =$B$27*1 -> 0 | Z27: =$B$27*1 -> 0 | AA27: =$B$27*1 -> 0 | AB27: =$B$27*1 -> 0 | AC27: =$B$27*1 -> 0 | AD27: =$B$27*1 -> 0 | ... AL27: =$B$27*1 -> 0
A28: =+'COSTOS DE OPERACION'!A28 -> Asesor Legal | B28: 0 | V28: =B$28 -> 0 | AL28: =B$28*1 -> 0
A29: =+'COSTOS DE OPERACION'!A29 -> Director Comercial | B29: 0 | C29: =B$29 -> 0
A30: =+'COSTOS DE OPERACION'!A30 -> Consultor de Preventa | B30: 0 | C30: =B$30 -> 0 | AL30: =B$30*1 -> 0
A31: =+'COSTOS DE OPERACION'!A31 -> Especialista en Licitaciones | B31: 0 | C31: =B$31 -> 0 | V31: =B$31 -> 0 | AL31: =B$31*1 -> 0
A32: =+'COSTOS DE OPERACION'!A32 -> Administrador de plataforma | B32: 0 | W32: =$B$31*1 -> 0 | X32: =$B$31*1 -> 0 | Y32: =$B$31*1 -> 0 | Z32: =$B$31*1 -> 0 | AA32: =$B$31*1 -> 0 | AB32: =$B$31*1 -> 0 | AC32: =$B$31*1 -> 0 | AD32: =$B$31*1 -> 0 | ... AL32: =$B$31*1 -> 0
A33: Previsión variable soporte (10% del total) | B33: 0 | W33: =$B$31*1 -> 0 | X33: =$B$31*1 -> 0 | Y33: =$B$31*1 -> 0 | Z33: =$B$31*1 -> 0 | AA33: =$B$31*1 -> 0 | AB33: =$B$31*1 -> 0 | AC33: =$B$31*1 -> 0 | AD33: =$B$31*1 -> 0 | ... AL33: =$B$31*1 -> 0
A34: Total | B34: =SUM(B3:B33) -> 0 | C34: =SUM(C3:C32) -> 0 | D34: =SUM(D3:D32) -> 0 | E34: =SUM(E3:E32) -> 0 | F34: =SUM(F3:F32) -> 0 | G34: =SUM(G3:G32) -> 0 | H34: =SUM(H3:H32) -> 0 | I34: =SUM(I3:I32) -> 0 | J34: =SUM(J3:J32) -> 0 | ... V34: =SUM(V3:V32) -> 0 | W34: =SUM(W3:W33) -> 0 | X34: =SUM(X3:X33) -> 0 | Y34: =SUM(Y3:Y33) -> 0 | Z34: =SUM(Z3:Z33) -> 0 | AA34: =SUM(AA3:AA33) -> 0 | AB34: =SUM(AB3:AB33) -> 0 | AC34: =SUM(AC3:AC33) -> 0 | AD34: =SUM(AD3:AD33) -> 0 | ... AL34: =SUM(AL3:AL33) -> 0
U35: Total | V35: =SUM(B34:V34) -> 0 | AK35: Total | AL35: =SUM(W34:AL34) -> 0
U36: Total previsión variable | V36: =SUM(G33:V33) -> 0 | AK36: Total previsión variable | AL36: =SUM(W33:AL33) -> 0
U37: Total s/variable | V37: =V35-V36 -> 0 | AK37: Total s/variable | AL37: =AL35-AL36 -> 0
A38: Costos de Capacitaciones
B39: Encargado | C39: Mes 1 | D39: Mes 2 | E39: Mes 3 | F39: Mes 4 | G39: Mes 5 | H39: Mes 6 | I39: Mes 7 | J39: Mes 8 | K39: Mes 9 | L39: Mes 10 | M39: Mes 11 | N39: Mes 12 | O39: Mes 13 | P39: Mes 14 | Q39: Mes 15 | R39: Mes 16 | S39: Mes 17 | T39: Mes 18 | U39: Mes 19 | V39: Mes 20
B40: ='COSTOS DE OPERACION'!B40 -> Líder de Implantación / Cambio | K40: =B$23 -> 0
B41: ='COSTOS DE OPERACION'!B41 -> Instructor de Capacitación | K41: =B$24*1 -> 0 | R41: =B$24*0.25 -> 0
B42: ='COSTOS DE OPERACION'!B42 -> Líder Funcional | K42: =B$7 -> 0
B43: ='COSTOS DE OPERACION'!B43 -> Documentador | K43: =B$22*2 -> 0 | L43: =B$22*2 -> 0
B44: Total UF | C44: =SUM(C40:C43) -> 0 | D44: =SUM(D40:D43) -> 0 | E44: =SUM(E40:E43) -> 0 | F44: =SUM(F40:F43) -> 0 | G44: =SUM(G40:G43) -> 0 | H44: =SUM(H40:H43) -> 0 | I44: =SUM(I40:I43) -> 0 | J44: =SUM(J40:J43) -> 0 | ... V44: =SUM(V40:V43) -> 0
U45: Total Año | V45: =SUM(C44:V44) -> 0
A47: Porcentaje adquisiciones y servicios | B47: 0.4

Sheet FLUJO DE CAJA COMPLETO
A1: Flujo de caja completo Mensual
A3: Mes | B3: 0 | C3: 1 | D3: 2 | E3: 3 | F3: 4 | G3: 5 | H3: 6 | I3: 7 | J3: 8 | K3: 9 | L3: 10 | M3: 11 | N3: 12 | O3: 13 | P3: 14 | Q3: 15 | R3: 16 | S3: 17 | T3: 18 | U3: 19 | V3: 20 | W3: 21 | X3: 22 | Y3: 23 | Z3: 24 | AA3: 25 | AB3: 26 | AC3: 27 | AD3: 28 | AE3: 29 | AF3: 30 | AG3: 31 | AH3: 32 | AI3: 33 | AJ3: 34 | AK3: 35 | AL3: =AK3+1 -> 36
A4: Fecha | C4: 45292 | D4: 45323 | E4: 45352 | F4: 45383 | G4: 45413 | H4: 45444 | I4: 45474 | J4: 45505 | K4: 45536 | L4: 45566 | M4: 45597 | N4: 45627 | O4: 45658 | P4: 45689 | Q4: 45717 | R4: 45748 | S4: 45778 | T4: 45809 | U4: 45839 | V4: 45870 | W4: 45901 | X4: 45931 | Y4: 45962 | Z4: 45992 | AA4: 46023 | AB4: 46054 | AC4: 46082 | AD4: 46113 | AE4: 46143 | AF4: 46174 | AG4: 46204 | AH4: 46235 | AI4: 46266 | AJ4: 46296 | AK4: 46327 | AL4: =AK4+31 -> 46358
A5: Ingresos (UF) | B5: ='FLUJO DE CAJA NETO'!B13 -> 0 | C5: ='FLUJO DE CAJA NETO'!C13 -> 0 | D5: ='FLUJO DE CAJA NETO'!D13 -> 0 | E5: ='FLUJO DE CAJA NETO'!E13 -> 0 | F5: ='FLUJO DE CAJA NETO'!F13 -> 0 | G5: ='FLUJO DE CAJA NETO'!G13 -> 0 | H5: ='FLUJO DE CAJA NETO'!H13 -> 0 | I5: ='FLUJO DE CAJA NETO'!I13 -> 0 | ... N5: ='FLUJO DE CAJA NETO'!N13 -> 0 | O5: ='FLUJO DE CAJA NETO'!O13+'TARIFAS DE OPERACION'!O34 -> 0 | P5: ='FLUJO DE CAJA NETO'!P13 -> 0 | Q5: ='FLUJO DE CAJA NETO'!Q13 -> 0 | R5: ='FLUJO DE CAJA NETO'!R13 -> 0 | S5: ='FLUJO DE CAJA NETO'!S13 -> 0 | T5: ='FLUJO DE CAJA NETO'!T13 -> 0 | U5: ='FLUJO DE CAJA NETO'!U13 -> 0 | V5: ='FLUJO DE CAJA NETO'!V13 -> 0 | W5: ='FLUJO DE CAJA NETO'!W13 -> 0 | ... AL5: ='FLUJO DE CAJA NETO'!AL13 -> 0
A6: Sueldos (UF) | C6: =-'COSTOS DE OPERACION'!C$34 -> 0 | D6: =-'COSTOS DE OPERACION'!D$34 -> 0 | E6: =-'COSTOS DE OPERACION'!E$34 -> 0 | F6: =-'COSTOS DE OPERACION'!F$34 -> 0 | G6: =-'COSTOS DE OPERACION'!G$34 -> 0 | H6: =-'COSTOS DE OPERACION'!H34 -> 0 | I6: =-'COSTOS DE OPERACION'!I34 -> 0 | J6: =-'COSTOS DE OPERACION'!J34 -> 0 | K6: =-'COSTOS DE OPERACION'!K34 -> 0 | L6: =-'COSTOS DE OPERACION'!L34 -> 0 | M6: =-'COSTOS DE OPERACION'!M34 -> 0 | N6: =-'COSTOS DE OPERACION'!N34 -> 0 | O6: =-'COSTOS DE OPERACION'!O34 -> 0 | ... AL6: =-'COSTOS DE OPERACION'!AL34 -> 0
A7: Pago Adquisiciones (UF) | C7: ='FLUJO DE CAJA NETO'!C33 -> 0 | D7: ='FLUJO DE CAJA NETO'!D33 -> 0 | E7: ='FLUJO DE CAJA NETO'!E33 -> 0 | F7: ='FLUJO DE CAJA NETO'!F33 -> 0 | G7: ='FLUJO DE CAJA NETO'!G33 -> 0 | H7: ='FLUJO DE CAJA NETO'!H33 -> 0 | I7: ='FLUJO DE CAJA NETO'!I33 -> 0 | J7: ='FLUJO DE CAJA NETO'!J33 -> 0 | ... AL7: ='FLUJO DE CAJA NETO'!AL33 -> 0
A8: Pago Servicios Proovedores (UF) | C8: =SUM('FLUJO DE CAJA NETO'!C35) -> 0 | D8: =SUM('FLUJO DE CAJA NETO'!D35) -> 0 | E8: =SUM('FLUJO DE CAJA NETO'!E35) -> 0 | F8: =SUM('FLUJO DE CAJA NETO'!F35) -> 0 | G8: =SUM('FLUJO DE CAJA NETO'!G35) -> 0 | H8: =SUM('FLUJO DE CAJA NETO'!H35) -> 0 | I8: =SUM('FLUJO DE CAJA NETO'!I35) -> 0 | J8: =SUM('FLUJO DE CAJA NETO'!J35) -> 0 | ... AL8: =SUM('FLUJO DE CAJA NETO'!AL35) -> 0
A9: Pago Cuota Prestamo | C9: =-FINANCIAMIENTO!$C$20 -> 0 | D9: =-FINANCIAMIENTO!$C$20 -> 0 | E9: =-FINANCIAMIENTO!$C$20 -> 0 | F9: =-FINANCIAMIENTO!$C$20 -> 0 | G9: =-FINANCIAMIENTO!$C$20 -> 0 | H9: =-FINANCIAMIENTO!$C$20 -> 0 | I9: =-FINANCIAMIENTO!$C$20 -> 0 | J9: =-FINANCIAMIENTO!$C$20 -> 0 | ... N9: =-FINANCIAMIENTO!$C$20 -> 0
A10: Depreciación | S10: =-'ADQUISICIONES IMPLEMENTACIÓN'!M8 -> 0 | AE10: =-'ADQUISICIONES OPERACIÓN'!M8 -> 0
A11: Total Sin Impuestos | C11: =SUM(C5:C10) -> 0 | D11: =SUM(D5:D10) -> 0 | E11: =SUM(E5:E10) -> 0 | F11: =SUM(F5:F10) -> 0 | G11: =SUM(G5:G10) -> 0 | H11: =SUM(H5:H10) -> 0 | I11: =SUM(I5:I10) -> 0 | J11: =SUM(J5:J10) -> 0 | ... AL11: =SUM(AL5:AL10) -> 0
A12: Impuestos 27% | C12: =C11*-27% -> 0 | D12: =D11*-27% -> 0 | E12: =E11*-27% -> 0 | F12: =F11*-27% -> 0 | G12: =G11*-27% -> 0 | H12: =H11*-27% -> 0 | I12: =I11*-27% -> 0 | J12: =J11*-27% -> 0 | ... AL12: =AL11*-27% -> 0
A13: Total Con Impuestos | C13: =SUM(C11:C12) -> 0 | D13: =SUM(D11:D12) -> 0 | E13: =SUM(E11:E12) -> 0 | F13: =SUM(F11:F12) -> 0 | G13: =SUM(G11:G12) -> 0 | H13: =SUM(H11:H12) -> 0 | I13: =SUM(I11:I12) -> 0 | J13: =SUM(J11:J12) -> 0 | ... AL13: =SUM(AL11:AL12) -> 0
A14: Capital de Trabajo | B14: =-RESUMEN!$B$8*PARÁMETROS!B19 -> 0 | AL14: =RESUMEN!B8*0.2+(-B14) -> 0
A15: Depreciación | C15: =-C10 -> 0 | D15: =-D10 -> 0 | E15: =-E10 -> 0 | F15: =-F10 -> 0 | G15: =-G10 -> 0 | H15: =-H10 -> 0 | I15: =-I10 -> 0 | J15: =-J10 -> 0 | ... AL15: =-AL10 -> 0
A16: Flujo Neto Proyecto Puro | B16: =SUM(B5:B14) -> 0 | C16: =SUM(C13:C15) -> 0 | D16: =SUM(D13:D15) -> 0 | E16: =SUM(E13:E15) -> 0 | F16: =SUM(F13:F15) -> 0 | G16: =SUM(G13:G15) -> 0 | H16: =SUM(H13:H15) -> 0 | I16: =SUM(I13:I15) -> 0 | J16: =SUM(J13:J15) -> 0 | ... AL16: =SUM(AL13:AL15) -> 0
A17: Tasa de inversionista mensual | C17: =PARÁMETROS!$B$18 -> 0.0015860903 | D17: =PARÁMETROS!$B$18 -> 0.0015860903 | E17: =PARÁMETROS!$B$18 -> 0.0015860903 | F17: =PARÁMETROS!$B$18 -> 0.0015860903 | G17: =PARÁMETROS!$B$18 -> 0.0015860903 | H17: =PARÁMETROS!$B$18 -> 0.0015860903 | I17: =PARÁMETROS!$B$18 -> 0.0015860903 | J17: =PARÁMETROS!$B$18 -> 0.0015860903 | ... AL17: =PARÁMETROS!$B$18 -> 0.0015860903
A18: Factor de ajuste | C18: =1+C17 -> 1.0015861 | D18: =1+D17 -> 1.0015861 | E18: =1+E17 -> 1.0015861 | F18: =1+F17 -> 1.0015861 | G18: =1+G17 -> 1.0015861 | H18: =1+H17 -> 1.0015861 | I18: =1+I17 -> 1.0015861 | J18: =1+J17 -> 1.0015861 | ... AL18: =1+AL17 -> 1.0015861
A19: Factor acumulado | C19: =C18 -> 1.0015861 | D19: =C19*D18 -> 1.0031747 | E19: =D19*E18 -> 1.0047658 | F19: =E19*F18 -> 1.0063595 | G19: =F19*G18 -> 1.0079556 | H19: =G19*H18 -> 1.0095544 | I19: =H19*I18 -> 1.0111556 | J19: =I19*J18 -> 1.0127594 | K19: =J19*K18 -> 1.0143657 | ... AL19: =AK19*AL18 -> 1.058713
A20: Flujo Neto Actualizado | B20: =B16 -> 0 | C20: =C16/C19 -> 0 | D20: =D16/D19 -> 0 | E20: =E16/E19 -> 0 | F20: =F16/F19 -> 0 | G20: =G16/G19 -> 0 | H20: =H16/H19 -> 0 | I20: =I16/I19 -> 0 | J20: =J16/J19 -> 0 | ... AL20: =AL16/AL19 -> 0
A21: VAN Acumulado | B21: =B16 -> 0 | C21: =C20+B21 -> 0 | D21: =D20+C21 -> 0 | E21: =E20+D21 -> 0 | F21: =F20+E21 -> 0 | G21: =G20+F21 -> 0 | H21: =H20+G21 -> 0 | I21: =I20+H21 -> 0 | J21: =J20+I21 -> 0 | ... AL21: =AL20+AK21 -> 0
A23: VAN Proyecto Puro | B23: =AL21 -> 0
A24: VAN Financiamiento | B24: =FINANCIAMIENTO!B14 -> 0
A25: VAN Proyecto Financiado | B25: =SUM(B23:B24,1) -> 1
A26: TIR | B26: =IRR(C16:AL16) -> #NUM!
A28: Flujo de caja completo Anual
A30: Año | B30: 0 | C30: 1 | D30: 2 | E30: 3 | H30: AÑO 1 | I30: AÑO 2 | J30: AÑO 3
A31: A.1 INGRESOS (UF) | C31: =SUM(C5:N5) -> 0 | D31: =SUM(O5:Z5) -> 0 | E31: =SUM(AA5:AL5) -> 0 | G31: MONTO | H31: =B50 -> 0 | I31: =H31-H34 -> 0 | J31: =I31-I34 -> 0
A32: SUELDOS (UF) | C32: =SUM(C6:N6) -> 0 | D32: =SUM(O6:Z6) -> 0 | E32: =SUM(AA6:AL6) -> 0 | G32: CUOTA | H32: =-PMT($B$48,$B$49,$H$31) -> 0 | I32: =-PMT($B$48,$B$49,$H$31) -> 0 | J32: =-PMT($B$48,$B$49,$H$31) -> 0
A33: PAGO ADQUISICIONES (UF) | C33: =SUM(C7:N7) -> 0 | D33: =SUM(O7:Z7) -> 0 | E33: =SUM(AA7:AL7) -> 0 | G33: INTERES | H33: =H31*$B$48 -> 0 | I33: =I31*$B$48 -> 0 | J33: =J31*$B$48 -> 0
A34: PAGO SERVICIOS PROVEEDORES (UF) | C34: =SUM(C8:N8) -> 0 | D34: =SUM(O8:Z8) -> 0 | E34: =SUM(AA8:AL8) -> 0 | G34: AMORTIZACION | H34: =H32-H33 -> 0 | I34: =I32-I33 -> 0 | J34: =J32-J33 -> 0
A35: DEPRECIACION | C35: =SUM(N10:Y10) -> 0 | D35: =SUM(O10:Z10) -> 0 | E35: =SUM(AA10:AL10) -> 0
A36: TOTAL SIN IMPUESTOS | C36: =SUM(C31:C35) -> 0 | D36: =SUM(D31:D35) -> 0 | E36: =SUM(E31:E35) -> 0 | G36: INTERES | H36: =-H33 -> 0 | I36: =-I33 -> 0 | J36: =-J33 -> 0
A37: IMPUESTOS 27% | C37: =-C36*0.27 -> 0 | D37: =-D36*0.27 -> 0 | E37: =-E36*0.27 -> 0 | G37: IMPUESTOS | H37: =H36*-0.27 -> 0 | I37: =I36*-0.27 -> 0 | J37: =J36*-0.27 -> 0
A38: TOTAL CON IMPUESTOS | C38: =C36+C37 -> 0 | D38: =D36+D37 -> 0 | E38: =E36+E37 -> 0 | G38: AMORTIZACION | H38: =-H34 -> 0 | I38: =-I34 -> 0 | J38: =-J34 -> 0
A39: CAPITAL DE TRABAJO | B39: =$B$16 -> 0 | E39: =-$B$16 -> 0 | G39: FLUJO | H39: =SUM(H36:H38) -> 0 | I39: =SUM(I36:I38) -> 0 | J39: =SUM(J36:J38) -> 0
A40: DEPRECIACION | C40: =SUM(C15:N15) -> 0 | D40: =SUM(O15:Z15) -> 0 | E40: =SUM(AA15:AK15) -> 0
A41: FLUJO NETO PROYECTO PURO | B41: =SUM(B39:B40) -> 0 | C41: =SUM(C38:C40) -> 0 | D41: =SUM(D38:D40) -> 0 | E41: =SUM(E38:E40) -> 0
A42: TASA DE INVERSIONISTA ANUAL | C42: =$B$48 -> 0.0192 | D42: =$B$48 -> 0.0192 | E42: =$B$48 -> 0.0192
A43: FACTOR DE AJUSTE | C43: =C42+1 -> 1.0192 | D43: =D42+1 -> 1.0192 | E43: =E42+1 -> 1.0192
A44: FACTOR ACUMULADO | C44: =C43 -> 1.0192 | D44: =C44*D43 -> 1.0387686 | E44: =D44*E43 -> 1.058713
A45: FLUJO NETO ACTUALIZADO | C45: =C41/C44 -> 0 | D45: =D41/D44 -> 0 | E45: =E41/E44 -> 0
A46: VAN ACUMULADO | B46: =B21 -> 0 | C46: =B46+C45 -> 0 | D46: =C46+D45 -> 0 | E46: =D46+E45 -> 0
A48: TASA INTERES ANUAL | B48: =PARÁMETROS!B17 -> 0.0192
A49: CUOTAS | B49: =MAX(B30:E30) -> 3
A50: MONTO (UF) | B50: =RESUMEN!B8*0.7 -> 0
A52: VAN PROYECTO PURO | B52: =E46 -> 0
A53: VAN FINANCIAMIENTO | B53: {=NPV(B48,H39:J39)+B50} -> 0
A54: VAN PROYECTO FINANCIADO | B54: =SUM(B52:B53) -> 0

Sheet FLUJO DE CAJA NETO
C1: Implementacion | W1: Operación
A2: Mes | B2: 0 | C2: 1 | D2: 2 | E2: 3 | F2: 4 | G2: 5 | H2: 6 | I2: 7 | J2: 8 | K2: 9 | L2: 10 | M2: 11 | N2: 12 | O2: 13 | P2: 14 | Q2: 15 | R2: 16 | S2: 17 | T2: 18 | U2: 19 | V2: 20 | W2: 21 | X2: 22 | Y2: 23 | Z2: 24 | AA2: 25 | AB2: 26 | AC2: 27 | AD2: 28 | AE2: 29 | AF2: 30 | AG2: 31 | AH2: 32 | AI2: 33 | AJ2: 34 | AK2: 35 | AL2: =AK2+1 -> 36
A3: Fecha | C3: 46023 | D3: 46054 | E3: 46082 | F3: 46113 | G3: 46143 | H3: 46174 | I3: 46204 | J3: 46235 | K3: 46266 | L3: 46296 | M3: 46327 | N3: 46357 | O3: 46388 | P3: 46419 | Q3: 46447 | R3: 46478 | S3: 46508 | T3: 46539 | U3: 46569 | V3: 46600 | W3: 46631 | X3: 46661 | Y3: 46692 | Z3: 46722 | AA3: 46753 | AB3: 46784 | AC3: 46813 | AD3: 46844 | AE3: 46874 | AF3: 46905 | AG3: 46935 | AH3: 46966 | AI3: 46997 | AJ3: 47027 | AK3: 47058 | AL3: 47088
A5: Flujo de Caja
A7: Flujo mes | B7: =B13-B27 -> 0 | C7: =C13-C27 -> 0 | D7: =D13-D27 -> 0 | E7: =E13-E27 -> 0 | F7: =F13-F27 -> 0 | G7: =G13-G27 -> 0 | H7: =H13-H27 -> 0 | I7: =I13-I27 -> 0 | ... AL7: =AL13-AL27 -> 0
A8: Flujo acumulado | B8: =B7 -> 0 | C8: =B8+C7 -> 0 | D8: =C8+D7 -> 0 | E8: =D8+E7 -> 0 | F8: =E8+F7 -> 0 | G8: =F8+G7 -> 0 | H8: =G8+H7 -> 0 | I8: =H8+I7 -> 0 | J8: =I8+J7 -> 0 | ... AL8: =AK8+AL7 -> 0
A10: Detalle
A13: Ingresos mes | B13: =SUM(B16:B23) -> 0 | C13: =SUM(C16:C23) -> 0 | D13: =SUM(D16:D23) -> 0 | E13: =SUM(E16:E23) -> 0 | F13: =SUM(F16:F23) -> 0 | G13: =SUM(G16:G23) -> 0 | H13: =SUM(H16:H23) -> 0 | I13: =SUM(I16:I23) -> 0 | ... AL13: =SUM(AL16:AL23) -> 0
A14: Ingresos acumulados | B14: =B13 -> 0 | C14: =C13+B14 -> 0 | D14: =D13+C14 -> 0 | E14: =E13+D14 -> 0 | F14: =F13+E14 -> 0 | G14: =G13+F14 -> 0 | H14: =H13+G14 -> 0 | I14: =I13+H14 -> 0 | J14: =J13+I14 -> 0 | ... AL14: =AL13+AK14 -> 0
A16: Hito 1: Levantamiento de Requerimientos | E16: =RESUMEN!$G$6*0.1 -> 0
A17: Hito 2: Entrega de Software y Data Center para pruebas | J17: =RESUMEN!$G$6*0.2 -> 0
A18: Hito 3: Certificacion de solución aprobado | L18: =RESUMEN!$G$6*0.2 -> 0
A19: Hito 4: Paso a producción | N19: =RESUMEN!$G$6*0.1 -> 0
A20: Hito 5: Entrega de software para pruebas (Etapa 2) | R20: =RESUMEN!$G$6*0.2 -> 0
A21: Hito 6: Paso a producción (Etapa 2) | V21: =RESUMEN!$G$6*0.2 -> 0
A22: Pago Mensual | W22: =RESUMEN!$G$7/16 -> 0 | X22: =RESUMEN!$G$7/16 -> 0 | Y22: =RESUMEN!$G$7/16 -> 0 | Z22: =RESUMEN!$G$7/16 -> 0 | AA22: =RESUMEN!$G$7/16 -> 0 | AB22: =RESUMEN!$G$7/16 -> 0 | AC22: =RESUMEN!$G$7/16 -> 0 | AD22: =RESUMEN!$G$7/16 -> 0 | ... AL22: =RESUMEN!$G$7/16 -> 0
A23: Credito Banco | B23: =RESUMEN!$B$8*PARÁMETROS!B20 -> 0
A25: Egresos
A27: Egresos mes | B27: =-SUM(B31:B35) -> 0 | C27: =-SUM(C31:C35) -> 0 | D27: =-SUM(D31:D35) -> 0 | E27: =-SUM(E31:E35) -> 0 | F27: =-SUM(F31:F35) -> 0 | G27: =-SUM(G31:G35) -> 0 | H27: =-SUM(H31:H35) -> 0 | I27: =-SUM(I31:I35) -> 0 | ... AL27: =-SUM(AL31:AL35) -> 0
A28: Egresos Acumulado | B28: =B27 -> 0 | C28: =C27+B28 -> 0 | D28: =D27+C28 -> 0 | E28: =E27+D28 -> 0 | F28: =F27+E28 -> 0 | G28: =G27+F28 -> 0 | H28: =H27+G28 -> 0 | I28: =I27+H28 -> 0 | J28: =J27+I28 -> 0 | ... AL28: =AL27+AK28 -> 0
A31: Inversión | B31: ='FLUJO DE CAJA COMPLETO'!B14 -> 0 | C31: ='FLUJO DE CAJA COMPLETO'!C9 -> 0 | D31: ='FLUJO DE CAJA COMPLETO'!D9 -> 0 | E31: ='FLUJO DE CAJA COMPLETO'!E9 -> 0 | F31: ='FLUJO DE CAJA COMPLETO'!F9 -> 0 | G31: ='FLUJO DE CAJA COMPLETO'!G9 -> 0 | H31: ='FLUJO DE CAJA COMPLETO'!H9 -> 0 | I31: ='FLUJO DE CAJA COMPLETO'!I9 -> 0 | J31: ='FLUJO DE CAJA COMPLETO'!J9 -> 0 | ... AL31: ='FLUJO DE CAJA COMPLETO'!AL9 -> 0
A32: Sueldos | C32: =-'COSTOS DE OPERACION'!C34 -> 0 | D32: =-'COSTOS DE OPERACION'!D34 -> 0 | E32: =-'COSTOS DE OPERACION'!E34 -> 0 | F32: =-'COSTOS DE OPERACION'!F34 -> 0 | G32: =-'COSTOS DE OPERACION'!G34 -> 0 | H32: =-'COSTOS DE OPERACION'!H34 -> 0 | I32: =-'COSTOS DE OPERACION'!I34 -> 0 | J32: =-'COSTOS DE OPERACION'!J34 -> 0 | ... AL32: =-'COSTOS DE OPERACION'!AL34 -> 0
A33: Adquisiciones | F33: =-'ADQUISICIONES IMPLEMENTACIÓN'!B70 -> 0 | W33: =-'ADQUISICIONES OPERACIÓN'!B48 -> 0
A34: Capacitaciones
A35: Servicios | L35: =-'ADQUISICIONES IMPLEMENTACIÓN'!C71 -> 0 | M35: =-'ADQUISICIONES IMPLEMENTACIÓN'!C71 -> 0 | N35: =-'ADQUISICIONES IMPLEMENTACIÓN'!C71 -> 0 | O35: =-'ADQUISICIONES IMPLEMENTACIÓN'!C71 -> 0 | P35: =-'ADQUISICIONES IMPLEMENTACIÓN'!C71 -> 0 | Q35: =-'ADQUISICIONES IMPLEMENTACIÓN'!C71 -> 0 | R35: =-'ADQUISICIONES IMPLEMENTACIÓN'!C71 -> 0 | S35: =-'ADQUISICIONES IMPLEMENTACIÓN'!C71 -> 0 | T35: =-'ADQUISICIONES IMPLEMENTACIÓN'!C71 -> 0 | U35: =-'ADQUISICIONES IMPLEMENTACIÓN'!C71 -> 0 | V35: =-'ADQUISICIONES IMPLEMENTACIÓN'!C71 -> 0 | W35: =-'ADQUISICIONES OPERACIÓN'!C49 -> 0 | X35: =-'ADQUISICIONES OPERACIÓN'!C49 -> 0 | Y35: =-'ADQUISICIONES OPERACIÓN'!C49 -> 0 | Z35: =-'ADQUISICIONES OPERACIÓN'!C49 -> 0 | AA35: =-'ADQUISICIONES OPERACIÓN'!C49 -> 0 | AB35: =-'ADQUISICIONES OPERACIÓN'!C49 -> 0 | AC35: =-'ADQUISICIONES OPERACIÓN'!C49 -> 0 | AD35: =-'ADQUISICIONES OPERACIÓN'!C49 -> 0 | AE35: =-'ADQUISICIONES OPERACIÓN'!C49 -> 0 | AF35: =-'ADQUISICIONES OPERACIÓN'!C49 -> 0 | AG35: =-'ADQUISICIONES OPERACIÓN'!C49 -> 0 | AH35: =-'ADQUISICIONES OPERACIÓN'!C49 -> 0 | AI35: =-'ADQUISICIONES OPERACIÓN'!C49 -> 0 | AJ35: =-'ADQUISICIONES OPERACIÓN'!C49 -> 0 | AK35: =-'ADQUISICIONES OPERACIÓN'!C49 -> 0 | AL35: =-'ADQUISICIONES OPERACIÓN'!C49 -> 0

Sheet FINANCIAMIENTO
A1: CONVERSIONES | B1: CLP
A2: Dólar | B2: ='Costos HH - Sueldos'!B4 -> 900 | C2: =+B2/B4 -> 0.0225
A3: Euro | B3: ='Costos HH - Sueldos'!B5 -> 1000 | C3: =+B3/B4 -> 0.025 | F3: UF | G3: USD | H3: CLP
A4: UF | B4: ='Costos HH - Sueldos'!B6 -> 40000 | C4: =+B4/B2 -> 44.444444 | E4: Monto Crédito | F4: =RESUMEN!B8*PARÁMETROS!B20 -> 0 | G4: =H4/('Costos HH - Sueldos'!B4) -> 0 | H4: =F4*('Costos HH - Sueldos'!B6) -> 0
A5: HH Mes | B5: 160 | C5: horas
A7: DATOS | E7: HITOS DE PAGO | F7: Fecha | G7: Pago | H7: IVA | I7: Total + IVA | K7: Pago en CLP | L7: Pago en USD
A8: Porcentaje de financiamiento propio | B8: =PARÁMETROS!B19 -> 0.2 | E8: Hito 1: Levantamiento de Requerimientos | F8: 46108 | G8: ='FLUJO DE CAJA NETO'!E16 -> 0 | H8: =G8*0.19 -> 0 | I8: =G8+H8 -> 0 | K8: =$G8*$B$4 -> 0 | L8: =$G8*$C$4 -> 0
A9: Porcentaje de financiamiento banco | B9: =PARÁMETROS!B20 -> 0.8 | E9: Hito 2: Entrega de Software y Data Center para pruebas | F9: 46265 | G9: ='FLUJO DE CAJA NETO'!J17 -> 0 | H9: =G9*0.19 -> 0 | I9: =G9+H9 -> 0 | K9: =$G9*$B$4 -> 0 | L9: =$G9*$C$4 -> 0
A10: Tasa Interes de Prestamo (Mensual) | B10: =PARÁMETROS!B13 -> 0.009 | E10: Hito 3: Certificacion de solución aprobado | F10: 46297 | G10: ='FLUJO DE CAJA NETO'!L18 -> 0 | H10: =G10*0.19 -> 0 | I10: =G10+H10 -> 0 | K10: =$G10*$B$4 -> 0 | L10: =$G10*$C$4 -> 0
A11: Tasa Interes de LC (Mensual) | B11: =PARÁMETROS!B15 -> 0.03 | E11: Hito 4: Paso a producción | F11: 46374 | G11: ='FLUJO DE CAJA NETO'!N19 -> 0 | H11: =G11*0.19 -> 0 | I11: =G11+H11 -> 0 | K11: =$G11*$B$4 -> 0 | L11: =$G11*$C$4 -> 0
A12: Impuestos | B12: =PARÁMETROS!$B$16 -> 0.27 | E12: Hito 5: Entrega de software para pruebas (Etapa 2) | F12: 46489 | G12: ='FLUJO DE CAJA NETO'!R20 -> 0 | H12: =G12*0.19 -> 0 | I12: =G12+H12 -> 0 | K12: =$G12*$B$4 -> 0 | L12: =$G12*$C$4 -> 0
A13: Cuotas | B13: 24 | E13: Hito 6: Paso a producción (Etapa 2) | F13: 46612 | G13: ='FLUJO DE CAJA NETO'!V21 -> 0 | H13: =G13*0.19 -> 0 | I13: =G13+H13 -> 0 | K13: =$G13*$B$4 -> 0 | L13: =$G13*$C$4 -> 0
A14: VAN Financiamiento | B14: {=F4+NPV(PARÁMETROS!B15,L20:L31)} -> 0 | E14: Pago Mensual | F14: DESDE sept 2027 | G14: ='FLUJO DE CAJA NETO'!W22 -> 0 | H14: =G14*0.19 -> 0 | I14: =G14+H14 -> 0 | K14: =$G14*$B$4 -> 0 | L14: =$G14*$C$4 -> 0
E15: Credito Banco | G15: ='FLUJO DE CAJA NETO'!B23 -> 0 | K15: =$G15*$B$4 -> 0 | L15: =$G15*$C$4 -> 0
A18: Tabla Amortizacion del Credito | G18: Flujo de Financiamiento
A19: Mes | B19: Saldo | C19: Cuota | D19: Interés Mensual | E19: Amortización | G19: Mes | H19: Interés Mensual | I19: Ahorro Tributario | J19: Con impuestos | K19: Amortización | L19: Flujo Neto Financiamiento
A20: 1 | B20: =F4 -> 0 | C20: =-PMT((PARÁMETROS!$B$13),$B$13,$B$20) -> 0 | D20: =(PARÁMETROS!$B$13)*B20 -> 0 | E20: =C20-D20 -> 0 | G20: 1 | H20: =-D20 -> 0 | I20: =-(PARÁMETROS!$B$16)*H20 -> 0 | J20: =H20+I20 -> 0 | K20: =-E20 -> 0 | L20: =K20+J20 -> 0
A21: 2 | B21: =B20-E20 -> 0 | C21: =-PMT((PARÁMETROS!$B$13),$B$13,$B$20) -> 0 | D21: =(PARÁMETROS!$B$13)*B21 -> 0 | E21: =C21-D21 -> 0 | G21: 2 | H21: =-D21 -> 0 | I21: =-(PARÁMETROS!$B$16)*H21 -> 0 | J21: =H21+I21 -> 0 | K21: =-E21 -> 0 | L21: =K21+J21 -> 0
A22: 3 | B22: =B21-E21 -> 0 | C22: =-PMT((PARÁMETROS!$B$13),$B$13,$B$20) -> 0 | D22: =(PARÁMETROS!$B$13)*B22 -> 0 | E22: =C22-D22 -> 0 | G22: 3 | H22: =-D22 -> 0 | I22: =-(PARÁMETROS!$B$16)*H22 -> 0 | J22: =H22+I22 -> 0 | K22: =-E22 -> 0 | L22: =K22+J22 -> 0
A23: 4 | B23: =B22-E22 -> 0 | C23: =-PMT((PARÁMETROS!$B$13),$B$13,$B$20) -> 0 | D23: =(PARÁMETROS!$B$13)*B23 -> 0 | E23: =C23-D23 -> 0 | G23: 4 | H23: =-D23 -> 0 | I23: =-(PARÁMETROS!$B$16)*H23 -> 0 | J23: =H23+I23 -> 0 | K23: =-E23 -> 0 | L23: =K23+J23 -> 0
A24: 5 | B24: =B23-E23 -> 0 | C24: =-PMT((PARÁMETROS!$B$13),$B$13,$B$20) -> 0 | D24: =(PARÁMETROS!$B$13)*B24 -> 0 | E24: =C24-D24 -> 0 | G24: 5 | H24: =-D24 -> 0 | I24: =-(PARÁMETROS!$B$16)*H24 -> 0 | J24: =H24+I24 -> 0 | K24: =-E24 -> 0 | L24: =K24+J24 -> 0
A25: 6 | B25: =B24-E24 -> 0 | C25: =-PMT((PARÁMETROS!$B$13),$B$13,$B$20) -> 0 | D25: =(PARÁMETROS!$B$13)*B25 -> 0 | E25: =C25-D25 -> 0 | G25: 6 | H25: =-D25 -> 0 | I25: =-(PARÁMETROS!$B$16)*H25 -> 0 | J25: =H25+I25 -> 0 | K25: =-E25 -> 0 | L25: =K25+J25 -> 0
A26: 7 | B26: =B25-E25 -> 0 | C26: =-PMT((PARÁMETROS!$B$13),$B$13,$B$20) -> 0 | D26: =(PARÁMETROS!$B$13)*B26 -> 0 | E26: =C26-D26 -> 0 | G26: 7 | H26: =-D26 -> 0 | I26: =-(PARÁMETROS!$B$16)*H26 -> 0 | J26: =H26+I26 -> 0 | K26: =-E26 -> 0 | L26: =K26+J26 -> 0
A27: 8 | B27: =B26-E26 -> 0 | C27: =-PMT((PARÁMETROS!$B$13),$B$13,$B$20) -> 0 | D27: =(PARÁMETROS!$B$13)*B27 -> 0 | E27: =C27-D27 -> 0 | G27: 8 | H27: =-D27 -> 0 | I27: =-(PARÁMETROS!$B$16)*H27 -> 0 | J27: =H27+I27 -> 0 | K27: =-E27 -> 0 | L27: =K27+J27 -> 0
A28: 9 | B28: =B27-E27 -> 0 | C28: =-PMT((PARÁMETROS!$B$13),$B$13,$B$20) -> 0 | D28: =(PARÁMETROS!$B$13)*B28 -> 0 | E28: =C28-D28 -> 0 | G28: 9 | H28: =-D28 -> 0 | I28: =-(PARÁMETROS!$B$16)*H28 -> 0 | J28: =H28+I28 -> 0 | K28: =-E28 -> 0 | L28: =K28+J28 -> 0
A29: 10 | B29: =B28-E28 -> 0 | C29: =-PMT((PARÁMETROS!$B$13),$B$13,$B$20) -> 0 | D29: =(PARÁMETROS!$B$13)*B29 -> 0 | E29: =C29-D29 -> 0 | G29: 10 | H29: =-D29 -> 0 | I29: =-(PARÁMETROS!$B$16)*H29 -> 0 | J29: =H29+I29 -> 0 | K29: =-E29 -> 0 | L29: =K29+J29 -> 0
A30: 11 | B30: =B29-E29 -> 0 | C30: =-PMT((PARÁMETROS!$B$13),$B$13,$B$20) -> 0 | D30: =(PARÁMETROS!$B$13)*B30 -> 0 | E30: =C30-D30 -> 0 | G30: 11 | H30: =-D30 -> 0 | I30: =-(PARÁMETROS!$B$16)*H30 -> 0 | J30: =H30+I30 -> 0 | K30: =-E30 -> 0 | L30: =K30+J30 -> 0
A31: =A30+1 -> 12 | B31: =B30-E30 -> 0 | C31: =-PMT((PARÁMETROS!$B$13),$B$13,$B$20) -> 0 | D31: =(PARÁMETROS!$B$13)*B31 -> 0 | E31: =C31-D31 -> 0 | G31: 12 | H31: =-D31 -> 0 | I31: =-(PARÁMETROS!$B$16)*H31 -> 0 | J31: =H31+I31 -> 0 | K31: =-E31 -> 0 | L31: =K31+J31 -> 0
A32: =A31+1 -> 13 | B32: =B31-E31 -> 0 | C32: =-PMT((PARÁMETROS!$B$13),$B$13,$B$20) -> 0 | D32: =(PARÁMETROS!$B$13)*B32 -> 0 | E32: =C32-D32 -> 0 | G32: =G31+1 -> 13 | H32: =-D32 -> 0 | I32: =-(PARÁMETROS!$B$16)*H32 -> 0 | J32: =H32+I32 -> 0 | K32: =-E32 -> 0 | L32: =K32+J32 -> 0
A33: =A32+1 -> 14 | B33: =B32-E32 -> 0 | C33: =-PMT((PARÁMETROS!$B$13),$B$13,$B$20) -> 0 | D33: =(PARÁMETROS!$B$13)*B33 -> 0 | E33: =C33-D33 -> 0 | G33: =G32+1 -> 14 | H33: =-D33 -> 0 | I33: =-(PARÁMETROS!$B$16)*H33 -> 0 | J33: =H33+I33 -> 0 | K33: =-E33 -> 0 | L33: =K33+J33 -> 0
A34: =A33+1 -> 15 | B34: =B33-E33 -> 0 | C34: =-PMT((PARÁMETROS!$B$13),$B$13,$B$20) -> 0 | D34: =(PARÁMETROS!$B$13)*B34 -> 0 | E34: =C34-D34 -> 0 | G34: =G33+1 -> 15 | H34: =-D34 -> 0 | I34: =-(PARÁMETROS!$B$16)*H34 -> 0 | J34: =H34+I34 -> 0 | K34: =-E34 -> 0 | L34: =K34+J34 -> 0
A35: =A34+1 -> 16 | B35: =B34-E34 -> 0 | C35: =-PMT((PARÁMETROS!$B$13),$B$13,$B$20) -> 0 | D35: =(PARÁMETROS!$B$13)*B35 -> 0 | E35: =C35-D35 -> 0 | G35: =G34+1 -> 16 | H35: =-D35 -> 0 | I35: =-(PARÁMETROS!$B$16)*H35 -> 0 | J35: =H35+I35 -> 0 | K35: =-E35 -> 0 | L35: =K35+J35 -> 0
A36: =A35+1 -> 17 | B36: =B35-E35 -> 0 | C36: =-PMT((PARÁMETROS!$B$13),$B$13,$B$20) -> 0 | D36: =(PARÁMETROS!$B$13)*B36 -> 0 | E36: =C36-D36 -> 0 | G36: =G35+1 -> 17 | H36: =-D36 -> 0 | I36: =-(PARÁMETROS!$B$16)*H36 -> 0 | J36: =H36+I36 -> 0 | K36: =-E36 -> 0 | L36: =K36+J36 -> 0
A37: =A36+1 -> 18 | B37: =B36-E36 -> 0 | C37: =-PMT((PARÁMETROS!$B$13),$B$13,$B$20) -> 0 | D37: =(PARÁMETROS!$B$13)*B37 -> 0 | E37: =C37-D37 -> 0 | G37: =G36+1 -> 18 | H37: =-D37 -> 0 | I37: =-(PARÁMETROS!$B$16)*H37 -> 0 | J37: =H37+I37 -> 0 | K37: =-E37 -> 0 | L37: =K37+J37 -> 0
A38: =A37+1 -> 19 | B38: =B37-E37 -> 0 | C38: =-PMT((PARÁMETROS!$B$13),$B$13,$B$20) -> 0 | D38: =(PARÁMETROS!$B$13)*B38 -> 0 | E38: =C38-D38 -> 0 | G38: =G37+1 -> 19 | H38: =-D38 -> 0 | I38: =-(PARÁMETROS!$B$16)*H38 -> 0 | J38: =H38+I38 -> 0 | K38: =-E38 -> 0 | L38: =K38+J38 -> 0
A39: =A38+1 -> 20 | B39: =B38-E38 -> 0 | C39: =-PMT((PARÁMETROS!$B$13),$B$13,$B$20) -> 0 | D39: =(PARÁMETROS!$B$13)*B39 -> 0 | E39: =C39-D39 -> 0 | G39: =G38+1 -> 20 | H39: =-D39 -> 0 | I39: =-(PARÁMETROS!$B$16)*H39 -> 0 | J39: =H39+I39 -> 0 | K39: =-E39 -> 0 | L39: =K39+J39 -> 0
A40: =A39+1 -> 21 | B40: =B39-E39 -> 0 | C40: =-PMT((PARÁMETROS!$B$13),$B$13,$B$20) -> 0 | D40: =(PARÁMETROS!$B$13)*B40 -> 0 | E40: =C40-D40 -> 0 | G40: =G39+1 -> 21 | H40: =-D40 -> 0 | I40: =-(PARÁMETROS!$B$16)*H40 -> 0 | J40: =H40+I40 -> 0 | K40: =-E40 -> 0 | L40: =K40+J40 -> 0
A41: =A40+1 -> 22 | B41: =B40-E40 -> 0 | C41: =-PMT((PARÁMETROS!$B$13),$B$13,$B$20) -> 0 | D41: =(PARÁMETROS!$B$13)*B41 -> 0 | E41: =C41-D41 -> 0 | G41: =G40+1 -> 22 | H41: =-D41 -> 0 | I41: =-(PARÁMETROS!$B$16)*H41 -> 0 | J41: =H41+I41 -> 0 | K41: =-E41 -> 0 | L41: =K41+J41 -> 0
A42: =A41+1 -> 23 | B42: =B41-E41 -> 0 | C42: =-PMT((PARÁMETROS!$B$13),$B$13,$B$20) -> 0 | D42: =(PARÁMETROS!$B$13)*B42 -> 0 | E42: =C42-D42 -> 0 | G42: =G41+1 -> 23 | H42: =-D42 -> 0 | I42: =-(PARÁMETROS!$B$16)*H42 -> 0 | J42: =H42+I42 -> 0 | K42: =-E42 -> 0 | L42: =K42+J42 -> 0
A43: =A42+1 -> 24 | B43: =B42-E42 -> 0 | C43: =-PMT((PARÁMETROS!$B$13),$B$13,$B$20) -> 0 | D43: =(PARÁMETROS!$B$13)*B43 -> 0 | E43: =C43-D43 -> 0 | G43: =G42+1 -> 24 | H43: =-D43 -> 0 | I43: =-(PARÁMETROS!$B$16)*H43 -> 0 | J43: =H43+I43 -> 0 | K43: =-E43 -> 0 | L43: =K43+J43 -> 0

Sheet COSTOS DE OPERACION
C1: Costos de Implementación | W1: Costos de soporte | AM1: Totales
B2: Costos Asociados Mensual (UF) | C2: Mes 1 | D2: Mes 2 | E2: Mes 3 | F2: Mes 4 | G2: Mes 5 | H2: Mes 6 | I2: Mes 7 | J2: Mes 8 | K2: Mes 9 | L2: Mes 10 | M2: Mes 11 | N2: Mes 12 | O2: Mes 13 | P2: Mes 14 | Q2: Mes 15 | R2: Mes 16 | S2: Mes 17 | T2: Mes 18 | U2: Mes 19 | V2: Mes 20 | W2: Mes 21 | X2: Mes 22 | Y2: Mes 23 | Z2: Mes 24 | AA2: Mes 25 | AB2: Mes 26 | AC2: Mes 27 | AD2: Mes 28 | AE2: Mes 29 | AF2: Mes 30 | AG2: Mes 31 | AH2: Mes 32 | AI2: Mes 33 | AJ2: Mes 34 | AK2: Mes 35 | AL2: Mes 36 | AM2: Implementación | AN2: Soporte | AO2: Total
A3: ='Costos HH - Sueldos'!$A11 -> Jefe de Proyecto | B3: 0 | C3: =B$3 -> 0 | D3: =B$3*1 -> 0 | E3: =B$3*1 -> 0 | F3: =B$3*1 -> 0 | G3: =B$3*1 -> 0 | H3: =B$3*1 -> 0 | I3: =B$3*1 -> 0 | J3: =B$3*1 -> 0 | K3: =B$3*1 -> 0 | L3: =B$3*1 -> 0 | M3: =B$3*1 -> 0 | N3: =B$3*1 -> 0 | O3: =B$3*1 -> 0 | P3: =B$3*1 -> 0 | Q3: =B$3*1 -> 0 | R3: =B$3*1 -> 0 | S3: =B$3*1 -> 0 | T3: =B$3*1 -> 0 | U3: =B$3*1 -> 0 | V3: =B$3*1 -> 0 | W3: =B$3*1 -> 0 | X3: =C$3*1 -> 0 | Y3: =D$3*1 -> 0 | Z3: =E$3*1 -> 0 | AA3: =F$3*1 -> 0 | AB3: =G$3*1 -> 0 | AC3: =H$3*1 -> 0 | AD3: =I$3*1 -> 0 | ... AL3: =Q$3*1 -> 0 | AM3: =SUM(C3:V3) -> 0 | AN3: =SUM(W3:AL3) -> 0 | AO3: =SUM(AM3,AN3) -> 0
A4: ='Costos HH - Sueldos'!$A12 -> LÃ­der de IntegraciÃ³n | B4: 0 | E4: =B$4 -> 0 | F4: =B$4*1 -> 0 | G4: =B$4*1 -> 0 | H4: =B$4*1 -> 0 | I4: =B$4*1 -> 0 | P4: =B$4 -> 0 | V4: =B$4 -> 0 | AM4: =SUM(C4:V4) -> 0 | AN4: =SUM(W4:AL4) -> 0 | AO4: =SUM(AM4,AN4) -> 0
A5: ='Costos HH - Sueldos'!$A13 -> Arquitecto de SoluciÃ³n | B5: 0 | D5: =B$5*1 -> 0 | E5: =B$5 -> 0 | J5: =B$5 -> 0 | R5: =B$5 -> 0 | S5: =B$5*1 -> 0 | T5: =B$5 -> 0 | AM5: =SUM(C5:V5) -> 0 | AN5: =SUM(W5:AL5) -> 0 | AO5: =SUM(AM5,AN5) -> 0
A6: ='Costos HH - Sueldos'!$A14 -> LÃ­der de Desarrollo | B6: 0 | D6: =B$6 -> 0 | E6: =B$6 -> 0 | F6: =B$6*1 -> 0 | G6: =B$6*1 -> 0 | H6: =B$6 -> 0 | I6: =B$6 -> 0 | K6: =B$6*1 -> 0 | L6: =B$6 -> 0 | N6: =B$6 -> 0 | R6: =B$6 -> 0 | S6: =B$6*1 -> 0 | T6: =B$6*1 -> 0 | U6: =B$6*1 -> 0 | AM6: =SUM(C6:V6) -> 0 | AN6: =SUM(W6:AL6) -> 0 | AO6: =SUM(AM6,AN6) -> 0
A7: ='Costos HH - Sueldos'!$A15 -> LÃ­der Funcional | B7: 0 | C7: =B$7 -> 0 | E7: =B$7 -> 0 | F7: =B$7*1 -> 0 | G7: =B$7*1 -> 0 | H7: =B$7 -> 0 | I7: =B$7*1 -> 0 | J7: =B$7*1 -> 0 | N7: =B$7 -> 0 | O7: =B$7 -> 0 | P7: =B$7 -> 0 | R7: =B$7 -> 0 | V7: =B$7 -> 0 | AM7: =SUM(C7:V7) -> 0 | AN7: =SUM(W7:AL7) -> 0 | AO7: =SUM(AM7,AN7) -> 0
A8: ='Costos HH - Sueldos'!$A16 -> Analista de Requerimientos | B8: 0 | C8: =B$8*4 -> 0 | D8: =B$8*4 -> 0 | E8: =B$8*4 -> 0 | J8: =(B$8*4/20)*3 -> 0 | AM8: =SUM(C8:V8) -> 0 | AN8: =SUM(W8:AL8) -> 0 | AO8: =SUM(AM8,AN8) -> 0
A9: ='Costos HH - Sueldos'!$A17 -> Desarrollador Full Stack | B9: 0 | F9: =B$9*1*8 -> 0 | G9: =B$9*1*8 -> 0 | H9: =B$9*1*8 -> 0 | I9: =B$9*1*8 -> 0 | J9: =B$9*1*8 -> 0 | K9: =B$9*8 -> 0 | L9: =B$9*8*0.5 -> 0 | R9: =B$9*8 -> 0 | S9: =B$9*1*8 -> 0 | T9: =B$9*1*8 -> 0 | U9: =B$9*1*8 -> 0 | AM9: =SUM(C9:V9) -> 0 | AN9: =SUM(W9:AL9) -> 0 | AO9: =SUM(AM9,AN9) -> 0
A10: ='Costos HH - Sueldos'!$A18 -> Desarrollador Front-end | B10: 0 | F10: =B$10*1 -> 0 | G10: =B$10*1 -> 0 | H10: =B$10*1 -> 0 | I10: =B$10*1 -> 0 | J10: =B$10*1 -> 0 | R10: =B$10 -> 0 | S10: =B$10*1 -> 0 | T10: =B$10*1 -> 0 | U10: =B$10*1 -> 0 | AM10: =SUM(C10:V10) -> 0 | AN10: =SUM(W10:AL10) -> 0 | AO10: =SUM(AM10,AN10) -> 0
A11: ='Costos HH - Sueldos'!$A19 -> Desarrollador Back-end | B11: 0 | F11: =B$11*1 -> 0 | G11: =B$11*1 -> 0 | H11: =B$11*1 -> 0 | I11: =B$11*1 -> 0 | J11: =B$11*1 -> 0 | K11: =B$11*1 -> 0 | L11: =B$11*1 -> 0 | R11: =B$11 -> 0 | S11: =B$11*1 -> 0 | T11: =B$11*1 -> 0 | U11: =B$11*1 -> 0 | AM11: =SUM(C11:V11) -> 0 | AN11: =SUM(W11:AL11) -> 0 | AO11: =SUM(AM11,AN11) -> 0
A12: ='Costos HH - Sueldos'!$A20 -> Desarrollador de Base de Datos | B12: 0 | I12: =B$12*1 -> 0 | J12: =B$12*1 -> 0 | K12: =B$12*1 -> 0 | AM12: =SUM(C12:V12) -> 0 | AN12: =SUM(W12:AL12) -> 0 | AO12: =SUM(AM12,AN12) -> 0
A13: ='Costos HH - Sueldos'!$A21 -> Diseñador UX | B13: 0 | D13: =B$13 -> 0 | E13: =(B$13/20)*5 -> 0 | AM13: =SUM(C13:V13) -> 0 | AN13: =SUM(W13:AL13) -> 0 | AO13: =SUM(AM13,AN13) -> 0
A14: ='Costos HH - Sueldos'!$A22 -> Especialista en Integración | B14: 0 | D14: =B$14*3 -> 0 | I14: =B$14*1*3 -> 0 | J14: =B$14*1*3 -> 0 | K14: =B$14*3 -> 0 | L14: =B$14*3 -> 0 | AM14: =SUM(C14:V14) -> 0 | AN14: =SUM(W14:AL14) -> 0 | AO14: =SUM(AM14,AN14) -> 0
A15: ='Costos HH - Sueldos'!$A23 -> Encargado de Seguridad | B15: 0 | F15: =B$15*1 -> 0 | G15: =B$15*1 -> 0 | H15: =B$15 -> 0 | I15: =B$15 -> 0 | P15: =B$15 -> 0 | V15: =B$15 -> 0 | W15: =$B$15*1 -> 0 | X15: =$B$15*1 -> 0 | Y15: =$B$15*1 -> 0 | Z15: =$B$15*1 -> 0 | AA15: =$B$15*1 -> 0 | AB15: =$B$15*1 -> 0 | AC15: =$B$15*1 -> 0 | AD15: =$B$15*1 -> 0 | ... AL15: =$B$15*1 -> 0 | AM15: =SUM(C15:V15) -> 0 | AN15: =SUM(W15:AL15) -> 0 | AO15: =SUM(AM15,AN15) -> 0
A16: ='Costos HH - Sueldos'!$A24 -> Ingeniero DevOps | B16: 0 | E16: =$B$16*2 -> 0 | F16: =$B$16*2 -> 0 | G16: =B$16*1*2 -> 0 | H16: =B$16*1*2 -> 0 | I16: =B$16*1*2 -> 0 | L16: =B$16*2 -> 0 | N16: =B$16*2 -> 0 | O16: =B$16*1*2 -> 0 | P16: =B$16*1*2 -> 0 | Q16: =B$16*1*2 -> 0 | R16: =B$16*2 -> 0 | AM16: =SUM(C16:V16) -> 0 | AN16: =SUM(W16:AL16) -> 0 | AO16: =SUM(AM16,AN16) -> 0
A17: ='Costos HH - Sueldos'!$A25 -> Administrador de Base de Datos | B17: 0 | I17: =B$17*1 -> 0 | J17: =B$17*1 -> 0 | K17: =B$17*1 -> 0 | O17: =B$17*1 -> 0 | AM17: =SUM(C17:V17) -> 0 | AN17: =SUM(W17:AL17) -> 0 | AO17: =SUM(AM17,AN17) -> 0
A18: ='Costos HH - Sueldos'!$A26 -> LÃ­der de Calidad y Pruebas | B18: 0 | C18: =B$18 -> 0 | H18: =B$18*1 -> 0 | I18: =B$18 -> 0 | K18: =$B$18*1 -> 0 | L18: =$B$18*1 -> 0 | M18: =$B$18*1 -> 0 | N18: =$B$18*1 -> 0 | P18: =$B$18*1 -> 0 | Q18: =$B$18*1 -> 0 | R18: =$B$18*1 -> 0 | AM18: =SUM(C18:V18) -> 0 | AN18: =SUM(W18:AL18) -> 0 | AO18: =SUM(AM18,AN18) -> 0
A19: ='Costos HH - Sueldos'!$A27 -> Operador de Mesa de Servicio (N1) | B19: 0 | L19: =B$19 -> 0 | M19: =B$19 -> 0 | W19: =B$19*1 -> 0 | X19: =B$19*1 -> 0 | Y19: =B$19*1 -> 0 | Z19: =B$19*1 -> 0 | AA19: =B$19*1 -> 0 | AB19: =B$19*1 -> 0 | AC19: =B$19*1 -> 0 | AD19: =B$19*1 -> 0 | AE19: =B$19*1 -> 0 | AF19: =B$19*1 -> 0 | AG19: =B$19*1 -> 0 | AH19: =B$19*1 -> 0 | AI19: =B$19*1 -> 0 | AJ19: =B$19*1 -> 0 | AK19: =B$19*1 -> 0 | AL19: =B$19*1 -> 0 | AM19: =SUM(C19:V19) -> 0 | AN19: =SUM(W19:AL19) -> 0 | AO19: =SUM(AM19,AN19) -> 0
A20: ='Costos HH - Sueldos'!$A28 -> Especialista en Soporte Técnico Nivel 2 | B20: 0 | L20: =B$20 -> 0 | M20: =B$20*1 -> 0 | N20: =B$20 -> 0 | W20: =B$20*1 -> 0 | X20: =B$20*1 -> 0 | Y20: =B$20*1 -> 0 | Z20: =B$20*1 -> 0 | AA20: =B$20*1 -> 0 | AB20: =B$20*1 -> 0 | AC20: =B$20*1 -> 0 | AD20: =B$20*1 -> 0 | AE20: =B$20*1 -> 0 | AF20: =B$20*1 -> 0 | AG20: =B$20*1 -> 0 | AH20: =B$20*1 -> 0 | AI20: =B$20*1 -> 0 | AJ20: =B$20*1 -> 0 | AK20: =B$20*1 -> 0 | AL20: =B$20*1 -> 0 | AM20: =SUM(C20:V20) -> 0 | AN20: =SUM(W20:AL20) -> 0 | AO20: =SUM(AM20,AN20) -> 0
A21: ='Costos HH - Sueldos'!$A29 -> Tester | B21: 0 | H21: =B$21*1*4 -> 0 | I21: =B$21*4 -> 0 | K21: =B$21*1*4 -> 0 | AM21: =SUM(C21:V21) -> 0 | AN21: =SUM(W21:AL21) -> 0 | AO21: =SUM(AM21,AN21) -> 0
A22: ='Costos HH - Sueldos'!$A30 -> Documentador | B22: 0 | I22: =B$22*1*2 -> 0 | R22: =B$22*2 -> 0 | T22: =B$22*2 -> 0 | U22: =B$22*2 -> 0 | V22: =B$22*2 -> 0 | W22: =$B$22*1 -> 0 | X22: =$B$22*1 -> 0 | Y22: =$B$22*1 -> 0 | Z22: =$B$22*1 -> 0 | AA22: =$B$22*1 -> 0 | AB22: =$B$22*1 -> 0 | AC22: =$B$22*1 -> 0 | AD22: =$B$22*1 -> 0 | ... AL22: =$B$22*1 -> 0 | AM22: =SUM(C22:V22) -> 0 | AN22: =SUM(W22:AL22) -> 0 | AO22: =SUM(AM22,AN22) -> 0
A23: ='Costos HH - Sueldos'!$A31 -> LÃ­der de ImplantaciÃ³n / Cambio | B23: 0 | C23: =B$23 -> 0 | W23: =B$23*1 -> 0 | X23: =B$23*1 -> 0 | Y23: =B$23*1 -> 0 | Z23: =B$23*1 -> 0 | AA23: =B$23*1 -> 0 | AB23: =B$23*1 -> 0 | AC23: =B$23*1 -> 0 | AD23: =B$23*1 -> 0 | AE23: =B$23*1 -> 0 | AF23: =B$23*1 -> 0 | AG23: =B$23*1 -> 0 | AH23: =B$23*1 -> 0 | AI23: =B$23*1 -> 0 | AJ23: =B$23*1 -> 0 | AK23: =B$23*1 -> 0 | AL23: =B$23*1 -> 0 | AM23: =SUM(C23:V23) -> 0 | AN23: =SUM(W23:AL23) -> 0 | AO23: =SUM(AM23,AN23) -> 0
A24: ='Costos HH - Sueldos'!$A32 -> Instructor de Capacitación | B24: 0 | P24: =B$24 -> 0 | R24: =B$24 -> 0 | AM24: =SUM(C24:V24) -> 0 | AN24: =SUM(W24:AL24) -> 0 | AO24: =SUM(AM24,AN24) -> 0
A25: ='Costos HH - Sueldos'!$A33 -> LÃ­der de Datos | B25: 0 | V25: =B$25 -> 0 | AM25: =SUM(C25:V25) -> 0 | AN25: =SUM(W25:AL25) -> 0 | AO25: =SUM(AM25,AN25) -> 0
A26: ='Costos HH - Sueldos'!$A34 -> LÃ­der de OperaciÃ³n / SRE | B26: 0 | V26: =B$26 -> 0 | AM26: =SUM(C26:V26) -> 0 | AN26: =SUM(W26:AL26) -> 0 | AO26: =SUM(AM26,AN26) -> 0
A27: ='Costos HH - Sueldos'!$A35 -> Gestor de Adquisiciones | B27: 0 | C27: =B$27 -> 0 | E27: =B$27 -> 0 | F27: =B$27*1 -> 0 | G27: =B$27*1 -> 0 | H27: =B$27*1 -> 0 | I27: =B$27*1 -> 0 | V27: =B$27 -> 0 | W27: =$B$27*1 -> 0 | X27: =$B$27*1 -> 0 | Y27: =$B$27*1 -> 0 | Z27: =$B$27*1 -> 0 | AA27: =$B$27*1 -> 0 | AB27: =$B$27*1 -> 0 | AC27: =$B$27*1 -> 0 | AD27: =$B$27*1 -> 0 | ... AL27: =$B$27*1 -> 0 | AM27: =SUM(C27:V27) -> 0 | AN27: =SUM(W27:AL27) -> 0 | AO27: =SUM(AM27,AN27) -> 0
A28: ='Costos HH - Sueldos'!$A36 -> Asesor Legal | B28: 0 | V28: =B$28 -> 0 | AL28: =B$28*1 -> 0 | AM28: =SUM(C28:V28) -> 0 | AN28: =SUM(W28:AL28) -> 0 | AO28: =SUM(AM28,AN28) -> 0
A29: ='Costos HH - Sueldos'!$A37 -> Apoyo en bodega nocturna | B29: 0 | C29: =B$29 -> 0 | AM29: =SUM(C29:V29) -> 0 | AN29: =SUM(W29:AL29) -> 0 | AO29: =SUM(AM29,AN29) -> 0
A30: ='Costos HH - Sueldos'!$A38 -> Apoyo en cross-docking | B30: 0 | C30: =B$30 -> 0 | AL30: =B$30*1 -> 0 | AM30: =SUM(C30:V30) -> 0 | AN30: =SUM(W30:AL30) -> 0 | AO30: =SUM(AM30,AN30) -> 0
A31: ='Costos HH - Sueldos'!$A39 -> AcompaÃ±ante en ruta | B31: 0 | C31: =B$31 -> 0 | V31: =B$31 -> 0 | AL31: =B$31*1 -> 0 | AM31: =SUM(C31:V31) -> 0 | AN31: =SUM(W31:AL31) -> 0 | AO31: =SUM(AM31,AN31) -> 0
A32: ='Costos HH - Sueldos'!$A40 -> Administrador de plataforma | B32: 0 | W32: =$B$31*1 -> 0 | X32: =$B$31*1 -> 0 | Y32: =$B$31*1 -> 0 | Z32: =$B$31*1 -> 0 | AA32: =$B$31*1 -> 0 | AB32: =$B$31*1 -> 0 | AC32: =$B$31*1 -> 0 | AD32: =$B$31*1 -> 0 | ... AL32: =$B$31*1 -> 0 | AM32: =SUM(C32:V32) -> 0 | AN32: =SUM(W32:AL32) -> 0 | AO32: =SUM(AM32,AN32) -> 0
A33: Previsión variable soporte (10% del total s/v) | B33: 0 | W33: 0 | X33: 0 | Y33: 0 | Z33: 0 | AA33: 0 | AB33: 0 | AC33: 0 | AD33: 0 | AE33: 0 | AF33: 0 | AG33: 0 | AH33: 0 | AI33: 0 | AJ33: 0 | AK33: 0 | AL33: 0 | AM33: =SUM(C33:V33) -> 0 | AN33: =SUM(W33:AL33) -> 0 | AO33: =SUM(AM33,AN33) -> 0
A34: Total | C34: =SUM(C3:C33) -> 0 | D34: =SUM(D3:D33) -> 0 | E34: =SUM(E3:E33) -> 0 | F34: =SUM(F3:F33) -> 0 | G34: =SUM(G3:G33) -> 0 | H34: =SUM(H3:H33) -> 0 | I34: =SUM(I3:I33) -> 0 | J34: =SUM(J3:J33) -> 0 | ... L34: =SUM(L3:L33) -> 0 | M34: =SUM(M3:M32) -> 0 | N34: =SUM(N3:N32) -> 0 | O34: =SUM(O3:O32) -> 0 | P34: =SUM(P3:P32) -> 0 | Q34: =SUM(Q3:Q32) -> 0 | R34: =SUM(R3:R32) -> 0 | S34: =SUM(S3:S32) -> 0 | T34: =SUM(T3:T32) -> 0 | ... V34: =SUM(V3:V32) -> 0 | W34: =SUM(W3:W33) -> 0 | X34: =SUM(X3:X33) -> 0 | Y34: =SUM(Y3:Y33) -> 0 | Z34: =SUM(Z3:Z33) -> 0 | AA34: =SUM(AA3:AA33) -> 0 | AB34: =SUM(AB3:AB33) -> 0 | AC34: =SUM(AC3:AC33) -> 0 | AD34: =SUM(AD3:AD33) -> 0 | ... AO34: =SUM(AO3:AO33) -> 0
U35: Total | V35: =SUM(C34:V34) -> 0 | AK35: Total | AL35: =SUM(W34:AL34) -> 0
U36: Total previsión variable | V36: =SUM(G33:V33) -> 0 | AK36: Total previsión variable | AL36: =SUM(W33:AL33) -> 0
U37: Total s/variable | V37: =V35-V36 -> 0 | AK37: Total s/variable | AL37: =AL35-AL36 -> 0
A38: Costos de Capacitaciones
B39: Encargado | C39: Mes 1 | D39: Mes 2 | E39: Mes 3 | F39: Mes 4 | G39: Mes 5 | H39: Mes 6 | I39: Mes 7 | J39: Mes 8 | K39: Mes 9 | L39: Mes 10 | M39: Mes 11 | N39: Mes 12 | O39: Mes 13 | P39: Mes 14 | Q39: Mes 15 | R39: Mes 16 | S39: Mes 17 | T39: Mes 18 | U39: Mes 19 | V39: Mes 20
B40: ='Costos HH - Sueldos'!A31 -> Líder de Implantación / Cambio | K40: =B$23 -> 0
B41: ='Costos HH - Sueldos'!A32 -> Instructor de Capacitación | K41: =B$24*1 -> 0
B42: ='Costos HH - Sueldos'!A15 -> Líder Funcional | K42: =B$7 -> 0
B43: ='Costos HH - Sueldos'!A30 -> Documentador | K43: =B$22*2 -> 0 | L43: =B$22*2 -> 0
B44: Total UF | C44: =SUM(C40:C43) -> 0 | D44: =SUM(D40:D43) -> 0 | E44: =SUM(E40:E43) -> 0 | F44: =SUM(F40:F43) -> 0 | G44: =SUM(G40:G43) -> 0 | H44: =SUM(H40:H43) -> 0 | I44: =SUM(I40:I43) -> 0 | J44: =SUM(J40:J43) -> 0 | ... V44: =SUM(V40:V43) -> 0
U45: Total | V45: =SUM(C44:V44) -> 0

Sheet ADQUISICIONES IMPLEMENTACIÓN
A2: USD | B2: =PARÁMETROS!$B$4 -> 900
A3: EURO | B3: =PARÁMETROS!$B$5 -> 1000
A4: UF | B4: =PARÁMETROS!$B$6 -> 40000
A5: HH | B5: =PARÁMETROS!$B$8 -> 160
A7: COMPONENTE | B7: DESCRIPCIÓN | C7: COSTO USD | D7: COSTO CLP | E7: COSTO UF | F7: CANTIDAD | G7: TOTAL USD | H7: TOTAL CLP | I7: TOTAL UF | J7: %IVA UF | K7: VIDA ÚTIL AÑOS | L7: DEPRECIACIÓN ANUAL | M7: DEPRECIACIÓN TOTAL
A8: // Sites Cloud | M8: =SUM(L9:L66) -> 0
D9: =C9*$B$2 -> 0 | E9: =D9/$B$4 -> 0 | F9: 0 | G9: =F9*C9 -> 0 | H9: =F9*D9 -> 0 | I9: =F9*E9 -> 0 | J9: =I9*0.19 -> 0 | K9: 0 | L9: 0
D10: =C10*$B$2 -> 0 | E10: =D10/$B$4 -> 0 | F10: 0 | G10: =F10*C10 -> 0 | H10: =F10*D10 -> 0 | I10: =F10*E10 -> 0 | J10: =I10*0.19 -> 0 | K10: 0 | L10: 0
D11: =C11*$B$2 -> 0 | E11: =D11/$B$4 -> 0 | F11: 0 | G11: =F11*C11 -> 0 | H11: =F11*D11 -> 0 | I11: =F11*E11 -> 0 | J11: =I11*0.19 -> 0 | K11: 0 | L11: 0
D12: =C12*$B$2 -> 0 | E12: =D12/$B$4 -> 0 | F12: 0 | G12: =F12*C12 -> 0 | H12: =F12*D12 -> 0 | I12: =F12*E12 -> 0 | J12: =I12*0.19 -> 0 | K12: 0 | L12: 0
D13: =C13*$B$2 -> 0 | E13: =D13/$B$4 -> 0 | F13: 0 | G13: =F13*C13 -> 0 | H13: =F13*D13 -> 0 | I13: =F13*E13 -> 0 | J13: =I13*0.19 -> 0 | K13: 0 | L13: 0
D14: =C14*$B$2 -> 0 | E14: =D14/$B$4 -> 0 | F14: 0 | G14: =F14*C14 -> 0 | H14: =F14*D14 -> 0 | I14: =F14*E14 -> 0 | J14: =I14*0.19 -> 0 | K14: 0 | L14: 0
D15: =C15*$B$2 -> 0 | E15: =D15/$B$4 -> 0 | F15: 0 | G15: =F15*C15 -> 0 | H15: =F15*D15 -> 0 | I15: =F15*E15 -> 0 | J15: =I15*0.19 -> 0 | K15: 0 | L15: 0
D16: =C16*$B$2 -> 0 | E16: =D16/$B$4 -> 0 | F16: 0 | G16: =F16*C16 -> 0 | H16: =F16*D16 -> 0 | I16: =F16*E16 -> 0 | J16: =I16*0.19 -> 0 | K16: 0 | L16: 0
D17: =C17*$B$2 -> 0 | E17: =D17/$B$4 -> 0 | F17: 0 | G17: =F17*C17 -> 0 | H17: =F17*D17 -> 0 | I17: =F17*E17 -> 0 | J17: =I17*0.19 -> 0 | K17: 0 | L17: 0
D18: =C18*$B$2 -> 0 | E18: =D18/$B$4 -> 0 | F18: 0 | G18: =F18*C18 -> 0 | H18: =F18*D18 -> 0 | I18: =F18*E18 -> 0 | J18: =I18*0.19 -> 0 | K18: 0 | L18: 0
D19: =C19*$B$2 -> 0 | E19: =D19/$B$4 -> 0 | F19: 0 | G19: =F19*C19 -> 0 | H19: =F19*D19 -> 0 | I19: =F19*E19 -> 0 | J19: =I19*0.19 -> 0 | K19: 0 | L19: 0
F20: Total | G20: =SUM(G9:G19) -> 0 | H20: =SUM(H9:H19) -> 0 | I20: =SUM(I9:I19) -> 0 | J20: =I20*0.19 -> 0
A21: // Equipos de red y oficina //
D22: =C22*$B$2 -> 0 | E22: =D22/$B$4 -> 0 | F22: 0 | G22: =F22*C22 -> 0 | H22: =F22*D22 -> 0 | I22: =F22*E22 -> 0 | J22: =I22*0.19 -> 0 | K22: 6 | L22: =I22/(K22)/12 -> 0
D23: =C23*$B$2 -> 0 | E23: =D23/$B$4 -> 0 | F23: 0 | G23: =F23*C23 -> 0 | H23: =F23*D23 -> 0 | I23: =F23*E23 -> 0 | J23: =I23*0.19 -> 0 | K23: 6 | L23: =I23/(K23)/12 -> 0
D24: =C24*$B$2 -> 0 | E24: =D24/$B$4 -> 0 | F24: 0 | G24: =F24*C24 -> 0 | H24: =F24*D24 -> 0 | I24: =F24*E24 -> 0 | J24: =I24*0.19 -> 0 | K24: 6 | L24: =I24/(K24)/12 -> 0
D25: =C25*$B$2 -> 0 | E25: =D25/$B$4 -> 0 | F25: 0 | G25: =F25*C25 -> 0 | H25: =F25*D25 -> 0 | I25: =F25*E25 -> 0 | J25: =I25*0.19 -> 0 | K25: 6 | L25: =I25/(K25)/12 -> 0
D26: =C26*$B$2 -> 0 | E26: =D26/$B$4 -> 0 | F26: 0 | G26: =F26*C26 -> 0 | H26: =F26*D26 -> 0 | I26: =F26*E26 -> 0 | J26: =I26*0.19 -> 0 | K26: 6 | L26: =I26/(K26)/12 -> 0
D27: =C27*$B$2 -> 0 | E27: =D27/$B$4 -> 0 | F27: 0 | G27: =F27*C27 -> 0 | H27: =F27*D27 -> 0 | I27: =F27*E27 -> 0 | J27: =I27*0.19 -> 0 | K27: 6 | L27: 0
D28: =C28*$B$2 -> 0 | E28: =D28/$B$4 -> 0 | F28: 0 | G28: =F28*C28 -> 0 | H28: =F28*D28 -> 0 | I28: =F28*E28 -> 0 | J28: =I28*0.19 -> 0 | K28: 6 | L28: 0
D29: =C29*$B$2 -> 0 | E29: =D29/$B$4 -> 0 | F29: 0 | G29: =F29*C29 -> 0 | H29: =F29*D29 -> 0 | I29: =F29*E29 -> 0 | J29: =I29*0.19 -> 0 | K29: 6 | L29: 0
D30: =C30*$B$2 -> 0 | E30: =D30/$B$4 -> 0 | F30: 0 | G30: =F30*C30 -> 0 | H30: =F30*D30 -> 0 | I30: =F30*E30 -> 0 | J30: =I30*0.19 -> 0 | K30: 6 | L30: 0
F31: Total | G31: =SUM(G22:G30) -> 0 | H31: =SUM(H22:H30) -> 0 | I31: =SUM(I22:I30) -> 0 | J31: =I31*0.19 -> 0
A32: // Seguridad //
D33: =C33*$B$2 -> 0 | E33: =D33/$B$4 -> 0 | F33: 0 | G33: =F33*C33 -> 0 | H33: =F33*D33 -> 0 | I33: =F33*E33 -> 0 | J33: =I33*0.19 -> 0 | K33: 7 | L33: =I33/(K33)/12 -> 0
D34: =C34*$B$2 -> 0 | E34: =D34/$B$4 -> 0 | F34: 0 | G34: =F34*C34 -> 0 | H34: =F34*D34 -> 0 | I34: =F34*E34 -> 0 | J34: =I34*0.19 -> 0 | K34: 7 | L34: =I34/(K34)/12 -> 0
D35: =C35*$B$2 -> 0 | E35: =D35/$B$4 -> 0 | F35: 0 | G35: =F35*C35 -> 0 | H35: =F35*D35 -> 0 | I35: =F35*E35 -> 0 | J35: =I35*0.19 -> 0 | K35: 7 | L35: =I35/(K35)/12 -> 0
D36: =C36*$B$2 -> 0 | E36: =D36/$B$4 -> 0 | F36: 0 | G36: =F36*C36 -> 0 | H36: =F36*D36 -> 0 | I36: =F36*E36 -> 0 | J36: =I36*0.19 -> 0 | K36: 7 | L36: =I36/(K36)/12 -> 0
D37: =C37*$B$2 -> 0 | E37: =D37/$B$4 -> 0 | F37: 0 | G37: =F37*C37 -> 0 | H37: =F37*D37 -> 0 | I37: =F37*E37 -> 0 | J37: =I37*0.19 -> 0 | K37: 7 | L37: =I37/(K37)/12 -> 0
F38: Total | G38: =SUM(G33:G37) -> 0 | H38: =SUM(H33:H37) -> 0 | I38: =SUM(I33:I37) -> 0 | J38: =I38*0.19 -> 0
A39: // Site Edge //
D40: =C40*$B$2 -> 0 | E40: =D40/$B$4 -> 0 | F40: 0 | G40: =F40*C40 -> 0 | H40: =F40*D40 -> 0 | I40: =F40*E40 -> 0 | J40: =I40*0.19 -> 0 | K40: 0 | L40: 0
D41: =C41*$B$2 -> 0 | E41: =D41/$B$4 -> 0 | F41: 0 | G41: =F41*C41 -> 0 | H41: =F41*D41 -> 0 | I41: =F41*E41 -> 0 | J41: =I41*0.19 -> 0 | K41: 10 | L41: =I41/(K41)/12 -> 0
D42: =C42*$B$2 -> 0 | E42: =D42/$B$4 -> 0 | F42: 0 | G42: =F42*C42 -> 0 | H42: =F42*D42 -> 0 | I42: =F42*E42 -> 0 | J42: =I42*0.19 -> 0 | K42: 15 | L42: =I42/(K42)/12 -> 0
D43: =C43*$B$2 -> 0 | E43: =D43/$B$4 -> 0 | F43: 0 | G43: =F43*C43 -> 0 | H43: =F43*D43 -> 0 | I43: =F43*E43 -> 0 | J43: =I43*0.19 -> 0 | K43: 10 | L43: =I43/(K43)/12 -> 0
D44: =C44*$B$2 -> 0 | E44: =D44/$B$4 -> 0 | F44: 0 | G44: =F44*C44 -> 0 | H44: =F44*D44 -> 0 | I44: =F44*E44 -> 0 | J44: =I44*0.19 -> 0 | K44: 15 | L44: =I44/(K44)/12 -> 0
D45: =C45*$B$2 -> 0 | E45: =D45/$B$4 -> 0 | F45: 0 | G45: =F45*C45 -> 0 | H45: =F45*D45 -> 0 | I45: =F45*E45 -> 0 | J45: =I45*0.19 -> 0 | K45: 6 | L45: =I45/(K45)/12 -> 0
D46: =C46*$B$2 -> 0 | E46: =D46/$B$4 -> 0 | F46: 0 | G46: =F46*C46 -> 0 | H46: =F46*D46 -> 0 | I46: =F46*E46 -> 0 | J46: =I46*0.19 -> 0 | K46: 10 | L46: =I46/(K46)/12 -> 0
D47: =C47*$B$2 -> 0 | E47: =D47/$B$4 -> 0 | F47: 0 | G47: =F47*C47 -> 0 | H47: =F47*D47 -> 0 | I47: =F47*E47 -> 0 | J47: =I47*0.19 -> 0 | K47: 10 | L47: =I47/(K47)/12 -> 0
D48: =C48*$B$2 -> 0 | E48: =D48/$B$4 -> 0 | F48: 0 | G48: =F48*C48 -> 0 | H48: =F48*D48 -> 0 | I48: =F48*E48 -> 0 | J48: =I48*0.19 -> 0 | K48: 10 | L48: =I48/(K48)/12 -> 0
F49: Total | G49: =SUM(G40:G48) -> 0 | H49: =SUM(H40:H48) -> 0 | I49: =SUM(I40:I48) -> 0 | J49: =I49*0.19 -> 0
A50: // Obras civiles y montaje
D51: =C51*$B$2 -> 0 | E51: =D51/$B$4 -> 0 | F51: 0 | G51: =F51*C51 -> 0 | H51: =F51*D51 -> 0 | I51: =F51*E51 -> 0 | J51: =I51*0.19 -> 0 | K51: 0 | L51: 0
D52: =C52*$B$2 -> 0 | E52: =D52/$B$4 -> 0 | F52: 0 | G52: =F52*C52 -> 0 | H52: =F52*D52 -> 0 | I52: =F52*E52 -> 0 | J52: =I52*0.19 -> 0 | K52: 0 | L52: 0
D53: =C53*$B$2 -> 0 | E53: =D53/$B$4 -> 0 | F53: 0 | G53: =F53*C53 -> 0 | H53: =F53*D53 -> 0 | I53: =F53*E53 -> 0 | J53: =I53*0.19 -> 0 | K53: 0 | L53: 0
D54: =C54*$B$2 -> 0 | E54: =D54/$B$4 -> 0 | F54: 0 | G54: =F54*C54 -> 0 | H54: =F54*D54 -> 0 | I54: =F54*E54 -> 0 | J54: =I54*0.19 -> 0 | K54: 0 | L54: 0
D55: =C55*$B$2 -> 0 | E55: =D55/$B$4 -> 0 | F55: 0 | G55: =F55*C55 -> 0 | H55: =F55*D55 -> 0 | I55: =F55*E55 -> 0 | J55: =I55*0.19 -> 0 | K55: 0 | L55: 0
D56: =C56*$B$2 -> 0 | E56: =D56/$B$4 -> 0 | F56: 0 | G56: =F56*C56 -> 0 | H56: =F56*D56 -> 0 | I56: =F56*E56 -> 0 | J56: =I56*0.19 -> 0 | K56: 0 | L56: 0
F57: Total | G57: =SUM(G51:G56) -> 0 | H57: =SUM(H51:H56) -> 0 | I57: =SUM(I51:I56) -> 0 | J57: =I57*0.19 -> 0
A58: // Proveedores de Internet //
D59: =C59*$B$2 -> 0 | E59: =D59/$B$4 -> 0 | F59: 0 | G59: =F59*C59 -> 0 | H59: =F59*D59 -> 0 | I59: =F59*E59 -> 0 | J59: =I59*0.19 -> 0 | K59: 0 | L59: 0
D60: =C60*$B$2 -> 0 | E60: =D60/$B$4 -> 0 | F60: 0 | G60: =F60*C60 -> 0 | H60: =F60*D60 -> 0 | I60: =F60*E60 -> 0 | J60: =I60*0.19 -> 0 | K60: 0 | L60: 0
F61: Total | G61: =SUM(G59:G60) -> 0 | H61: =SUM(H59:H60) -> 0 | I61: =SUM(I59:I60) -> 0 | J61: =I61*0.19 -> 0
A62: // Servicios externos //
D63: =C63*$B$2 -> 0 | E63: =D63/$B$4 -> 0 | F63: 0 | G63: =F63*C63 -> 0 | H63: =F63*D63 -> 0 | I63: =F63*E63 -> 0 | J63: =I63*0.19 -> 0 | K63: 0 | L63: 0
D64: =C64*$B$2 -> 0 | E64: =D64/$B$4 -> 0 | F64: 0 | G64: =F64*C64 -> 0 | H64: =F64*D64 -> 0 | I64: =F64*E64 -> 0 | J64: =I64*0.19 -> 0 | K64: 0 | L64: 0
D65: =C65*$B$2 -> 0 | E65: =D65/$B$4 -> 0 | F65: 0 | G65: =F65*C65 -> 0 | H65: =F65*D65 -> 0 | I65: =F65*E65 -> 0 | J65: =I65*0.19 -> 0 | K65: 0 | L65: 0
D66: =C66*$B$2 -> 0 | E66: =D66/$B$4 -> 0 | F66: 0 | G66: =F66*C66 -> 0 | H66: =F66*D66 -> 0 | I66: =F66*E66 -> 0 | J66: =I66*0.19 -> 0 | K66: 0 | L66: 0
F67: Total | G67: =SUM(G63:G66) -> 0 | H67: =SUM(H63:H66) -> 0 | I67: =SUM(I63:I66) -> 0 | J67: =I67*0.19 -> 0
B69: HARDWARE (UF) | C69: SOFTWARE (UF)
A70: ADQUISICIONES FASE IMPLEMENTACIÓN | B70: =SUM(I31,I38,I49,I57) -> 0 | C70: 0
A71: SERVICIOS RECURRENTES FASE IMPLEMENTACIÓN | B71: 0 | C71: =SUM(I20,I61,I67) -> 0

Sheet ADQUISICIONES OPERACIÓN
A1: CONVERSIONES
A2: USD | B2: =PARÁMETROS!$B$4 -> 900
A3: EURO | B3: =PARÁMETROS!$B$5 -> 1000
A4: UF | B4: =PARÁMETROS!$B$6 -> 40000
A5: HH | B5: =PARÁMETROS!$B$8 -> 160
A7: COMPONENTE | B7: DESCRIPCIÓN | C7: COSTO USD | D7: COSTO CLP | E7: COSTO UF | F7: CANTIDAD | G7: TOTAL USD | H7: TOTAL CLP | I7: TOTAL UF | J7: %IVA UF | K7: VIDA ÚTIL AÑOS | L7: DEPRECIACIÓN ANUAL | M7: DEPRECIACIÓN TOTAL
A8: // Sites Cloud | M8: =SUM(L9:L44) -> 0
D9: =C9*$B$2 -> 0 | E9: =D9/$B$4 -> 0 | F9: 0 | G9: =F9*C9 -> 0 | H9: =F9*D9 -> 0 | I9: =F9*E9 -> 0 | J9: =I9*0.19 -> 0 | K9: 0 | L9: 0
D10: =C10*$B$2 -> 0 | E10: =D10/$B$4 -> 0 | F10: 0 | G10: =F10*C10 -> 0 | H10: =F10*D10 -> 0 | I10: =F10*E10 -> 0 | J10: =I10*0.19 -> 0 | K10: 0 | L10: 0
D11: =C11*$B$2 -> 0 | E11: =D11/$B$4 -> 0 | F11: 0 | G11: =F11*C11 -> 0 | H11: =F11*D11 -> 0 | I11: =F11*E11 -> 0 | J11: =I11*0.19 -> 0 | K11: 0 | L11: 0
D12: =C12*$B$2 -> 0 | E12: =D12/$B$4 -> 0 | F12: 0 | G12: =F12*C12 -> 0 | H12: =F12*D12 -> 0 | I12: =F12*E12 -> 0 | J12: =I12*0.19 -> 0 | K12: 0 | L12: 0
D13: =C13*$B$2 -> 0 | E13: =D13/$B$4 -> 0 | F13: 0 | G13: =F13*C13 -> 0 | H13: =F13*D13 -> 0 | I13: =F13*E13 -> 0 | J13: =I13*0.19 -> 0 | K13: 0 | L13: 0
D14: =C14*$B$2 -> 0 | E14: =D14/$B$4 -> 0 | F14: 0 | G14: =F14*C14 -> 0 | H14: =F14*D14 -> 0 | I14: =F14*E14 -> 0 | J14: =I14*0.19 -> 0 | K14: 0 | L14: 0
D15: =C15*$B$2 -> 0 | E15: =D15/$B$4 -> 0 | F15: 0 | G15: =F15*C15 -> 0 | H15: =F15*D15 -> 0 | I15: =F15*E15 -> 0 | J15: =I15*0.19 -> 0 | K15: 0 | L15: 0
D16: =C16*$B$2 -> 0 | E16: =D16/$B$4 -> 0 | F16: 0 | G16: =F16*C16 -> 0 | H16: =F16*D16 -> 0 | I16: =F16*E16 -> 0 | J16: =I16*0.19 -> 0 | K16: 0 | L16: 0
D17: =C17*$B$2 -> 0 | E17: =D17/$B$4 -> 0 | F17: 0 | G17: =F17*C17 -> 0 | H17: =F17*D17 -> 0 | I17: =F17*E17 -> 0 | J17: =I17*0.19 -> 0 | K17: 0 | L17: 0
D18: =C18*$B$2 -> 0 | E18: =D18/$B$4 -> 0 | F18: 0 | G18: =F18*C18 -> 0 | H18: =F18*D18 -> 0 | I18: =F18*E18 -> 0 | J18: =I18*0.19 -> 0 | K18: 0 | L18: 0
D19: =C19*$B$2 -> 0 | E19: =D19/$B$4 -> 0 | F19: 0 | G19: =F19*C19 -> 0 | H19: =F19*D19 -> 0 | I19: =F19*E19 -> 0 | J19: =I19*0.19 -> 0 | K19: 0 | L19: 0
F20: Total | G20: =SUM(G9:G19) -> 0 | H20: =SUM(H9:H19) -> 0 | I20: =SUM(I9:I19) -> 0 | J20: =I20*0.19 -> 0
A21: // Equipos de red y oficina //
D22: =C22*$B$2 -> 0 | E22: =D22/$B$4 -> 0 | F22: 0 | G22: =F22*C22 -> 0 | H22: =F22*D22 -> 0 | I22: =F22*E22 -> 0 | J22: =I22*0.19 -> 0 | K22: 6 | L22: =I22/(K22)/12 -> 0
D23: =C23*$B$2 -> 0 | E23: =D23/$B$4 -> 0 | F23: 0 | G23: =F23*C23 -> 0 | H23: =F23*D23 -> 0 | I23: =F23*E23 -> 0 | J23: =I23*0.19 -> 0 | K23: 6 | L23: =I23/(K23)/12 -> 0
D24: =C24*$B$2 -> 0 | E24: =D24/$B$4 -> 0 | F24: 0 | G24: =F24*C24 -> 0 | H24: =F24*D24 -> 0 | I24: =F24*E24 -> 0 | J24: =I24*0.19 -> 0 | K24: 6 | L24: =I24/(K24)/12 -> 0
D25: =C25*$B$2 -> 0 | E25: =D25/$B$4 -> 0 | F25: 0 | G25: =F25*C25 -> 0 | H25: =F25*D25 -> 0 | I25: =F25*E25 -> 0 | J25: =I25*0.19 -> 0 | K25: 6 | L25: =I25/(K25)/12 -> 0
D26: =C26*$B$2 -> 0 | E26: =D26/$B$4 -> 0 | F26: 0 | G26: =F26*C26 -> 0 | H26: =F26*D26 -> 0 | I26: =F26*E26 -> 0 | J26: =I26*0.19 -> 0 | K26: 6 | L26: 0
F27: Total | G27: =SUM(G22:G26) -> 0 | H27: =SUM(H22:H26) -> 0 | I27: =SUM(I22:I26) -> 0 | J27: =I27*0.19 -> 0
A28: // Seguridad //
D29: =C29*$B$2 -> 0 | E29: =D29/$B$4 -> 0 | F29: 0 | G29: =F29*C29 -> 0 | H29: =F29*D29 -> 0 | I29: =F29*E29 -> 0 | J29: =I29*0.19 -> 0 | K29: 7 | L29: =I29/(K29)/12 -> 0
D30: =C30*$B$2 -> 0 | E30: =D30/$B$4 -> 0 | F30: 0 | G30: =F30*C30 -> 0 | H30: =F30*D30 -> 0 | I30: =F30*E30 -> 0 | J30: =I30*0.19 -> 0 | K30: 7 | L30: =I30/(K30)/12 -> 0
F31: Total | G31: =SUM(G29:G30) -> 0 | H31: =SUM(H29:H30) -> 0 | I31: =SUM(I29:I30) -> 0 | J31: =I31*0.19 -> 0
A32: // Obras civiles y montaje //
D33: =C33*$B$2 -> 0 | E33: =D33/$B$4 -> 0 | F33: 0 | G33: =F33*C33 -> 0 | H33: =F33*D33 -> 0 | I33: =F33*E33 -> 0 | J33: =I33*0.19 -> 0 | K33: 0 | L33: 0
D34: =C34*$B$2 -> 0 | E34: =D34/$B$4 -> 0 | F34: 0 | G34: =F34*C34 -> 0 | H34: =F34*D34 -> 0 | I34: =F34*E34 -> 0 | J34: =I34*0.19 -> 0 | K34: 0 | L34: 0
F35: Total | G35: =SUM(G33:G34) -> 0 | H35: =SUM(H33:H34) -> 0 | I35: =SUM(I33:I34) -> 0 | J35: =I35*0.19 -> 0
A36: // Proveedores de Internet //
D37: =C37*$B$2 -> 0 | E37: =D37/$B$4 -> 0 | F37: 0 | G37: =F37*C37 -> 0 | H37: =F37*D37 -> 0 | I37: =F37*E37 -> 0 | J37: =I37*0.19 -> 0 | K37: 0 | L37: 0
D38: =C38*$B$2 -> 0 | E38: =D38/$B$4 -> 0 | F38: 0 | G38: =F38*C38 -> 0 | H38: =F38*D38 -> 0 | I38: =F38*E38 -> 0 | J38: =I38*0.19 -> 0 | K38: 0 | L38: 0
F39: Total | G39: =SUM(G37:G38) -> 0 | H39: =SUM(H37:H38) -> 0 | I39: =SUM(I37:I38) -> 0 | J39: =I39*0.19 -> 0
A40: // Servicios externos //
D41: =C41*$B$2 -> 0 | E41: =D41/$B$4 -> 0 | F41: 0 | G41: =F41*C41 -> 0 | H41: =F41*D41 -> 0 | I41: =F41*E41 -> 0 | J41: =I41*0.19 -> 0 | K41: 0 | L41: 0
D42: =C42*$B$2 -> 0 | E42: =D42/$B$4 -> 0 | F42: 0 | G42: =F42*C42 -> 0 | H42: =F42*D42 -> 0 | I42: =F42*E42 -> 0 | J42: =I42*0.19 -> 0 | K42: 0 | L42: 0
D43: =C43*$B$2 -> 0 | E43: =D43/$B$4 -> 0 | F43: 0 | G43: =F43*C43 -> 0 | H43: =F43*D43 -> 0 | I43: =F43*E43 -> 0 | J43: =I43*0.19 -> 0 | K43: 0 | L43: 0
D44: =C44*$B$2 -> 0 | E44: =D44/$B$4 -> 0 | F44: 0 | G44: =F44*C44 -> 0 | H44: =F44*D44 -> 0 | I44: =F44*E44 -> 0 | J44: =I44*0.19 -> 0 | K44: 0 | L44: 0
F45: Total | G45: =SUM(G41:G44) -> 0 | H45: =SUM(H41:H44) -> 0 | I45: =SUM(I41:I44) -> 0 | J45: =I45*0.19 -> 0
B47: HARDWARE | C47: SOFTWARE (UF)
A48: ADQUISICIONES FASE OPERACIÓN | B48: =SUM(I27,I31,I35) -> 0 | C48: 0
A49: SERVICIOS RECURRENTES FASE OPERACIÓN | B49: 0 | C49: =SUM(I20,I39,I45) -> 0
