Workbook

Sheet Léeme
A1: LafroX — Planilla de cálculos del Subdocumento 9 (Plan de calidad)
A2: Licitación TFEP-01/2026, Caso 02 — Logística, Distribuidora Puelche S.A. Planilla de trabajo; no es entregable.
A4: Propósito | B4: Reunir en un solo lugar los datos obligatorios y los cálculos que el SD9, sus anexos y los Formularios T-13 y T-17 deben mostrar, con fórmulas vivas que se recalculan al cambiar un dato.
A5: Convención de colores | B5: Texto azul = dato de entrada tomado de las Bases o de otro subdocumento. Fondo amarillo = supuesto de LafroX que el grupo debe confirmar. Texto verde = vínculo a la hoja Datos_Base. Texto negro = fórmula.
A6: Cómo se usa | B6: Cambiar un valor sólo en Datos_Base (o en una celda amarilla). Las demás hojas lo leen de allí. Excel recalcula al abrir.
A7: Datos_Base | B7: Todos los datos con valor, unidad y fuente (archivo y sección).
A8: ISO25010 | B8: Umbrales por característica y subcaracterística (Art. 24 BA) con método, ambiente y paquete EDT.
A9: Metricas_Codigo | B9: Umbrales bloqueantes de código por lenguaje y puerta; columna «Medido» para simular una medición.
A10: Carga_Estres | B10: TPS, usuarios, dispositivos y mensajes para la prueba a 1,5× el peak y los escalones de estrés.
A11: Disponibilidad | B11: Presupuesto de error por nivel de servicio (SD4 Tabla 16).
A12: Casos_Prueba | B12: Estimación del número de casos y de la duración de la batería de regresión.
A13: HH_Calidad | B13: Paquetes de calidad del T-15 distribuidos por mes, totales por rol y categoría de costo de la calidad, capacidad de evaluadores.
A14: Calendario | B14: Matriz de 56 meses por tipo de prueba, con congelamientos y conteos (insumo de T-13 y Figura 9.9).
A15: Aceptacion_T17 | B15: Hitos H1–H12: entrega, revisión de 10 días hábiles, subsanación de 10 y holgura contra la reserva del T-15.
... A21: Decisiones vigentes | B21: Cobertura: ≥70 % lógica de negocio Y ≥80 % unitaria global, ambas bloqueantes. Pruebas de intrusión: anuales y antes de cada paso a producción.

Sheet Datos_Base
A1: Datos base
A2: Fuente de todas las demás hojas. Azul = dato de fuente; amarillo = supuesto de LafroX.
A4: ID | B4: Dato | C4: Valor | D4: Unidad | E4: Fuente | F4: Tipo
A5: TPS_REG | B5: Transacciones por segundo en régimen normal | C5: 12.34 | D5: TPS | E5: SD4 §4.2, Tabla 33 | F5: Fuente
A6: TPS_DESP | B6: TPS en el peak de la ventana de despacho 05:30–07:00 | C6: 6.94 | D6: TPS | E6: SD4 §4.2, Tabla 33 | F6: Fuente
A7: TPS_SEP | B7: TPS en el peak de septiembre (base de la prueba de carga) | C7: 14.66 | D7: TPS | E7: SD4 §4.2, Tabla 33 | F7: Fuente
A8: FACT_CARGA | B8: Factor de la prueba de carga sobre el peak | C8: 1.5 | D8: × | E8: BA Art. 24; BTT RT-09.06; BTT §20.1 | F8: Fuente
A9: FACT_CREC | B9: Crecimiento sin rediseño en 3 años | C9: 3 | D9: × | E9: BTT RT-09.03 | F9: Fuente
A10: USR_REG | B10: Usuarios concurrentes en régimen | C10: 438.3 | D10: usuarios | E10: SD4 §4.2, Tabla 33 | F10: Fuente
A11: USR_MAX | B11: Usuarios concurrentes, cota extrema | C11: 775.33 | D11: usuarios | E11: SD4 §4.2, Tabla 33 | F11: Fuente
A12: USR_REGIS | B12: Personas usuarias registradas | C12: 15180 | D12: usuarios | E12: SD4 §4.2, Tabla 33 | F12: Fuente
A13: DISP | B13: Dispositivos de terreno en operación simultánea | C13: 158 | D13: disp. | E13: SD4 §4.2, Tabla 33 | F13: Fuente
A14: MSG_NORM | B14: Mensajes de integración por día, régimen | C14: 230252 | D14: msj/día | E14: SD4 §4.2 (INT-01 a INT-15) | F14: Fuente
A15: MSG_PEAK | B15: Mensajes de integración por día, peak | C15: 353333 | D15: msj/día | E15: SD4 §4.2 (INT-01 a INT-15) | F15: Fuente
A16: N_MOD | B16: Módulos del monolito modular (M1–M12) | C16: 12 | D16: módulos | E16: SD4 §4.1 | F16: Fuente
... A59: QA_DIV | B59: Personas de la División QA de LafroX | C59: 10 | D59: personas | E59: SD1 §1.2 | F59: Fuente

Sheet ISO25010
A1: Umbrales de calidad del producto según ISO/IEC 25010
A2: Ocho características exigidas por BA Art. 24. Umbral, fuente, método de verificación, ambiente y paquete EDT.
A4: Característica | B4: Subcaracterística | C4: Métrica | D4: Umbral | E4: Fuente del umbral | F4: Método de verificación | G4: Ambiente | H4: Paquete EDT
A5: Funcionalidad | B5: Completitud funcional | C5: Requerimientos ofertados con caso de prueba aprobado | D5: 100 % | E5: Caso cap. 17.1; T-14 1.2.4 | F5: Matriz 9.C (requisito → caso → resultado) | G5: QA | H5: 1.2.4, 3.8.1, 3.9.1
A6: Funcionalidad | B6: Corrección funcional | C6: Casos de aceptación firmados sin defecto crítico/alto abierto | D6: 100 % / 0 | E6: BTT §20.1; BA Art. 17.3 | F6: Pruebas de aceptación con la Contraparte Técnica | G6: PREPROD | H6: 3.8.2, 3.9.2
A7: Funcionalidad | B7: Pertinencia funcional | C7: Resultados R18 medidos con su método en el mes comprometido | D7: 16 de 16 | E7: Caso cap. 18; SD3 Tabla 3.A.13 | F7: Protocolo de aceptación T-17 | G7: PROD | H7: 4.2, 4.3
A8: Desempeño | B8: Comportamiento temporal | C8: p95 confirmación de línea de picking | D8: ≤ 1 s | E8: Caso cap. 15 RT-09.01; SD4 Tabla 31 | F8: Prueba de carga a 1,5× el peak | G8: PREPROD | H8: 3.8.4, 3.9.3
A9: Desempeño | B9: Comportamiento temporal | C9: p95 registro de entrega en el local | D9: ≤ 2 s | E9: Caso cap. 15 RT-09.01 | F9: Prueba de carga y prueba de terreno | G9: PREPROD | H9: 3.8.4, 3.8.3
A10: Desempeño | B10: Comportamiento temporal | C10: p95 línea de preventa / consulta de stock y crédito | D10: ≤ 1,5 s / ≤ 2 s | E10: Caso cap. 15 RT-09.01 | F10: Prueba de carga | G10: PREPROD | H10: 3.8.4
A11: Desempeño | B11: Comportamiento temporal | C11: p95 API consulta / escritura / carga de página | D11: ≤ 500 ms / ≤ 800 ms / ≤ 2 s | E11: BTT §9.1; SD4 Tabla 31 | F11: Prueba de carga + regresión de desempeño semanal | G11: QA/PREPROD | H11: 1.5.2, 3.8.4
A12: Desempeño | B12: Capacidad | C12: TPS sostenidos sin violar los p95 | D12: ≥ 21,99 TPS (ver Carga_Estres) | E12: BTT RT-09.06; SD4 §4.2 | F12: Prueba de carga y estrés hasta el quiebre | G12: PREPROD | H12: 3.8.4, 3.9.3
A13: Desempeño | B13: Utilización de recursos | C13: CPU/memoria en el peak × 1,5 | D13: ≤ 70 % (supuesto) | E13: SD4 plan de capacidad | F13: Telemetría OpenTelemetry durante la prueba | G13: PREPROD | H13: 3.8.4
A14: Compatibilidad | B14: Interoperabilidad | C14: Contratos OpenAPI 3.1 / AsyncAPI sin ruptura | D14: 0 contratos rotos | E14: BA Art. 23; SD6 §6.2 | F14: Pruebas de contrato en CI | G14: DEV/QA | H14: 1.5.2
A15: Compatibilidad | B15: Interoperabilidad | C15: Flujos de las 15 integraciones ejecutados sin error | D15: 15 de 15 | E15: BTT §20.1 (integración) | F15: Pruebas de integración en QA | G15: QA | H15: 3.8.1, 3.9.1
... A33: Portabilidad | B33: Reemplazabilidad | C33: Exportación completa en formato abierto | D33: 100 % de entidades | E33: BA Art. 23 | F33: Prueba de exportación | G33: PREPROD | H33: 3.9.2
A35: Métricas por característica
A36: Funcionalidad | B36: =COUNTIF($A$5:$A$33,A36)
A37: Desempeño | B37: =COUNTIF($A$5:$A$33,A37)
A38: Compatibilidad | B38: =COUNTIF($A$5:$A$33,A38)
A39: Usabilidad | B39: =COUNTIF($A$5:$A$33,A39)
A40: Fiabilidad | B40: =COUNTIF($A$5:$A$33,A40)
A41: Seguridad | B41: =COUNTIF($A$5:$A$33,A41)
A42: Mantenibilidad | B42: =COUNTIF($A$5:$A$33,A42)
A43: Portabilidad | B43: =COUNTIF($A$5:$A$33,A43)
A44: Total | B44: =SUM(B36:B43)
A45: Características sin métrica | B45: =COUNTIF(B36:B43,0)

Sheet Metricas_Codigo
A1: Métricas de código con umbral bloqueante
A2: Columna «Medido» = valor de ejemplo editable (azul). «Resultado» indica si la puerta deja pasar o bloquea.
A4: Métrica | B4: Lenguaje / capa | C4: Herramienta | D4: Operador | E4: Umbral | F4: Medido (ejemplo) | G4: Resultado | H4: Puerta | I4: Fuente del umbral
A5: Cobertura de lógica de negocio | B5: PHP / Laravel | C5: PHPUnit + Xdebug/PCOV | D5: >= | E5: =Datos_Base!$C$27 | F5: 0.74 | G5: =IF(D5=">=",IF(F5>=E5,"PASA","BLOQUEA"),IF(F5<=E5,"PASA","BLOQUEA")) | H5: G2 | I5: BA Art. 24; RT-04.11
A6: Cobertura unitaria global | B6: PHP / Laravel | C6: PHPUnit + Xdebug/PCOV | D6: >= | E6: =Datos_Base!$C$28 | F6: 0.81 | G6: =IF(D6=">=",IF(F6>=E6,"PASA","BLOQUEA"),IF(F6<=E6,"PASA","BLOQUEA")) | H6: G2 | I6: SD1 §1.3; SD6 §6.2
A7: Cobertura de lógica de negocio | B7: Kotlin / Android | C7: JUnit 5 + Kover | D7: >= | E7: =Datos_Base!$C$27 | F7: 0.72 | G7: =IF(D7=">=",IF(F7>=E7,"PASA","BLOQUEA"),IF(F7<=E7,"PASA","BLOQUEA")) | H7: G2 | I7: BA Art. 24; RT-04.11
A8: Cobertura unitaria global | B8: Kotlin / Android | C8: JUnit 5 + Kover | D8: >= | E8: =Datos_Base!$C$28 | F8: 0.78 | G8: =IF(D8=">=",IF(F8>=E8,"PASA","BLOQUEA"),IF(F8<=E8,"PASA","BLOQUEA")) | H8: G2 | I8: SD1 §1.3; SD6 §6.2
A9: Cobertura unitaria global | B9: Angular / TypeScript | C9: Jest (Istanbul) | D9: >= | E9: =Datos_Base!$C$28 | F9: 0.83 | G9: =IF(D9=">=",IF(F9>=E9,"PASA","BLOQUEA"),IF(F9<=E9,"PASA","BLOQUEA")) | H9: G2 | I9: SD1 §1.3; SD6 §6.2
A10: Errores de análisis estático (nivel 8) | B10: PHP / Laravel | C10: PHPStan + Larastan | D10: <= | E10: 0 | F10: 0 | G10: =IF(D10=">=",IF(F10>=E10,"PASA","BLOQUEA"),IF(F10<=E10,"PASA","BLOQUEA")) | H10: G2 | I10: SD4 §4.2.4; SD6
A11: Infracciones de estilo | B11: PHP / Laravel | C11: Laravel Pint | D11: <= | E11: 0 | F11: 0 | G11: =IF(D11=">=",IF(F11>=E11,"PASA","BLOQUEA"),IF(F11<=E11,"PASA","BLOQUEA")) | H11: G1 | I11: SD4 §4.2.4
A12: Complejidad ciclomática máxima por método | B12: PHP / Kotlin / TS | C12: PHPMD · detekt · ESLint complexity | D12: <= | E12: 10 | F12: 9 | G12: =IF(D12=">=",IF(F12>=E12,"PASA","BLOQUEA"),IF(F12<=E12,"PASA","BLOQUEA")) | H12: G2 | I12: Supuesto LafroX (McCabe)
A13: Complejidad cognitiva máxima por método | B13: PHP / Kotlin / TS | C13: PHPMD · detekt · eslint-plugin-sonarjs | D13: <= | E13: 15 | F13: 12 | G13: =IF(D13=">=",IF(F13>=E13,"PASA","BLOQUEA"),IF(F13<=E13,"PASA","BLOQUEA")) | H13: G2 | I13: Supuesto LafroX
A14: Violaciones de dependencia entre módulos | B14: PHP / Laravel | C14: deptrac | D14: <= | E14: 0 | F14: 0 | G14: =IF(D14=">=",IF(F14>=E14,"PASA","BLOQUEA"),IF(F14<=E14,"PASA","BLOQUEA")) | H14: G2 | I14: BTT RT-02.02; SD4 §4.1
A15: Inestabilidad de los módulos núcleo (Ce/(Ca+Ce)) | B15: PHP / Laravel | C15: PhpMetrics | D15: <= | E15: 0.5 | F15: 0.42 | G15: =IF(D15=">=",IF(F15>=E15,"PASA","BLOQUEA"),IF(F15<=E15,"PASA","BLOQUEA")) | H15: G2 | I15: Supuesto LafroX (Martin)
A16: Duplicación de código | B16: Todos | C16: PHPCPD · jscpd | D16: <= | E16: 0.03 | F16: 0.021 | G16: =IF(D16=">=",IF(F16>=E16,"PASA","BLOQUEA"),IF(F16<=E16,"PASA","BLOQUEA")) | H16: G2 | I16: Supuesto LafroX
A17: Razón de deuda técnica (esfuerzo de remediación / desarrollo) | B17: Todos | C17: Registro 8.2.4 + análisis estático | D17: <= | E17: 0.05 | F17: 0.04 | G17: =IF(D17=">=",IF(F17>=E17,"PASA","BLOQUEA"),IF(F17<=E17,"PASA","BLOQUEA")) | H17: G2 | I17: BA Art. 24 (gestión de deuda); supuesto
A18: Infracciones de estilo / lint | B18: Kotlin / Android | C18: detekt + ktlint | D18: <= | E18: 0 | F18: 0 | G18: =IF(D18=">=",IF(F18>=E18,"PASA","BLOQUEA"),IF(F18<=E18,"PASA","BLOQUEA")) | H18: G1 | I18: Supuesto LafroX
A19: Errores de lint | B19: Angular / TypeScript | C19: ESLint | D19: <= | E19: 0 | F19: 0 | G19: =IF(D19=">=",IF(F19>=E19,"PASA","BLOQUEA"),IF(F19<=E19,"PASA","BLOQUEA")) | H19: G1 | I19: Supuesto LafroX
A20: Vulnerabilidades críticas o altas (SAST/SCA) | B20: Todos | C20: GitLab SAST + composer audit / npm audit | D20: <= | E20: 0 | F20: 0 | G20: =IF(D20=">=",IF(F20>=E20,"PASA","BLOQUEA"),IF(F20<=E20,"PASA","BLOQUEA")) | H20: G2 | I20: BTT RT-04.05
A21: Secretos detectados en el código | B21: Todos | C21: GitLab Secret Detection | D21: <= | E21: 0 | F21: 0 | G21: =IF(D21=">=",IF(F21>=E21,"PASA","BLOQUEA"),IF(F21<=E21,"PASA","BLOQUEA")) | H21: G1 | I21: BTT RT-04.05, RT-04.09
... A28: Revisores aprobadores por solicitud de fusión | B28: Todos | C28: GitLab (rama protegida) | D28: >= | E28: 1 | F28: 1 | G28: =IF(D28=">=",IF(F28>=E28,"PASA","BLOQUEA"),IF(F28<=E28,"PASA","BLOQUEA")) | H28: G1 | I28: BTT RT-04.03
A30: Métricas que bloquean con los valores de ejemplo | B30: =COUNTIF(G5:G28,"BLOQUEA")
A31: Leyenda de puertas | B31: G0 compromiso local · G1 solicitud de fusión · G2 integración continua · G3 promoción a QA · G4 promoción a PREPROD · G5 paso a PROD · G6 operación

Sheet Carga_Estres
A1: Prueba de carga y escalones de estrés
A2: Base: peak de septiembre del SD4. BTT RT-09.06 exige 1,5× el peak; RT-09.03 exige soportar 3× sin rediseño.
A4: Escenario | B4: Factor | C4: TPS | D4: Usuarios concurrentes (cota extrema) | E4: Usuarios concurrentes (régimen) | F4: Dispositivos de terreno | G4: Mensajes de integración / día | H4: Mensajes / s (promedio) | I4: Uso
A5: Peak de septiembre (referencia) | B5: 1 | C5: =Datos_Base!$C$7*B5 | D5: =Datos_Base!$C$11*B5 | E5: =Datos_Base!$C$10*B5 | F5: =Datos_Base!$C$13*B5 | G5: =Datos_Base!$C$15*B5 | H5: =G5/86400 | I5: Línea de comparación
A6: Prueba de carga obligatoria | B6: =Datos_Base!$C$8 | C6: =Datos_Base!$C$7*B6 | D6: =Datos_Base!$C$11*B6 | E6: =Datos_Base!$C$10*B6 | F6: =Datos_Base!$C$13*B6 | G6: =Datos_Base!$C$15*B6 | H6: =G6/86400 | I6: Criterio de salida: todos los p95 de ISO25010 cumplidos (BTT §20.1)
A7: Estrés escalón 1 | B7: 2 | C7: =Datos_Base!$C$7*B7 | D7: =Datos_Base!$C$11*B7 | E7: =Datos_Base!$C$10*B7 | F7: =Datos_Base!$C$13*B7 | G7: =Datos_Base!$C$15*B7 | H7: =G7/86400 | I7: Buscar el componente que se satura primero (RT-09.05)
A8: Estrés escalón 2 = crecimiento a 3 años | B8: =Datos_Base!$C$9 | C8: =Datos_Base!$C$7*B8 | D8: =Datos_Base!$C$11*B8 | E8: =Datos_Base!$C$10*B8 | F8: =Datos_Base!$C$13*B8 | G8: =Datos_Base!$C$15*B8 | H8: =G8/86400 | I8: Debe sostenerse sin rediseño (RT-09.03)
A9: Estrés escalón 3 (hasta el quiebre) | B9: 4 | C9: =Datos_Base!$C$7*B9 | D9: =Datos_Base!$C$11*B9 | E9: =Datos_Base!$C$10*B9 | F9: =Datos_Base!$C$13*B9 | G9: =Datos_Base!$C$15*B9 | H9: =G9/86400 | I9: Registrar el punto de quiebre y la degradación controlada (RT-09.08)
A11: Ventana de despacho 05:30–07:00 a 1,5× | B11: =Datos_Base!$C$8 | C11: =Datos_Base!$C$6*B11 | I11: Escenario adicional: sin indisponibilidad en la ventana crítica (Caso RT-10.05)
A12: Régimen normal a 1,5× | B12: =Datos_Base!$C$8 | C12: =Datos_Base!$C$5*B12 | I12: Prueba de resistencia (soak) de 8 h en turno nocturno simulado (supuesto)
A14: Comprobación: TPS de prueba = 21,99 | C14: =IF(ROUND(C6,2)=21.99,"OK","REVISAR")

Sheet Disponibilidad
A1: Presupuesto de error por nivel de servicio
A2: Indisponibilidad admisible = (1 − disponibilidad) × días × 24 × 60. SD4 Tabla 16.
A4: Nivel | B4: Disponibilidad | C4: Minutos admisibles / mes | D4: Horas admisibles / año | E4: Minutos admisibles en 05:30–07:00 | F4: Uso en el SD9
A5: Crítico | B5: =Datos_Base!$C$18 | C5: =(1-B5)*Datos_Base!$C$22*24*60 | D5: =(1-B5)*365*24 | E5: 0 | F5: Congela despliegues si se consume el 100 % (SD4 §4.2.4)
A6: Alto | B6: =Datos_Base!$C$19 | C6: =(1-B6)*Datos_Base!$C$22*24*60 | D6: =(1-B6)*365*24 | E6: n/a | F6: Seguimiento mensual en el informe de calidad
A7: Medio | B7: =Datos_Base!$C$20 | C7: =(1-B7)*Datos_Base!$C$22*24*60 | D7: =(1-B7)*365*24 | E7: n/a | F7: Seguimiento mensual en el informe de calidad
A8: Bajo | B8: =Datos_Base!$C$21 | C8: =(1-B8)*Datos_Base!$C$22*24*60 | D8: =(1-B8)*365*24 | E8: n/a | F8: Seguimiento mensual en el informe de calidad
A10: Comprobación crítico = 43,2 min | C10: =IF(ROUND(C5,1)=43.2,"OK","REVISAR")

Sheet Casos_Prueba
A1: Estimación de casos de prueba y de la batería de regresión
A2: Celdas amarillas = supuestos de LafroX que el grupo debe confirmar antes de citarlos en el SD9.
A4: Grupo | B4: Cantidad | C4: Casos por elemento | D4: Casos estimados | E4: Fuente / supuesto
A5: Requerimientos de prioridad crítica | B5: =Datos_Base!$C$37 | C5: 5 | D5: =B5*C5 | E5: Supuesto: flujo normal, 2 alternativos, 2 de error
A6: Requerimientos de prioridad alta | B6: =Datos_Base!$C$38 | C6: 3 | D6: =B6*C6 | E6: Supuesto: flujo normal, 1 alternativo, 1 de error
A7: Requerimientos de prioridad media | B7: =Datos_Base!$C$39 | C7: 2 | D7: =B7*C7 | E7: Supuesto: flujo normal y 1 de error
A8: RT en estado Cumple | B8: =Datos_Base!$C$42 | C8: 1 | D8: =B8*C8 | E8: Supuesto: un caso de verificación por RT
A9: RT en estado Cumple parcialmente | B9: =Datos_Base!$C$43 | C9: 1 | D9: =B9*C9 | E9: Supuesto: verifica la parte comprometida
A10: Integraciones (casos de contrato) | B10: =Datos_Base!$C$17 | C10: 6 | D10: =B10*C10 | E10: Supuesto: éxito, error, lentitud, duplicado, orden, versión (RT-10.08)
A11: Total de casos | D11: =SUM(D5:D10)
A12: Comprobación: crítico+alto+medio+absorbidos+no cumple = filas RF+RNF del T-12 | D12: =IF(B5+B6+B7+Datos_Base!$C$40+Datos_Base!$C$41=Datos_Base!$C$35+Datos_Base!$C$36,"OK","REVISAR")
A14: Batería de regresión
A15: Proporción automatizada | C15: 0.8 | E15: Supuesto; el resto es manual o de terreno
A16: Minutos por caso automatizado (paralelismo incluido) | C16: 0.5 | E16: Supuesto
A17: Minutos por caso manual | C17: 15 | E17: Supuesto
A18: Ciclos de regresión completos por iteración | C18: 1 | E18: Antes de cada promoción a PREPROD (BTT §20.1)
A19: Ejecutores paralelos de la regresión | C19: 2 | E19: Supuesto; GitLab CI con dos ejecutores
A20: Casos automatizados | D20: =ROUND(D11*C15,0)
A21: Duración de la regresión automatizada en un ejecutor (h) | D21: =D20*C16/60
A22: Duración con ejecutores paralelos (h) | D22: =D21/C19
A23: Casos manuales | D23: =D11-D20
A24: HH manuales por ciclo | D24: =D23*C17/60*C18
A25: ¿La regresión automatizada cabe en una noche (≤ 8 h)? | D25: =IF(D22<=8,"Sí","No")

Sheet HH_Calidad
A1: Paquetes de calidad del T-15 distribuidos por mes
A2: HH uniformes entre mes inicial y final del T-15 §4.2. Categoría COQ según PMBOK cap. 8.
A4: Paquete | B4: Nombre | C4: Rol | D4: Mes ini | E4: Mes fin | F4: HH | G4: Categoría COQ | H4: 1 | I4: 2 | J4: 3 | K4: 4 | L4: 5 | M4: 6 | N4: 7 | O4: 8 | P4: 9 | Q4: 10 | R4: 11 | S4: 12 | T4: 13 | U4: 14 | V4: 15 | W4: 16 | X4: 17 | Y4: 18 | Z4: 19 | AA4: 20 | AB4: 21 | AC4: 22 | AD4: 23 | AE4: 24 | AF4: 25 | AG4: 26 | AH4: 27 | AI4: 28 | AJ4: 29 | AK4: 30 | AL4: 31 | AM4: 32 | AN4: 33 | AO4: 34 | AP4: 35 | AQ4: 36 | AR4: 37 | AS4: 38 | AT4: 39 | AU4: 40 | AV4: 41 | AW4: 42 | AX4: 43 | AY4: 44 | AZ4: 45 | BA4: 46 | BB4: 47 | BC4: 48 | BD4: 49 | BE4: 50 | BF4: 51 | BG4: 52 | BH4: 53 | BI4: 54 | BJ4: 55 | BK4: 56 | BL4: Suma meses
A5: 1.2.4 | B5: Matriz de trazabilidad (H1) | C5: CAL | D5: 2 | E5: 2 | F5: 80 | G5: Prevención | H5: =IF(AND(H$4*1>=$D5,H$4*1<=$E5),$F5/($E5-$D5+1),0) | I5: =IF(AND(I$4*1>=$D5,I$4*1<=$E5),$F5/($E5-$D5+1),0) | J5: =IF(AND(J$4*1>=$D5,J$4*1<=$E5),$F5/($E5-$D5+1),0) | K5: =IF(AND(K$4*1>=$D5,K$4*1<=$E5),$F5/($E5-$D5+1),0) | L5: =IF(AND(L$4*1>=$D5,L$4*1<=$E5),$F5/($E5-$D5+1),0) | M5: =IF(AND(M$4*1>=$D5,M$4*1<=$E5),$F5/($E5-$D5+1),0) | N5: =IF(AND(N$4*1>=$D5,N$4*1<=$E5),$F5/($E5-$D5+1),0) | O5: =IF(AND(O$4*1>=$D5,O$4*1<=$E5),$F5/($E5-$D5+1),0) | ... BK5: =IF(AND(BK$4*1>=$D5,BK$4*1<=$E5),$F5/($E5-$D5+1),0) | BL5: =SUM(H5:BK5)
A6: 1.5.1 | B6: Plan de calidad y plan de pruebas | C6: CAL | D6: 2 | E6: 2 | F6: 80 | G6: Prevención | H6: =IF(AND(H$4*1>=$D6,H$4*1<=$E6),$F6/($E6-$D6+1),0) | I6: =IF(AND(I$4*1>=$D6,I$4*1<=$E6),$F6/($E6-$D6+1),0) | J6: =IF(AND(J$4*1>=$D6,J$4*1<=$E6),$F6/($E6-$D6+1),0) | K6: =IF(AND(K$4*1>=$D6,K$4*1<=$E6),$F6/($E6-$D6+1),0) | L6: =IF(AND(L$4*1>=$D6,L$4*1<=$E6),$F6/($E6-$D6+1),0) | M6: =IF(AND(M$4*1>=$D6,M$4*1<=$E6),$F6/($E6-$D6+1),0) | N6: =IF(AND(N$4*1>=$D6,N$4*1<=$E6),$F6/($E6-$D6+1),0) | O6: =IF(AND(O$4*1>=$D6,O$4*1<=$E6),$F6/($E6-$D6+1),0) | ... BK6: =IF(AND(BK$4*1>=$D6,BK$4*1<=$E6),$F6/($E6-$D6+1),0) | BL6: =SUM(H6:BK6)
A7: 1.5.2 | B7: Puertas de calidad automáticas | C7: CAL | D7: 6 | E7: 20 | F7: 80 | G7: Prevención | H7: =IF(AND(H$4*1>=$D7,H$4*1<=$E7),$F7/($E7-$D7+1),0) | I7: =IF(AND(I$4*1>=$D7,I$4*1<=$E7),$F7/($E7-$D7+1),0) | J7: =IF(AND(J$4*1>=$D7,J$4*1<=$E7),$F7/($E7-$D7+1),0) | K7: =IF(AND(K$4*1>=$D7,K$4*1<=$E7),$F7/($E7-$D7+1),0) | L7: =IF(AND(L$4*1>=$D7,L$4*1<=$E7),$F7/($E7-$D7+1),0) | M7: =IF(AND(M$4*1>=$D7,M$4*1<=$E7),$F7/($E7-$D7+1),0) | N7: =IF(AND(N$4*1>=$D7,N$4*1<=$E7),$F7/($E7-$D7+1),0) | O7: =IF(AND(O$4*1>=$D7,O$4*1<=$E7),$F7/($E7-$D7+1),0) | ... BK7: =IF(AND(BK$4*1>=$D7,BK$4*1<=$E7),$F7/($E7-$D7+1),0) | BL7: =SUM(H7:BK7)
A8: 2.6.1 | B8: Investigación de usuarios | C8: IMP | D8: 2 | E8: 2 | F8: 240 | G8: Prevención | H8: =IF(AND(H$4*1>=$D8,H$4*1<=$E8),$F8/($E8-$D8+1),0) | I8: =IF(AND(I$4*1>=$D8,I$4*1<=$E8),$F8/($E8-$D8+1),0) | J8: =IF(AND(J$4*1>=$D8,J$4*1<=$E8),$F8/($E8-$D8+1),0) | K8: =IF(AND(K$4*1>=$D8,K$4*1<=$E8),$F8/($E8-$D8+1),0) | L8: =IF(AND(L$4*1>=$D8,L$4*1<=$E8),$F8/($E8-$D8+1),0) | M8: =IF(AND(M$4*1>=$D8,M$4*1<=$E8),$F8/($E8-$D8+1),0) | N8: =IF(AND(N$4*1>=$D8,N$4*1<=$E8),$F8/($E8-$D8+1),0) | O8: =IF(AND(O$4*1>=$D8,O$4*1<=$E8),$F8/($E8-$D8+1),0) | ... BK8: =IF(AND(BK$4*1>=$D8,BK$4*1<=$E8),$F8/($E8-$D8+1),0) | BL8: =SUM(H8:BK8)
A9: 2.6.2 | B9: Prototipos y pruebas de usabilidad | C9: IMP | D9: 3 | E9: 3 | F9: 240 | G9: Prevención | H9: =IF(AND(H$4*1>=$D9,H$4*1<=$E9),$F9/($E9-$D9+1),0) | I9: =IF(AND(I$4*1>=$D9,I$4*1<=$E9),$F9/($E9-$D9+1),0) | J9: =IF(AND(J$4*1>=$D9,J$4*1<=$E9),$F9/($E9-$D9+1),0) | K9: =IF(AND(K$4*1>=$D9,K$4*1<=$E9),$F9/($E9-$D9+1),0) | L9: =IF(AND(L$4*1>=$D9,L$4*1<=$E9),$F9/($E9-$D9+1),0) | M9: =IF(AND(M$4*1>=$D9,M$4*1<=$E9),$F9/($E9-$D9+1),0) | N9: =IF(AND(N$4*1>=$D9,N$4*1<=$E9),$F9/($E9-$D9+1),0) | O9: =IF(AND(O$4*1>=$D9,O$4*1<=$E9),$F9/($E9-$D9+1),0) | ... BK9: =IF(AND(BK$4*1>=$D9,BK$4*1<=$E9),$F9/($E9-$D9+1),0) | BL9: =SUM(H9:BK9)
A10: 2.6.3 | B10: Indicadores de usabilidad | C10: IMP | D10: 4 | E10: 4 | F10: 240 | G10: Prevención | H10: =IF(AND(H$4*1>=$D10,H$4*1<=$E10),$F10/($E10-$D10+1),0) | I10: =IF(AND(I$4*1>=$D10,I$4*1<=$E10),$F10/($E10-$D10+1),0) | J10: =IF(AND(J$4*1>=$D10,J$4*1<=$E10),$F10/($E10-$D10+1),0) | K10: =IF(AND(K$4*1>=$D10,K$4*1<=$E10),$F10/($E10-$D10+1),0) | L10: =IF(AND(L$4*1>=$D10,L$4*1<=$E10),$F10/($E10-$D10+1),0) | M10: =IF(AND(M$4*1>=$D10,M$4*1<=$E10),$F10/($E10-$D10+1),0) | N10: =IF(AND(N$4*1>=$D10,N$4*1<=$E10),$F10/($E10-$D10+1),0) | O10: =IF(AND(O$4*1>=$D10,O$4*1<=$E10),$F10/($E10-$D10+1),0) | ... BK10: =IF(AND(BK$4*1>=$D10,BK$4*1<=$E10),$F10/($E10-$D10+1),0) | BL10: =SUM(H10:BK10)
A11: 3.8.1 | B11: Integración, regresión e idempotencia E1 (H4) | C11: CAL | D11: 9 | E11: 9 | F11: 160 | G11: Evaluación | H11: =IF(AND(H$4*1>=$D11,H$4*1<=$E11),$F11/($E11-$D11+1),0) | I11: =IF(AND(I$4*1>=$D11,I$4*1<=$E11),$F11/($E11-$D11+1),0) | J11: =IF(AND(J$4*1>=$D11,J$4*1<=$E11),$F11/($E11-$D11+1),0) | K11: =IF(AND(K$4*1>=$D11,K$4*1<=$E11),$F11/($E11-$D11+1),0) | L11: =IF(AND(L$4*1>=$D11,L$4*1<=$E11),$F11/($E11-$D11+1),0) | M11: =IF(AND(M$4*1>=$D11,M$4*1<=$E11),$F11/($E11-$D11+1),0) | N11: =IF(AND(N$4*1>=$D11,N$4*1<=$E11),$F11/($E11-$D11+1),0) | O11: =IF(AND(O$4*1>=$D11,O$4*1<=$E11),$F11/($E11-$D11+1),0) | ... BK11: =IF(AND(BK$4*1>=$D11,BK$4*1<=$E11),$F11/($E11-$D11+1),0) | BL11: =SUM(H11:BK11)
A12: 3.8.2 | B12: Aceptación y accesibilidad E1 | C12: CAL | D12: 9 | E12: 10 | F12: 320 | G12: Evaluación | H12: =IF(AND(H$4*1>=$D12,H$4*1<=$E12),$F12/($E12-$D12+1),0) | I12: =IF(AND(I$4*1>=$D12,I$4*1<=$E12),$F12/($E12-$D12+1),0) | J12: =IF(AND(J$4*1>=$D12,J$4*1<=$E12),$F12/($E12-$D12+1),0) | K12: =IF(AND(K$4*1>=$D12,K$4*1<=$E12),$F12/($E12-$D12+1),0) | L12: =IF(AND(L$4*1>=$D12,L$4*1<=$E12),$F12/($E12-$D12+1),0) | M12: =IF(AND(M$4*1>=$D12,M$4*1<=$E12),$F12/($E12-$D12+1),0) | N12: =IF(AND(N$4*1>=$D12,N$4*1<=$E12),$F12/($E12-$D12+1),0) | O12: =IF(AND(O$4*1>=$D12,O$4*1<=$E12),$F12/($E12-$D12+1),0) | ... BK12: =IF(AND(BK$4*1>=$D12,BK$4*1<=$E12),$F12/($E12-$D12+1),0) | BL12: =SUM(H12:BK12)
A13: 3.8.3 | B13: Perfil operacional: sin señal, sin enlace, −22 °C | C13: CAL | D13: 9 | E13: 10 | F13: 320 | G13: Evaluación | H13: =IF(AND(H$4*1>=$D13,H$4*1<=$E13),$F13/($E13-$D13+1),0) | I13: =IF(AND(I$4*1>=$D13,I$4*1<=$E13),$F13/($E13-$D13+1),0) | J13: =IF(AND(J$4*1>=$D13,J$4*1<=$E13),$F13/($E13-$D13+1),0) | K13: =IF(AND(K$4*1>=$D13,K$4*1<=$E13),$F13/($E13-$D13+1),0) | L13: =IF(AND(L$4*1>=$D13,L$4*1<=$E13),$F13/($E13-$D13+1),0) | M13: =IF(AND(M$4*1>=$D13,M$4*1<=$E13),$F13/($E13-$D13+1),0) | N13: =IF(AND(N$4*1>=$D13,N$4*1<=$E13),$F13/($E13-$D13+1),0) | O13: =IF(AND(O$4*1>=$D13,O$4*1<=$E13),$F13/($E13-$D13+1),0) | ... BK13: =IF(AND(BK$4*1>=$D13,BK$4*1<=$E13),$F13/($E13-$D13+1),0) | BL13: =SUM(H13:BK13)
A14: 3.8.4 | B14: Carga 1,5× peak y resiliencia E1 | C14: CAL | D14: 9 | E14: 10 | F14: 320 | G14: Evaluación | H14: =IF(AND(H$4*1>=$D14,H$4*1<=$E14),$F14/($E14-$D14+1),0) | I14: =IF(AND(I$4*1>=$D14,I$4*1<=$E14),$F14/($E14-$D14+1),0) | J14: =IF(AND(J$4*1>=$D14,J$4*1<=$E14),$F14/($E14-$D14+1),0) | K14: =IF(AND(K$4*1>=$D14,K$4*1<=$E14),$F14/($E14-$D14+1),0) | L14: =IF(AND(L$4*1>=$D14,L$4*1<=$E14),$F14/($E14-$D14+1),0) | M14: =IF(AND(M$4*1>=$D14,M$4*1<=$E14),$F14/($E14-$D14+1),0) | N14: =IF(AND(N$4*1>=$D14,N$4*1<=$E14),$F14/($E14-$D14+1),0) | O14: =IF(AND(O$4*1>=$D14,O$4*1<=$E14),$F14/($E14-$D14+1),0) | ... BK14: =IF(AND(BK$4*1>=$D14,BK$4*1<=$E14),$F14/($E14-$D14+1),0) | BL14: =SUM(H14:BK14)
A15: 3.8.5 | B15: Recuperación ante desastres E1 | C15: CAL | D15: 9 | E15: 10 | F15: 320 | G15: Evaluación | H15: =IF(AND(H$4*1>=$D15,H$4*1<=$E15),$F15/($E15-$D15+1),0) | I15: =IF(AND(I$4*1>=$D15,I$4*1<=$E15),$F15/($E15-$D15+1),0) | J15: =IF(AND(J$4*1>=$D15,J$4*1<=$E15),$F15/($E15-$D15+1),0) | K15: =IF(AND(K$4*1>=$D15,K$4*1<=$E15),$F15/($E15-$D15+1),0) | L15: =IF(AND(L$4*1>=$D15,L$4*1<=$E15),$F15/($E15-$D15+1),0) | M15: =IF(AND(M$4*1>=$D15,M$4*1<=$E15),$F15/($E15-$D15+1),0) | N15: =IF(AND(N$4*1>=$D15,N$4*1<=$E15),$F15/($E15-$D15+1),0) | O15: =IF(AND(O$4*1>=$D15,O$4*1<=$E15),$F15/($E15-$D15+1),0) | ... BK15: =IF(AND(BK$4*1>=$D15,BK$4*1<=$E15),$F15/($E15-$D15+1),0) | BL15: =SUM(H15:BK15)
A16: 3.8.6 | B16: Seguridad ofensiva E1 (tercero) | C16: SEG | D16: 9 | E16: 9 | F16: 160 | G16: Evaluación | H16: =IF(AND(H$4*1>=$D16,H$4*1<=$E16),$F16/($E16-$D16+1),0) | I16: =IF(AND(I$4*1>=$D16,I$4*1<=$E16),$F16/($E16-$D16+1),0) | J16: =IF(AND(J$4*1>=$D16,J$4*1<=$E16),$F16/($E16-$D16+1),0) | K16: =IF(AND(K$4*1>=$D16,K$4*1<=$E16),$F16/($E16-$D16+1),0) | L16: =IF(AND(L$4*1>=$D16,L$4*1<=$E16),$F16/($E16-$D16+1),0) | M16: =IF(AND(M$4*1>=$D16,M$4*1<=$E16),$F16/($E16-$D16+1),0) | N16: =IF(AND(N$4*1>=$D16,N$4*1<=$E16),$F16/($E16-$D16+1),0) | O16: =IF(AND(O$4*1>=$D16,O$4*1<=$E16),$F16/($E16-$D16+1),0) | ... BK16: =IF(AND(BK$4*1>=$D16,BK$4*1<=$E16),$F16/($E16-$D16+1),0) | BL16: =SUM(H16:BK16)
... A37: 8.3.1 | B37: INN-02 mantenimiento de escenarios de regresión | C37: CAL | D37: 21 | E37: 56 | F37: 576 | G37: Evaluación | H37: =IF(AND(H$4*1>=$D37,H$4*1<=$E37),$F37/($E37-$D37+1),0) | I37: =IF(AND(I$4*1>=$D37,I$4*1<=$E37),$F37/($E37-$D37+1),0) | J37: =IF(AND(J$4*1>=$D37,J$4*1<=$E37),$F37/($E37-$D37+1),0) | K37: =IF(AND(K$4*1>=$D37,K$4*1<=$E37),$F37/($E37-$D37+1),0) | L37: =IF(AND(L$4*1>=$D37,L$4*1<=$E37),$F37/($E37-$D37+1),0) | M37: =IF(AND(M$4*1>=$D37,M$4*1<=$E37),$F37/($E37-$D37+1),0) | N37: =IF(AND(N$4*1>=$D37,N$4*1<=$E37),$F37/($E37-$D37+1),0) | O37: =IF(AND(O$4*1>=$D37,O$4*1<=$E37),$F37/($E37-$D37+1),0) | ... BK37: =IF(AND(BK$4*1>=$D37,BK$4*1<=$E37),$F37/($E37-$D37+1),0) | BL37: =SUM(H37:BK37)
A38: Total | F38: =SUM(F5:F37) | H38: =SUM(H5:H37) | I38: =SUM(I5:I37) | J38: =SUM(J5:J37) | K38: =SUM(K5:K37) | L38: =SUM(L5:L37) | M38: =SUM(M5:M37) | N38: =SUM(N5:N37) | O38: =SUM(O5:O37) | ... BL38: =SUM(BL5:BL37)
A39: HH CAL | H39: =SUMIF($C$5:$C$37,"CAL",H5:H37) | I39: =SUMIF($C$5:$C$37,"CAL",I5:I37) | J39: =SUMIF($C$5:$C$37,"CAL",J5:J37) | K39: =SUMIF($C$5:$C$37,"CAL",K5:K37) | L39: =SUMIF($C$5:$C$37,"CAL",L5:L37) | M39: =SUMIF($C$5:$C$37,"CAL",M5:M37) | N39: =SUMIF($C$5:$C$37,"CAL",N5:N37) | O39: =SUMIF($C$5:$C$37,"CAL",O5:O37) | ... BK39: =SUMIF($C$5:$C$37,"CAL",BK5:BK37)
A40: Dotación CAL (T-15) | B40: Personas equivalentes CAL por mes, T-15 tabla mensual | H40: 0 | I40: 3 | J40: 2 | K40: 1 | L40: 2 | M40: 1 | N40: 1 | O40: 1 | P40: 8 | Q40: 6 | R40: 1 | S40: 1 | T40: 2 | U40: 2 | V40: 2 | W40: 10 | X40: 3 | Y40: 2 | Z40: 2 | AA40: 1 | AB40: 1 | AC40: 1 | AD40: 1 | AE40: 1 | AF40: 1 | AG40: 1 | AH40: 1 | AI40: 1 | AJ40: 1 | AK40: 1 | AL40: 1 | AM40: 1 | AN40: 1 | AO40: 1 | AP40: 1 | AQ40: 1 | AR40: 1 | AS40: 1 | AT40: 1 | AU40: 1 | AV40: 1 | AW40: 1 | AX40: 1 | AY40: 1 | AZ40: 1 | BA40: 1 | BB40: 1 | BC40: 1 | BD40: 1 | BE40: 1 | BF40: 1 | BG40: 1 | BH40: 1 | BI40: 1 | BJ40: 1 | BK40: 1
A41: Capacidad CAL | B41: Personas × días hábiles × horas | H41: =H40*Datos_Base!$C$52*Datos_Base!$C$51 | I41: =I40*Datos_Base!$C$52*Datos_Base!$C$51 | J41: =J40*Datos_Base!$C$52*Datos_Base!$C$51 | K41: =K40*Datos_Base!$C$52*Datos_Base!$C$51 | L41: =L40*Datos_Base!$C$52*Datos_Base!$C$51 | M41: =M40*Datos_Base!$C$52*Datos_Base!$C$51 | N41: =N40*Datos_Base!$C$52*Datos_Base!$C$51 | O41: =O40*Datos_Base!$C$52*Datos_Base!$C$51 | ... BK41: =BK40*Datos_Base!$C$52*Datos_Base!$C$51
A42: Evaluadores | B42: Capacidad máxima de evaluadores subcontratados (meses 9–12 y 16–18) | H42: 0 | I42: 0 | J42: 0 | K42: 0 | L42: 0 | M42: 0 | N42: 0 | O42: 0 | P42: =Datos_Base!$C$50*Datos_Base!$C$52*Datos_Base!$C$51 | Q42: =Datos_Base!$C$50*Datos_Base!$C$52*Datos_Base!$C$51 | R42: =Datos_Base!$C$50*Datos_Base!$C$52*Datos_Base!$C$51 | S42: =Datos_Base!$C$50*Datos_Base!$C$52*Datos_Base!$C$51 | T42: 0 | U42: 0 | V42: 0 | W42: =Datos_Base!$C$50*Datos_Base!$C$52*Datos_Base!$C$51 | X42: =Datos_Base!$C$50*Datos_Base!$C$52*Datos_Base!$C$51 | Y42: =Datos_Base!$C$50*Datos_Base!$C$52*Datos_Base!$C$51 | Z42: 0 | AA42: 0 | AB42: 0 | AC42: 0 | AD42: 0 | AE42: 0 | AF42: 0 | AG42: 0 | AH42: 0 | AI42: 0 | AJ42: 0 | AK42: 0 | AL42: 0 | AM42: 0 | AN42: 0 | AO42: 0 | AP42: 0 | AQ42: 0 | AR42: 0 | AS42: 0 | AT42: 0 | AU42: 0 | AV42: 0 | AW42: 0 | AX42: 0 | AY42: 0 | AZ42: 0 | BA42: 0 | BB42: 0 | BC42: 0 | BD42: 0 | BE42: 0 | BF42: 0 | BG42: 0 | BH42: 0 | BI42: 0 | BJ42: 0 | BK42: 0
A45: Resumen
B46: HH de paquetes CAL (debe ser 4.656) | F46: =SUMIF(C5:C37,"CAL",F5:F37)
B47: HH de paquetes de pruebas SEG | F47: =SUMIF(C5:C37,"SEG",F5:F37)
B48: HH de paquetes de pruebas SRE | F48: =SUMIF(C5:C37,"SRE",F5:F37)
B49: HH de paquetes IMP ligados a calidad | F49: =SUMIF(C5:C37,"IMP",F5:F37)
B50: HH de deuda técnica (DES) | F50: =SUMIF(C5:C37,"DES",F5:F37)
B51: HH totales ligadas a calidad | F51: =F38
B52: Participación en las HH del proyecto | F52: =F38/Datos_Base!$C$47
B53: Reserva protegida E1 de CAL (meses 13–20) | F53: =Datos_Base!$C$49
B54: Comprobación CAL = 4.656 | F54: =IF(F46=4656,"OK","REVISAR")
B55: Comprobación suma por meses = suma de paquetes | F55: =IF(ROUND(BL38,2)=ROUND(F38,2),"OK","REVISAR")
B56: Meses en que las HH CAL superan la capacidad CAL | F56: =SUMPRODUCT(--(H39:BK39>H41:BK41))
B57: Meses con evaluadores y sin paquete de pruebas V | F57: =SUMPRODUCT(--(H42:BK42>0),--(H38:BK38<=200))

Sheet Calendario
A1: Calendario de pruebas (T-13) — meses 1 a 56
A2: 1 = la prueba ocurre en el mes. Columnas rojas = congelamiento (1–25 sep. y diciembre, Caso RT-10.05). «Toca PROD» = la prueba interviene producción.
A4: Fecha del mes | D4: =DATE(2027,1+D6,1) | E4: =DATE(2027,1+E6,1) | F4: =DATE(2027,1+F6,1) | G4: =DATE(2027,1+G6,1) | H4: =DATE(2027,1+H6,1) | I4: =DATE(2027,1+I6,1) | J4: =DATE(2027,1+J6,1) | K4: =DATE(2027,1+K6,1) | ... BG4: =DATE(2027,1+BG6,1)
A5: Congelamiento | D5: =IF(OR(MONTH(D4)=9,MONTH(D4)=12),"CONG","") | E5: =IF(OR(MONTH(E4)=9,MONTH(E4)=12),"CONG","") | F5: =IF(OR(MONTH(F4)=9,MONTH(F4)=12),"CONG","") | G5: =IF(OR(MONTH(G4)=9,MONTH(G4)=12),"CONG","") | H5: =IF(OR(MONTH(H4)=9,MONTH(H4)=12),"CONG","") | I5: =IF(OR(MONTH(I4)=9,MONTH(I4)=12),"CONG","") | J5: =IF(OR(MONTH(J4)=9,MONTH(J4)=12),"CONG","") | K5: =IF(OR(MONTH(K4)=9,MONTH(K4)=12),"CONG","") | ... BG5: =IF(OR(MONTH(BG4)=9,MONTH(BG4)=12),"CONG","")
A6: Tipo de prueba | B6: Paquete EDT | C6: Toca PROD | D6: 1 | E6: 2 | F6: 3 | G6: 4 | H6: 5 | I6: 6 | J6: 7 | K6: 8 | L6: 9 | M6: 10 | N6: 11 | O6: 12 | P6: 13 | Q6: 14 | R6: 15 | S6: 16 | T6: 17 | U6: 18 | V6: 19 | W6: 20 | X6: 21 | Y6: 22 | Z6: 23 | AA6: 24 | AB6: 25 | AC6: 26 | AD6: 27 | AE6: 28 | AF6: 29 | AG6: 30 | AH6: 31 | AI6: 32 | AJ6: 33 | AK6: 34 | AL6: 35 | AM6: 36 | AN6: 37 | AO6: 38 | AP6: 39 | AQ6: 40 | AR6: 41 | AS6: 42 | AT6: 43 | AU6: 44 | AV6: 45 | AW6: 46 | AX6: 47 | AY6: 48 | AZ6: 49 | BA6: 50 | BB6: 51 | BC6: 52 | BD6: 53 | BE6: 54 | BF6: 55 | BG6: 56 | BH6: Total | BI6: Conflictos con congelamiento
A7: Usabilidad con usuarios reales | B7: 2.6.2 | C7: No | F7: 1 | BH7: =SUM(D7:BG7) | BI7: =IF(C7="Sí",SUMPRODUCT((D7:BG7=1)*(D$5:BG$5="CONG")),0)
A8: Integración y regresión | B8: 3.8.1 · 3.9.1 | C8: No | L8: 1 | S8: 1 | BH8: =SUM(D8:BG8) | BI8: =IF(C8="Sí",SUMPRODUCT((D8:BG8=1)*(D$5:BG$5="CONG")),0)
A9: Aceptación de usuario y accesibilidad | B9: 3.8.2 · 3.9.2 | C9: No | L9: 1 | M9: 1 | S9: 1 | BH9: =SUM(D9:BG9) | BI9: =IF(C9="Sí",SUMPRODUCT((D9:BG9=1)*(D$5:BG$5="CONG")),0)
A10: Perfil operacional (14 h sin señal, 24 h sin enlace, −22 °C) | B10: 3.8.3 | C10: No | L10: 1 | M10: 1 | BH10: =SUM(D10:BG10) | BI10: =IF(C10="Sí",SUMPRODUCT((D10:BG10=1)*(D$5:BG$5="CONG")),0)
A11: Carga a 1,5× y estrés | B11: 3.8.4 · 3.9.3 · 8.2 | C11: No | L11: 1 | M11: 1 | S11: 1 | AH11: 1 | AT11: 1 | BF11: 1 | BH11: =SUM(D11:BG11) | BI11: =IF(C11="Sí",SUMPRODUCT((D11:BG11=1)*(D$5:BG$5="CONG")),0)
A12: Resiliencia (inyección de fallas) | B12: 3.8.4 · 3.9.3 · 8.2.2 | C12: Sí | L12: 1 | M12: 1 | S12: 1 | AC12: 1 | AJ12: 1 | AO12: 1 | AV12: 1 | BA12: 1 | BF12: 1 | BH12: =SUM(D12:BG12) | BI12: =IF(C12="Sí",SUMPRODUCT((D12:BG12=1)*(D$5:BG$5="CONG")),0)
A13: Recuperación ante desastres (conmutación real) | B13: 3.8.5 · 3.9.4 · 8.1.3 | C13: Sí | M13: 1 | S13: 1 | AD13: 1 | AK13: 1 | AP13: 1 | AW13: 1 | BB13: 1 | BE13: 1 | BH13: =SUM(D13:BG13) | BI13: =IF(C13="Sí",SUMPRODUCT((D13:BG13=1)*(D$5:BG$5="CONG")),0)
A14: Seguridad ofensiva por tercero | B14: 3.8.6 · 3.9.5 · 8.2.2 | C14: Sí | L14: 1 | S14: 1 | AE14: 1 | AQ14: 1 | BC14: 1 | BH14: =SUM(D14:BG14) | BI14: =IF(C14="Sí",SUMPRODUCT((D14:BG14=1)*(D$5:BG$5="CONG")),0)
A15: Despliegue sin interrupción en PREPROD | B15: 3.8.8 · 3.9.7 | C15: No | L15: 1 | M15: 1 | S15: 1 | BH15: =SUM(D15:BG15) | BI15: =IF(C15="Sí",SUMPRODUCT((D15:BG15=1)*(D$5:BG$5="CONG")),0)
A16: Ensayos y corte de migración | B16: 3.7.2 · 3.7.3 · 3.7.5 | C16: No | L16: 1 | M16: 1 | O16: 1 | BH16: =SUM(D16:BG16) | BI16: =IF(C16="Sí",SUMPRODUCT((D16:BG16=1)*(D$5:BG$5="CONG")),0)
A17: Ensayo de reversión | B17: 4.1.2 | C17: No | N17: 1 | BH17: =SUM(D17:BG17) | BI17: =IF(C17="Sí",SUMPRODUCT((D17:BG17=1)*(D$5:BG$5="CONG")),0)
A18: Restauración de respaldos (muestra) | B18: 8.1.6 | C18: No | X18: 1 | Y18: 1 | Z18: 1 | AA18: 1 | AB18: 1 | AC18: 1 | AD18: 1 | AE18: 1 | AF18: 1 | AG18: 1 | AH18: 1 | AI18: 1 | AJ18: 1 | AK18: 1 | AL18: 1 | AM18: 1 | AN18: 1 | AO18: 1 | AP18: 1 | AQ18: 1 | AR18: 1 | AS18: 1 | AT18: 1 | AU18: 1 | AV18: 1 | AW18: 1 | AX18: 1 | AY18: 1 | AZ18: 1 | BA18: 1 | BB18: 1 | BC18: 1 | BD18: 1 | BE18: 1 | BF18: 1 | BG18: 1 | BH18: =SUM(D18:BG18) | BI18: =IF(C18="Sí",SUMPRODUCT((D18:BG18=1)*(D$5:BG$5="CONG")),0)
A19: Hitos E-25 | E19: H1 | G19: H2 | I19: H3 | M19: H4 | O19: H5 | P19: H6 | Q19: H8 | S19: H7 | T19: H9 | U19: H10 | V19: H11 | X19: H12
A21: Conteos en Operación (meses 21–56)
A22: Pruebas DR en Operación (debe ser 6) | B22: =SUM(X13:BG13)
A23: Restauraciones en Operación (debe ser 36) | B23: =SUM(X18:BG18)
A24: Pentest anuales en Operación (debe ser 3) | B24: =SUM(X14:BG14)
A25: Resiliencia semestral en Operación (debe ser 6) | B25: =SUM(X12:BG12)
A26: Conflictos totales con congelamiento (debe ser 0) | B26: =SUM(BI7:BI18)
A27: Nota | B27: Los meses de Operación son propuesta de LafroX (evitan septiembre, diciembre y los 3 primeros días hábiles). Validarlos con el SD10/SD11 y con la Contraparte.

Sheet Aceptacion_T17
A1: Protocolo de aceptación por hito (T-17) — plazos del Art. 18.3
A2: Fecha límite = acta − 10 días hábiles (T-15 Tabla 5.2). Holgura con observación = reserva − subsanación. Negativo = requiere revisión anticipada del borrador.
A4: Hito | B4: Mes E-25 | C4: Entregable que gatilla el hito | D4: Paquete | E4: Entrega programada | F4: Acta sin observaciones (entrega + revisión) | G4: Acta con observaciones (+ subsanación) | H4: Reserva T-15 (días háb.) | I4: Holgura con observación (días háb.) | J4: Control
A5: H1 | B5: 2 | C5: Línea base de alcance y matriz de trazabilidad | D5: 1.2.1, 1.2.4 | E5: =DATE(2027,3,9) | F5: =WORKDAY(E5,Datos_Base!$C$33) | G5: =WORKDAY(E5,Datos_Base!$C$33+Datos_Base!$C$34) | H5: 6 | I5: =H5-Datos_Base!$C$34 | J5: =IF(I5<0,"Revisión anticipada del borrador con la Contraparte","Reserva absorbe la subsanación")
A6: H2 | B6: 4 | C6: Arquitectura, plan de seguridad y modelo de datos | D6: 2.1, 2.2, 2.4.1 | E6: =DATE(2027,4,29) | F6: =WORKDAY(E6,Datos_Base!$C$33) | G6: =WORKDAY(E6,Datos_Base!$C$33+Datos_Base!$C$34) | H6: 12 | I6: =H6-Datos_Base!$C$34 | J6: =IF(I6<0,"Revisión anticipada del borrador con la Contraparte","Reserva absorbe la subsanación")
A7: H3 | B7: 6 | C7: Infraestructura híbrida y 4 ambientes con observabilidad | D7: 3.1, 6.x | E7: =DATE(2027,6,21) | F7: =WORKDAY(E7,Datos_Base!$C$33) | G7: =WORKDAY(E7,Datos_Base!$C$33+Datos_Base!$C$34) | H7: 19 | I7: =H7-Datos_Base!$C$34 | J7: =IF(I7<0,"Revisión anticipada del borrador con la Contraparte","Reserva absorbe la subsanación")
A8: H4 | B8: 10 | C8: Software E1 para pruebas, QA superado y evidencia de cobertura | D8: 3.8.1 | E8: =DATE(2027,10,20) | F8: =WORKDAY(E8,Datos_Base!$C$33) | G8: =WORKDAY(E8,Datos_Base!$C$33+Datos_Base!$C$34) | H8: 19 | I8: =H8-Datos_Base!$C$34 | J8: =IF(I8<0,"Revisión anticipada del borrador con la Contraparte","Reserva absorbe la subsanación")
A9: H5 | B9: 12 | C9: Certificación E1: aceptación, carga, resiliencia, seguridad | D9: 3.8.7 | E9: =DATE(2027,11,29) | F9: =WORKDAY(E9,Datos_Base!$C$33) | G9: =WORKDAY(E9,Datos_Base!$C$33+Datos_Base!$C$34) | H9: 35 | I9: =H9-Datos_Base!$C$34 | J9: =IF(I9<0,"Revisión anticipada del borrador con la Contraparte","Reserva absorbe la subsanación")
A10: H6 | B10: 13 | C10: Inicio marcha blanca E1, reversión activa, usuarios capacitados | D10: 4.2, 7.3.1 | E10: Fecha contractual fija | F10: n/a | G10: n/a | H10: n/a | I10: n/a | J10: Plan de reversión activo y usuarios certificados
A11: H7 | B11: 16 | C11: Paso a producción E1 y cierre de marcha blanca (Art. 17.3) | D11: 4.2 | E11: Fecha contractual fija | F11: n/a | G11: n/a | H11: n/a | I11: n/a | J11: Condiciones copulativas del Art. 17.3 + acta
A12: H8 | B12: 14 | C12: Línea base de alcance y diseño detallado E2 | D12: 1.2.5, 2.4.2 | E12: =DATE(2028,3,13) | F12: =WORKDAY(E12,Datos_Base!$C$33) | G12: =WORKDAY(E12,Datos_Base!$C$33+Datos_Base!$C$34) | H12: 4 | I12: =H12-Datos_Base!$C$34 | J12: =IF(I12<0,"Revisión anticipada del borrador con la Contraparte","Reserva absorbe la subsanación")
A13: H9 | B13: 17 | C13: Software E2 para pruebas, QA superado | D13: 3.9.1 | E13: =DATE(2028,5,18) | F13: =WORKDAY(E13,Datos_Base!$C$33) | G13: =WORKDAY(E13,Datos_Base!$C$33+Datos_Base!$C$34) | H13: 21 | I13: =H13-Datos_Base!$C$34 | J13: =IF(I13<0,"Revisión anticipada del borrador con la Contraparte","Reserva absorbe la subsanación")
A14: H10 | B14: 18 | C14: Certificación E2 y cierre del desarrollo | D14: 3.9.6 | E14: =DATE(2028,6,12) | F14: =WORKDAY(E14,Datos_Base!$C$33) | G14: =WORKDAY(E14,Datos_Base!$C$33+Datos_Base!$C$34) | H14: 25 | I14: =H14-Datos_Base!$C$34 | J14: =IF(I14<0,"Revisión anticipada del borrador con la Contraparte","Reserva absorbe la subsanación")
A15: H11 | B15: 19 | C15: Inicio marcha blanca E2 en convivencia con E1 | D15: 4.3 | E15: Fecha contractual fija | F15: n/a | G15: n/a | H15: n/a | I15: n/a | J15: Plan de reversión activo y usuarios certificados
A16: H12 | B16: 21 | C16: Paso a producción E2 y aceptación final | D16: 4.3 | E16: Fecha contractual fija | F16: n/a | G16: n/a | H16: n/a | I16: n/a | J16: Condiciones copulativas del Art. 17.3 + acta
A18: Hitos con holgura negativa | C18: =COUNTIF(I5:I16,"<0")
A19: Nota | C19: WORKDAY no descuenta feriados chilenos; agregar la lista de feriados como tercer argumento antes de citar las fechas.

Sheet COQ
A1: Costo de la calidad en HH (PMBOK, 2017, cap. 8)
A2: Sin valores monetarios (BA Art. 50.2). Conformidad = prevención + evaluación; no conformidad = fallas (valor esperado SD8).
A4: Categoría | B4: Origen | C4: HH | D4: Proporción
A5: Prevención | B5: Paquetes HH_Calidad con categoría Prevención | C5: =SUMIF(HH_Calidad!$G$5:$G$37,"Prevención",HH_Calidad!$F$5:$F$37) | D5: =C5/$C$9
A6: Evaluación | B6: Paquetes HH_Calidad con categoría Evaluación | C6: =SUMIF(HH_Calidad!$G$5:$G$37,"Evaluación",HH_Calidad!$F$5:$F$37) | D6: =C6/$C$9
A7: Fallas internas | B7: VE R8-31 (repetir certificación) + R8-32 (evaluadores) | C7: =Datos_Base!$C$55+Datos_Base!$C$56 | D7: =C7/$C$9
A8: Fallas externas | B8: VE R8-18 (marcha blanca no cumple, extensión a costo de LafroX) | C8: =Datos_Base!$C$54 | D8: =C8/$C$9
A9: Total | C9: =SUM(C5:C8) | D9: =SUM(D5:D8)
A11: Costo de conformidad | C11: =C5+C6
A12: Costo de no conformidad | C12: =C7+C8
A13: Razón conformidad / no conformidad | C13: =C11/C12
A14: Costo de calidad / HH del proyecto | C14: =C9/Datos_Base!$C$47

Sheet Metricas_Proceso
A1: Métricas de proceso y producto (fórmulas con valores de ejemplo)
A2: Azul = valor de ejemplo para mostrar la fórmula; se reemplaza por la medición real de cada iteración.
A4: Métrica | B4: Entrada 1 | C4: Entrada 2 | D4: Resultado | E4: Meta | F4: Cumple | G4: Fórmula / fuente
A5: Eficiencia de remoción de defectos (DRE) | B5: 380 | C5: 20 | D5: =B5/(B5+C5) | E5: 0.95 | F5: =IF(D5>=E5,"Sí","No") | G5: Defectos antes de PROD / total. Meta: supuesto LafroX
A6: Densidad de defectos escapados (por 1.000 casos) | B6: 10 | C6: =Casos_Prueba!D11 | D6: =B6/C6*1000 | E6: 10 | F6: =IF(D6<=E6,"Sí","No") | G6: Defectos en PROD / casos de prueba × 1.000. Supuesto
A7: Tasa de cambios fallidos | B7: 1 | C7: 26 | D7: =B7/C7 | E7: =Datos_Base!$C$29 | F7: =IF(D7<=E7,"Sí","No") | G7: Despliegues fallidos / total (RT-04.12; SD4)
A8: Tiempo del commit a producción (días hábiles) | B8: 4 | D8: =B8 | E8: =Datos_Base!$C$30 | F8: =IF(D8<=E8,"Sí","No") | G8: Mediana del período (RT-04.12; SD4)
A9: Tiempo de restauración (h) | B9: 2.5 | D9: =B9 | E9: =Datos_Base!$C$31 | F9: =IF(D9<=E9,"Sí","No") | G9: Mediana de incidentes (RT-04.12; SD4)
A10: Consumo del presupuesto de error crítico | B10: 12 | C10: =Disponibilidad!C5 | D10: =B10/C10 | E10: 1 | F10: =IF(D10<=E10,"Sí","No") | G10: Minutos indisponibles / presupuesto (SD4 §4.2.4)
A11: Requerimientos con prueba aprobada | B11: 640 | C11: =Datos_Base!$C$45 | D11: =B11/C11 | E11: 1 | F11: =IF(D11>=E11,"Sí","No") | G11: Cobertura de la matriz 9.C (RT-04.04)
A12: Defectos críticos/altos abiertos al cierre de marcha blanca | B12: 0 | D12: =B12 | E12: 0 | F12: =IF(D12<=E12,"Sí","No") | G12: BA Art. 17.3

Sheet Inconsistencias
A1: Inconsistencias detectadas para el SD9
A2: Se corrigen en la etapa de redacción; manda el subdocumento anterior salvo decisión del grupo.
A4: N° | B4: Tema | C4: Dónde | D4: Qué dice | E4: Corrección propuesta | F4: Estado
A5: 1 | B5: Cobertura | C5: T-14 1.5.2; SD4 §4.2.4 | D5: 80 % del código modificado / dos métricas | E5: ≥70 % lógica de negocio Y ≥80 % unitaria global, ambas bloqueantes (decisión del grupo) | F5: Abierta
A6: 2 | B6: Pentest | C6: SD1 §1.3; SD3 RNF-14.06 | D6: Semestral | E6: Anual y antes de cada paso a producción (RT-11.20; T-14 8.2.2) | F6: Abierta
A7: 3 | B7: Meses de certificación | C7: T-14 3.8.7, 3.9.1, 3.9.6 | D7: Mes 10 (H5), mes 16 (H9), meses 16–17 (H10) | E7: Separar mes de ejecución y mes del hito (H5 m12, H9 m17, H10 m18) | F7: Abierta
A8: 4 | B8: Refuerzo de evaluadores | C8: SD6 §6.1.3 vs T-15 | D8: Meses 9–12 y 16–18; paquetes V sólo en 9–10 y 16–17 | E8: Ajustar el período o justificar 11–12 y 18 (subsanación) | F8: Abierta
A9: 5 | B9: TPS en régimen | C9: SD5 Anexos Tabla A.22 vs SD4 Tabla 33 | D9: 12,30 vs 12,34 TPS | E9: Usar 12,34 (SD4 manda) | F9: Abierta
A10: 6 | B10: Resultados R18 en E1 | C10: SD7 Tabla 7.11 vs Anexo 7.C | D10: 12 vs 14 | E10: Unificar y citar el mismo número en el T-17 | F10: Abierta
A11: 7 | B11: Columnas del T-12 | C11: SD3 §3.2 | D11: Dice que el T-12 trae prueba y criterio | E11: Matriz 9.C del SD9 aporta prueba y criterio; ajustar la frase del SD3 | F11: Abierta
A12: 8 | B12: Verificación RNF-14.07 | C12: SD3 Anexos | D12: SAST/DAST verificado con ejercicio de recuperación | E12: Verificar con puertas G2/G4 y DAST (OWASP ZAP) | F12: Abierta
A13: 9 | B13: CMMI-DEV N3 | C13: SD1 §1.4 | D13: Válido hasta nov-2026; contrato desde feb-2027 | E13: Declarar la reevaluación SCAMPI A antes del inicio o retirar el nivel como vigente | F13: Abierta
A14: 10 | B14: RNF fuera del catálogo | C14: T-12 Parte A vs SD3 Tabla 3.A.5a | D14: RNF-06.02, 06.03, 11.03 y 11.04 figuran como Cumple con componente propio en el T-12, pero el SD3 los declara absorbidos o alias | E14: La matriz 9.C los verifica con la fila que los absorbe; aclarar en el T-12 | F14: Abierta
A15: 11 | B15: Conteo de requisitos | C15: SD3 §3.2 vs T-12 | D15: 261 requisitos (175 RF y 86 RNF) frente a 271 filas (181 RF y 90 RNF) | E15: Explicar en el SD3 que la diferencia son filas absorbidas, alias y no ofertadas | F15: Abierta
A16: 12 | B16: Herramientas sin nombrar | C16: SD4, SD6 | D16: Sin pruebas Kotlin, carga, DAST, accesibilidad, inyección de fallas ni métricas de complejidad | E16: JUnit 5/Espresso/Kover, k6, OWASP ZAP, axe-core, AWS FIS, PHPMD/deptrac/PhpMetrics; propagar al SD4/SD6 | F16: Abierta

Sheet Figuras
A1: Figuras draw.io planificadas para el SD9
A2: Carpeta 09_plan_calidad/Diagramas/. Elaboración propia, texto ≥ 9 pt.
A4: Figura | B4: Archivo | C4: Contenido | D4: Sección | E4: Datos de esta planilla | F4: Estado
A5: 9.1 | B5: Fig_9-1_Marco_Calidad.drawio | C5: Vista general: normas → modelo → métricas → puertas → evidencia → aceptación | D5: 9.1.1 | E5: — | F5: Por dibujar
A6: 9.2 | B6: Fig_9-2_Modelo_ISO25010.drawio | C6: Árbol de 8 características con métrica y umbral | D6: 9.1.3 | E6: ISO25010 | F6: Por dibujar
A7: 9.3 | B7: Fig_9-3_Puertas_Calidad.drawio | C7: Pipeline GitLab CI/CodeBuild con puertas G0–G6 | D7: 9.2.1 | E7: Metricas_Codigo | F7: Por dibujar
A8: 9.4 | B8: Fig_9-4_Niveles_Ambientes.drawio | C8: Niveles y tipos de prueba 29119 por ambiente | D8: 9.2.3 | E8: Calendario | F8: Por dibujar
A9: 9.5 | B9: Fig_9-5_Datos_Prueba.drawio | C9: Flujo de datos de prueba sintéticos y anonimizados | D9: 9.2.3 | E9: — | F9: Por dibujar
A10: 9.6 | B10: Fig_9-6_Modelo_V.drawio | C10: Modelo en V: diseño ↔ nivel de prueba ↔ hito E-25 | D10: 9.2.4 | E10: Aceptacion_T17 | F10: Por dibujar
A11: 9.7 | B11: Fig_9-7_Cadena_Trazabilidad.drawio | C11: Origen → RF/RNF/RT → M/INT → EDT → caso → despliegue → R18 | D11: 9.2.4 | E11: Casos_Prueba | F11: Por dibujar
A12: 9.8 | B12: Fig_9-8_Ciclo_Defectos.drawio | C12: Ciclo de vida del defecto y severidades | D12: 9.2.4 | E12: Metricas_Proceso | F12: Por dibujar
A13: 9.9 | B13: Fig_9-9_Calidad_Cronograma.drawio | C13: 56 meses: paquetes de calidad, hitos, congelamientos y pruebas periódicas | D13: 9.3 | E13: HH_Calidad, Calendario | F13: Por dibujar
A14: 9.10 | B14: Fig_9-10_Flujo_Aceptacion.drawio | C14: Entrega → 10 d.h. revisión → observaciones → 10 d.h. subsanación → acta | D14: 9.3 / T-17 | E14: Aceptacion_T17 | F14: Por dibujar
