Workbook

Sheet Resumen
A2: Estimación por puntos de casos de uso
A4: LafroX para Distribuidora Puelche. Alcance E1 + E2 e innovaciones. Valores propuestos al 30/10/2026.
A8: Medida | B8: Resultado | C8: Unidad / origen | E8: Actividad | F8: Participación | G8: Horas de desarrollo
A9: Actores incluidos | B9: =SUM('Actores UAW'!$E$9:$E$100) -> 32 | C9: Roles y sistemas externos | E9: =Esfuerzo!A20 -> Análisis | F9: =Esfuerzo!B20 -> 0.1 | G9: =Esfuerzo!C20 -> 4749.3906
A10: Casos de uso incluidos | B10: =COUNTIF('Catalogo CU'!$G$9:$G$500,1) -> 91 | C10: Objetivos del actor | E10: =Esfuerzo!A21 -> Diseño | F10: =Esfuerzo!B21 -> 0.2 | G10: =Esfuerzo!C21 -> 9498.7812
A11: Transacciones incluidas | B11: =SUMIFS('Catalogo CU'!$J$9:$J$500,'Catalogo CU'!$G$9:$G$500,1) -> 390 | C11: Interacciones, sin multiplicar repeticiones | E11: =Esfuerzo!A22 -> Programación | F11: =Esfuerzo!B22 -> 0.4 | G11: =Esfuerzo!C22 -> 18997.562
A12: Peso de actores UAW | B12: ='Actores UAW'!B5 -> 75 | C12: puntos | E12: =Esfuerzo!A23 -> Pruebas | F12: =Esfuerzo!B23 -> 0.15 | G12: =Esfuerzo!C23 -> 7124.0859
A13: Peso de casos UUCW | B13: ='Casos UUCW'!B5 -> 790 | C13: puntos | E13: =Esfuerzo!A24 -> Sobrecarga | F13: =Esfuerzo!B24 -> 0.15 | G13: =Esfuerzo!C24 -> 7124.0859
A14: Puntos sin ajustar UUCP | B14: ='Puntos sin ajustar'!B11 -> 865 | C14: puntos
A15: Factor técnico TCF | B15: ='Factores tecnicos'!B5 -> 1.255 | C15: coeficiente
A16: Factor de ambiente EF | B16: ='Factores ambiente'!B5 -> 0.875 | C16: coeficiente | E16: Etapa contractual | F16: UUCW | G16: Horas de desarrollo
A17: Puntos ajustados UCP | B17: ='Puntos ajustados'!B12 -> 949.87812 | C17: UCP | E17: Etapa 1 | F17: ='Puntos sin ajustar'!C10 -> 630 | G17: =Esfuerzo!D14 -> 37874.887
A18: Factor de conversión | B18: =Esfuerzo!B11 -> 20 | C18: HH por UCP | E18: Etapa 2 | F18: ='Puntos sin ajustar'!D10 -> 160 | G18: =Esfuerzo!E14 -> 9619.019
A19: Horas de programación | B19: =Esfuerzo!B12 -> 18997.562 | C19: HH
A20: Horas totales de desarrollo | B20: =Esfuerzo!B14 -> 47493.906 | C20: HH, lectura B del PDF
A23: Cómo editar
A24: 1. Cambie puntuaciones amarillas en Factores ambiente o Factores tecnicos.
A25: 2. Para cambiar complejidad de un caso, edite sus filas de Transacciones y la columna Contar.
A26: 3. Para excluir alcance, cambie Incluir a 0 en el Catálogo o en Actores UAW.
A27: 4. Las fórmulas actualizan factores, puntos, conversión, horas y distribución. Excel debe usar cálculo automático.
A29: Estado del esfuerzo | B29: =Esfuerzo!B15 -> Calculado con valores propuestos
A31: Las horas excluyen operación, infraestructura, migración, capacitación ejecutada y reservas.
A33: Celdas amarillas: entradas editables. Valores sin relleno amarillo: fórmulas, datos fuente o reglas publicadas.

Sheet Catalogo CU
A2: Catálogo de casos de uso
A4: Desglose propuesto desde requisitos. Las cantidades se calculan desde Transacciones; edite el detalle para cambiarlas.
A8: ID caso | B8: Módulo | C8: Etapa | D8: Caso de uso | E8: Descripción y resultado | F8: Actores (ID) | G8: Incluir | H8: Principal | I8: Alternativo | J8: Total tx | K8: Requisitos / innovación | L8: Fuente funcional | M8: Control
A9: CU-001 | B9: M1 Recepción | C9: E1 | D9: Registrar recepción de proveedor | E9: Registrar cantidades, lote y vencimiento contra la orden de compra; el cierre conserva discrepancias y solicita el ingreso al ERP. | F9: A14, A04 | G9: 1 | H9: =SUMIFS(Transacciones!$G$9:$G$3000,Transacciones!$B$9:$B$3000,A9,Transacciones!$D$9:$D$3000,"Principal") -> 5 | I9: =SUMIFS(Transacciones!$G$9:$G$3000,Transacciones!$B$9:$B$3000,A9,Transacciones!$D$9:$D$3000,"Alternativo adicional") -> 1 | J9: =SUM(H9:I9) -> 6 | K9: RF-01.01, RF-01.02, RF-01.03, RF-01.06, RF-01.09 | L9: SD3 Anexo 3.A | M9: =IF(AND(ISNUMBER(G9),G9=0),"Excluido",IF(AND(ISNUMBER(G9),G9=1,COUNTIF($A$9:$A$500,A9)=1,OR(C9="E1",C9="E2"),D9<>"",E9<>"",F9<>"",J9>=1,COUNTIFS(Transacciones!$B$9:$B$3000,A9,Transacciones!$H$9:$H$3000,"<>Válido")=0),"Válido","Revisar caso o detalle")) -> Válido
A10: CU-002 | B10: M1 Recepción | C10: E1 | D10: Registrar no conformidad en recepción | E10: Documentar una anomalía con evidencia y retener la cantidad afectada para evaluación de Calidad. | F10: A14, A09 | G10: 1 | H10: =SUMIFS(Transacciones!$G$9:$G$3000,Transacciones!$B$9:$B$3000,A10,Transacciones!$D$9:$D$3000,"Principal") -> 4 | I10: =SUMIFS(Transacciones!$G$9:$G$3000,Transacciones!$B$9:$B$3000,A10,Transacciones!$D$9:$D$3000,"Alternativo adicional") -> 0 | J10: =SUM(H10:I10) -> 4 | K10: RF-01.04, RF-01.05 | L10: SD3 Anexo 3.A | M10: =IF(AND(ISNUMBER(G10),G10=0),"Excluido",IF(AND(ISNUMBER(G10),G10=1,COUNTIF($A$9:$A$500,A10)=1,OR(C10="E1",C10="E2"),D10<>"",E10<>"",F10<>"",J10>=1,COUNTIFS(Transacciones!$B$9:$B$3000,A10,Transacciones!$H$9:$H$3000,"<>Válido")=0),"Válido","Revisar caso o detalle")) -> Válido
A11: CU-003 | B11: M1 Recepción | C11: E1 | D11: Identificar unidad logística con SSCC | E11: Generar e imprimir la identificación logística de un pallet con vínculo a su contenido, sin confundir SSCC con lote. | F11: A14, A04 | G11: 1 | H11: =SUMIFS(Transacciones!$G$9:$G$3000,Transacciones!$B$9:$B$3000,A11,Transacciones!$D$9:$D$3000,"Principal") -> 3 | I11: =SUMIFS(Transacciones!$G$9:$G$3000,Transacciones!$B$9:$B$3000,A11,Transacciones!$D$9:$D$3000,"Alternativo adicional") -> 0 | J11: =SUM(H11:I11) -> 3 | K11: RF-01.07 | L11: SD3 Anexo 3.A | M11: =IF(AND(ISNUMBER(G11),G11=0),"Excluido",IF(AND(ISNUMBER(G11),G11=1,COUNTIF($A$9:$A$500,A11)=1,OR(C11="E1",C11="E2"),D11<>"",E11<>"",F11<>"",J11>=1,COUNTIFS(Transacciones!$B$9:$B$3000,A11,Transacciones!$H$9:$H$3000,"<>Válido")=0),"Válido","Revisar caso o detalle")) -> Válido
A12: CU-004 | B12: M1 Recepción | C12: E1 | D12: Ubicar unidad logística en bodega | E12: Asociar una unidad logística a una posición térmicamente compatible y registrar el movimiento. | F12: A04, A14 | G12: 1 | H12: =SUMIFS(Transacciones!$G$9:$G$3000,Transacciones!$B$9:$B$3000,A12,Transacciones!$D$9:$D$3000,"Principal") -> 3 | I12: =SUMIFS(Transacciones!$G$9:$G$3000,Transacciones!$B$9:$B$3000,A12,Transacciones!$D$9:$D$3000,"Alternativo adicional") -> 0 | J12: =SUM(H12:I12) -> 3 | K12: RF-01.08, RF-01.11 | L12: SD3 Anexo 3.A | M12: =IF(AND(ISNUMBER(G12),G12=0),"Excluido",IF(AND(ISNUMBER(G12),G12=1,COUNTIF($A$9:$A$500,A12)=1,OR(C12="E1",C12="E2"),D12<>"",E12<>"",F12<>"",J12>=1,COUNTIFS(Transacciones!$B$9:$B$3000,A12,Transacciones!$H$9:$H$3000,"<>Válido")=0),"Válido","Revisar caso o detalle")) -> Válido
A13: CU-005 | B13: M1 Recepción | C13: E1 | D13: Mantener maestro de productos | E13: Mantener fichas y atributos logísticos, comerciales y sanitarios con historial de cambios. | F13: A10, A13, A16 | G13: 1 | H13: =SUMIFS(Transacciones!$G$9:$G$3000,Transacciones!$B$9:$B$3000,A13,Transacciones!$D$9:$D$3000,"Principal") -> 5 | I13: =SUMIFS(Transacciones!$G$9:$G$3000,Transacciones!$B$9:$B$3000,A13,Transacciones!$D$9:$D$3000,"Alternativo adicional") -> 0 | J13: =SUM(H13:I13) -> 5 | K13: RF-01.10 | L13: SD3 Anexo 3.A | M13: =IF(AND(ISNUMBER(G13),G13=0),"Excluido",IF(AND(ISNUMBER(G13),G13=1,COUNTIF($A$9:$A$500,A13)=1,OR(C13="E1",C13="E2"),D13<>"",E13<>"",F13<>"",J13>=1,COUNTIFS(Transacciones!$B$9:$B$3000,A13,Transacciones!$H$9:$H$3000,"<>Válido")=0),"Válido","Revisar caso o detalle")) -> Válido
A14: CU-006 | B14: M2 Inventario | C14: E1 | D14: Configurar instalaciones y ubicaciones | E14: Mantener sitios, zonas térmicas y posiciones, con disponibilidad local para operar sin WAN. | F14: A13, A14 | G14: 1 | H14: =SUMIFS(Transacciones!$G$9:$G$3000,Transacciones!$B$9:$B$3000,A14,Transacciones!$D$9:$D$3000,"Principal") -> 5 | I14: =SUMIFS(Transacciones!$G$9:$G$3000,Transacciones!$B$9:$B$3000,A14,Transacciones!$D$9:$D$3000,"Alternativo adicional") -> 0 | J14: =SUM(H14:I14) -> 5 | K14: RF-02.01 | L14: SD3 Anexo 3.A | M14: =IF(AND(ISNUMBER(G14),G14=0),"Excluido",IF(AND(ISNUMBER(G14),G14=1,COUNTIF($A$9:$A$500,A14)=1,OR(C14="E1",C14="E2"),D14<>"",E14<>"",F14<>"",J14>=1,COUNTIFS(Transacciones!$B$9:$B$3000,A14,Transacciones!$H$9:$H$3000,"<>Válido")=0),"Válido","Revisar caso o detalle")) -> Válido
A15: CU-007 | B15: M2 Inventario | C15: E1 | D15: Consultar stock y disponibilidad | E15: Consultar existencias físicas, comprometidas, disponibles y en tránsito por SKU y sitio, mostrando antigüedad sin conexión. | F15: A01, A14, A13 | G15: 1 | H15: =SUMIFS(Transacciones!$G$9:$G$3000,Transacciones!$B$9:$B$3000,A15,Transacciones!$D$9:$D$3000,"Principal") -> 3 | I15: =SUMIFS(Transacciones!$G$9:$G$3000,Transacciones!$B$9:$B$3000,A15,Transacciones!$D$9:$D$3000,"Alternativo adicional") -> 0 | J15: =SUM(H15:I15) -> 3 | K15: RF-02.02, RF-02.05, RF-03.01, RF-03.02 | L15: SD3 Anexo 3.A | M15: =IF(AND(ISNUMBER(G15),G15=0),"Excluido",IF(AND(ISNUMBER(G15),G15=1,COUNTIF($A$9:$A$500,A15)=1,OR(C15="E1",C15="E2"),D15<>"",E15<>"",F15<>"",J15>=1,COUNTIFS(Transacciones!$B$9:$B$3000,A15,Transacciones!$H$9:$H$3000,"<>Válido")=0),"Válido","Revisar caso o detalle")) -> Válido
A16: CU-008 | B16: M2 Inventario | C16: E1 | D16: Aprobar y ejecutar propuesta de slotting | E16: Proponer y aprobar reubicaciones por rotación, capacidad y compatibilidad térmica. | F16: A14, A04 | G16: 1 | H16: =SUMIFS(Transacciones!$G$9:$G$3000,Transacciones!$B$9:$B$3000,A16,Transacciones!$D$9:$D$3000,"Principal") -> 5 | I16: =SUMIFS(Transacciones!$G$9:$G$3000,Transacciones!$B$9:$B$3000,A16,Transacciones!$D$9:$D$3000,"Alternativo adicional") -> 0 | J16: =SUM(H16:I16) -> 5 | K16: RF-02.03 | L16: SD3 Anexo 3.A | M16: =IF(AND(ISNUMBER(G16),G16=0),"Excluido",IF(AND(ISNUMBER(G16),G16=1,COUNTIF($A$9:$A$500,A16)=1,OR(C16="E1",C16="E2"),D16<>"",E16<>"",F16<>"",J16>=1,COUNTIFS(Transacciones!$B$9:$B$3000,A16,Transacciones!$H$9:$H$3000,"<>Válido")=0),"Válido","Revisar caso o detalle")) -> Válido
A17: CU-009 | B17: M2 Inventario | C17: E1 | D17: Realizar conteo cíclico y ajuste | E17: Planificar conteos ciegos y resolver diferencias con umbral y segregación de autorización. | F17: A14, A04 | G17: 1 | H17: =SUMIFS(Transacciones!$G$9:$G$3000,Transacciones!$B$9:$B$3000,A17,Transacciones!$D$9:$D$3000,"Principal") -> 5 | I17: =SUMIFS(Transacciones!$G$9:$G$3000,Transacciones!$B$9:$B$3000,A17,Transacciones!$D$9:$D$3000,"Alternativo adicional") -> 1 | J17: =SUM(H17:I17) -> 6 | K17: RF-02.04 | L17: SD3 Anexo 3.A | M17: =IF(AND(ISNUMBER(G17),G17=0),"Excluido",IF(AND(ISNUMBER(G17),G17=1,COUNTIF($A$9:$A$500,A17)=1,OR(C17="E1",C17="E2"),D17<>"",E17<>"",F17<>"",J17>=1,COUNTIFS(Transacciones!$B$9:$B$3000,A17,Transacciones!$H$9:$H$3000,"<>Válido")=0),"Válido","Revisar caso o detalle")) -> Válido
A18: CU-010 | B18: M2 Inventario | C18: E1 | D18: Transferir inventario entre sitios | E18: Despachar y recibir existencias en tránsito, conservando la autoridad local y el movimiento hacia el ERP. | F18: A14, A04 | G18: 1 | H18: =SUMIFS(Transacciones!$G$9:$G$3000,Transacciones!$B$9:$B$3000,A18,Transacciones!$D$9:$D$3000,"Principal") -> 5 | I18: =SUMIFS(Transacciones!$G$9:$G$3000,Transacciones!$B$9:$B$3000,A18,Transacciones!$D$9:$D$3000,"Alternativo adicional") -> 1 | J18: =SUM(H18:I18) -> 6 | K18: RF-02.06 | L18: SD3 Anexo 3.A | M18: =IF(AND(ISNUMBER(G18),G18=0),"Excluido",IF(AND(ISNUMBER(G18),G18=1,COUNTIF($A$9:$A$500,A18)=1,OR(C18="E1",C18="E2"),D18<>"",E18<>"",F18<>"",J18>=1,COUNTIFS(Transacciones!$B$9:$B$3000,A18,Transacciones!$H$9:$H$3000,"<>Válido")=0),"Válido","Revisar caso o detalle")) -> Válido
A19: CU-011 | B19: M2 Inventario | C19: E1 | D19: Consultar ocupación de bodegas | E19: Consultar capacidad utilizada por instalación y zona con histórico exportable. | F19: A14, A13 | G19: 1 | H19: =SUMIFS(Transacciones!$G$9:$G$3000,Transacciones!$B$9:$B$3000,A19,Transacciones!$D$9:$D$3000,"Principal") -> 3 | I19: =SUMIFS(Transacciones!$G$9:$G$3000,Transacciones!$B$9:$B$3000,A19,Transacciones!$D$9:$D$3000,"Alternativo adicional") -> 0 | J19: =SUM(H19:I19) -> 3 | K19: RF-02.07 | L19: SD3 Anexo 3.A | M19: =IF(AND(ISNUMBER(G19),G19=0),"Excluido",IF(AND(ISNUMBER(G19),G19=1,COUNTIF($A$9:$A$500,A19)=1,OR(C19="E1",C19="E2"),D19<>"",E19<>"",F19<>"",J19>=1,COUNTIFS(Transacciones!$B$9:$B$3000,A19,Transacciones!$H$9:$H$3000,"<>Válido")=0),"Válido","Revisar caso o detalle")) -> Válido
A20: CU-012 | B20: M2 Inventario | C20: E1 | D20: Gestionar alertas de vencimiento en bodega | E20: Revisar lotes próximos a vencer y registrar una acción permitida sin sustituir FEFO. | F20: A14, A09 | G20: 1 | H20: =SUMIFS(Transacciones!$G$9:$G$3000,Transacciones!$B$9:$B$3000,A20,Transacciones!$D$9:$D$3000,"Principal") -> 3 | I20: =SUMIFS(Transacciones!$G$9:$G$3000,Transacciones!$B$9:$B$3000,A20,Transacciones!$D$9:$D$3000,"Alternativo adicional") -> 0 | J20: =SUM(H20:I20) -> 3 | K20: RF-02.09 | L20: SD3 Anexo 3.A | M20: =IF(AND(ISNUMBER(G20),G20=0),"Excluido",IF(AND(ISNUMBER(G20),G20=1,COUNTIF($A$9:$A$500,A20)=1,OR(C20="E1",C20="E2"),D20<>"",E20<>"",F20<>"",J20>=1,COUNTIFS(Transacciones!$B$9:$B$3000,A20,Transacciones!$H$9:$H$3000,"<>Válido")=0),"Válido","Revisar caso o detalle")) -> Válido
... A99: CU-091 | B99: Base compartida | C99: E1 | D99: Clasificar información y aplicar acceso | E99: Asignar nivel de sensibilidad a conjuntos de información y revisar controles de acceso correspondientes. | F99: A15 | G99: 1 | H99: =SUMIFS(Transacciones!$G$9:$G$3000,Transacciones!$B$9:$B$3000,A99,Transacciones!$D$9:$D$3000,"Principal") -> 4 | I99: =SUMIFS(Transacciones!$G$9:$G$3000,Transacciones!$B$9:$B$3000,A99,Transacciones!$D$9:$D$3000,"Alternativo adicional") -> 0 | J99: =SUM(H99:I99) -> 4 | K99: RF-14.01-BTT | L99: SD3 Anexo 3.A | M99: =IF(AND(ISNUMBER(G99),G99=0),"Excluido",IF(AND(ISNUMBER(G99),G99=1,COUNTIF($A$9:$A$500,A99)=1,OR(C99="E1",C99="E2"),D99<>"",E99<>"",F99<>"",J99>=1,COUNTIFS(Transacciones!$B$9:$B$3000,A99,Transacciones!$H$9:$H$3000,"<>Válido")=0),"Válido","Revisar caso o detalle")) -> Válido

Sheet Transacciones
A2: Transacciones por caso de uso
A4: Amarillo: entradas editables. Contar = 1 incluye la interacción; 0 la excluye. No sumar repeticiones del mismo tipo.
A8: ID transacción | B8: ID caso | C8: N.º | D8: Flujo | E8: Acción del actor | F8: Respuesta del sistema | G8: Contar | H8: Control
A9: CU-001-T01 | B9: CU-001 | C9: 1 | D9: Principal | E9: Selecciona la orden de compra y el andén | F9: Muestra líneas esperadas y recepción abierta | G9: 1 | H9: =IF(G9=0,"Válido",IF(AND(ISNUMBER(G9),G9=1,A9<>"",COUNTIF($A$9:$A$3000,A9)=1,COUNTIF('Catalogo CU'!$A$9:$A$500,B9)=1,ISNUMBER(C9),C9>=1,OR(D9="Principal",D9="Alternativo adicional"),E9<>"",F9<>""),"Válido","Revisar transacción")) -> Válido
A10: CU-001-T02 | B10: CU-001 | C10: 2 | D10: Principal | E10: Escanea el producto y su lote GS1 | F10: Identifica SKU, lote y vencimiento y muestra los datos capturados | G10: 1 | H10: =IF(G10=0,"Válido",IF(AND(ISNUMBER(G10),G10=1,A10<>"",COUNTIF($A$9:$A$3000,A10)=1,COUNTIF('Catalogo CU'!$A$9:$A$500,B10)=1,ISNUMBER(C10),C10>=1,OR(D10="Principal",D10="Alternativo adicional"),E10<>"",F10<>""),"Válido","Revisar transacción")) -> Válido
A11: CU-001-T03 | B11: CU-001 | C11: 3 | D11: Principal | E11: Registra cantidades y confirma los datos de la línea | F11: Valida campos obligatorios y muestra diferencias contra la orden | G11: 1 | H11: =IF(G11=0,"Válido",IF(AND(ISNUMBER(G11),G11=1,A11<>"",COUNTIF($A$9:$A$3000,A11)=1,COUNTIF('Catalogo CU'!$A$9:$A$500,B11)=1,ISNUMBER(C11),C11>=1,OR(D11="Principal",D11="Alternativo adicional"),E11<>"",F11<>""),"Válido","Revisar transacción")) -> Válido
A12: CU-001-T04 | B12: CU-001 | C12: 4 | D12: Principal | E12: Solicita el resumen de recepción | F12: Presenta cantidades, lotes y discrepancias del documento | G12: 1 | H12: =IF(G12=0,"Válido",IF(AND(ISNUMBER(G12),G12=1,A12<>"",COUNTIF($A$9:$A$3000,A12)=1,COUNTIF('Catalogo CU'!$A$9:$A$500,B12)=1,ISNUMBER(C12),C12>=1,OR(D12="Principal",D12="Alternativo adicional"),E12<>"",F12<>""),"Válido","Revisar transacción")) -> Válido
A13: CU-001-T05 | B13: CU-001 | C13: 5 | D13: Principal | E13: Confirma el cierre de la recepción | F13: Registra el ingreso y devuelve identificador y estado de integración | G13: 1 | H13: =IF(G13=0,"Válido",IF(AND(ISNUMBER(G13),G13=1,A13<>"",COUNTIF($A$9:$A$3000,A13)=1,COUNTIF('Catalogo CU'!$A$9:$A$500,B13)=1,ISNUMBER(C13),C13>=1,OR(D13="Principal",D13="Alternativo adicional"),E13<>"",F13<>""),"Válido","Revisar transacción")) -> Válido
A14: CU-001-T06 | B14: CU-001 | C14: 6 | D14: Alternativo adicional | E14: Ingresa manualmente un código no reconocido | F14: Valida el ingreso autorizado y devuelve la línea identificada | G14: 1 | H14: =IF(G14=0,"Válido",IF(AND(ISNUMBER(G14),G14=1,A14<>"",COUNTIF($A$9:$A$3000,A14)=1,COUNTIF('Catalogo CU'!$A$9:$A$500,B14)=1,ISNUMBER(C14),C14>=1,OR(D14="Principal",D14="Alternativo adicional"),E14<>"",F14<>""),"Válido","Revisar transacción")) -> Válido
A15: CU-002-T01 | B15: CU-002 | C15: 1 | D15: Principal | E15: Selecciona recepción y cantidad afectada | F15: Muestra SKU y lote vinculados | G15: 1 | H15: =IF(G15=0,"Válido",IF(AND(ISNUMBER(G15),G15=1,A15<>"",COUNTIF($A$9:$A$3000,A15)=1,COUNTIF('Catalogo CU'!$A$9:$A$500,B15)=1,ISNUMBER(C15),C15>=1,OR(D15="Principal",D15="Alternativo adicional"),E15<>"",F15<>""),"Válido","Revisar transacción")) -> Válido
A16: CU-002-T02 | B16: CU-002 | C16: 2 | D16: Principal | E16: Indica tipo de no conformidad y observaciones | F16: Valida la causa y muestra el detalle | G16: 1 | H16: =IF(G16=0,"Válido",IF(AND(ISNUMBER(G16),G16=1,A16<>"",COUNTIF($A$9:$A$3000,A16)=1,COUNTIF('Catalogo CU'!$A$9:$A$500,B16)=1,ISNUMBER(C16),C16>=1,OR(D16="Principal",D16="Alternativo adicional"),E16<>"",F16<>""),"Válido","Revisar transacción")) -> Válido
A17: CU-002-T03 | B17: CU-002 | C17: 3 | D17: Principal | E17: Adjunta la fotografía | F17: Confirma el archivo y su vinculación | G17: 1 | H17: =IF(G17=0,"Válido",IF(AND(ISNUMBER(G17),G17=1,A17<>"",COUNTIF($A$9:$A$3000,A17)=1,COUNTIF('Catalogo CU'!$A$9:$A$500,B17)=1,ISNUMBER(C17),C17>=1,OR(D17="Principal",D17="Alternativo adicional"),E17<>"",F17<>""),"Válido","Revisar transacción")) -> Válido
A18: CU-002-T04 | B18: CU-002 | C18: 4 | D18: Principal | E18: Confirma la no conformidad | F18: Registra cuarentena y devuelve estado y aviso a Calidad | G18: 1 | H18: =IF(G18=0,"Válido",IF(AND(ISNUMBER(G18),G18=1,A18<>"",COUNTIF($A$9:$A$3000,A18)=1,COUNTIF('Catalogo CU'!$A$9:$A$500,B18)=1,ISNUMBER(C18),C18>=1,OR(D18="Principal",D18="Alternativo adicional"),E18<>"",F18<>""),"Válido","Revisar transacción")) -> Válido
A19: CU-003-T01 | B19: CU-003 | C19: 1 | D19: Principal | E19: Selecciona el pallet recibido | F19: Muestra contenido, lotes y vencimientos | G19: 1 | H19: =IF(G19=0,"Válido",IF(AND(ISNUMBER(G19),G19=1,A19<>"",COUNTIF($A$9:$A$3000,A19)=1,COUNTIF('Catalogo CU'!$A$9:$A$500,B19)=1,ISNUMBER(C19),C19>=1,OR(D19="Principal",D19="Alternativo adicional"),E19<>"",F19<>""),"Válido","Revisar transacción")) -> Válido
A20: CU-003-T02 | B20: CU-003 | C20: 2 | D20: Principal | E20: Confirma su identificación | F20: Asigna SSCC único y presenta etiqueta GS1-128 | G20: 1 | H20: =IF(G20=0,"Válido",IF(AND(ISNUMBER(G20),G20=1,A20<>"",COUNTIF($A$9:$A$3000,A20)=1,COUNTIF('Catalogo CU'!$A$9:$A$500,B20)=1,ISNUMBER(C20),C20>=1,OR(D20="Principal",D20="Alternativo adicional"),E20<>"",F20<>""),"Válido","Revisar transacción")) -> Válido
... A398: CU-091-T04 | B398: CU-091 | C398: 4 | D398: Principal | E398: Confirma clasificación autorizada | F398: Publica nivel y conserva auditoría | G398: 1 | H398: =IF(G398=0,"Válido",IF(AND(ISNUMBER(G398),G398=1,A398<>"",COUNTIF($A$9:$A$3000,A398)=1,COUNTIF('Catalogo CU'!$A$9:$A$500,B398)=1,ISNUMBER(C398),C398>=1,OR(D398="Principal",D398="Alternativo adicional"),E398<>"",F398<>""),"Válido","Revisar transacción")) -> Válido

Sheet Actores UAW
A2: Peso de los actores sin ajustar
A4: Un actor por rol o contrato de interacción. Amarillo: interfaz e inclusión. Los cuatro roles humanos adicionales están justificados.
A5: UAW | B5: =IF(COUNTIF(J9:J100,"Revisar*")>0,"Revisar actores",SUM(G9:G100)) -> 75
A8: ID actor | B8: Actor | C8: Interfaz | D8: Clase | E8: Incluir | F8: Peso | G8: Aporte UAW | H8: Criterio de conteo | I8: Fuente | J8: Control
A9: A01 | B9: Preventista | C9: Gráfica | D9: =IF(C9="API","Simple",IF(C9="Protocolo","Medio",IF(C9="Gráfica","Complejo","Revisar interfaz"))) -> Complejo | E9: 1 | F9: =IF(D9="Simple",'Criterios y fuentes'!$B$25,IF(D9="Medio",'Criterios y fuentes'!$B$26,IF(D9="Complejo",'Criterios y fuentes'!$B$27,"Revisar"))) -> 3 | G9: =IF(E9=0,0,IF(J9="Válido",E9*F9,"Revisar actor")) -> 3 | H9: Rol, no 62 personas. | I9: SD3 §3.4.2 / Anexo 3.A, actores | J9: =IF(AND(ISNUMBER(E9),OR(E9=0,E9=1),COUNTIF($A$9:$A$100,A9)=1,OR(C9="API",C9="Protocolo",C9="Gráfica")),"Válido","Revisar actor") -> Válido
A10: A02 | B10: Conductor propio | C10: Gráfica | D10: =IF(C10="API","Simple",IF(C10="Protocolo","Medio",IF(C10="Gráfica","Complejo","Revisar interfaz"))) -> Complejo | E10: 1 | F10: =IF(D10="Simple",'Criterios y fuentes'!$B$25,IF(D10="Medio",'Criterios y fuentes'!$B$26,IF(D10="Complejo",'Criterios y fuentes'!$B$27,"Revisar"))) -> 3 | G10: =IF(E10=0,0,IF(J10="Válido",E10*F10,"Revisar actor")) -> 3 | H10: Mantiene rol propio del catálogo. | I10: SD3 §3.4.2 | J10: =IF(AND(ISNUMBER(E10),OR(E10=0,E10=1),COUNTIF($A$9:$A$100,A10)=1,OR(C10="API",C10="Protocolo",C10="Gráfica")),"Válido","Revisar actor") -> Válido
A11: A03 | B11: Conductor externo | C11: Gráfica | D11: =IF(C11="API","Simple",IF(C11="Protocolo","Medio",IF(C11="Gráfica","Complejo","Revisar interfaz"))) -> Complejo | E11: 1 | F11: =IF(D11="Simple",'Criterios y fuentes'!$B$25,IF(D11="Medio",'Criterios y fuentes'!$B$26,IF(D11="Complejo",'Criterios y fuentes'!$B$27,"Revisar"))) -> 3 | G11: =IF(E11=0,0,IF(J11="Válido",E11*F11,"Revisar actor")) -> 3 | H11: Rol concreto con relación externa y vigencia por turno. | I11: SD3 §3.4.2 / RF-06.08 | J11: =IF(AND(ISNUMBER(E11),OR(E11=0,E11=1),COUNTIF($A$9:$A$100,A11)=1,OR(C11="API",C11="Protocolo",C11="Gráfica")),"Válido","Revisar actor") -> Válido
A12: A04 | B12: Preparador | C12: Gráfica | D12: =IF(C12="API","Simple",IF(C12="Protocolo","Medio",IF(C12="Gráfica","Complejo","Revisar interfaz"))) -> Complejo | E12: 1 | F12: =IF(D12="Simple",'Criterios y fuentes'!$B$25,IF(D12="Medio",'Criterios y fuentes'!$B$26,IF(D12="Complejo",'Criterios y fuentes'!$B$27,"Revisar"))) -> 3 | G12: =IF(E12=0,0,IF(J12="Válido",E12*F12,"Revisar actor")) -> 3 | H12: Recepción y movimientos solo con autorización funcional. | I12: SD3 §3.4.2 | J12: =IF(AND(ISNUMBER(E12),OR(E12=0,E12=1),COUNTIF($A$9:$A$100,A12)=1,OR(C12="API",C12="Protocolo",C12="Gráfica")),"Válido","Revisar actor") -> Válido
A13: A05 | B13: Cliente del canal tradicional | C13: Gráfica | D13: =IF(C13="API","Simple",IF(C13="Protocolo","Medio",IF(C13="Gráfica","Complejo","Revisar interfaz"))) -> Complejo | E13: 1 | F13: =IF(D13="Simple",'Criterios y fuentes'!$B$25,IF(D13="Medio",'Criterios y fuentes'!$B$26,IF(D13="Complejo",'Criterios y fuentes'!$B$27,"Revisar"))) -> 3 | G13: =IF(E13=0,0,IF(J13="Válido",E13*F13,"Revisar actor")) -> 3 | H13: Incluye food service con iguales permisos. No exige dispositivo al cliente. | I13: SD3 §3.4.2 | J13: =IF(AND(ISNUMBER(E13),OR(E13=0,E13=1),COUNTIF($A$9:$A$100,A13)=1,OR(C13="API",C13="Protocolo",C13="Gráfica")),"Válido","Revisar actor") -> Válido
A14: A06 | B14: Cliente del canal moderno | C14: Gráfica | D14: =IF(C14="API","Simple",IF(C14="Protocolo","Medio",IF(C14="Gráfica","Complejo","Revisar interfaz"))) -> Complejo | E14: 1 | F14: =IF(D14="Simple",'Criterios y fuentes'!$B$25,IF(D14="Medio",'Criterios y fuentes'!$B$26,IF(D14="Complejo",'Criterios y fuentes'!$B$27,"Revisar"))) -> 3 | G14: =IF(E14=0,0,IF(J14="Válido",E14*F14,"Revisar actor")) -> 3 | H14: La identidad EDI se cuenta por separado como sistema. | I14: SD3 §3.4.2 | J14: =IF(AND(ISNUMBER(E14),OR(E14=0,E14=1),COUNTIF($A$9:$A$100,A14)=1,OR(C14="API",C14="Protocolo",C14="Gráfica")),"Válido","Revisar actor") -> Válido
A15: A07 | B15: Empresa transportista | C15: Gráfica | D15: =IF(C15="API","Simple",IF(C15="Protocolo","Medio",IF(C15="Gráfica","Complejo","Revisar interfaz"))) -> Complejo | E15: 1 | F15: =IF(D15="Simple",'Criterios y fuentes'!$B$25,IF(D15="Medio",'Criterios y fuentes'!$B$26,IF(D15="Complejo",'Criterios y fuentes'!$B$27,"Revisar"))) -> 3 | G15: =IF(E15=0,0,IF(J15="Válido",E15*F15,"Revisar actor")) -> 3 | H15: Un rol por empresa, sin multiplicar por diez empresas. | I15: SD3 §3.4.2 | J15: =IF(AND(ISNUMBER(E15),OR(E15=0,E15=1),COUNTIF($A$9:$A$100,A15)=1,OR(C15="API",C15="Protocolo",C15="Gráfica")),"Válido","Revisar actor") -> Válido
A16: A08 | B16: Proveedor | C16: Gráfica | D16: =IF(C16="API","Simple",IF(C16="Protocolo","Medio",IF(C16="Gráfica","Complejo","Revisar interfaz"))) -> Complejo | E16: 1 | F16: =IF(D16="Simple",'Criterios y fuentes'!$B$25,IF(D16="Medio",'Criterios y fuentes'!$B$26,IF(D16="Complejo",'Criterios y fuentes'!$B$27,"Revisar"))) -> 3 | G16: =IF(E16=0,0,IF(J16="Válido",E16*F16,"Revisar actor")) -> 3 | H16: Solo consulta sus documentos, sin aprobar recepción física. | I16: SD3 §3.4.2 | J16: =IF(AND(ISNUMBER(E16),OR(E16=0,E16=1),COUNTIF($A$9:$A$100,A16)=1,OR(C16="API",C16="Protocolo",C16="Gráfica")),"Válido","Revisar actor") -> Válido
A17: A09 | B17: Jefa de Calidad | C17: Gráfica | D17: =IF(C17="API","Simple",IF(C17="Protocolo","Medio",IF(C17="Gráfica","Complejo","Revisar interfaz"))) -> Complejo | E17: 1 | F17: =IF(D17="Simple",'Criterios y fuentes'!$B$25,IF(D17="Medio",'Criterios y fuentes'!$B$26,IF(D17="Complejo",'Criterios y fuentes'!$B$27,"Revisar"))) -> 3 | G17: =IF(E17=0,0,IF(J17="Válido",E17*F17,"Revisar actor")) -> 3 | H17: Decisión sanitaria separada de captura de terreno. | I17: SD3 §3.4.2 | J17: =IF(AND(ISNUMBER(E17),OR(E17=0,E17=1),COUNTIF($A$9:$A$100,A17)=1,OR(C17="API",C17="Protocolo",C17="Gráfica")),"Válido","Revisar actor") -> Válido
A18: A10 | B18: Gerente Comercial | C18: Gráfica | D18: =IF(C18="API","Simple",IF(C18="Protocolo","Medio",IF(C18="Gráfica","Complejo","Revisar interfaz"))) -> Complejo | E18: 1 | F18: =IF(D18="Simple",'Criterios y fuentes'!$B$25,IF(D18="Medio",'Criterios y fuentes'!$B$26,IF(D18="Complejo",'Criterios y fuentes'!$B$27,"Revisar"))) -> 3 | G18: =IF(E18=0,0,IF(J18="Válido",E18*F18,"Revisar actor")) -> 3 | H18: Condiciones comerciales y excepciones de canal. | I18: SD3 §3.4.2 | J18: =IF(AND(ISNUMBER(E18),OR(E18=0,E18=1),COUNTIF($A$9:$A$100,A18)=1,OR(C18="API",C18="Protocolo",C18="Gráfica")),"Válido","Revisar actor") -> Válido
A19: A11 | B19: Gerente de Finanzas | C19: Gráfica | D19: =IF(C19="API","Simple",IF(C19="Protocolo","Medio",IF(C19="Gráfica","Complejo","Revisar interfaz"))) -> Complejo | E19: 1 | F19: =IF(D19="Simple",'Criterios y fuentes'!$B$25,IF(D19="Medio",'Criterios y fuentes'!$B$26,IF(D19="Complejo",'Criterios y fuentes'!$B$27,"Revisar"))) -> 3 | G19: =IF(E19=0,0,IF(J19="Válido",E19*F19,"Revisar actor")) -> 3 | H19: Incluye función de caja habilitada; no incorpora personal nuevo a la dotación. | I19: SD3 §3.4.2 | J19: =IF(AND(ISNUMBER(E19),OR(E19=0,E19=1),COUNTIF($A$9:$A$100,A19)=1,OR(C19="API",C19="Protocolo",C19="Gráfica")),"Válido","Revisar actor") -> Válido
A20: A12 | B20: Planificador de Rutas | C20: Gráfica | D20: =IF(C20="API","Simple",IF(C20="Protocolo","Medio",IF(C20="Gráfica","Complejo","Revisar interfaz"))) -> Complejo | E20: 1 | F20: =IF(D20="Simple",'Criterios y fuentes'!$B$25,IF(D20="Medio",'Criterios y fuentes'!$B$26,IF(D20="Complejo",'Criterios y fuentes'!$B$27,"Revisar"))) -> 3 | G20: =IF(E20=0,0,IF(J20="Válido",E20*F20,"Revisar actor")) -> 3 | H20: No se cuenta un actor por vehículo. | I20: SD3 §3.4.2 | J20: =IF(AND(ISNUMBER(E20),OR(E20=0,E20=1),COUNTIF($A$9:$A$100,A20)=1,OR(C20="API",C20="Protocolo",C20="Gráfica")),"Válido","Revisar actor") -> Válido
... A40: A32 | B40: Proveedor de mapas y geocodificación | C40: API | D40: =IF(C40="API","Simple",IF(C40="Protocolo","Medio",IF(C40="Gráfica","Complejo","Revisar interfaz"))) -> Simple | E40: 1 | F40: =IF(D40="Simple",'Criterios y fuentes'!$B$25,IF(D40="Medio",'Criterios y fuentes'!$B$26,IF(D40="Complejo",'Criterios y fuentes'!$B$27,"Revisar"))) -> 1 | G40: =IF(E40=0,0,IF(J40="Válido",E40*F40,"Revisar actor")) -> 1 | H40: Se integra en planificación; optimizador propio permanece dentro de la frontera. | I40: SD4 Anexo 4-H | J40: =IF(AND(ISNUMBER(E40),OR(E40=0,E40=1),COUNTIF($A$9:$A$100,A40)=1,OR(C40="API",C40="Protocolo",C40="Gráfica")),"Válido","Revisar actor") -> Válido

Sheet Casos UUCW
A2: Peso de los casos de uso sin ajustar
A4: Clase automática: 1–3 transacciones = 5; 4–7 = 10; 8 o más = 15. Las exclusiones aportan cero.
A5: UUCW | B5: =IF(OR(COUNTIF(I9:I500,"Revisar*")>0,COUNTIF('Catalogo CU'!$G$9:$G$500,1)<>COUNTIF(D9:D500,1)),"Revisar cobertura CU",SUM(H9:H500)) -> 790
A8: ID caso | B8: Caso de uso | C8: Etapa | D8: Incluir | E8: Transacciones | F8: Complejidad | G8: Peso | H8: Aporte UUCW | I8: Control
A9: CU-001 | B9: =INDEX('Catalogo CU'!$D$9:$D$500,MATCH(A9,'Catalogo CU'!$A$9:$A$500,0)) -> Registrar recepción de proveedor | C9: =INDEX('Catalogo CU'!$C$9:$C$500,MATCH(A9,'Catalogo CU'!$A$9:$A$500,0)) -> E1 | D9: =INDEX('Catalogo CU'!$G$9:$G$500,MATCH(A9,'Catalogo CU'!$A$9:$A$500,0)) -> 1 | E9: =INDEX('Catalogo CU'!$J$9:$J$500,MATCH(A9,'Catalogo CU'!$A$9:$A$500,0)) -> 6 | F9: =IF(D9=0,"Excluido",IF(I9<>"Válido","Revisar",IF(E9<='Criterios y fuentes'!$F$25,"Simple",IF(E9<='Criterios y fuentes'!$F$26,"Medio","Complejo")))) -> Medio | G9: =IF(F9="Excluido",0,IF(F9="Simple",'Criterios y fuentes'!$G$25,IF(F9="Medio",'Criterios y fuentes'!$G$26,IF(F9="Complejo",'Criterios y fuentes'!$G$27,"Revisar")))) -> 10 | H9: =IF(D9=0,0,IF(I9="Válido",D9*G9,"Revisar CU")) -> 10 | I9: =IF(COUNTIF('Catalogo CU'!$A$9:$A$500,A9)<>1,"Revisar ID",IF(COUNTIF($A$9:$A$500,A9)<>1,"Revisar duplicado",INDEX('Catalogo CU'!$M$9:$M$500,MATCH(A9,'Catalogo CU'!$A$9:$A$500,0)))) -> Válido
A10: CU-002 | B10: =INDEX('Catalogo CU'!$D$9:$D$500,MATCH(A10,'Catalogo CU'!$A$9:$A$500,0)) -> Registrar no conformidad en recepción | C10: =INDEX('Catalogo CU'!$C$9:$C$500,MATCH(A10,'Catalogo CU'!$A$9:$A$500,0)) -> E1 | D10: =INDEX('Catalogo CU'!$G$9:$G$500,MATCH(A10,'Catalogo CU'!$A$9:$A$500,0)) -> 1 | E10: =INDEX('Catalogo CU'!$J$9:$J$500,MATCH(A10,'Catalogo CU'!$A$9:$A$500,0)) -> 4 | F10: =IF(D10=0,"Excluido",IF(I10<>"Válido","Revisar",IF(E10<='Criterios y fuentes'!$F$25,"Simple",IF(E10<='Criterios y fuentes'!$F$26,"Medio","Complejo")))) -> Medio | G10: =IF(F10="Excluido",0,IF(F10="Simple",'Criterios y fuentes'!$G$25,IF(F10="Medio",'Criterios y fuentes'!$G$26,IF(F10="Complejo",'Criterios y fuentes'!$G$27,"Revisar")))) -> 10 | H10: =IF(D10=0,0,IF(I10="Válido",D10*G10,"Revisar CU")) -> 10 | I10: =IF(COUNTIF('Catalogo CU'!$A$9:$A$500,A10)<>1,"Revisar ID",IF(COUNTIF($A$9:$A$500,A10)<>1,"Revisar duplicado",INDEX('Catalogo CU'!$M$9:$M$500,MATCH(A10,'Catalogo CU'!$A$9:$A$500,0)))) -> Válido
A11: CU-003 | B11: =INDEX('Catalogo CU'!$D$9:$D$500,MATCH(A11,'Catalogo CU'!$A$9:$A$500,0)) -> Identificar unidad logística con SSCC | C11: =INDEX('Catalogo CU'!$C$9:$C$500,MATCH(A11,'Catalogo CU'!$A$9:$A$500,0)) -> E1 | D11: =INDEX('Catalogo CU'!$G$9:$G$500,MATCH(A11,'Catalogo CU'!$A$9:$A$500,0)) -> 1 | E11: =INDEX('Catalogo CU'!$J$9:$J$500,MATCH(A11,'Catalogo CU'!$A$9:$A$500,0)) -> 3 | F11: =IF(D11=0,"Excluido",IF(I11<>"Válido","Revisar",IF(E11<='Criterios y fuentes'!$F$25,"Simple",IF(E11<='Criterios y fuentes'!$F$26,"Medio","Complejo")))) -> Simple | G11: =IF(F11="Excluido",0,IF(F11="Simple",'Criterios y fuentes'!$G$25,IF(F11="Medio",'Criterios y fuentes'!$G$26,IF(F11="Complejo",'Criterios y fuentes'!$G$27,"Revisar")))) -> 5 | H11: =IF(D11=0,0,IF(I11="Válido",D11*G11,"Revisar CU")) -> 5 | I11: =IF(COUNTIF('Catalogo CU'!$A$9:$A$500,A11)<>1,"Revisar ID",IF(COUNTIF($A$9:$A$500,A11)<>1,"Revisar duplicado",INDEX('Catalogo CU'!$M$9:$M$500,MATCH(A11,'Catalogo CU'!$A$9:$A$500,0)))) -> Válido
A12: CU-004 | B12: =INDEX('Catalogo CU'!$D$9:$D$500,MATCH(A12,'Catalogo CU'!$A$9:$A$500,0)) -> Ubicar unidad logística en bodega | C12: =INDEX('Catalogo CU'!$C$9:$C$500,MATCH(A12,'Catalogo CU'!$A$9:$A$500,0)) -> E1 | D12: =INDEX('Catalogo CU'!$G$9:$G$500,MATCH(A12,'Catalogo CU'!$A$9:$A$500,0)) -> 1 | E12: =INDEX('Catalogo CU'!$J$9:$J$500,MATCH(A12,'Catalogo CU'!$A$9:$A$500,0)) -> 3 | F12: =IF(D12=0,"Excluido",IF(I12<>"Válido","Revisar",IF(E12<='Criterios y fuentes'!$F$25,"Simple",IF(E12<='Criterios y fuentes'!$F$26,"Medio","Complejo")))) -> Simple | G12: =IF(F12="Excluido",0,IF(F12="Simple",'Criterios y fuentes'!$G$25,IF(F12="Medio",'Criterios y fuentes'!$G$26,IF(F12="Complejo",'Criterios y fuentes'!$G$27,"Revisar")))) -> 5 | H12: =IF(D12=0,0,IF(I12="Válido",D12*G12,"Revisar CU")) -> 5 | I12: =IF(COUNTIF('Catalogo CU'!$A$9:$A$500,A12)<>1,"Revisar ID",IF(COUNTIF($A$9:$A$500,A12)<>1,"Revisar duplicado",INDEX('Catalogo CU'!$M$9:$M$500,MATCH(A12,'Catalogo CU'!$A$9:$A$500,0)))) -> Válido
A13: CU-005 | B13: =INDEX('Catalogo CU'!$D$9:$D$500,MATCH(A13,'Catalogo CU'!$A$9:$A$500,0)) -> Mantener maestro de productos | C13: =INDEX('Catalogo CU'!$C$9:$C$500,MATCH(A13,'Catalogo CU'!$A$9:$A$500,0)) -> E1 | D13: =INDEX('Catalogo CU'!$G$9:$G$500,MATCH(A13,'Catalogo CU'!$A$9:$A$500,0)) -> 1 | E13: =INDEX('Catalogo CU'!$J$9:$J$500,MATCH(A13,'Catalogo CU'!$A$9:$A$500,0)) -> 5 | F13: =IF(D13=0,"Excluido",IF(I13<>"Válido","Revisar",IF(E13<='Criterios y fuentes'!$F$25,"Simple",IF(E13<='Criterios y fuentes'!$F$26,"Medio","Complejo")))) -> Medio | G13: =IF(F13="Excluido",0,IF(F13="Simple",'Criterios y fuentes'!$G$25,IF(F13="Medio",'Criterios y fuentes'!$G$26,IF(F13="Complejo",'Criterios y fuentes'!$G$27,"Revisar")))) -> 10 | H13: =IF(D13=0,0,IF(I13="Válido",D13*G13,"Revisar CU")) -> 10 | I13: =IF(COUNTIF('Catalogo CU'!$A$9:$A$500,A13)<>1,"Revisar ID",IF(COUNTIF($A$9:$A$500,A13)<>1,"Revisar duplicado",INDEX('Catalogo CU'!$M$9:$M$500,MATCH(A13,'Catalogo CU'!$A$9:$A$500,0)))) -> Válido
A14: CU-006 | B14: =INDEX('Catalogo CU'!$D$9:$D$500,MATCH(A14,'Catalogo CU'!$A$9:$A$500,0)) -> Configurar instalaciones y ubicaciones | C14: =INDEX('Catalogo CU'!$C$9:$C$500,MATCH(A14,'Catalogo CU'!$A$9:$A$500,0)) -> E1 | D14: =INDEX('Catalogo CU'!$G$9:$G$500,MATCH(A14,'Catalogo CU'!$A$9:$A$500,0)) -> 1 | E14: =INDEX('Catalogo CU'!$J$9:$J$500,MATCH(A14,'Catalogo CU'!$A$9:$A$500,0)) -> 5 | F14: =IF(D14=0,"Excluido",IF(I14<>"Válido","Revisar",IF(E14<='Criterios y fuentes'!$F$25,"Simple",IF(E14<='Criterios y fuentes'!$F$26,"Medio","Complejo")))) -> Medio | G14: =IF(F14="Excluido",0,IF(F14="Simple",'Criterios y fuentes'!$G$25,IF(F14="Medio",'Criterios y fuentes'!$G$26,IF(F14="Complejo",'Criterios y fuentes'!$G$27,"Revisar")))) -> 10 | H14: =IF(D14=0,0,IF(I14="Válido",D14*G14,"Revisar CU")) -> 10 | I14: =IF(COUNTIF('Catalogo CU'!$A$9:$A$500,A14)<>1,"Revisar ID",IF(COUNTIF($A$9:$A$500,A14)<>1,"Revisar duplicado",INDEX('Catalogo CU'!$M$9:$M$500,MATCH(A14,'Catalogo CU'!$A$9:$A$500,0)))) -> Válido
A15: CU-007 | B15: =INDEX('Catalogo CU'!$D$9:$D$500,MATCH(A15,'Catalogo CU'!$A$9:$A$500,0)) -> Consultar stock y disponibilidad | C15: =INDEX('Catalogo CU'!$C$9:$C$500,MATCH(A15,'Catalogo CU'!$A$9:$A$500,0)) -> E1 | D15: =INDEX('Catalogo CU'!$G$9:$G$500,MATCH(A15,'Catalogo CU'!$A$9:$A$500,0)) -> 1 | E15: =INDEX('Catalogo CU'!$J$9:$J$500,MATCH(A15,'Catalogo CU'!$A$9:$A$500,0)) -> 3 | F15: =IF(D15=0,"Excluido",IF(I15<>"Válido","Revisar",IF(E15<='Criterios y fuentes'!$F$25,"Simple",IF(E15<='Criterios y fuentes'!$F$26,"Medio","Complejo")))) -> Simple | G15: =IF(F15="Excluido",0,IF(F15="Simple",'Criterios y fuentes'!$G$25,IF(F15="Medio",'Criterios y fuentes'!$G$26,IF(F15="Complejo",'Criterios y fuentes'!$G$27,"Revisar")))) -> 5 | H15: =IF(D15=0,0,IF(I15="Válido",D15*G15,"Revisar CU")) -> 5 | I15: =IF(COUNTIF('Catalogo CU'!$A$9:$A$500,A15)<>1,"Revisar ID",IF(COUNTIF($A$9:$A$500,A15)<>1,"Revisar duplicado",INDEX('Catalogo CU'!$M$9:$M$500,MATCH(A15,'Catalogo CU'!$A$9:$A$500,0)))) -> Válido
A16: CU-008 | B16: =INDEX('Catalogo CU'!$D$9:$D$500,MATCH(A16,'Catalogo CU'!$A$9:$A$500,0)) -> Aprobar y ejecutar propuesta de slotting | C16: =INDEX('Catalogo CU'!$C$9:$C$500,MATCH(A16,'Catalogo CU'!$A$9:$A$500,0)) -> E1 | D16: =INDEX('Catalogo CU'!$G$9:$G$500,MATCH(A16,'Catalogo CU'!$A$9:$A$500,0)) -> 1 | E16: =INDEX('Catalogo CU'!$J$9:$J$500,MATCH(A16,'Catalogo CU'!$A$9:$A$500,0)) -> 5 | F16: =IF(D16=0,"Excluido",IF(I16<>"Válido","Revisar",IF(E16<='Criterios y fuentes'!$F$25,"Simple",IF(E16<='Criterios y fuentes'!$F$26,"Medio","Complejo")))) -> Medio | G16: =IF(F16="Excluido",0,IF(F16="Simple",'Criterios y fuentes'!$G$25,IF(F16="Medio",'Criterios y fuentes'!$G$26,IF(F16="Complejo",'Criterios y fuentes'!$G$27,"Revisar")))) -> 10 | H16: =IF(D16=0,0,IF(I16="Válido",D16*G16,"Revisar CU")) -> 10 | I16: =IF(COUNTIF('Catalogo CU'!$A$9:$A$500,A16)<>1,"Revisar ID",IF(COUNTIF($A$9:$A$500,A16)<>1,"Revisar duplicado",INDEX('Catalogo CU'!$M$9:$M$500,MATCH(A16,'Catalogo CU'!$A$9:$A$500,0)))) -> Válido
A17: CU-009 | B17: =INDEX('Catalogo CU'!$D$9:$D$500,MATCH(A17,'Catalogo CU'!$A$9:$A$500,0)) -> Realizar conteo cíclico y ajuste | C17: =INDEX('Catalogo CU'!$C$9:$C$500,MATCH(A17,'Catalogo CU'!$A$9:$A$500,0)) -> E1 | D17: =INDEX('Catalogo CU'!$G$9:$G$500,MATCH(A17,'Catalogo CU'!$A$9:$A$500,0)) -> 1 | E17: =INDEX('Catalogo CU'!$J$9:$J$500,MATCH(A17,'Catalogo CU'!$A$9:$A$500,0)) -> 6 | F17: =IF(D17=0,"Excluido",IF(I17<>"Válido","Revisar",IF(E17<='Criterios y fuentes'!$F$25,"Simple",IF(E17<='Criterios y fuentes'!$F$26,"Medio","Complejo")))) -> Medio | G17: =IF(F17="Excluido",0,IF(F17="Simple",'Criterios y fuentes'!$G$25,IF(F17="Medio",'Criterios y fuentes'!$G$26,IF(F17="Complejo",'Criterios y fuentes'!$G$27,"Revisar")))) -> 10 | H17: =IF(D17=0,0,IF(I17="Válido",D17*G17,"Revisar CU")) -> 10 | I17: =IF(COUNTIF('Catalogo CU'!$A$9:$A$500,A17)<>1,"Revisar ID",IF(COUNTIF($A$9:$A$500,A17)<>1,"Revisar duplicado",INDEX('Catalogo CU'!$M$9:$M$500,MATCH(A17,'Catalogo CU'!$A$9:$A$500,0)))) -> Válido
A18: CU-010 | B18: =INDEX('Catalogo CU'!$D$9:$D$500,MATCH(A18,'Catalogo CU'!$A$9:$A$500,0)) -> Transferir inventario entre sitios | C18: =INDEX('Catalogo CU'!$C$9:$C$500,MATCH(A18,'Catalogo CU'!$A$9:$A$500,0)) -> E1 | D18: =INDEX('Catalogo CU'!$G$9:$G$500,MATCH(A18,'Catalogo CU'!$A$9:$A$500,0)) -> 1 | E18: =INDEX('Catalogo CU'!$J$9:$J$500,MATCH(A18,'Catalogo CU'!$A$9:$A$500,0)) -> 6 | F18: =IF(D18=0,"Excluido",IF(I18<>"Válido","Revisar",IF(E18<='Criterios y fuentes'!$F$25,"Simple",IF(E18<='Criterios y fuentes'!$F$26,"Medio","Complejo")))) -> Medio | G18: =IF(F18="Excluido",0,IF(F18="Simple",'Criterios y fuentes'!$G$25,IF(F18="Medio",'Criterios y fuentes'!$G$26,IF(F18="Complejo",'Criterios y fuentes'!$G$27,"Revisar")))) -> 10 | H18: =IF(D18=0,0,IF(I18="Válido",D18*G18,"Revisar CU")) -> 10 | I18: =IF(COUNTIF('Catalogo CU'!$A$9:$A$500,A18)<>1,"Revisar ID",IF(COUNTIF($A$9:$A$500,A18)<>1,"Revisar duplicado",INDEX('Catalogo CU'!$M$9:$M$500,MATCH(A18,'Catalogo CU'!$A$9:$A$500,0)))) -> Válido
A19: CU-011 | B19: =INDEX('Catalogo CU'!$D$9:$D$500,MATCH(A19,'Catalogo CU'!$A$9:$A$500,0)) -> Consultar ocupación de bodegas | C19: =INDEX('Catalogo CU'!$C$9:$C$500,MATCH(A19,'Catalogo CU'!$A$9:$A$500,0)) -> E1 | D19: =INDEX('Catalogo CU'!$G$9:$G$500,MATCH(A19,'Catalogo CU'!$A$9:$A$500,0)) -> 1 | E19: =INDEX('Catalogo CU'!$J$9:$J$500,MATCH(A19,'Catalogo CU'!$A$9:$A$500,0)) -> 3 | F19: =IF(D19=0,"Excluido",IF(I19<>"Válido","Revisar",IF(E19<='Criterios y fuentes'!$F$25,"Simple",IF(E19<='Criterios y fuentes'!$F$26,"Medio","Complejo")))) -> Simple | G19: =IF(F19="Excluido",0,IF(F19="Simple",'Criterios y fuentes'!$G$25,IF(F19="Medio",'Criterios y fuentes'!$G$26,IF(F19="Complejo",'Criterios y fuentes'!$G$27,"Revisar")))) -> 5 | H19: =IF(D19=0,0,IF(I19="Válido",D19*G19,"Revisar CU")) -> 5 | I19: =IF(COUNTIF('Catalogo CU'!$A$9:$A$500,A19)<>1,"Revisar ID",IF(COUNTIF($A$9:$A$500,A19)<>1,"Revisar duplicado",INDEX('Catalogo CU'!$M$9:$M$500,MATCH(A19,'Catalogo CU'!$A$9:$A$500,0)))) -> Válido
A20: CU-012 | B20: =INDEX('Catalogo CU'!$D$9:$D$500,MATCH(A20,'Catalogo CU'!$A$9:$A$500,0)) -> Gestionar alertas de vencimiento en bodega | C20: =INDEX('Catalogo CU'!$C$9:$C$500,MATCH(A20,'Catalogo CU'!$A$9:$A$500,0)) -> E1 | D20: =INDEX('Catalogo CU'!$G$9:$G$500,MATCH(A20,'Catalogo CU'!$A$9:$A$500,0)) -> 1 | E20: =INDEX('Catalogo CU'!$J$9:$J$500,MATCH(A20,'Catalogo CU'!$A$9:$A$500,0)) -> 3 | F20: =IF(D20=0,"Excluido",IF(I20<>"Válido","Revisar",IF(E20<='Criterios y fuentes'!$F$25,"Simple",IF(E20<='Criterios y fuentes'!$F$26,"Medio","Complejo")))) -> Simple | G20: =IF(F20="Excluido",0,IF(F20="Simple",'Criterios y fuentes'!$G$25,IF(F20="Medio",'Criterios y fuentes'!$G$26,IF(F20="Complejo",'Criterios y fuentes'!$G$27,"Revisar")))) -> 5 | H20: =IF(D20=0,0,IF(I20="Válido",D20*G20,"Revisar CU")) -> 5 | I20: =IF(COUNTIF('Catalogo CU'!$A$9:$A$500,A20)<>1,"Revisar ID",IF(COUNTIF($A$9:$A$500,A20)<>1,"Revisar duplicado",INDEX('Catalogo CU'!$M$9:$M$500,MATCH(A20,'Catalogo CU'!$A$9:$A$500,0)))) -> Válido
... A99: CU-091 | B99: =INDEX('Catalogo CU'!$D$9:$D$500,MATCH(A99,'Catalogo CU'!$A$9:$A$500,0)) -> Clasificar información y aplicar acceso | C99: =INDEX('Catalogo CU'!$C$9:$C$500,MATCH(A99,'Catalogo CU'!$A$9:$A$500,0)) -> E1 | D99: =INDEX('Catalogo CU'!$G$9:$G$500,MATCH(A99,'Catalogo CU'!$A$9:$A$500,0)) -> 1 | E99: =INDEX('Catalogo CU'!$J$9:$J$500,MATCH(A99,'Catalogo CU'!$A$9:$A$500,0)) -> 4 | F99: =IF(D99=0,"Excluido",IF(I99<>"Válido","Revisar",IF(E99<='Criterios y fuentes'!$F$25,"Simple",IF(E99<='Criterios y fuentes'!$F$26,"Medio","Complejo")))) -> Medio | G99: =IF(F99="Excluido",0,IF(F99="Simple",'Criterios y fuentes'!$G$25,IF(F99="Medio",'Criterios y fuentes'!$G$26,IF(F99="Complejo",'Criterios y fuentes'!$G$27,"Revisar")))) -> 10 | H99: =IF(D99=0,0,IF(I99="Válido",D99*G99,"Revisar CU")) -> 10 | I99: =IF(COUNTIF('Catalogo CU'!$A$9:$A$500,A99)<>1,"Revisar ID",IF(COUNTIF($A$9:$A$500,A99)<>1,"Revisar duplicado",INDEX('Catalogo CU'!$M$9:$M$500,MATCH(A99,'Catalogo CU'!$A$9:$A$500,0)))) -> Válido

Sheet Puntos sin ajustar
A2: Puntos de casos de uso sin ajustar
A4: UUCP = UAW + UUCW. Los actores se cuentan una vez; su reparto E1/E2 es proporcional al peso funcional.
A8: Componente | B8: Total | C8: Etapa 1 | D8: Etapa 2 | E8: Criterio
A9: UAW | B9: ='Actores UAW'!B5 -> 75 | C9: =IF(AND(ISNUMBER(B9),ISNUMBER(B10),B10>0),B9*C10/B10,"Revisar alcance") -> 59.810127 | D9: =IF(AND(ISNUMBER(B9),ISNUMBER(C9)),B9-C9,"Revisar alcance") -> 15.189873 | E9: Reparto proporcional a UUCW para distribuir esfuerzo; no son actores adicionales.
A10: UUCW | B10: ='Casos UUCW'!B5 -> 790 | C10: =IF(ISNUMBER(B10),SUMIFS('Casos UUCW'!$H$9:$H$500,'Casos UUCW'!$C$9:$C$500,"E1"),"Revisar casos") -> 630 | D10: =IF(ISNUMBER(B10),SUMIFS('Casos UUCW'!$H$9:$H$500,'Casos UUCW'!$C$9:$C$500,"E2"),"Revisar casos") -> 160 | E10: Suma de aportes de casos incluidos según etapa del Catálogo.
A11: UUCP | B11: =IF(AND(ISNUMBER(B9),ISNUMBER(B10)),SUM(B9:B10),"Revisar conteo") -> 865 | C11: =IF(AND(ISNUMBER(C9),ISNUMBER(C10)),SUM(C9:C10),"Revisar conteo") -> 689.81013 | D11: =IF(AND(ISNUMBER(D9),ISNUMBER(D10)),SUM(D9:D10),"Revisar conteo") -> 175.18987 | E11: Tamaño bruto del alcance completo; etapas aditivas.

Sheet Factores tecnicos
A2: Factor de complejidad técnica
A4: Puntuaciones propuestas y justificadas. Cambie valores enteros de 0 a 5 en las celdas amarillas.
A5: TCF | B5: =IF(ISNUMBER(E5),'Criterios y fuentes'!$B$31+'Criterios y fuentes'!$B$32*E5,"Revisar puntuaciones") -> 1.255 | D5: Suma ponderada | E5: =IF(COUNTIF(H9:H21,"<>Válido")>0,"Revisar factores",SUM(E9:E21)) -> 65.5
A8: ID | B8: Factor técnico | C8: Peso | D8: Puntuación | E8: Peso × valor | F8: Justificación propuesta | G8: Referencia | H8: Control
A9: T1 | B9: Sistema distribuido | C9: 2 | D9: 5 | E9: =IF(H9="Válido",C9*D9,"Revisar valor") -> 10 | F9: Nube, cinco sitios y terminales con autoridad local y reconciliación. | G9: SD3 §§3.3–3.4; SD4 continuidad | H9: =IF(AND(ISNUMBER(D9),D9>=0,D9<=5,MOD(D9,1)=0),"Válido","Revisar puntuación") -> Válido
A10: T2 | B10: Objetivos de desempeño | C10: 1 | D10: 5 | E10: =IF(H10="Válido",C10*D10,"Revisar valor") -> 5 | F10: Hay umbrales exigibles para pedido, picking, stock y planificación en peak. | G10: SD4 dimensionamiento; SD9 pruebas | H10: =IF(AND(ISNUMBER(D10),D10>=0,D10<=5,MOD(D10,1)=0),"Válido","Revisar puntuación") -> Válido
A11: T3 | B11: Eficiencia del usuario final | C11: 1 | D11: 5 | E11: =IF(H11="Válido",C11*D11,"Revisar valor") -> 5 | F11: Picking nocturno, ventana de despacho y trabajo de campo exigen pocos pasos. | G11: SD2 problema; SD3 RF-05; SD9 | H11: =IF(AND(ISNUMBER(D11),D11>=0,D11<=5,MOD(D11,1)=0),"Válido","Revisar puntuación") -> Válido
A12: T4 | B12: Procesamiento interno complejo | C12: 1 | D12: 5 | E12: =IF(H12="Válido",C12*D12,"Revisar valor") -> 5 | F12: FEFO, reservas concurrentes, VRP, reglas sanitarias, EDI y costeo. | G12: SD3 RF; SD4 módulos; SD5 | H12: =IF(AND(ISNUMBER(D12),D12>=0,D12<=5,MOD(D12,1)=0),"Válido","Revisar puntuación") -> Válido
A13: T5 | B13: Código reutilizable | C13: 1 | D13: 3 | E13: =IF(H13="Válido",C13*D13,"Revisar valor") -> 3 | F13: Base compartida reutilizable entre módulos; no se exige producto genérico para otras empresas. | G13: SD4 base compartida | H13: =IF(AND(ISNUMBER(D13),D13>=0,D13<=5,MOD(D13,1)=0),"Válido","Revisar puntuación") -> Válido
A14: T6 | B14: Facilidad de instalación | C14: 0.5 | D14: 4 | E14: =IF(H14="Válido",C14*D14,"Revisar valor") -> 2 | F14: Olas, borde, móviles y reversión con continuidad operacional. | G14: SD4 despliegue; SD6 DevSecOps; SD7 | H14: =IF(AND(ISNUMBER(D14),D14>=0,D14<=5,MOD(D14,1)=0),"Válido","Revisar puntuación") -> Válido
A15: T7 | B15: Facilidad de uso | C15: 0.5 | D15: 5 | E15: =IF(H15="Válido",C15*D15,"Revisar valor") -> 2.5 | F15: Guantes, frío, rotación de preparadores y canal tradicional sin obligación digital. | G15: SD2; SD3 adopción; SD9 accesibilidad | H15: =IF(AND(ISNUMBER(D15),D15>=0,D15<=5,MOD(D15,1)=0),"Válido","Revisar puntuación") -> Válido
A16: T8 | B16: Portabilidad | C16: 2 | D16: 4 | E16: =IF(H16="Válido",C16*D16,"Revisar valor") -> 8 | F16: Navegadores, Android y despliegue híbrido; no se asume portabilidad ilimitada. | G16: SD4 tecnologías y sitios | H16: =IF(AND(ISNUMBER(D16),D16>=0,D16<=5,MOD(D16,1)=0),"Válido","Revisar puntuación") -> Válido
A17: T9 | B17: Facilidad de cambio | C17: 1 | D17: 5 | E17: =IF(H17="Válido",C17*D17,"Revisar valor") -> 5 | F17: Parámetros, flujos, plantillas y doble aprobación sin desarrollo. | G17: SD3 RF-17.02/03/06/09 | H17: =IF(AND(ISNUMBER(D17),D17>=0,D17<=5,MOD(D17,1)=0),"Válido","Revisar puntuación") -> Válido
A18: T10 | B18: Concurrencia | C18: 1 | D18: 5 | E18: =IF(H18="Válido",C18*D18,"Revisar valor") -> 5 | F18: Reserva central, turnos y fuentes concurrentes en peak de septiembre. | G18: SD3 RF-03.03; SD4 carga; SD5 | H18: =IF(AND(ISNUMBER(D18),D18>=0,D18<=5,MOD(D18,1)=0),"Válido","Revisar puntuación") -> Válido
A19: T11 | B19: Objetivos de seguridad | C19: 1 | D19: 5 | E19: =IF(H19="Válido",C19*D19,"Revisar valor") -> 5 | F19: SSO, MFA, segregación, auditoría y protección de datos en campo. | G19: SD3 RF-15; SD4 seguridad; SD9 | H19: =IF(AND(ISNUMBER(D19),D19>=0,D19<=5,MOD(D19,1)=0),"Válido","Revisar puntuación") -> Válido
A20: T12 | B20: Acceso de terceras partes | C20: 1 | D20: 5 | E20: =IF(H20="Válido",C20*D20,"Revisar valor") -> 5 | F20: Portales, ERP, EDI, pagos, mapas, sensores y telemetría. | G20: SD3 actores; SD4 Anexo 4-H | H20: =IF(AND(ISNUMBER(D20),D20>=0,D20<=5,MOD(D20,1)=0),"Válido","Revisar puntuación") -> Válido
A21: T13 | B21: Entrenamiento a usuarios | C21: 1 | D21: 5 | E21: =IF(H21="Válido",C21*D21,"Revisar valor") -> 5 | F21: Varios perfiles y alta rotación requieren UX y ayudas de aprendizaje; ejecución de cursos se estima aparte. | G21: SD2; SD3 §3.4.4; SD7 capacitación | H21: =IF(AND(ISNUMBER(D21),D21>=0,D21<=5,MOD(D21,1)=0),"Válido","Revisar puntuación") -> Válido

Sheet Factores ambiente
A2: Factor de ambiente del equipo
A4: Puntuaciones propuestas. E1–E6: mayor valor favorece al equipo. E7–E8 tienen peso negativo; mayor valor aumenta esfuerzo.
A5: EF | B5: =IF(ISNUMBER(E5),'Criterios y fuentes'!$B$33-'Criterios y fuentes'!$B$34*E5,"Revisar puntuaciones") -> 0.875 | D5: Suma ponderada | E5: =IF(COUNTIF(I9:I16,"<>Válido")>0,"Revisar factores",SUM(E9:E16)) -> 17.5
A6: Adversos | B6: =IF(COUNTIF(I9:I16,"<>Válido")>0,"Revisar ambiente",SUM(H9:H16)) -> 1
A8: ID | B8: Factor de ambiente | C8: Peso | D8: Puntuación | E8: Peso × valor | F8: Justificación propuesta | G8: Referencia | H8: Desfavorable | I8: Control
A9: E1 | B9: Experiencia en el modelo de proyecto | C9: 1.5 | D9: 4 | E9: =IF(I9="Válido",C9*D9,"Revisar valor") -> 6 | F9: Propuesto: la organización declara RUP iterativo y DevSecOps, con gobierno formal. | G9: SD1 gobierno; SD6 §6.2 | H9: =IF(I9<>"Válido","Revisar",IF(C9>0,IF(D9<3,1,0),IF(D9>3,1,0))) -> 0 | I9: =IF(AND(ISNUMBER(D9),D9>=0,D9<=5,MOD(D9,1)=0),"Válido","Revisar puntuación") -> Válido
A10: E2 | B10: Experiencia en el negocio | C10: 0.5 | D10: 3 | E10: =IF(I10="Válido",C10*D10,"Revisar valor") -> 1.5 | F10: Propuesto: experiencia sectorial declarada, pero debe validarse con usuarios y particularidades de Puelche. | G10: SD1 experiencia; SD2; SD3 supuestos | H10: =IF(I10<>"Válido","Revisar",IF(C10>0,IF(D10<3,1,0),IF(D10>3,1,0))) -> 0 | I10: =IF(AND(ISNUMBER(D10),D10>=0,D10<=5,MOD(D10,1)=0),"Válido","Revisar puntuación") -> Válido
A11: E3 | B11: Experiencia en orientación a objetos | C11: 1 | D11: 4 | E11: =IF(I11="Válido",C11*D11,"Revisar valor") -> 4 | F11: Propuesto: equipo especializado en PHP/Laravel y Kotlin; no existe medición individual aportada. | G11: SD1 dotación; SD4 tecnologías | H11: =IF(I11<>"Válido","Revisar",IF(C11>0,IF(D11<3,1,0),IF(D11>3,1,0))) -> 0 | I11: =IF(AND(ISNUMBER(D11),D11>=0,D11<=5,MOD(D11,1)=0),"Válido","Revisar puntuación") -> Válido
A12: E4 | B12: Capacidad del analista líder | C12: 0.5 | D12: 4 | E12: =IF(I12="Válido",C12*D12,"Revisar valor") -> 2 | F12: Propuesto: roles de arquitectura/datos identificados; validar desempeño del analista asignado. | G12: SD1 estructura; SD6; SD9 | H12: =IF(I12<>"Válido","Revisar",IF(C12>0,IF(D12<3,1,0),IF(D12>3,1,0))) -> 0 | I12: =IF(AND(ISNUMBER(D12),D12>=0,D12<=5,MOD(D12,1)=0),"Válido","Revisar puntuación") -> Válido
A13: E5 | B13: Motivación | C13: 1 | D13: 4 | E13: =IF(I13="Válido",C13*D13,"Revisar valor") -> 4 | F13: Propuesto para planificación; requiere consenso del equipo, no se presenta como dato observado. | G13: Supuesto de estimación autorizado por el usuario | H13: =IF(I13<>"Válido","Revisar",IF(C13>0,IF(D13<3,1,0),IF(D13>3,1,0))) -> 0 | I13: =IF(AND(ISNUMBER(D13),D13>=0,D13<=5,MOD(D13,1)=0),"Válido","Revisar puntuación") -> Válido
A14: E6 | B14: Estabilidad de requisitos | C14: 2 | D14: 2 | E14: =IF(I14="Válido",C14*D14,"Revisar valor") -> 4 | F14: Propuesto conservador: contratos externos, reglas térmicas y consultas pendientes pueden cambiar el alcance. | G14: SD3 supuestos y vacíos; SD8 riesgos | H14: =IF(I14<>"Válido","Revisar",IF(C14>0,IF(D14<3,1,0),IF(D14>3,1,0))) -> 1 | I14: =IF(AND(ISNUMBER(D14),D14>=0,D14<=5,MOD(D14,1)=0),"Válido","Revisar puntuación") -> Válido
A15: E7 | B15: Personal a tiempo parcial | C15: -1 | D15: 2 | E15: =IF(I15="Válido",C15*D15,"Revisar valor") -> -2 | F15: Propuesto: núcleo de construcción concentrado con especialistas compartidos y etapas solapadas; validar dedicación real. | G15: SD1 dedicaciones; SD7 T-15 | H15: =IF(I15<>"Válido","Revisar",IF(C15>0,IF(D15<3,1,0),IF(D15>3,1,0))) -> 0 | I15: =IF(AND(ISNUMBER(D15),D15>=0,D15<=5,MOD(D15,1)=0),"Válido","Revisar puntuación") -> Válido
A16: E8 | B16: Dificultad del lenguaje y herramientas | C16: -1 | D16: 2 | E16: =IF(I16="Válido",C16*D16,"Revisar valor") -> -2 | F16: Propuesto: tecnologías conocidas por la empresa; la complejidad distribuida ya se valora en TCF. | G16: SD1 PHP/Laravel/Kotlin; SD4; SD6 | H16: =IF(I16<>"Válido","Revisar",IF(C16>0,IF(D16<3,1,0),IF(D16>3,1,0))) -> 0 | I16: =IF(AND(ISNUMBER(D16),D16>=0,D16<=5,MOD(D16,1)=0),"Válido","Revisar puntuación") -> Válido

Sheet Puntos ajustados
A2: Puntos de casos de uso ajustados
A4: UCP = UUCP × TCF × EF. Se conserva precisión en las fórmulas y solo se formatea la presentación.
A8: Componente | B8: Total | C8: Etapa 1 | D8: Etapa 2 | E8: Interpretación
A9: UUCP | B9: ='Puntos sin ajustar'!B11 -> 865 | C9: ='Puntos sin ajustar'!C11 -> 689.81013 | D9: ='Puntos sin ajustar'!D11 -> 175.18987 | E9: Tamaño bruto del inventario de actores y objetivos.
A10: TCF | B10: ='Factores tecnicos'!B5 -> 1.255 | C10: ='Factores tecnicos'!B5 -> 1.255 | D10: ='Factores tecnicos'!B5 -> 1.255 | E10: Ajuste por exigencias del producto.
A11: EF | B11: ='Factores ambiente'!B5 -> 0.875 | C11: ='Factores ambiente'!B5 -> 0.875 | D11: ='Factores ambiente'!B5 -> 0.875 | E11: Ajuste por equipo y contexto.
A12: UCP | B12: =IF(AND(ISNUMBER(B9),ISNUMBER(B10),ISNUMBER(B11)),B9*B10*B11,"Revisar factores o conteo") -> 949.87812 | C12: =IF(AND(ISNUMBER(C9),ISNUMBER(C10),ISNUMBER(C11)),C9*C10*C11,"Revisar factores o conteo") -> 757.49775 | D12: =IF(AND(ISNUMBER(D9),ISNUMBER(D10),ISNUMBER(D11)),D9*D10*D11,"Revisar factores o conteo") -> 192.38038 | E12: Puntos ajustados que alimentan programación.

Sheet Esfuerzo
A2: Estimación de esfuerzo de desarrollo
A4: Lectura B del curso: UCP × CF son horas de programación; el total se obtiene dividiendo por la participación de programación.
A5: Total de desarrollo (HH) | B5: =B14 -> 47493.906
A8: Paso | B8: Valor | C8: Unidad | D8: Etapa 1 | E8: Etapa 2 | F8: Criterio
A9: Puntos ajustados | B9: ='Puntos ajustados'!B12 -> 949.87812 | C9: UCP | D9: ='Puntos ajustados'!C12 -> 757.49775 | E9: ='Puntos ajustados'!D12 -> 192.38038 | F9: Provienen de la hoja de puntos ajustados.
A10: Factores desfavorables | B10: ='Factores ambiente'!B6 -> 1 | C10: cantidad | F10: E1–E6 menores que 3; E7–E8 mayores que 3.
A11: Factor de conversión | B11: =IF(ISNUMBER(B10),IF(B10>='Criterios y fuentes'!$E$33,"Replantear",IF(B10<='Criterios y fuentes'!$E$31,'Criterios y fuentes'!$F$31,'Criterios y fuentes'!$F$32)),"Revisar ambiente") -> 20 | C11: HH/UCP | F11: Hasta 2: 20; 3–4: 28; desde 5: replantear y no emitir horas.
A12: Esfuerzo de programación | B12: =IF(AND(ISNUMBER(B9),ISNUMBER(B11)),B9*B11,IF(B11="Replantear","Replantear","Revisar entradas")) -> 18997.562 | C12: HH | D12: =IF(AND(ISNUMBER(D9),ISNUMBER($B$11)),D9*$B$11,$B$12) -> 15149.955 | E12: =IF(AND(ISNUMBER(E9),ISNUMBER($B$11)),E9*$B$11,$B$12) -> 3847.6076 | F12: Producto UCP × CF sin redondeo intermedio.
A13: Participación de programación | B13: =B22 -> 0.4 | C13: proporción | F13: Se enlaza al porcentaje editable de la actividad Programación.
A14: Esfuerzo total de desarrollo | B14: =IF(B11="Replantear","Replantear",IF(NOT(ISNUMBER(B12)),"Revisar entradas",IF(AND(COUNT(B20:B24)=5,MIN(B20:B24)>=0,MAX(B20:B24)<=1,ABS(SUM(B20:B24)-1)<0.000000001,B22>0),B12/B22,"Revisar porcentajes"))) -> 47493.906 | C14: HH | D14: =IF(AND(ISNUMBER(D12),ISNUMBER($B$14)),D12/$B$22,$B$14) -> 37874.887 | E14: =IF(AND(ISNUMBER(E12),ISNUMBER($B$14)),E12/$B$22,$B$14) -> 9619.019 | F14: Programación dividida por su participación en el total.
A15: Estado del cálculo | B15: =IF(B11="Replantear","Replantear: 5 o más factores desfavorables",IF(ISNUMBER(B14),"Calculado con valores propuestos",B14)) -> Calculado con valores propuestos | F15: Las horas no se presentan como cero cuando faltan factores o se debe replantear.
A19: Actividad | B19: Participación | C19: Horas totales | D19: Horas E1 | E19: Horas E2 | F19: Incluye
A20: Análisis | B20: 0.1 | C20: =IF(ISNUMBER($B$14),$B$14*$B20,$B$14) -> 4749.3906 | D20: =IF(ISNUMBER($D$14),$D$14*$B20,$D$14) -> 3787.4887 | E20: =IF(ISNUMBER($E$14),$E$14*$B20,$E$14) -> 961.9019 | F20: Levantamiento, casos de uso y especificación funcional.
A21: Diseño | B21: 0.2 | C21: =IF(ISNUMBER($B$14),$B$14*$B21,$B$14) -> 9498.7812 | D21: =IF(ISNUMBER($D$14),$D$14*$B21,$D$14) -> 7574.9775 | E21: =IF(ISNUMBER($E$14),$E$14*$B21,$E$14) -> 1923.8038 | F21: Arquitectura, datos, diseño detallado y experiencia de usuario.
A22: Programación | B22: 0.4 | C22: =IF(ISNUMBER($B$14),$B$14*$B22,$B$14) -> 18997.562 | D22: =IF(ISNUMBER($D$14),$D$14*$B22,$D$14) -> 15149.955 | E22: =IF(ISNUMBER($E$14),$E$14*$B22,$E$14) -> 3847.6076 | F22: Construcción, integraciones y pruebas unitarias.
A23: Pruebas | B23: 0.15 | C23: =IF(ISNUMBER($B$14),$B$14*$B23,$B$14) -> 7124.0859 | D23: =IF(ISNUMBER($D$14),$D$14*$B23,$D$14) -> 5681.2331 | E23: =IF(ISNUMBER($E$14),$E$14*$B23,$E$14) -> 1442.8528 | F23: Integración, sistema, aceptación y corrección de defectos.
A24: Sobrecarga | B24: 0.15 | C24: =IF(ISNUMBER($B$14),$B$14*$B24,$B$14) -> 7124.0859 | D24: =IF(ISNUMBER($D$14),$D$14*$B24,$D$14) -> 5681.2331 | E24: =IF(ISNUMBER($E$14),$E$14*$B24,$E$14) -> 1442.8528 | F24: Gestión, aseguramiento, documentación y coordinación del desarrollo.
A25: Total | B25: =SUM(B20:B24) -> 1 | C25: =IF(ISNUMBER($B$14),SUM(C20:C24),$B$14) -> 47493.906 | D25: =IF(ISNUMBER($B$14),SUM(D20:D24),$B$14) -> 37874.887 | E25: =IF(ISNUMBER($B$14),SUM(E20:E24),$B$14) -> 9619.019 | F25: La suma de participaciones debe ser 100 %.
A28: No incluye operación, infraestructura, migración, capacitación ejecutada ni reservas.
A30: Las actividades de desarrollo no son las etapas contractuales E1/E2. El reparto por etapa usa la regla visible en UUCP.
A32: Sin histórico medido de productividad: se utiliza la regla de conversión del PDF; las puntuaciones del equipo son propuestas.

Sheet Cobertura
A2: Cobertura de requisitos e innovaciones
A4: Control independiente: 180 requisitos de SD3 y cinco innovaciones. Los entregables o servicios se justifican sin inflar casos de uso.
A8: ID fuente | B8: Requisito u objetivo | C8: Prioridad / etapa | D8: Casos de uso | E8: Tratamiento | F8: Estado de selección | G8: Fundamento
A9: RF-01.01 | B9: El sistema debe registrar la recepción física de un proveedor validando las cantidades recibidas por SKU contra la OC y generando una alerta por cada discrepancia, sin bloquear el cierre. | C9: Crítica / E1 | D9: CU-001 | E9: Funcional | F9: =IF(AND(COUNTIF('Catalogo CU'!$A$9:$A$500,"CU-001")=1),IF(SUMIF('Catalogo CU'!$A$9:$A$500,"CU-001",'Catalogo CU'!$G$9:$G$500)=1,"Incluido",IF(SUMIF('Catalogo CU'!$A$9:$A$500,"CU-001",'Catalogo CU'!$G$9:$G$500)>0,"Parcial por selección","Fuera por selección")),"Revisar vínculo") -> Incluido | G9: Cubierto por los objetivos indicados; los pasos internos no se suman como transacciones.
A10: RF-01.02 | B10: El sistema debe exigir el número de lote del proveedor en campo estructurado para todo SKU con trazabilidad obligatoria, capturándolo por escaneo GS1 (AI 10) o ingreso manual, y bloqueando el avance si el campo está vacío. | C10: Crítica / E1 | D10: CU-001 | E10: Funcional | F10: =IF(AND(COUNTIF('Catalogo CU'!$A$9:$A$500,"CU-001")=1),IF(SUMIF('Catalogo CU'!$A$9:$A$500,"CU-001",'Catalogo CU'!$G$9:$G$500)=1,"Incluido",IF(SUMIF('Catalogo CU'!$A$9:$A$500,"CU-001",'Catalogo CU'!$G$9:$G$500)>0,"Parcial por selección","Fuera por selección")),"Revisar vínculo") -> Incluido | G10: Cubierto por los objetivos indicados; los pasos internos no se suman como transacciones.
A11: RF-01.03 | B11: El sistema debe registrar la fecha de vencimiento en formato DD/MM/AAAA para todo SKU con control de vencimiento habilitado, vinculándola al lote y a la ubicación asignada como entrada para la lógica FEFO. | C11: Crítica / E1 | D11: CU-001 | E11: Funcional | F11: =IF(AND(COUNTIF('Catalogo CU'!$A$9:$A$500,"CU-001")=1),IF(SUMIF('Catalogo CU'!$A$9:$A$500,"CU-001",'Catalogo CU'!$G$9:$G$500)=1,"Incluido",IF(SUMIF('Catalogo CU'!$A$9:$A$500,"CU-001",'Catalogo CU'!$G$9:$G$500)>0,"Parcial por selección","Fuera por selección")),"Revisar vínculo") -> Incluido | G11: Cubierto por los objetivos indicados; los pasos internos no se suman como transacciones.
A12: RF-01.04 | B12: El sistema debe permitir registrar una no conformidad durante la recepción seleccionando su tipo desde una lista predefinida e ingresando SKU, lote, cantidad afectada y al menos una fotografía capturada desde el dispositivo. | C12: Alta / E1 | D12: CU-002 | E12: Funcional | F12: =IF(AND(COUNTIF('Catalogo CU'!$A$9:$A$500,"CU-002")=1),IF(SUMIF('Catalogo CU'!$A$9:$A$500,"CU-002",'Catalogo CU'!$G$9:$G$500)=1,"Incluido",IF(SUMIF('Catalogo CU'!$A$9:$A$500,"CU-002",'Catalogo CU'!$G$9:$G$500)>0,"Parcial por selección","Fuera por selección")),"Revisar vínculo") -> Incluido | G12: Cubierto por los objetivos indicados; los pasos internos no se suman como transacciones.
A13: RF-01.05 | B13: Al confirmar una no conformidad, el sistema debe cambiar automáticamente a estado ‘Cuarentena’ la cantidad afectada del SKU/lote correspondiente, bloqueándola para picking, y notificar al perfil de calidad mediante una alerta en la aplicación. | C13: Alta / E1 | D13: CU-002 | E13: Funcional | F13: =IF(AND(COUNTIF('Catalogo CU'!$A$9:$A$500,"CU-002")=1),IF(SUMIF('Catalogo CU'!$A$9:$A$500,"CU-002",'Catalogo CU'!$G$9:$G$500)=1,"Incluido",IF(SUMIF('Catalogo CU'!$A$9:$A$500,"CU-002",'Catalogo CU'!$G$9:$G$500)>0,"Parcial por selección","Fuera por selección")),"Revisar vínculo") -> Incluido | G13: Cubierto por los objetivos indicados; los pasos internos no se suman como transacciones.
A14: RF-01.06 | B14: El sistema debe decodificar códigos de barras GS1 interpretando los AIs 01 (GTIN), 10 (lote), 17 (vencimiento) y 00 (SSCC), autocompletando los campos en pantalla; ante código inválido o no registrado, habilita el ingreso manual. | C14: Alta / E1 | D14: CU-001 | E14: Funcional | F14: =IF(AND(COUNTIF('Catalogo CU'!$A$9:$A$500,"CU-001")=1),IF(SUMIF('Catalogo CU'!$A$9:$A$500,"CU-001",'Catalogo CU'!$G$9:$G$500)=1,"Incluido",IF(SUMIF('Catalogo CU'!$A$9:$A$500,"CU-001",'Catalogo CU'!$G$9:$G$500)>0,"Parcial por selección","Fuera por selección")),"Revisar vínculo") -> Incluido | G14: Cubierto por los objetivos indicados; los pasos internos no se suman como transacciones.
A15: RF-01.07 | B15: Al finalizar el registro de un pallet, el sistema debe generar automáticamente un SSCC bajo estándar GS1-128 vinculado al GTIN, lote, fecha de vencimiento y fecha de recepción, e imprimir la etiqueta en la impresora térmica del andén. | C15: Media / E1 | D15: CU-003 | E15: Funcional | F15: =IF(AND(COUNTIF('Catalogo CU'!$A$9:$A$500,"CU-003")=1),IF(SUMIF('Catalogo CU'!$A$9:$A$500,"CU-003",'Catalogo CU'!$G$9:$G$500)=1,"Incluido",IF(SUMIF('Catalogo CU'!$A$9:$A$500,"CU-003",'Catalogo CU'!$G$9:$G$500)>0,"Parcial por selección","Fuera por selección")),"Revisar vínculo") -> Incluido | G15: Cubierto por los objetivos indicados; los pasos internos no se suman como transacciones.
A16: RF-01.08 | B16: El sistema debe permitir asociar un SSCC a una dirección de almacenamiento (pasillo-columna-nivel) escaneando ambas etiquetas y validando la compatibilidad térmica antes de confirmar. | C16: Media / E1 | D16: CU-004 | E16: Funcional | F16: =IF(AND(COUNTIF('Catalogo CU'!$A$9:$A$500,"CU-004")=1),IF(SUMIF('Catalogo CU'!$A$9:$A$500,"CU-004",'Catalogo CU'!$G$9:$G$500)=1,"Incluido",IF(SUMIF('Catalogo CU'!$A$9:$A$500,"CU-004",'Catalogo CU'!$G$9:$G$500)>0,"Parcial por selección","Fuera por selección")),"Revisar vínculo") -> Incluido | G16: Cubierto por los objetivos indicados; los pasos internos no se suman como transacciones.
A17: RF-01.09 | B17: Al cerrar una recepción, el sistema debe enviar automáticamente la transacción de ingreso de inventario al ERP mediante su interfaz de integración; si el ERP no está disponible, encola la transacción para reintento automático. | C17: Crítica / E1 | D17: CU-001, CU-035 | E17: Funcional | F17: =IF(AND(COUNTIF('Catalogo CU'!$A$9:$A$500,"CU-001")=1,COUNTIF('Catalogo CU'!$A$9:$A$500,"CU-035")=1),IF(SUMIF('Catalogo CU'!$A$9:$A$500,"CU-001",'Catalogo CU'!$G$9:$G$500)+SUMIF('Catalogo CU'!$A$9:$A$500,"CU-035",'Catalogo CU'!$G$9:$G$500)=2,"Incluido",IF(SUMIF('Catalogo CU'!$A$9:$A$500,"CU-001",'Catalogo CU'!$G$9:$G$500)+SUMIF('Catalogo CU'!$A$9:$A$500,"CU-035",'Catalogo CU'!$G$9:$G$500)>0,"Parcial por selección","Fuera por selección")),"Revisar vínculo") -> Incluido | G17: Cubierto por los objetivos indicados; los pasos internos no se suman como transacciones.
A18: RF-01.10 | B18: El sistema debe permitir crear y mantener fichas de producto con atributos obligatorios: descripción, formato, GTIN, SKU interno, tipo de almacenamiento, temperatura mínima y máxima (°C), peso neto (kg), dimensiones (cm), días de vida útil, indicadores de trazabilidad y control de vencimiento (sí/no), clasificación sanitaria y RUT del proveedor. | C18: Crítica / E1 | D18: CU-005 | E18: Funcional | F18: =IF(AND(COUNTIF('Catalogo CU'!$A$9:$A$500,"CU-005")=1),IF(SUMIF('Catalogo CU'!$A$9:$A$500,"CU-005",'Catalogo CU'!$G$9:$G$500)=1,"Incluido",IF(SUMIF('Catalogo CU'!$A$9:$A$500,"CU-005",'Catalogo CU'!$G$9:$G$500)>0,"Parcial por selección","Fuera por selección")),"Revisar vínculo") -> Incluido | G18: Cubierto por los objetivos indicados; los pasos internos no se suman como transacciones.
A19: RF-01.11 | B19: El sistema debe validar la compatibilidad térmica entre el tipo de almacenamiento del SKU y la zona de temperatura de la ubicación destino al realizar un putaway, bloqueando la operación si no son compatibles. | C19: Crítica / E1 | D19: CU-004 | E19: Funcional | F19: =IF(AND(COUNTIF('Catalogo CU'!$A$9:$A$500,"CU-004")=1),IF(SUMIF('Catalogo CU'!$A$9:$A$500,"CU-004",'Catalogo CU'!$G$9:$G$500)=1,"Incluido",IF(SUMIF('Catalogo CU'!$A$9:$A$500,"CU-004",'Catalogo CU'!$G$9:$G$500)>0,"Parcial por selección","Fuera por selección")),"Revisar vínculo") -> Incluido | G19: Cubierto por los objetivos indicados; los pasos internos no se suman como transacciones.
A20: RF-02.01 | B20: El sistema debe permitir registrar y configurar cada instalación de la red logística (centros de distribución y plataformas de cross-docking), definiendo su topología interna: zonas operativas (seco con rango 15–25 °C, refrigerado con rango 2–8 °C, congelado con rango -18 a -25 °C), pasillos, racks, niveles y posiciones individuales de almacenamiento. La configuración debe estar disponible en modo offline. | C20: Alta / E1 | D20: CU-006 | E20: Funcional | F20: =IF(AND(COUNTIF('Catalogo CU'!$A$9:$A$500,"CU-006")=1),IF(SUMIF('Catalogo CU'!$A$9:$A$500,"CU-006",'Catalogo CU'!$G$9:$G$500)=1,"Incluido",IF(SUMIF('Catalogo CU'!$A$9:$A$500,"CU-006",'Catalogo CU'!$G$9:$G$500)>0,"Parcial por selección","Fuera por selección")),"Revisar vínculo") -> Incluido | G20: Cubierto por los objetivos indicados; los pasos internos no se suman como transacciones.
A21: RF-02.02 | B21: El sistema debe consolidar el stock físico en unidades de cada SKU en todos los nodos de la red logística. | C21: Alta / E1 | D21: CU-007 | E21: Funcional | F21: =IF(AND(COUNTIF('Catalogo CU'!$A$9:$A$500,"CU-007")=1),IF(SUMIF('Catalogo CU'!$A$9:$A$500,"CU-007",'Catalogo CU'!$G$9:$G$500)=1,"Incluido",IF(SUMIF('Catalogo CU'!$A$9:$A$500,"CU-007",'Catalogo CU'!$G$9:$G$500)>0,"Parcial por selección","Fuera por selección")),"Revisar vínculo") -> Incluido | G21: Cubierto por los objetivos indicados; los pasos internos no se suman como transacciones.
A22: RF-02.03 | B22: El sistema debe calcular periódicamente una propuesta de reasignación de ubicaciones (slotting) basada en la clasificación de rotación (ABC) del último período configurable, considerando además peso, volumen y compatibilidad de zona. Los productos de clasificación A deben proponerse en ubicaciones cercanas a los andenes de salida. La propuesta debe ser aprobada por el jefe de bodega antes de generar instrucciones de movimiento. | C22: Alta / E1 | D22: CU-008 | E22: Funcional | F22: =IF(AND(COUNTIF('Catalogo CU'!$A$9:$A$500,"CU-008")=1),IF(SUMIF('Catalogo CU'!$A$9:$A$500,"CU-008",'Catalogo CU'!$G$9:$G$500)=1,"Incluido",IF(SUMIF('Catalogo CU'!$A$9:$A$500,"CU-008",'Catalogo CU'!$G$9:$G$500)>0,"Parcial por selección","Fuera por selección")),"Revisar vínculo") -> Incluido | G22: Cubierto por los objetivos indicados; los pasos internos no se suman como transacciones.
A23: RF-02.04 | B23: El sistema debe generar un plan de conteo cíclico mensual que cubra una cantidad de posiciones definidas, seleccionando posiciones por criterios configurables (rotación, valor, discrepancia histórica). Las tareas de conteo deben asignarse a los dispositivos de los operarios de bodega en modo de conteo ciego, sin mostrar la cantidad teórica. Tras el ingreso de la cantidad física, el sistema compara contra el teórico y registra la diferencia con su causa en campo estructurado. | C23: Alta / E1 | D23: CU-009 | E23: Funcional | F23: =IF(AND(COUNTIF('Catalogo CU'!$A$9:$A$500,"CU-009")=1),IF(SUMIF('Catalogo CU'!$A$9:$A$500,"CU-009",'Catalogo CU'!$G$9:$G$500)=1,"Incluido",IF(SUMIF('Catalogo CU'!$A$9:$A$500,"CU-009",'Catalogo CU'!$G$9:$G$500)>0,"Parcial por selección","Fuera por selección")),"Revisar vínculo") -> Incluido | G23: Cubierto por los objetivos indicados; los pasos internos no se suman como transacciones.
A24: RF-02.05 | B24: El sistema debe calcular el stock disponible para venta por SKU y por centro de distribución, definido como la diferencia entre el stock físico registrado y el inventario comprometido por pedidos confirmados pendientes de preparación. En modo desconectado, la consulta debe reflejar el stock al momento de la última sincronización, indicando la antigüedad del dato. | C24: Alta / E1 | D24: CU-007 | E24: Funcional | F24: =IF(AND(COUNTIF('Catalogo CU'!$A$9:$A$500,"CU-007")=1),IF(SUMIF('Catalogo CU'!$A$9:$A$500,"CU-007",'Catalogo CU'!$G$9:$G$500)=1,"Incluido",IF(SUMIF('Catalogo CU'!$A$9:$A$500,"CU-007",'Catalogo CU'!$G$9:$G$500)>0,"Parcial por selección","Fuera por selección")),"Revisar vínculo") -> Incluido | G24: Cubierto por los objetivos indicados; los pasos internos no se suman como transacciones.
A25: RF-02.06 | B25: El sistema debe registrar como «en tránsito» todo inventario despachado desde un nodo de origen hacia un nodo destino, desde la carga confirmada hasta la recepción confirmada en destino, y generar la transacción de transferencia correspondiente en el ERP. | C25: Media / E1 | D25: CU-010, CU-035 | E25: Funcional | F25: =IF(AND(COUNTIF('Catalogo CU'!$A$9:$A$500,"CU-010")=1,COUNTIF('Catalogo CU'!$A$9:$A$500,"CU-035")=1),IF(SUMIF('Catalogo CU'!$A$9:$A$500,"CU-010",'Catalogo CU'!$G$9:$G$500)+SUMIF('Catalogo CU'!$A$9:$A$500,"CU-035",'Catalogo CU'!$G$9:$G$500)=2,"Incluido",IF(SUMIF('Catalogo CU'!$A$9:$A$500,"CU-010",'Catalogo CU'!$G$9:$G$500)+SUMIF('Catalogo CU'!$A$9:$A$500,"CU-035",'Catalogo CU'!$G$9:$G$500)>0,"Parcial por selección","Fuera por selección")),"Revisar vínculo") -> Incluido | G25: Cubierto por los objetivos indicados; los pasos internos no se suman como transacciones.
A26: RF-02.07 | B26: El sistema debe permitir consultar el nivel de ocupación de cada centro de distribución, desglosado por zona operativa (seco, refrigerado, congelado), expresado como porcentaje de ubicaciones físicas utilizadas respecto de la capacidad total configurada. | C26: Alta / E1 | D26: CU-011 | E26: Funcional | F26: =IF(AND(COUNTIF('Catalogo CU'!$A$9:$A$500,"CU-011")=1),IF(SUMIF('Catalogo CU'!$A$9:$A$500,"CU-011",'Catalogo CU'!$G$9:$G$500)=1,"Incluido",IF(SUMIF('Catalogo CU'!$A$9:$A$500,"CU-011",'Catalogo CU'!$G$9:$G$500)>0,"Parcial por selección","Fuera por selección")),"Revisar vínculo") -> Incluido | G26: Cubierto por los objetivos indicados; los pasos internos no se suman como transacciones.
A27: RF-02.08 | B27: El sistema debe dirigir la preparación de pedidos (picking) asignando tareas de recolección al dispositivo del preparador, indicando: ubicación, producto, lote, cantidad, y secuencia optimizada de recorrido. El preparador confirma cada línea en el dispositivo. Al no encontrar un producto o encontrar cantidad insuficiente, el preparador debe registrar el faltante con su causa en un campo estructurado (sin stock, producto dañado, producto vencido, error de ubicación, otro). | C27: Alta / E1 | D27: CU-022 | E27: Funcional | F27: =IF(AND(COUNTIF('Catalogo CU'!$A$9:$A$500,"CU-022")=1),IF(SUMIF('Catalogo CU'!$A$9:$A$500,"CU-022",'Catalogo CU'!$G$9:$G$500)=1,"Incluido",IF(SUMIF('Catalogo CU'!$A$9:$A$500,"CU-022",'Catalogo CU'!$G$9:$G$500)>0,"Parcial por selección","Fuera por selección")),"Revisar vínculo") -> Incluido | G27: Cubierto por los objetivos indicados; los pasos internos no se suman como transacciones.
A28: RF-02.09 | B28: El sistema debe gestionar el almacenamiento de productos con fecha de vencimiento aplicando la regla FEFO (First Expired, First Out), priorizando en la preparación de pedidos los lotes con fecha de vencimiento más próxima. El sistema debe alertar cuando un producto en stock alcance un umbral de vida útil remanente configurable. | C28: Alta / E1 | D28: CU-012 | E28: Funcional | F28: =IF(AND(COUNTIF('Catalogo CU'!$A$9:$A$500,"CU-012")=1),IF(SUMIF('Catalogo CU'!$A$9:$A$500,"CU-012",'Catalogo CU'!$G$9:$G$500)=1,"Incluido",IF(SUMIF('Catalogo CU'!$A$9:$A$500,"CU-012",'Catalogo CU'!$G$9:$G$500)>0,"Parcial por selección","Fuera por selección")),"Revisar vínculo") -> Incluido | G28: Cubierto por los objetivos indicados; los pasos internos no se suman como transacciones.
A29: RF-02.10 | B29: El sistema debe proveer una interfaz de trazabilidad que permita buscar y detallar el ciclo de vida completo de un lote. Al consultar un lote específico, debe desglosar su estado actual, ubicación física en bodega, datos de recepción de proveedor y detalle de salida (clientes/mermas). | C29: Alta / E1 | D29: CU-040 | E29: Funcional | F29: =IF(AND(COUNTIF('Catalogo CU'!$A$9:$A$500,"CU-040")=1),IF(SUMIF('Catalogo CU'!$A$9:$A$500,"CU-040",'Catalogo CU'!$G$9:$G$500)=1,"Incluido",IF(SUMIF('Catalogo CU'!$A$9:$A$500,"CU-040",'Catalogo CU'!$G$9:$G$500)>0,"Parcial por selección","Fuera por selección")),"Revisar vínculo") -> Incluido | G29: Cubierto por los objetivos indicados; los pasos internos no se suman como transacciones.
A30: RF-03.01 | B30: La app debe mostrar, con conectividad, el stock disponible en tiempo real para cada SKU al tomar el pedido. | C30: Crítica / E1 | D30: CU-007 | E30: Funcional | F30: =IF(AND(COUNTIF('Catalogo CU'!$A$9:$A$500,"CU-007")=1),IF(SUMIF('Catalogo CU'!$A$9:$A$500,"CU-007",'Catalogo CU'!$G$9:$G$500)=1,"Incluido",IF(SUMIF('Catalogo CU'!$A$9:$A$500,"CU-007",'Catalogo CU'!$G$9:$G$500)>0,"Parcial por selección","Fuera por selección")),"Revisar vínculo") -> Incluido | G30: Cubierto por los objetivos indicados; los pasos internos no se suman como transacciones.
A31: RF-03.02 | B31: La app debe mostrar, sin conectividad, el stock según la última sincronización válida, con su antigüedad visible. | C31: Crítica / E1 | D31: CU-007 | E31: Funcional | F31: =IF(AND(COUNTIF('Catalogo CU'!$A$9:$A$500,"CU-007")=1),IF(SUMIF('Catalogo CU'!$A$9:$A$500,"CU-007",'Catalogo CU'!$G$9:$G$500)=1,"Incluido",IF(SUMIF('Catalogo CU'!$A$9:$A$500,"CU-007",'Catalogo CU'!$G$9:$G$500)>0,"Parcial por selección","Fuera por selección")),"Revisar vínculo") -> Incluido | G31: Cubierto por los objetivos indicados; los pasos internos no se suman como transacciones.
A32: RF-03.03 | B32: El sistema debe reservar el stock comprometido en el momento de la confirmación del pedido en el servidor central de la solución operacional, por orden de llegada a ese servidor (S-08, RNG-01), sin depender de la disponibilidad del ERP. | C32: Alta / E1 | D32: CU-014 | E32: Funcional | F32: =IF(AND(COUNTIF('Catalogo CU'!$A$9:$A$500,"CU-014")=1),IF(SUMIF('Catalogo CU'!$A$9:$A$500,"CU-014",'Catalogo CU'!$G$9:$G$500)=1,"Incluido",IF(SUMIF('Catalogo CU'!$A$9:$A$500,"CU-014",'Catalogo CU'!$G$9:$G$500)>0,"Parcial por selección","Fuera por selección")),"Revisar vínculo") -> Incluido | G32: Cubierto por los objetivos indicados; los pasos internos no se suman como transacciones.
A33: RF-03.04 | B33: La app debe mostrar, con conectividad, el crédito disponible y la deuda vencida del cliente al tomar el pedido. | C33: Crítica / E1 | D33: CU-014 | E33: Funcional | F33: =IF(AND(COUNTIF('Catalogo CU'!$A$9:$A$500,"CU-014")=1),IF(SUMIF('Catalogo CU'!$A$9:$A$500,"CU-014",'Catalogo CU'!$G$9:$G$500)=1,"Incluido",IF(SUMIF('Catalogo CU'!$A$9:$A$500,"CU-014",'Catalogo CU'!$G$9:$G$500)>0,"Parcial por selección","Fuera por selección")),"Revisar vínculo") -> Incluido | G33: Cubierto por los objetivos indicados; los pasos internos no se suman como transacciones.
A34: RF-03.05 | B34: La app debe mostrar, sin conectividad, el crédito y la deuda según la última sincronización válida, con su antigüedad visible. | C34: Crítica / E1 | D34: CU-014 | E34: Funcional | F34: =IF(AND(COUNTIF('Catalogo CU'!$A$9:$A$500,"CU-014")=1),IF(SUMIF('Catalogo CU'!$A$9:$A$500,"CU-014",'Catalogo CU'!$G$9:$G$500)=1,"Incluido",IF(SUMIF('Catalogo CU'!$A$9:$A$500,"CU-014",'Catalogo CU'!$G$9:$G$500)>0,"Parcial por selección","Fuera por selección")),"Revisar vínculo") -> Incluido | G34: Cubierto por los objetivos indicados; los pasos internos no se suman como transacciones.
A35: RF-03.06 | B35: La app debe mostrar el historial de compra del cliente (productos y frecuencia). | C35: Alta / E1 | D35: CU-014 | E35: Funcional | F35: =IF(AND(COUNTIF('Catalogo CU'!$A$9:$A$500,"CU-014")=1),IF(SUMIF('Catalogo CU'!$A$9:$A$500,"CU-014",'Catalogo CU'!$G$9:$G$500)=1,"Incluido",IF(SUMIF('Catalogo CU'!$A$9:$A$500,"CU-014",'Catalogo CU'!$G$9:$G$500)>0,"Parcial por selección","Fuera por selección")),"Revisar vínculo") -> Incluido | G35: Cubierto por los objetivos indicados; los pasos internos no se suman como transacciones.
A36: RF-03.07 | B36: La app debe permitir aplicar una promoción vigente (3x2, descuento por volumen) a una línea de pedido, calculando el descuento automáticamente. | C36: Alta / E1 | D36: CU-014 | E36: Funcional | F36: =IF(AND(COUNTIF('Catalogo CU'!$A$9:$A$500,"CU-014")=1),IF(SUMIF('Catalogo CU'!$A$9:$A$500,"CU-014",'Catalogo CU'!$G$9:$G$500)=1,"Incluido",IF(SUMIF('Catalogo CU'!$A$9:$A$500,"CU-014",'Catalogo CU'!$G$9:$G$500)>0,"Parcial por selección","Fuera por selección")),"Revisar vínculo") -> Incluido | G36: Cubierto por los objetivos indicados; los pasos internos no se suman como transacciones.
A37: RF-03.08 | B37: El sistema debe alertar al preventista cuando el pedido, sumado a la deuda vencida, supere el límite de crédito del cliente. | C37: Crítica / E1 | D37: CU-014 | E37: Funcional | F37: =IF(AND(COUNTIF('Catalogo CU'!$A$9:$A$500,"CU-014")=1),IF(SUMIF('Catalogo CU'!$A$9:$A$500,"CU-014",'Catalogo CU'!$G$9:$G$500)=1,"Incluido",IF(SUMIF('Catalogo CU'!$A$9:$A$500,"CU-014",'Catalogo CU'!$G$9:$G$500)>0,"Parcial por selección","Fuera por selección")),"Revisar vínculo") -> Incluido | G37: Cubierto por los objetivos indicados; los pasos internos no se suman como transacciones.
A38: RF-03.09 | B38: El sistema debe bloquear el envío del pedido cuando este, sumado a la deuda vencida, supere el límite de crédito en más de 110 %. | C38: Crítica / E1 | D38: CU-014 | E38: Funcional | F38: =IF(AND(COUNTIF('Catalogo CU'!$A$9:$A$500,"CU-014")=1),IF(SUMIF('Catalogo CU'!$A$9:$A$500,"CU-014",'Catalogo CU'!$G$9:$G$500)=1,"Incluido",IF(SUMIF('Catalogo CU'!$A$9:$A$500,"CU-014",'Catalogo CU'!$G$9:$G$500)>0,"Parcial por selección","Fuera por selección")),"Revisar vínculo") -> Incluido | G38: Cubierto por los objetivos indicados; los pasos internos no se suman como transacciones.
A39: RF-03.10 | B39: El sistema debe permitir que un supervisor autorice, de forma registrada, el envío de un pedido bloqueado. | C39: Alta / E1 | D39: CU-015 | E39: Funcional | F39: =IF(AND(COUNTIF('Catalogo CU'!$A$9:$A$500,"CU-015")=1),IF(SUMIF('Catalogo CU'!$A$9:$A$500,"CU-015",'Catalogo CU'!$G$9:$G$500)=1,"Incluido",IF(SUMIF('Catalogo CU'!$A$9:$A$500,"CU-015",'Catalogo CU'!$G$9:$G$500)>0,"Parcial por selección","Fuera por selección")),"Revisar vínculo") -> Incluido | G39: Cubierto por los objetivos indicados; los pasos internos no se suman como transacciones.
A40: RF-03.11 | B40: El sistema debe registrar y conservar en cada pedido de preventa el precio acordado por el preventista al tomarlo, conforme a las condiciones comerciales autorizadas, sin modificarlo por cambios posteriores de la lista de precios. | C40: Media / E1 | D40: CU-014, CU-016 | E40: Funcional | F40: =IF(AND(COUNTIF('Catalogo CU'!$A$9:$A$500,"CU-014")=1,COUNTIF('Catalogo CU'!$A$9:$A$500,"CU-016")=1),IF(SUMIF('Catalogo CU'!$A$9:$A$500,"CU-014",'Catalogo CU'!$G$9:$G$500)+SUMIF('Catalogo CU'!$A$9:$A$500,"CU-016",'Catalogo CU'!$G$9:$G$500)=2,"Incluido",IF(SUMIF('Catalogo CU'!$A$9:$A$500,"CU-014",'Catalogo CU'!$G$9:$G$500)+SUMIF('Catalogo CU'!$A$9:$A$500,"CU-016",'Catalogo CU'!$G$9:$G$500)>0,"Parcial por selección","Fuera por selección")),"Revisar vínculo") -> Incluido | G40: Cubierto por los objetivos indicados; los pasos internos no se suman como transacciones.
A41: RF-03.12 | B41: El sistema debe generar una alerta al responsable comercial cuando el importe calculado para el despacho o la facturación difiera del precio registrado en el pedido, para corregir la discrepancia antes de facturar y conservar el precio acordado (RF-03.11). | C41: Media / E1 | D41: CU-016 | E41: Funcional | F41: =IF(AND(COUNTIF('Catalogo CU'!$A$9:$A$500,"CU-016")=1),IF(SUMIF('Catalogo CU'!$A$9:$A$500,"CU-016",'Catalogo CU'!$G$9:$G$500)=1,"Incluido",IF(SUMIF('Catalogo CU'!$A$9:$A$500,"CU-016",'Catalogo CU'!$G$9:$G$500)>0,"Parcial por selección","Fuera por selección")),"Revisar vínculo") -> Incluido | G41: Cubierto por los objetivos indicados; los pasos internos no se suman como transacciones.
A42: RF-03.13 | B42: El sistema debe informar al preventista la fecha y ventana horaria de entrega que puede comprometer, considerando stock, capacidad de despacho y restricciones del cliente. | C42: Crítica / E1 | D42: CU-014 | E42: Funcional | F42: =IF(AND(COUNTIF('Catalogo CU'!$A$9:$A$500,"CU-014")=1),IF(SUMIF('Catalogo CU'!$A$9:$A$500,"CU-014",'Catalogo CU'!$G$9:$G$500)=1,"Incluido",IF(SUMIF('Catalogo CU'!$A$9:$A$500,"CU-014",'Catalogo CU'!$G$9:$G$500)>0,"Parcial por selección","Fuera por selección")),"Revisar vínculo") -> Incluido | G42: Cubierto por los objetivos indicados; los pasos internos no se suman como transacciones.
A43: RF-03.14 | B43: El sistema debe generar sugerencias de productos usando historial de compra, frecuencia, productos habituales y promociones vigentes. | C43: Alta / E1 | D43: CU-014 | E43: Funcional | F43: =IF(AND(COUNTIF('Catalogo CU'!$A$9:$A$500,"CU-014")=1),IF(SUMIF('Catalogo CU'!$A$9:$A$500,"CU-014",'Catalogo CU'!$G$9:$G$500)=1,"Incluido",IF(SUMIF('Catalogo CU'!$A$9:$A$500,"CU-014",'Catalogo CU'!$G$9:$G$500)>0,"Parcial por selección","Fuera por selección")),"Revisar vínculo") -> Incluido | G43: Cubierto por los objetivos indicados; los pasos internos no se suman como transacciones.
A44: RF-03.15 | B44: La app debe generar un identificador único en el dispositivo al crear un pedido sin conectividad. | C44: Crítica / E1 | D44: CU-014 | E44: Funcional | F44: =IF(AND(COUNTIF('Catalogo CU'!$A$9:$A$500,"CU-014")=1),IF(SUMIF('Catalogo CU'!$A$9:$A$500,"CU-014",'Catalogo CU'!$G$9:$G$500)=1,"Incluido",IF(SUMIF('Catalogo CU'!$A$9:$A$500,"CU-014",'Catalogo CU'!$G$9:$G$500)>0,"Parcial por selección","Fuera por selección")),"Revisar vínculo") -> Incluido | G44: Cubierto por los objetivos indicados; los pasos internos no se suman como transacciones.
A45: RF-03.16 | B45: El sistema debe detectar y descartar automáticamente los reenvíos duplicados de un pedido con el mismo identificador único al sincronizar. | C45: Crítica / E1 | D45: CU-014, CU-017 | E45: Funcional | F45: =IF(AND(COUNTIF('Catalogo CU'!$A$9:$A$500,"CU-014")=1,COUNTIF('Catalogo CU'!$A$9:$A$500,"CU-017")=1),IF(SUMIF('Catalogo CU'!$A$9:$A$500,"CU-014",'Catalogo CU'!$G$9:$G$500)+SUMIF('Catalogo CU'!$A$9:$A$500,"CU-017",'Catalogo CU'!$G$9:$G$500)=2,"Incluido",IF(SUMIF('Catalogo CU'!$A$9:$A$500,"CU-014",'Catalogo CU'!$G$9:$G$500)+SUMIF('Catalogo CU'!$A$9:$A$500,"CU-017",'Catalogo CU'!$G$9:$G$500)>0,"Parcial por selección","Fuera por selección")),"Revisar vínculo") -> Incluido | G45: Cubierto por los objetivos indicados; los pasos internos no se suman como transacciones.
A46: RF-04.01 | B46: El sistema debe asignar pedidos a la flota, secuenciando la ruta en función de la capacidad volumétrica y zonas logísticas de entrega. | C46: Alta / E1 | D46: CU-018 | E46: Funcional | F46: =IF(AND(COUNTIF('Catalogo CU'!$A$9:$A$500,"CU-018")=1),IF(SUMIF('Catalogo CU'!$A$9:$A$500,"CU-018",'Catalogo CU'!$G$9:$G$500)=1,"Incluido",IF(SUMIF('Catalogo CU'!$A$9:$A$500,"CU-018",'Catalogo CU'!$G$9:$G$500)>0,"Parcial por selección","Fuera por selección")),"Revisar vínculo") -> Incluido | G46: Cubierto por los objetivos indicados; los pasos internos no se suman como transacciones.
A47: RF-04.02 | B47: El sistema debe permitir modificar manualmente la secuencia de ruta y reasignar pedidos entre vehículos | C47: Media / E1 | D47: CU-019 | E47: Funcional | F47: =IF(AND(COUNTIF('Catalogo CU'!$A$9:$A$500,"CU-019")=1),IF(SUMIF('Catalogo CU'!$A$9:$A$500,"CU-019",'Catalogo CU'!$G$9:$G$500)=1,"Incluido",IF(SUMIF('Catalogo CU'!$A$9:$A$500,"CU-019",'Catalogo CU'!$G$9:$G$500)>0,"Parcial por selección","Fuera por selección")),"Revisar vínculo") -> Incluido | G47: Cubierto por los objetivos indicados; los pasos internos no se suman como transacciones.
A48: RF-04.03 | B48: El sistema debe bloquear la adición de líneas de pedido a una ruta si la sumatoria excede los límites de peso o volumen nominales del vehículo. | C48: Alta / E1 | D48: CU-018, CU-019 | E48: Funcional | F48: =IF(AND(COUNTIF('Catalogo CU'!$A$9:$A$500,"CU-018")=1,COUNTIF('Catalogo CU'!$A$9:$A$500,"CU-019")=1),IF(SUMIF('Catalogo CU'!$A$9:$A$500,"CU-018",'Catalogo CU'!$G$9:$G$500)+SUMIF('Catalogo CU'!$A$9:$A$500,"CU-019",'Catalogo CU'!$G$9:$G$500)=2,"Incluido",IF(SUMIF('Catalogo CU'!$A$9:$A$500,"CU-018",'Catalogo CU'!$G$9:$G$500)+SUMIF('Catalogo CU'!$A$9:$A$500,"CU-019",'Catalogo CU'!$G$9:$G$500)>0,"Parcial por selección","Fuera por selección")),"Revisar vínculo") -> Incluido | G48: Cubierto por los objetivos indicados; los pasos internos no se suman como transacciones.
A49: RF-04.04 | B49: El sistema debe permitir la configuración de ventanas horarias específicas por cliente y ajustar la secuencia para cumplirlas. | C49: Alta / E1 | D49: CU-018, CU-020 | E49: Funcional | F49: =IF(AND(COUNTIF('Catalogo CU'!$A$9:$A$500,"CU-018")=1,COUNTIF('Catalogo CU'!$A$9:$A$500,"CU-020")=1),IF(SUMIF('Catalogo CU'!$A$9:$A$500,"CU-018",'Catalogo CU'!$G$9:$G$500)+SUMIF('Catalogo CU'!$A$9:$A$500,"CU-020",'Catalogo CU'!$G$9:$G$500)=2,"Incluido",IF(SUMIF('Catalogo CU'!$A$9:$A$500,"CU-018",'Catalogo CU'!$G$9:$G$500)+SUMIF('Catalogo CU'!$A$9:$A$500,"CU-020",'Catalogo CU'!$G$9:$G$500)>0,"Parcial por selección","Fuera por selección")),"Revisar vínculo") -> Incluido | G49: Cubierto por los objetivos indicados; los pasos internos no se suman como transacciones.
A50: RF-04.05 | B50: El sistema debe restringir la asignación de pedidos refrigerados o congelados exclusivamente a vehículos con equipo de frío. | C50: Alta / E1 | D50: CU-018, CU-019, CU-020 | E50: Funcional | F50: =IF(AND(COUNTIF('Catalogo CU'!$A$9:$A$500,"CU-018")=1,COUNTIF('Catalogo CU'!$A$9:$A$500,"CU-019")=1,COUNTIF('Catalogo CU'!$A$9:$A$500,"CU-020")=1),IF(SUMIF('Catalogo CU'!$A$9:$A$500,"CU-018",'Catalogo CU'!$G$9:$G$500)+SUMIF('Catalogo CU'!$A$9:$A$500,"CU-019",'Catalogo CU'!$G$9:$G$500)+SUMIF('Catalogo CU'!$A$9:$A$500,"CU-020",'Catalogo CU'!$G$9:$G$500)=3,"Incluido",IF(SUMIF('Catalogo CU'!$A$9:$A$500,"CU-018",'Catalogo CU'!$G$9:$G$500)+SUMIF('Catalogo CU'!$A$9:$A$500,"CU-019",'Catalogo CU'!$G$9:$G$500)+SUMIF('Catalogo CU'!$A$9:$A$500,"CU-020",'Catalogo CU'!$G$9:$G$500)>0,"Parcial por selección","Fuera por selección")),"Revisar vínculo") -> Incluido | G50: Cubierto por los objetivos indicados; los pasos internos no se suman como transacciones.
A51: RF-04.06 | B51: El sistema debe crear un aviso al contacto del cliente con la hora estimada de llegada incluyendo una ventana de 30 minutos. | C51: Media / E1 | D51: CU-079, CU-080 | E51: Funcional | F51: =IF(AND(COUNTIF('Catalogo CU'!$A$9:$A$500,"CU-079")=1,COUNTIF('Catalogo CU'!$A$9:$A$500,"CU-080")=1),IF(SUMIF('Catalogo CU'!$A$9:$A$500,"CU-079",'Catalogo CU'!$G$9:$G$500)+SUMIF('Catalogo CU'!$A$9:$A$500,"CU-080",'Catalogo CU'!$G$9:$G$500)=2,"Incluido",IF(SUMIF('Catalogo CU'!$A$9:$A$500,"CU-079",'Catalogo CU'!$G$9:$G$500)+SUMIF('Catalogo CU'!$A$9:$A$500,"CU-080",'Catalogo CU'!$G$9:$G$500)>0,"Parcial por selección","Fuera por selección")),"Revisar vínculo") -> Incluido | G51: Cubierto por los objetivos indicados; los pasos internos no se suman como transacciones.
A52: RF-04.07 | B52: El sistema debe permitir parametrizar franjas horarias de recepción en la ficha maestra de cada cliente (Ventana Horaria). | C52: Alta / E1 | D52: CU-020 | E52: Funcional | F52: =IF(AND(COUNTIF('Catalogo CU'!$A$9:$A$500,"CU-020")=1),IF(SUMIF('Catalogo CU'!$A$9:$A$500,"CU-020",'Catalogo CU'!$G$9:$G$500)=1,"Incluido",IF(SUMIF('Catalogo CU'!$A$9:$A$500,"CU-020",'Catalogo CU'!$G$9:$G$500)>0,"Parcial por selección","Fuera por selección")),"Revisar vínculo") -> Incluido | G52: Cubierto por los objetivos indicados; los pasos internos no se suman como transacciones.
A53: RF-04.08 | B53: El sistema debe calcular el costo de cada entrega tras haber sido realizada. | C53: Alta / E2 | D53: CU-048 | E53: Funcional | F53: =IF(AND(COUNTIF('Catalogo CU'!$A$9:$A$500,"CU-048")=1),IF(SUMIF('Catalogo CU'!$A$9:$A$500,"CU-048",'Catalogo CU'!$G$9:$G$500)=1,"Incluido",IF(SUMIF('Catalogo CU'!$A$9:$A$500,"CU-048",'Catalogo CU'!$G$9:$G$500)>0,"Parcial por selección","Fuera por selección")),"Revisar vínculo") -> Incluido | G53: Cubierto por los objetivos indicados; los pasos internos no se suman como transacciones.
A54: RF-05.01 | B54: El jefe de bodega debe poder iniciar la generación manualmente o configurar la generación automática al cierre de pedidos del turno. Las misiones deben permitir agrupación por pedido individual o por consolidación de pedidos de una misma ruta. | C54: Alta / E1 | D54: CU-021 | E54: Funcional | F54: =IF(AND(COUNTIF('Catalogo CU'!$A$9:$A$500,"CU-021")=1),IF(SUMIF('Catalogo CU'!$A$9:$A$500,"CU-021",'Catalogo CU'!$G$9:$G$500)=1,"Incluido",IF(SUMIF('Catalogo CU'!$A$9:$A$500,"CU-021",'Catalogo CU'!$G$9:$G$500)>0,"Parcial por selección","Fuera por selección")),"Revisar vínculo") -> Incluido | G54: Cubierto por los objetivos indicados; los pasos internos no se suman como transacciones.
A55: RF-05.02 | B55: El sistema debe exigir la validación de cada línea recolectada escaneando el código GS1. El escaneo debe validar el SKU y capturar el Lote exacto tomado. Permite ingreso manual solo como contingencia auditable. | C55: Alta / E1 | D55: CU-022 | E55: Funcional | F55: =IF(AND(COUNTIF('Catalogo CU'!$A$9:$A$500,"CU-022")=1),IF(SUMIF('Catalogo CU'!$A$9:$A$500,"CU-022",'Catalogo CU'!$G$9:$G$500)=1,"Incluido",IF(SUMIF('Catalogo CU'!$A$9:$A$500,"CU-022",'Catalogo CU'!$G$9:$G$500)>0,"Parcial por selección","Fuera por selección")),"Revisar vínculo") -> Incluido | G55: Cubierto por los objetivos indicados; los pasos internos no se suman como transacciones.
A56: RF-05.03 | B56: El sistema debe exigir la selección obligatoria de un motivo parametrizable de una lista estructurada, cada vez que se reporte una cantidad recolectada inferior a la solicitada. | C56: Alta / E1 | D56: CU-022 | E56: Funcional | F56: =IF(AND(COUNTIF('Catalogo CU'!$A$9:$A$500,"CU-022")=1),IF(SUMIF('Catalogo CU'!$A$9:$A$500,"CU-022",'Catalogo CU'!$G$9:$G$500)=1,"Incluido",IF(SUMIF('Catalogo CU'!$A$9:$A$500,"CU-022",'Catalogo CU'!$G$9:$G$500)>0,"Parcial por selección","Fuera por selección")),"Revisar vínculo") -> Incluido | G56: Cubierto por los objetivos indicados; los pasos internos no se suman como transacciones.
A57: RF-05.04 | B57: El sistema debe secuenciar las líneas de la misión de preparación priorizando las zonas en el siguiente orden: seco → refrigerado → congelado, para minimizar el tiempo de exposición de los productos de frío fuera de su zona térmica. | C57: Alta / E1 | D57: CU-021, CU-022 | E57: Funcional | F57: =IF(AND(COUNTIF('Catalogo CU'!$A$9:$A$500,"CU-021")=1,COUNTIF('Catalogo CU'!$A$9:$A$500,"CU-022")=1),IF(SUMIF('Catalogo CU'!$A$9:$A$500,"CU-021",'Catalogo CU'!$G$9:$G$500)+SUMIF('Catalogo CU'!$A$9:$A$500,"CU-022",'Catalogo CU'!$G$9:$G$500)=2,"Incluido",IF(SUMIF('Catalogo CU'!$A$9:$A$500,"CU-021",'Catalogo CU'!$G$9:$G$500)+SUMIF('Catalogo CU'!$A$9:$A$500,"CU-022",'Catalogo CU'!$G$9:$G$500)>0,"Parcial por selección","Fuera por selección")),"Revisar vínculo") -> Incluido | G57: Cubierto por los objetivos indicados; los pasos internos no se suman como transacciones.
A58: RF-05.05 | B58: El sistema debe asignar el inventario para la preparación de pedidos aplicando estrictamente la regla lógica FEFO (First Expired, First Out) según la fecha de vencimiento del lote. | C58: Alta / E1 | D58: CU-021, CU-022 | E58: Funcional | F58: =IF(AND(COUNTIF('Catalogo CU'!$A$9:$A$500,"CU-021")=1,COUNTIF('Catalogo CU'!$A$9:$A$500,"CU-022")=1),IF(SUMIF('Catalogo CU'!$A$9:$A$500,"CU-021",'Catalogo CU'!$G$9:$G$500)+SUMIF('Catalogo CU'!$A$9:$A$500,"CU-022",'Catalogo CU'!$G$9:$G$500)=2,"Incluido",IF(SUMIF('Catalogo CU'!$A$9:$A$500,"CU-021",'Catalogo CU'!$G$9:$G$500)+SUMIF('Catalogo CU'!$A$9:$A$500,"CU-022",'Catalogo CU'!$G$9:$G$500)>0,"Parcial por selección","Fuera por selección")),"Revisar vínculo") -> Incluido | G58: Cubierto por los objetivos indicados; los pasos internos no se suman como transacciones.
A59: RF-05.06 | B59: El sistema debe enviar al ERP, al cerrar una misión de preparación, el detalle consolidado por cada línea: SKU, cantidad efectivamente recolectada y lote correspondiente, vinculado al ID del pedido original. | C59: Alta / E1 | D59: CU-022, CU-024 | E59: Funcional | F59: =IF(AND(COUNTIF('Catalogo CU'!$A$9:$A$500,"CU-022")=1,COUNTIF('Catalogo CU'!$A$9:$A$500,"CU-024")=1),IF(SUMIF('Catalogo CU'!$A$9:$A$500,"CU-022",'Catalogo CU'!$G$9:$G$500)+SUMIF('Catalogo CU'!$A$9:$A$500,"CU-024",'Catalogo CU'!$G$9:$G$500)=2,"Incluido",IF(SUMIF('Catalogo CU'!$A$9:$A$500,"CU-022",'Catalogo CU'!$G$9:$G$500)+SUMIF('Catalogo CU'!$A$9:$A$500,"CU-024",'Catalogo CU'!$G$9:$G$500)>0,"Parcial por selección","Fuera por selección")),"Revisar vínculo") -> Incluido | G59: Cubierto por los objetivos indicados; los pasos internos no se suman como transacciones.
A60: RF-05.07 | B60: El sistema debe dirigir la carga de pedidos preparados en el camión siguiendo la secuencia inversa de la ruta asignada, garantizando que el primer cliente a visitar sea el último cargado (más accesible). El cargador debe confirmar cada bulto/pallet escaneando su SSCC. | C60: Alta / E1 | D60: CU-023 | E60: Funcional | F60: =IF(AND(COUNTIF('Catalogo CU'!$A$9:$A$500,"CU-023")=1),IF(SUMIF('Catalogo CU'!$A$9:$A$500,"CU-023",'Catalogo CU'!$G$9:$G$500)=1,"Incluido",IF(SUMIF('Catalogo CU'!$A$9:$A$500,"CU-023",'Catalogo CU'!$G$9:$G$500)>0,"Parcial por selección","Fuera por selección")),"Revisar vínculo") -> Incluido | G60: Cubierto por los objetivos indicados; los pasos internos no se suman como transacciones.
A61: RF-06.01 | B61: El sistema debe permitir marcar la recepción conforme de bultos mediante validación por línea de pedido individual o marcado masivo por guía. | C61: Alta / E1 | D61: CU-026 | E61: Funcional | F61: =IF(AND(COUNTIF('Catalogo CU'!$A$9:$A$500,"CU-026")=1),IF(SUMIF('Catalogo CU'!$A$9:$A$500,"CU-026",'Catalogo CU'!$G$9:$G$500)=1,"Incluido",IF(SUMIF('Catalogo CU'!$A$9:$A$500,"CU-026",'Catalogo CU'!$G$9:$G$500)>0,"Parcial por selección","Fuera por selección")),"Revisar vínculo") -> Incluido | G61: Cubierto por los objetivos indicados; los pasos internos no se suman como transacciones.
A62: RF-06.02 | B62: El sistema debe permitir capturar la firma digital del receptor como evidencia de entrega, asociada a la guía de despacho electrónica. | C62: Crítica / E1 | D62: CU-026 | E62: Funcional | F62: =IF(AND(COUNTIF('Catalogo CU'!$A$9:$A$500,"CU-026")=1),IF(SUMIF('Catalogo CU'!$A$9:$A$500,"CU-026",'Catalogo CU'!$G$9:$G$500)=1,"Incluido",IF(SUMIF('Catalogo CU'!$A$9:$A$500,"CU-026",'Catalogo CU'!$G$9:$G$500)>0,"Parcial por selección","Fuera por selección")),"Revisar vínculo") -> Incluido | G62: Cubierto por los objetivos indicados; los pasos internos no se suman como transacciones.
A63: RF-06.03 | B63: El sistema debe permitir reportar un rechazo total o parcial seleccionando la cantidad y el motivo desde un catálogo predefinido. | C63: Media / E1 | D63: CU-026 | E63: Funcional | F63: =IF(AND(COUNTIF('Catalogo CU'!$A$9:$A$500,"CU-026")=1),IF(SUMIF('Catalogo CU'!$A$9:$A$500,"CU-026",'Catalogo CU'!$G$9:$G$500)=1,"Incluido",IF(SUMIF('Catalogo CU'!$A$9:$A$500,"CU-026",'Catalogo CU'!$G$9:$G$500)>0,"Parcial por selección","Fuera por selección")),"Revisar vínculo") -> Incluido | G63: Cubierto por los objetivos indicados; los pasos internos no se suman como transacciones.
A64: RF-06.04 | B64: El sistema debe permitir reportar un local cerrado, indicando la dirección del cliente. | C64: Media / E1 | D64: CU-027 | E64: Funcional | F64: =IF(AND(COUNTIF('Catalogo CU'!$A$9:$A$500,"CU-027")=1),IF(SUMIF('Catalogo CU'!$A$9:$A$500,"CU-027",'Catalogo CU'!$G$9:$G$500)=1,"Incluido",IF(SUMIF('Catalogo CU'!$A$9:$A$500,"CU-027",'Catalogo CU'!$G$9:$G$500)>0,"Parcial por selección","Fuera por selección")),"Revisar vínculo") -> Incluido | G64: Cubierto por los objetivos indicados; los pasos internos no se suman como transacciones.
A65: RF-06.05 | B65: El sistema debe permitir digitar el monto exacto recaudado en pagos realizados en efectivo | C65: Crítica / E1 | D65: CU-028 | E65: Funcional | F65: =IF(AND(COUNTIF('Catalogo CU'!$A$9:$A$500,"CU-028")=1),IF(SUMIF('Catalogo CU'!$A$9:$A$500,"CU-028",'Catalogo CU'!$G$9:$G$500)=1,"Incluido",IF(SUMIF('Catalogo CU'!$A$9:$A$500,"CU-028",'Catalogo CU'!$G$9:$G$500)>0,"Parcial por selección","Fuera por selección")),"Revisar vínculo") -> Incluido | G65: Cubierto por los objetivos indicados; los pasos internos no se suman como transacciones.
A66: RF-06.07 | B66: El sistema debe sincronizarse automaticamente, al detectar la reconexión de señal o el regreso al centro de distribución, sincronizar automaticamente todos los registros generados durante el turno, recuperando la totalidad de los despachos registrados, consolidandolos en un reporte de cierre. | C66: Crítica / E1 | D66: CU-017 | E66: Funcional | F66: =IF(AND(COUNTIF('Catalogo CU'!$A$9:$A$500,"CU-017")=1),IF(SUMIF('Catalogo CU'!$A$9:$A$500,"CU-017",'Catalogo CU'!$G$9:$G$500)=1,"Incluido",IF(SUMIF('Catalogo CU'!$A$9:$A$500,"CU-017",'Catalogo CU'!$G$9:$G$500)>0,"Parcial por selección","Fuera por selección")),"Revisar vínculo") -> Incluido | G66: Cubierto por los objetivos indicados; los pasos internos no se suman como transacciones.
A67: RF-06.08 | B67: El sistema debe permitir al conductor de una empresa externa iniciar su jornada usando las credenciales temporales por OTP (código de un solo uso) emitido por su jefe de flota; la sesión común posterior la provee RF-15.02. sin necesidad de correo corporativo. | C67: Alta / E1 | D67: CU-025 | E67: Funcional | F67: =IF(AND(COUNTIF('Catalogo CU'!$A$9:$A$500,"CU-025")=1),IF(SUMIF('Catalogo CU'!$A$9:$A$500,"CU-025",'Catalogo CU'!$G$9:$G$500)=1,"Incluido",IF(SUMIF('Catalogo CU'!$A$9:$A$500,"CU-025",'Catalogo CU'!$G$9:$G$500)>0,"Parcial por selección","Fuera por selección")),"Revisar vínculo") -> Incluido | G67: Cubierto por los objetivos indicados; los pasos internos no se suman como transacciones.
A68: RF-06.09 | B68: Al registrar una entrega, el sistema debe permitir al conductor capturar la cantidad de canastillos y pallets devueltos por el cliente, identificando el tipo y estado. | C68: Alta / E1 | D68: CU-038 | E68: Funcional | F68: =IF(AND(COUNTIF('Catalogo CU'!$A$9:$A$500,"CU-038")=1),IF(SUMIF('Catalogo CU'!$A$9:$A$500,"CU-038",'Catalogo CU'!$G$9:$G$500)=1,"Incluido",IF(SUMIF('Catalogo CU'!$A$9:$A$500,"CU-038",'Catalogo CU'!$G$9:$G$500)>0,"Parcial por selección","Fuera por selección")),"Revisar vínculo") -> Incluido | G68: Cubierto por los objetivos indicados; los pasos internos no se suman como transacciones.
A69: RF-06.10 | B69: El sistema debe actualizar el saldo del cliente y del parque retornable en línea o en modo diferido según conectividad, asociando el registro a la entrega o a la guía correspondiente | C69: Alta / E1 | D69: CU-038 | E69: Funcional | F69: =IF(AND(COUNTIF('Catalogo CU'!$A$9:$A$500,"CU-038")=1),IF(SUMIF('Catalogo CU'!$A$9:$A$500,"CU-038",'Catalogo CU'!$G$9:$G$500)=1,"Incluido",IF(SUMIF('Catalogo CU'!$A$9:$A$500,"CU-038",'Catalogo CU'!$G$9:$G$500)>0,"Parcial por selección","Fuera por selección")),"Revisar vínculo") -> Incluido | G69: Cubierto por los objetivos indicados; los pasos internos no se suman como transacciones.
A70: RF-06.11 | B70: El sistema debe ofrecer al cliente la opción de confirmar la recepción mediante un código QR único generado por la app del conductor, cuando el cliente disponga de teléfono inteligente. | C70: Media / E1 | D70: CU-026 | E70: Funcional | F70: =IF(AND(COUNTIF('Catalogo CU'!$A$9:$A$500,"CU-026")=1),IF(SUMIF('Catalogo CU'!$A$9:$A$500,"CU-026",'Catalogo CU'!$G$9:$G$500)=1,"Incluido",IF(SUMIF('Catalogo CU'!$A$9:$A$500,"CU-026",'Catalogo CU'!$G$9:$G$500)>0,"Parcial por selección","Fuera por selección")),"Revisar vínculo") -> Incluido | G70: Cubierto por los objetivos indicados; los pasos internos no se suman como transacciones.
A71: RF-06.12 | B71: El sistema debe permitir confirmar la recepción del cliente aun si este no dispone de teléfono o conectividad, mediante captura de firma en pantalla o el registro fotografico de la recepcion, dejando evidencia vinculada a la guia de despacho electrónica en su acuse de recibo. | C71: Media / E1 | D71: CU-026 | E71: Funcional | F71: =IF(AND(COUNTIF('Catalogo CU'!$A$9:$A$500,"CU-026")=1),IF(SUMIF('Catalogo CU'!$A$9:$A$500,"CU-026",'Catalogo CU'!$G$9:$G$500)=1,"Incluido",IF(SUMIF('Catalogo CU'!$A$9:$A$500,"CU-026",'Catalogo CU'!$G$9:$G$500)>0,"Parcial por selección","Fuera por selección")),"Revisar vínculo") -> Incluido | G71: Cubierto por los objetivos indicados; los pasos internos no se suman como transacciones.
A72: RF-06.13 | B72: La app de reparto debe permitir imprimir en terreno un comprobante térmico de entrega para el cliente usando una impresora portátil Bluetooth en aquellos casos donde el cliente requiera respaldo físico. | C72: Media / E1 | D72: CU-026 | E72: Funcional | F72: =IF(AND(COUNTIF('Catalogo CU'!$A$9:$A$500,"CU-026")=1),IF(SUMIF('Catalogo CU'!$A$9:$A$500,"CU-026",'Catalogo CU'!$G$9:$G$500)=1,"Incluido",IF(SUMIF('Catalogo CU'!$A$9:$A$500,"CU-026",'Catalogo CU'!$G$9:$G$500)>0,"Parcial por selección","Fuera por selección")),"Revisar vínculo") -> Incluido | G72: Cubierto por los objetivos indicados; los pasos internos no se suman como transacciones.
A73: RF-07.02 | B73: El sistema debe generar la planilla digital de rendición individual al retorno del camión, contrastando los valores declarados por el conductor en la aplicación móvil contra las entregas al contado realizadas y facturas cobradas. | C73: Alta / E1 | D73: CU-031 | E73: Funcional | F73: =IF(AND(COUNTIF('Catalogo CU'!$A$9:$A$500,"CU-031")=1),IF(SUMIF('Catalogo CU'!$A$9:$A$500,"CU-031",'Catalogo CU'!$G$9:$G$500)=1,"Incluido",IF(SUMIF('Catalogo CU'!$A$9:$A$500,"CU-031",'Catalogo CU'!$G$9:$G$500)>0,"Parcial por selección","Fuera por selección")),"Revisar vínculo") -> Incluido | G73: Cubierto por los objetivos indicados; los pasos internos no se suman como transacciones.
A74: RF-07.03 | B74: El sistema debe obligar al registro estructurado y categorizado de causales para cualquier diferencia detectada en la rendición de caja (descuentos comerciales autorizados, diferencias de cambio, siniestro en ruta), bloqueando el cierre de la liquidación si existe saldo sin justificar. | C74: Alta / E1 | D74: CU-031 | E74: Funcional | F74: =IF(AND(COUNTIF('Catalogo CU'!$A$9:$A$500,"CU-031")=1),IF(SUMIF('Catalogo CU'!$A$9:$A$500,"CU-031",'Catalogo CU'!$G$9:$G$500)=1,"Incluido",IF(SUMIF('Catalogo CU'!$A$9:$A$500,"CU-031",'Catalogo CU'!$G$9:$G$500)>0,"Parcial por selección","Fuera por selección")),"Revisar vínculo") -> Incluido | G74: Cubierto por los objetivos indicados; los pasos internos no se suman como transacciones.
A75: RF-07.04 | B75: El sistema debe proveer una consola de gestión para la cartera de crédito a 30 días sincronizada con el ERP, asignando carteras de clientes a ejecutivos de cobranza y registrando bitácoras de gestión, compromisos de pago y fechas de recontacto. | C75: Alta / E1 | D75: CU-032 | E75: Funcional | F75: =IF(AND(COUNTIF('Catalogo CU'!$A$9:$A$500,"CU-032")=1),IF(SUMIF('Catalogo CU'!$A$9:$A$500,"CU-032",'Catalogo CU'!$G$9:$G$500)=1,"Incluido",IF(SUMIF('Catalogo CU'!$A$9:$A$500,"CU-032",'Catalogo CU'!$G$9:$G$500)>0,"Parcial por selección","Fuera por selección")),"Revisar vínculo") -> Incluido | G75: Cubierto por los objetivos indicados; los pasos internos no se suman como transacciones.
A76: RF-07.05 | B76: El sistema debe notificar en la aplicación móvil de preventa el estado de bloqueo o mora de un cliente (>30 días o cupo excedido), bloqueando preventivamente el ingreso de pedidos a crédito y permitiendo únicamente venta al contado o cobro de deuda. | C76: Alta / E1 | D76: CU-014 | E76: Funcional | F76: =IF(AND(COUNTIF('Catalogo CU'!$A$9:$A$500,"CU-014")=1),IF(SUMIF('Catalogo CU'!$A$9:$A$500,"CU-014",'Catalogo CU'!$G$9:$G$500)=1,"Incluido",IF(SUMIF('Catalogo CU'!$A$9:$A$500,"CU-014",'Catalogo CU'!$G$9:$G$500)>0,"Parcial por selección","Fuera por selección")),"Revisar vínculo") -> Incluido | G76: Cubierto por los objetivos indicados; los pasos internos no se suman como transacciones.
A77: RF-07.06 | B77: El sistema debe integrarse vía Bluetooth con terminales de pago portátil (POS) en la aplicación móvil de reparto para cobro con tarjeta en ruta, capturando el código de autorización bancario y conciliando el voucher automáticamente en la liquidación diaria. | C77: Alta / E1 | D77: CU-029 | E77: Funcional | F77: =IF(AND(COUNTIF('Catalogo CU'!$A$9:$A$500,"CU-029")=1),IF(SUMIF('Catalogo CU'!$A$9:$A$500,"CU-029",'Catalogo CU'!$G$9:$G$500)=1,"Incluido",IF(SUMIF('Catalogo CU'!$A$9:$A$500,"CU-029",'Catalogo CU'!$G$9:$G$500)>0,"Parcial por selección","Fuera por selección")),"Revisar vínculo") -> Incluido | G77: Cubierto por los objetivos indicados; los pasos internos no se suman como transacciones.
A78: RF-07.07 | B78: El sistema debe disponer en el portal web de autoatención el estado de cuenta y la cartola de antigüedad de deuda (tramos corriente, 30, 60, 90+ días) descargable en formatos PDF y Excel para clientes autenticados. | C78: Alta / E2 | D78: CU-059 | E78: Funcional | F78: =IF(AND(COUNTIF('Catalogo CU'!$A$9:$A$500,"CU-059")=1),IF(SUMIF('Catalogo CU'!$A$9:$A$500,"CU-059",'Catalogo CU'!$G$9:$G$500)=1,"Incluido",IF(SUMIF('Catalogo CU'!$A$9:$A$500,"CU-059",'Catalogo CU'!$G$9:$G$500)>0,"Parcial por selección","Fuera por selección")),"Revisar vínculo") -> Incluido | G78: Cubierto por los objetivos indicados; los pasos internos no se suman como transacciones.
A79: RF-07.08 | B79: El sistema debe proveer una bandeja de validación para pagos reportados en el portal web de clientes, permitiendo al cajero verificar el comprobante bancario y autorizar su traspaso estructurado al ERP. | C79: Alta / E2 | D79: CU-033, CU-034 | E79: Funcional | F79: =IF(AND(COUNTIF('Catalogo CU'!$A$9:$A$500,"CU-033")=1,COUNTIF('Catalogo CU'!$A$9:$A$500,"CU-034")=1),IF(SUMIF('Catalogo CU'!$A$9:$A$500,"CU-033",'Catalogo CU'!$G$9:$G$500)+SUMIF('Catalogo CU'!$A$9:$A$500,"CU-034",'Catalogo CU'!$G$9:$G$500)=2,"Incluido",IF(SUMIF('Catalogo CU'!$A$9:$A$500,"CU-033",'Catalogo CU'!$G$9:$G$500)+SUMIF('Catalogo CU'!$A$9:$A$500,"CU-034",'Catalogo CU'!$G$9:$G$500)>0,"Parcial por selección","Fuera por selección")),"Revisar vínculo") -> Incluido | G79: Cubierto por los objetivos indicados; los pasos internos no se suman como transacciones.
A80: RF-07.09 | B80: El sistema debe transferir de forma estructurada, asíncrona e idempotente los comprobantes de recaudación y cierres comerciales aprobados hacia el ERP para actualizar automáticamente las cuentas por cobrar. | C80: Alta / E1 | D80: CU-035 | E80: Funcional | F80: =IF(AND(COUNTIF('Catalogo CU'!$A$9:$A$500,"CU-035")=1),IF(SUMIF('Catalogo CU'!$A$9:$A$500,"CU-035",'Catalogo CU'!$G$9:$G$500)=1,"Incluido",IF(SUMIF('Catalogo CU'!$A$9:$A$500,"CU-035",'Catalogo CU'!$G$9:$G$500)>0,"Parcial por selección","Fuera por selección")),"Revisar vínculo") -> Incluido | G80: Cubierto por los objetivos indicados; los pasos internos no se suman como transacciones.
A81: RF-07.10 | B81: El sistema debe permitir el registro de anticipos o pagos parciales en entregas al contado desde la aplicación móvil de reparto, emitiendo un comprobante digital de abono y traspasando el saldo insoluto a la cuenta corriente del cliente en el ERP. | C81: Alta / E1 | D81: CU-028 | E81: Funcional | F81: =IF(AND(COUNTIF('Catalogo CU'!$A$9:$A$500,"CU-028")=1),IF(SUMIF('Catalogo CU'!$A$9:$A$500,"CU-028",'Catalogo CU'!$G$9:$G$500)=1,"Incluido",IF(SUMIF('Catalogo CU'!$A$9:$A$500,"CU-028",'Catalogo CU'!$G$9:$G$500)>0,"Parcial por selección","Fuera por selección")),"Revisar vínculo") -> Incluido | G81: Cubierto por los objetivos indicados; los pasos internos no se suman como transacciones.
A82: RF-07.11 | B82: El sistema debe permitir al preventista registrar la cobranza en efectivo de facturas vencidas en el local del cliente desde su terminal móvil, emitiendo un recibo provisional digital y forzando su rendición diaria en caja. | C82: Alta / E1 | D82: CU-030 | E82: Funcional | F82: =IF(AND(COUNTIF('Catalogo CU'!$A$9:$A$500,"CU-030")=1),IF(SUMIF('Catalogo CU'!$A$9:$A$500,"CU-030",'Catalogo CU'!$G$9:$G$500)=1,"Incluido",IF(SUMIF('Catalogo CU'!$A$9:$A$500,"CU-030",'Catalogo CU'!$G$9:$G$500)>0,"Parcial por selección","Fuera por selección")),"Revisar vínculo") -> Incluido | G82: Cubierto por los objetivos indicados; los pasos internos no se suman como transacciones.
A83: RF-08.01 | B83: El sistema debe permitir al conductor registrar la devolución de productos en el momento de la entrega, capturando SKU, cantidad y motivo (daño / vencimiento / producto no pedido / error), operando en modo offline. | C83: Crítica / E1 | D83: CU-036 | E83: Funcional | F83: =IF(AND(COUNTIF('Catalogo CU'!$A$9:$A$500,"CU-036")=1),IF(SUMIF('Catalogo CU'!$A$9:$A$500,"CU-036",'Catalogo CU'!$G$9:$G$500)=1,"Incluido",IF(SUMIF('Catalogo CU'!$A$9:$A$500,"CU-036",'Catalogo CU'!$G$9:$G$500)>0,"Parcial por selección","Fuera por selección")),"Revisar vínculo") -> Incluido | G83: Cubierto por los objetivos indicados; los pasos internos no se suman como transacciones.
A84: RF-08.02 | B84: Al recepcionar una devolución en el andén del CD, el sistema debe permitir seleccionar el destino final del producto (reingreso a stock / venta con descuento / devolución al proveedor / destrucción) y enviar la transacción al ERP mediante su interfaz de integración. | C84: Crítica / E1 | D84: CU-037, CU-045 | E84: Funcional | F84: =IF(AND(COUNTIF('Catalogo CU'!$A$9:$A$500,"CU-037")=1,COUNTIF('Catalogo CU'!$A$9:$A$500,"CU-045")=1),IF(SUMIF('Catalogo CU'!$A$9:$A$500,"CU-037",'Catalogo CU'!$G$9:$G$500)+SUMIF('Catalogo CU'!$A$9:$A$500,"CU-045",'Catalogo CU'!$G$9:$G$500)=2,"Incluido",IF(SUMIF('Catalogo CU'!$A$9:$A$500,"CU-037",'Catalogo CU'!$G$9:$G$500)+SUMIF('Catalogo CU'!$A$9:$A$500,"CU-045",'Catalogo CU'!$G$9:$G$500)>0,"Parcial por selección","Fuera por selección")),"Revisar vínculo") -> Incluido | G84: Cubierto por los objetivos indicados; los pasos internos no se suman como transacciones.
A85: RF-08.03 | B85: El sistema debe mantener una cuenta corriente de envases retornables por cliente, actualizando el saldo en cada entrega y devolución registrada por el conductor. | C85: Alta / E1 | D85: CU-038 | E85: Funcional | F85: =IF(AND(COUNTIF('Catalogo CU'!$A$9:$A$500,"CU-038")=1),IF(SUMIF('Catalogo CU'!$A$9:$A$500,"CU-038",'Catalogo CU'!$G$9:$G$500)=1,"Incluido",IF(SUMIF('Catalogo CU'!$A$9:$A$500,"CU-038",'Catalogo CU'!$G$9:$G$500)>0,"Parcial por selección","Fuera por selección")),"Revisar vínculo") -> Incluido | G85: Cubierto por los objetivos indicados; los pasos internos no se suman como transacciones.
A86: RF-08.04 | B86: El sistema debe generar una alerta al preventista cuando el saldo de envases retornables de un cliente supere el umbral configurado por el administrador. | C86: Alta / E1 | D86: CU-038 | E86: Funcional | F86: =IF(AND(COUNTIF('Catalogo CU'!$A$9:$A$500,"CU-038")=1),IF(SUMIF('Catalogo CU'!$A$9:$A$500,"CU-038",'Catalogo CU'!$G$9:$G$500)=1,"Incluido",IF(SUMIF('Catalogo CU'!$A$9:$A$500,"CU-038",'Catalogo CU'!$G$9:$G$500)>0,"Parcial por selección","Fuera por selección")),"Revisar vínculo") -> Incluido | G86: Cubierto por los objetivos indicados; los pasos internos no se suman como transacciones.
A87: RF-08.05 | B87: El sistema debe permitir registrar mermas por vencimiento detectadas en conteo cíclico, preparación de pedidos o góndola del cliente, asociando cada registro al SKU y al lote correspondiente. | C87: Alta / E1 | D87: CU-039 | E87: Funcional | F87: =IF(AND(COUNTIF('Catalogo CU'!$A$9:$A$500,"CU-039")=1),IF(SUMIF('Catalogo CU'!$A$9:$A$500,"CU-039",'Catalogo CU'!$G$9:$G$500)=1,"Incluido",IF(SUMIF('Catalogo CU'!$A$9:$A$500,"CU-039",'Catalogo CU'!$G$9:$G$500)>0,"Parcial por selección","Fuera por selección")),"Revisar vínculo") -> Incluido | G87: Cubierto por los objetivos indicados; los pasos internos no se suman como transacciones.
A88: RF-08.06 | B88: El sistema debe reportar la pérdida de envases retornables desglosada por cliente, tipo de envase y zona, con actualización diaria. | C88: Alta / E1 | D88: CU-038 | E88: Funcional | F88: =IF(AND(COUNTIF('Catalogo CU'!$A$9:$A$500,"CU-038")=1),IF(SUMIF('Catalogo CU'!$A$9:$A$500,"CU-038",'Catalogo CU'!$G$9:$G$500)=1,"Incluido",IF(SUMIF('Catalogo CU'!$A$9:$A$500,"CU-038",'Catalogo CU'!$G$9:$G$500)>0,"Parcial por selección","Fuera por selección")),"Revisar vínculo") -> Incluido | G88: Cubierto por los objetivos indicados; los pasos internos no se suman como transacciones.
A89: RF-08.07 | B89: El sistema debe incluir el costo de devoluciones y mermas por cliente como componente del cálculo del costo de servir (Épica 11). | C89: Alta / E2 | D89: CU-048 | E89: Funcional | F89: =IF(AND(COUNTIF('Catalogo CU'!$A$9:$A$500,"CU-048")=1),IF(SUMIF('Catalogo CU'!$A$9:$A$500,"CU-048",'Catalogo CU'!$G$9:$G$500)=1,"Incluido",IF(SUMIF('Catalogo CU'!$A$9:$A$500,"CU-048",'Catalogo CU'!$G$9:$G$500)>0,"Parcial por selección","Fuera por selección")),"Revisar vínculo") -> Incluido | G89: Cubierto por los objetivos indicados; los pasos internos no se suman como transacciones.
A90: RF-09.01 | B90: El sistema debe permitir la trazabilidad 'hacia adelante' (forward tracing): dado un lote específico, debe listar todos los clientes que recibieron productos de ese lote, con fecha de entrega, guía y cantidad. | C90: Crítica / E1 | D90: CU-040, CU-041 | E90: Funcional | F90: =IF(AND(COUNTIF('Catalogo CU'!$A$9:$A$500,"CU-040")=1,COUNTIF('Catalogo CU'!$A$9:$A$500,"CU-041")=1),IF(SUMIF('Catalogo CU'!$A$9:$A$500,"CU-040",'Catalogo CU'!$G$9:$G$500)+SUMIF('Catalogo CU'!$A$9:$A$500,"CU-041",'Catalogo CU'!$G$9:$G$500)=2,"Incluido",IF(SUMIF('Catalogo CU'!$A$9:$A$500,"CU-040",'Catalogo CU'!$G$9:$G$500)+SUMIF('Catalogo CU'!$A$9:$A$500,"CU-041",'Catalogo CU'!$G$9:$G$500)>0,"Parcial por selección","Fuera por selección")),"Revisar vínculo") -> Incluido | G90: Cubierto por los objetivos indicados; los pasos internos no se suman como transacciones.
A91: RF-09.02 | B91: El sistema debe permitir la trazabilidad 'hacia atrás' (backward tracing): dado un producto en el local del cliente (SKU + lote), debe identificar el origen (proveedor, fecha de recepción y orden de compra) | C91: Crítica / E1 | D91: CU-040, CU-041 | E91: Funcional | F91: =IF(AND(COUNTIF('Catalogo CU'!$A$9:$A$500,"CU-040")=1,COUNTIF('Catalogo CU'!$A$9:$A$500,"CU-041")=1),IF(SUMIF('Catalogo CU'!$A$9:$A$500,"CU-040",'Catalogo CU'!$G$9:$G$500)+SUMIF('Catalogo CU'!$A$9:$A$500,"CU-041",'Catalogo CU'!$G$9:$G$500)=2,"Incluido",IF(SUMIF('Catalogo CU'!$A$9:$A$500,"CU-040",'Catalogo CU'!$G$9:$G$500)+SUMIF('Catalogo CU'!$A$9:$A$500,"CU-041",'Catalogo CU'!$G$9:$G$500)>0,"Parcial por selección","Fuera por selección")),"Revisar vínculo") -> Incluido | G91: Cubierto por los objetivos indicados; los pasos internos no se suman como transacciones.
A92: RF-09.03 | B92: El sistema debe registrar de forma automática y continua la temperatura de las cámaras de refrigerado y congelado, con lecturas cada 5 minutos como mínimo | C92: Crítica / E1 | D92: CU-042 | E92: Funcional | F92: =IF(AND(COUNTIF('Catalogo CU'!$A$9:$A$500,"CU-042")=1),IF(SUMIF('Catalogo CU'!$A$9:$A$500,"CU-042",'Catalogo CU'!$G$9:$G$500)=1,"Incluido",IF(SUMIF('Catalogo CU'!$A$9:$A$500,"CU-042",'Catalogo CU'!$G$9:$G$500)>0,"Parcial por selección","Fuera por selección")),"Revisar vínculo") -> Incluido | G92: Cubierto por los objetivos indicados; los pasos internos no se suman como transacciones.
A93: RF-09.04 | B93: El sistema debe registrar de forma automática y continua la temperatura en los camiones con equipo de frío (18 propios y 10 de transportistas, todos con sensor instalado antes de la ola de reparto; S-28), durante todo el trayecto desde la carga hasta la entrega. | C93: Crítica / E1 | D93: CU-042 | E93: Funcional | F93: =IF(AND(COUNTIF('Catalogo CU'!$A$9:$A$500,"CU-042")=1),IF(SUMIF('Catalogo CU'!$A$9:$A$500,"CU-042",'Catalogo CU'!$G$9:$G$500)=1,"Incluido",IF(SUMIF('Catalogo CU'!$A$9:$A$500,"CU-042",'Catalogo CU'!$G$9:$G$500)>0,"Parcial por selección","Fuera por selección")),"Revisar vínculo") -> Incluido | G93: Cubierto por los objetivos indicados; los pasos internos no se suman como transacciones.
A94: RF-09.05 | B94: El sistema debe generar una alerta en tiempo real (notificación en cabina y en plataforma de monitoreo) cuando se detecte una excursión de temperatura que supere la desviación continua de 2 °C por 15 minutos para el tipo de producto. | C94: Crítica / E1 | D94: CU-044 | E94: Funcional | F94: =IF(AND(COUNTIF('Catalogo CU'!$A$9:$A$500,"CU-044")=1),IF(SUMIF('Catalogo CU'!$A$9:$A$500,"CU-044",'Catalogo CU'!$G$9:$G$500)=1,"Incluido",IF(SUMIF('Catalogo CU'!$A$9:$A$500,"CU-044",'Catalogo CU'!$G$9:$G$500)>0,"Parcial por selección","Fuera por selección")),"Revisar vínculo") -> Incluido | G94: Cubierto por los objetivos indicados; los pasos internos no se suman como transacciones.
A95: RF-09.06 | B95: Ante una excursión térmica crítica y sostenida, el sistema debe bloquear preventivamente el despacho del lote afectado y notificar a Calidad; ante una excursión menor y transitoria, debe emitir una alerta preventiva en cabina. El conductor recibe la alerta y registra sus observaciones; Calidad decide liberar, bloquear o rechazar (LafroX, 2026c, sección «Arbitraje de tensiones operacionales y comerciales», tensión 2; Anexo 2.2, S-04). | C95: Media / E1 | D95: CU-044 | E95: Funcional | F95: =IF(AND(COUNTIF('Catalogo CU'!$A$9:$A$500,"CU-044")=1),IF(SUMIF('Catalogo CU'!$A$9:$A$500,"CU-044",'Catalogo CU'!$G$9:$G$500)=1,"Incluido",IF(SUMIF('Catalogo CU'!$A$9:$A$500,"CU-044",'Catalogo CU'!$G$9:$G$500)>0,"Parcial por selección","Fuera por selección")),"Revisar vínculo") -> Incluido | G95: Cubierto por los objetivos indicados; los pasos internos no se suman como transacciones.
A96: RF-09.07 | B96: El sistema debe permitir al conductor registrar el rechazo de un producto entregado por 'sospecha de ruptura de cadena de frío', asociando el evento al sensor de temperatura del camión en ese tramo. | C96: Crítica / E1 | D96: CU-036 | E96: Funcional | F96: =IF(AND(COUNTIF('Catalogo CU'!$A$9:$A$500,"CU-036")=1),IF(SUMIF('Catalogo CU'!$A$9:$A$500,"CU-036",'Catalogo CU'!$G$9:$G$500)=1,"Incluido",IF(SUMIF('Catalogo CU'!$A$9:$A$500,"CU-036",'Catalogo CU'!$G$9:$G$500)>0,"Parcial por selección","Fuera por selección")),"Revisar vínculo") -> Incluido | G96: Cubierto por los objetivos indicados; los pasos internos no se suman como transacciones.
A97: RF-09.08 | B97: El sistema debe registrar, en el momento de la preparación (picking), el lote específico que se le asigna a cada línea de pedido, para los productos con control sanitario. | C97: Crítica / E1 | D97: CU-022 | E97: Funcional | F97: =IF(AND(COUNTIF('Catalogo CU'!$A$9:$A$500,"CU-022")=1),IF(SUMIF('Catalogo CU'!$A$9:$A$500,"CU-022",'Catalogo CU'!$G$9:$G$500)=1,"Incluido",IF(SUMIF('Catalogo CU'!$A$9:$A$500,"CU-022",'Catalogo CU'!$G$9:$G$500)>0,"Parcial por selección","Fuera por selección")),"Revisar vínculo") -> Incluido | G97: Cubierto por los objetivos indicados; los pasos internos no se suman como transacciones.
A98: RF-09.09 | B98: El sistema debe generar la evidencia de cumplimiento de cadena de frío exigible ante la autoridad sanitaria y ante el cliente, para un envío determinado. | C98: Crítica / E1 | D98: CU-046 | E98: Funcional | F98: =IF(AND(COUNTIF('Catalogo CU'!$A$9:$A$500,"CU-046")=1),IF(SUMIF('Catalogo CU'!$A$9:$A$500,"CU-046",'Catalogo CU'!$G$9:$G$500)=1,"Incluido",IF(SUMIF('Catalogo CU'!$A$9:$A$500,"CU-046",'Catalogo CU'!$G$9:$G$500)>0,"Parcial por selección","Fuera por selección")),"Revisar vínculo") -> Incluido | G98: Cubierto por los objetivos indicados; los pasos internos no se suman como transacciones.
A99: RF-11.01 | B99: El sistema debe programar y distribuir vía correo electrónico reportes ejecutivos consolidados (en formatos PDF y XLSX) con periodicidad semanal y mensual, desglosando la evolución de OTIF, Fill Rate, Merma por vencimiento y Costo de Servir por zona y canal de comercialización. | C99: Media / E2 | D99: CU-050 | E99: Funcional | F99: =IF(AND(COUNTIF('Catalogo CU'!$A$9:$A$500,"CU-050")=1),IF(SUMIF('Catalogo CU'!$A$9:$A$500,"CU-050",'Catalogo CU'!$G$9:$G$500)=1,"Incluido",IF(SUMIF('Catalogo CU'!$A$9:$A$500,"CU-050",'Catalogo CU'!$G$9:$G$500)>0,"Parcial por selección","Fuera por selección")),"Revisar vínculo") -> Incluido | G99: Cubierto por los objetivos indicados; los pasos internos no se suman como transacciones.
A100: RF-11.02 | B100: El sistema debe calcular el Costo de Servir real por entrega y por cliente, imputando los costos directos de transporte (combustible devengado vía GPS, peajes, tiempo de conducción y tiempo de descarga) y los costos indirectos prorrateados (bodega y administración). | C100: Media / E2 | D100: CU-048 | E100: Funcional | F100: =IF(AND(COUNTIF('Catalogo CU'!$A$9:$A$500,"CU-048")=1),IF(SUMIF('Catalogo CU'!$A$9:$A$500,"CU-048",'Catalogo CU'!$G$9:$G$500)=1,"Incluido",IF(SUMIF('Catalogo CU'!$A$9:$A$500,"CU-048",'Catalogo CU'!$G$9:$G$500)>0,"Parcial por selección","Fuera por selección")),"Revisar vínculo") -> Incluido | G100: Cubierto por los objetivos indicados; los pasos internos no se suman como transacciones.
A101: RF-11.03 | B101: El sistema debe calcular diariamente el indicador OTIF por cliente, ruta, zona y total consolidado, definiendo «On-Time» como el cumplimiento de fecha y ventana horaria pactada e «In-Full» como la entrega del 100% de ítems y unidades pedidas, obligando al registro de causal tipificada ante desvíos. | C101: Alta / E1 | D101: CU-047 | E101: Funcional | F101: =IF(AND(COUNTIF('Catalogo CU'!$A$9:$A$500,"CU-047")=1),IF(SUMIF('Catalogo CU'!$A$9:$A$500,"CU-047",'Catalogo CU'!$G$9:$G$500)=1,"Incluido",IF(SUMIF('Catalogo CU'!$A$9:$A$500,"CU-047",'Catalogo CU'!$G$9:$G$500)>0,"Parcial por selección","Fuera por selección")),"Revisar vínculo") -> Incluido | G101: Cubierto por los objetivos indicados; los pasos internos no se suman como transacciones.
A102: RF-11.04 | B102: El sistema debe calcular automáticamente el Fill Rate (unidades entregadas vs. pedidas) y el índice de Perfect Order contrastando la orden de venta original contra los datos de entrega física confirmados en el dispositivo móvil de reparto, sin requerir interacción tecnológica del cliente tradicional. | C102: Alta / E1 | D102: CU-047 | E102: Funcional | F102: =IF(AND(COUNTIF('Catalogo CU'!$A$9:$A$500,"CU-047")=1),IF(SUMIF('Catalogo CU'!$A$9:$A$500,"CU-047",'Catalogo CU'!$G$9:$G$500)=1,"Incluido",IF(SUMIF('Catalogo CU'!$A$9:$A$500,"CU-047",'Catalogo CU'!$G$9:$G$500)>0,"Parcial por selección","Fuera por selección")),"Revisar vínculo") -> Incluido | G102: Cubierto por los objetivos indicados; los pasos internos no se suman como transacciones.
A103: RF-11.05 | B103: El sistema debe calcular diariamente la utilización de capacidad volumétrica (m^3) y de peso (kg) por viaje despachado, alertando aquellos camiones que salgan con una ocupación inferior al umbral configurable (ej. < 65%). | C103: Alta / E1 | D103: CU-047 | E103: Funcional | F103: =IF(AND(COUNTIF('Catalogo CU'!$A$9:$A$500,"CU-047")=1),IF(SUMIF('Catalogo CU'!$A$9:$A$500,"CU-047",'Catalogo CU'!$G$9:$G$500)=1,"Incluido",IF(SUMIF('Catalogo CU'!$A$9:$A$500,"CU-047",'Catalogo CU'!$G$9:$G$500)>0,"Parcial por selección","Fuera por selección")),"Revisar vínculo") -> Incluido | G103: Cubierto por los objetivos indicados; los pasos internos no se suman como transacciones.
A104: RF-11.06 | B104: El sistema debe proveer un Tablero de Control Operacional en tiempo real que consolide el avance de rutas de despacho, porcentaje de entregas cumplidas, devoluciones en tránsito, alertas activas de cadena de frío y monto recaudado en efectivo. | C104: Alta / E1 | D104: CU-051 | E104: Funcional | F104: =IF(AND(COUNTIF('Catalogo CU'!$A$9:$A$500,"CU-051")=1),IF(SUMIF('Catalogo CU'!$A$9:$A$500,"CU-051",'Catalogo CU'!$G$9:$G$500)=1,"Incluido",IF(SUMIF('Catalogo CU'!$A$9:$A$500,"CU-051",'Catalogo CU'!$G$9:$G$500)>0,"Parcial por selección","Fuera por selección")),"Revisar vínculo") -> Incluido | G104: Cubierto por los objetivos indicados; los pasos internos no se suman como transacciones.
A105: RF-11.07 | B105: El sistema debe procesar automáticamente la liquidación y cierre comercial individual por camión al retornar a base, consolidando documentos tributarios entregados, devoluciones físicas recibidas, cobranzas en efectivo y balance de envases retornables. | C105: Alta / E1 | D105: CU-031 | E105: Funcional | F105: =IF(AND(COUNTIF('Catalogo CU'!$A$9:$A$500,"CU-031")=1),IF(SUMIF('Catalogo CU'!$A$9:$A$500,"CU-031",'Catalogo CU'!$G$9:$G$500)=1,"Incluido",IF(SUMIF('Catalogo CU'!$A$9:$A$500,"CU-031",'Catalogo CU'!$G$9:$G$500)>0,"Parcial por selección","Fuera por selección")),"Revisar vínculo") -> Incluido | G105: Cubierto por los objetivos indicados; los pasos internos no se suman como transacciones.
...

Sheet Criterios y fuentes
A2: Criterios de estimación y fuentes
A4: Fecha de corte: 30/10/2026. Los flujos y las puntuaciones son propuestas de estimación revisables.
A8: Criterio | B8: Decisión adoptada
A9: Frontera | B9: Software operacional, apps, portales, reglas de borde, adaptadores y extensiones ofertadas. ERP, cadenas, fuentes físicas y proveedores de servicios quedan fuera.
A10: Granularidad | B10: Un caso representa un objetivo completo del actor. No se cuenta por pantalla, módulo, llamada interna ni cantidad de usuarios.
A11: Transacción | B11: Una fila es una ida y vuelta observable: acción del actor, procesamiento y respuesta. No se multiplica por líneas de pedido, productos o repeticiones.
A12: Flujos alternativos | B12: Solo se agregan si requieren una interacción nueva. Un error de validación o una respuesta sustitutiva no agrega por sí mismo otra transacción.
A13: Inclusiones | B13: Se cuentan aparte cuando tienen objetivo reutilizable propio. El caso consumidor no repite las transacciones del servicio incluido.
A14: Extensiones y abstractos | B14: Las extensiones quedan dentro del caso base cuando agregan interacciones. Los casos abstractos no se cuentan.
A15: Procesos periódicos | B15: Se cuenta un único actor simple, Planificador automático. No se cuentan por separado sus relojes ni servicios internos.
A16: Actores adicionales | B16: Se proponen abastecimiento y tres perfiles de INN-02. Los 15 roles humanos del SD3 se conservan. No se multiplican por personas, empresas o dispositivos.
A17: Convención de esfuerzo | B17: Lectura B del PDF, pp. 51–52: UCP × CF son horas de programación. Total de desarrollo = programación ÷ porcentaje de programación.
A18: Etapas E1 y E2 | B18: La base compartida se construye una sola vez en E1; E2 añade sus objetivos. UAW se reparte proporcionalmente a UUCW solo para distribuir horas, sin volver a contar actores.
A19: Exclusiones de esfuerzo | B19: El resultado cubre desarrollo y su sobrecarga. Se estiman aparte migración/saneamiento, infraestructura/licencias, capacitación ejecutada, implantación, soporte, operación y reservas.
... A22: Comparación con EDT | B22: El T-15 contiene desarrollo, operación, implantación y reservas. Sus 220.023 HH contractuales no son comparables directamente con estas horas funcionales; no se fuerza una conciliación de ámbitos distintos.
A24: Tipo de actor | B24: Peso publicado | D24: Clase CU | E24: Desde | F24: Hasta | G24: Peso
A25: Simple | B25: 1 | D25: Simple | E25: 1 | F25: 3 | G25: 5
A26: Medio | B26: 2 | D26: Medio | E26: 4 | F26: 7 | G26: 10
A27: Complejo | B27: 3 | D27: Complejo | E27: 8 | F27: Sin límite | G27: 15
A30: Constante | B30: Valor publicado | D30: Conversión | E30: Desfavorables | F30: h/UCP
A31: Base TCF | B31: 0.6 | D31: Favorable: hasta | E31: 2 | F31: 20
A32: Coeficiente TCF | B32: 0.01 | D32: Exigente: hasta | E32: 4 | F32: 28
A33: Base EF | B33: 1.4 | D33: Replantear: desde | E33: 5 | F33: Sin estimación
A34: Coeficiente EF | B34: 0.03
A36: Método: FEP03.26 - Estimación de Software, Moya, 2026, pp. 24–52 y 65–66.
A39: Documento | B39: Referencia | C39: Versión revisada | D39: Uso en la estimación | E39: Disponibilidad
A40: PDF de método | B40: FEP03.26 - Estimación de Software.pdf, pp. 24–52, 65–66 | C40: PDF entregado por el usuario | D40: Reglas, pesos, factores, conversión y lectura B | E40: Disponible
A41: SD1 | B41: contenido.tex, estructura y gobierno | C41: origin/LafroX-Subdoc1-LateX · ffa82f3 | D41: Antecedentes del equipo y tecnología; no medición de productividad | E41: Desarrollado
A42: SD2 | B42: contenido.tex y anexos | C42: LafroX-Subdoc2-LateX · 4c86e7f | D42: Necesidades, familias y restricciones operacionales | E42: Desarrollado
A43: SD3 | B43: contenido.tex; tablas_anexo/rf_caso, rf_propios, rf_btt y actores_sistema | C43: LafroX-Subdoc3-LateX · 95238e4 | D43: Base funcional: 180 requisitos y 15 roles humanos | E43: Desarrollado
A44: SD4 | B44: 04/partes/4.1_logica y anexos 4-H, 4-N; dimensionamiento | C44: subdoc-4 · 0dea169 | D44: Integraciones, autoridades, frío local y continuidad | E44: Desarrollado
A45: SD5 | B45: 05_modelo_datos/contenido.tex y anexos | C45: LafroX-Subdoc5-LateX · 939be98 | D45: Lote/SSCC, idempotencia, trazabilidad y datos | E45: Desarrollado
A46: SD6 | B46: subdocumento_6/contenido.tex | C46: LafroX-Subdoc6-LateX · 7966b2e | D46: RUP iterativo, DevSecOps y métodos de gestión | E46: Desarrollado
A47: SD7 | B47: formulario-t14 y formulario-t15/contenido.tex | C47: LafroX-Subdoc7-LateX · 3fd3b74 | D47: Paquetes, etapas, construcción y ámbito contractual | E47: Desarrollado
A48: SD8 | B48: 08_plan_riesgos/contenido.tex | C48: Lafrox_Subdocumento_8_Latex_Nuevo · c1ca4bd | D48: Incertidumbre y reservas separadas de tamaño funcional | E48: Desarrollado
A49: SD9 | B49: SD9_v_nueva/09_plan_calidad/contenido.tex | C49: LafroX-Subdoc9-LateX · a4e1c63 | D49: Pruebas, aceptación y exigencias de producto | E49: Desarrollado
A50: SD10–SD12 | B50: subdocumento-ejemplo/contenido.tex; ramas de cada SD | C50: origin/LafroX-Subdoc10/11/12-LateX | D50: Solo plantillas de ejemplo. Servicio, planes y roles se contrastan con SD3/4/6/7 | E50: Sin contenido específico
... A53: Bases | B53: Caso_02_Logistica; Bases Técnicas Transversales; aclaraciones | C53: Copias de main y subdoc-4 | D53: Contraste de requisitos y límites; ERP único emisor | E53: Disponibles
